Workbook

Sheet Cover Page
A1: NBFC SECTOR BACKTESTING PROJECT
A2: Comprehensive Strategy Performance Analysis | FY 2025–26
A4: Submitted By | B4: Vishv Jeet Singh Thakur
A5: Submitted To | B5: Nikesh Ruparel
A6: College | B6: UPES
A7: Branch | B7: MBA in Strategic Financial Management in collaboration with EY
A8: Batch | B8: F4- Jun-2026
A9: Sector Allocated | B9: NBFC – General
A11: NBFC Sector – Company Reference List | FY 2025–26 | Date: 26 June 2026
A12: Company Name | B12: Trading Symbol | C12: Official Category | D12: Market Cap (₹ Cr)
A13: Aavas Financiers | B13: AAVAS | C13: =IF(D13<20000,"Mid Cap","Large Cap") -> Mid Cap | D13: 11813
A14: Home First Finance Company India | B14: HOMEFIRST | C14: =IF(D14<20000,"Mid Cap","Large Cap") -> Mid Cap | D14: 12456
A15: Five-Star Business Finance | B15: FIVESTAR | C15: =IF(D15<20000,"Mid Cap","Large Cap") -> Mid Cap | D15: 14670
A16: IIFL Finance | B16: IIFL | C16: =IF(D16<20000,"Mid Cap","Large Cap") -> Large Cap | D16: 21679
A17: Manappuram Finance | B17: MANAPPURAM | C17: =IF(D17<20000,"Mid Cap","Large Cap") -> Large Cap | D17: 29918
A18: LIC Housing Finance | B18: LICHSGFIN | C18: =IF(D18<20000,"Mid Cap","Large Cap") -> Large Cap | D18: 30245
A19: Poonawalla Fincorp | B19: POONAWALLA | C19: =IF(D19<20000,"Mid Cap","Large Cap") -> Large Cap | D19: 38768
A20: Mahindra & Mahindra Financial Services | B20: M&MFIN | C20: =IF(D20<20000,"Mid Cap","Large Cap") -> Large Cap | D20: 45668
A21: Sundaram Finance | B21: SUNDARMFIN | C21: =IF(D21<20000,"Mid Cap","Large Cap") -> Large Cap | D21: 51409
A22: L&T Finance | B22: LTF | C22: =IF(D22<20000,"Mid Cap","Large Cap") -> Large Cap | D22: 74915
A23: Aditya Birla Capital | B23: ABCAPITAL | C23: =IF(D23<20000,"Mid Cap","Large Cap") -> Large Cap | D23: 106853
A24: Muthoot Finance | B24: MUTHOOTFIN | C24: =IF(D24<20000,"Mid Cap","Large Cap") -> Large Cap | D24: 121468
... A27: Bajaj Finance | B27: BAJFINANCE | C27: =IF(D27<20000,"Mid Cap","Large Cap") -> Large Cap | D27: 610393
A28: Sector Average | D28: =AVERAGE(D13:D27) -> 104428.4
A30: 📌 Note: Mid Cap = Market Cap < ₹20,000 Cr | Large Cap = Market Cap ≥ ₹20,000 Cr | Companies sorted by ascending market capitalization

Sheet Content
A1: TABLE OF CONTENTS
A2: NBFC Sector Backtesting Project | FY 2025–26 | 10 Strategies × 15 NBFC Stocks
A4: # | B4: Section | C4: What's Inside | D4: Go To
A5: 1 | B5: Cover Page | C5: Project details, submission info & NBFC company reference list | D5: Open sheet ▸
A6: 2 | B6: Vwap | C6: VWAP Intraday Strategy — quarter-wise Buy/Sell backtest results | D6: Open sheet ▸
A7: 3 | B7: SuperTrend | C7: SuperTrend Intraday Strategy — quarter-wise Buy/Sell backtest results | D7: Open sheet ▸
A8: 4 | B8: MA | C8: Moving Average Intraday Strategy — quarter-wise Buy/Sell backtest results | D8: Open sheet ▸
A9: 5 | B9: MACD | C9: MACD Intraday Strategy — quarter-wise Buy/Sell backtest results | D9: Open sheet ▸
A10: 6 | B10: RSI | C10: RSI Intraday Strategy — quarter-wise Buy/Sell backtest results | D10: Open sheet ▸
A11: 7 | B11: Stochastic RSI | C11: Stochastic RSI Intraday Strategy — quarter-wise Buy/Sell backtest results | D11: Open sheet ▸
A12: 8 | B12: BB | C12: Bollinger Bands Intraday Strategy — quarter-wise Buy/Sell backtest results | D12: Open sheet ▸
A13: 9 | B13: AO | C13: Awesome Oscillator Intraday Strategy — quarter-wise Buy/Sell backtest results | D13: Open sheet ▸
A14: 10 | B14: PPS | C14: Pivot Point Standard Intraday Strategy — quarter-wise Buy/Sell backtest results | D14: Open sheet ▸
A15: 11 | B15: WA | C15: Williams Alligator Intraday Strategy — quarter-wise Buy/Sell backtest results | D15: Open sheet ▸
A16: 12 | B16: Results | C16: Final leaderboard — all 10 strategies ranked by FY net P&L, with key takeaways | D16: Open sheet ▸
A18: 📌 Note: Click "Open sheet ▸" to jump directly to a section. Each strategy sheet is broken out by quarter (Q1–Q4) plus a Financial Year summary.

Sheet Vwap
A1: NBFC – General Sector | Backtesting Report
A2: Student: Vishv Jeet Singh Thakur | Institution: UPES | Strategy: VWAP Intraday (5-Minute) | Time: 9:15 AM – 3:00 PM | Financial Year: FY 2025–26
A4: Q1 (Quarter 1): April 1, 2025 – June 30, 2025
A5: BUY / LONG CALL SIDE | H5: SELL / SHORT CALL SIDE
A6: Company Name | B6: Segment | C6: P&L (₹) | D6: Wins | E6: Losses | F6: Total Trades | H6: Company Name | I6: Segment | J6: P&L (₹) | K6: Wins | L6: Losses | M6: Total Trades
A7: Aavas Financiers | B7: NSE | C7: 1229.65 | D7: 36 | E7: 57 | F7: =SUM(D7,E7) -> 93 | H7: Aavas Financiers | I7: NSE | J7: 264.6 | K7: 39 | L7: 52 | M7: =SUM(K7,L7) -> 91
A8: Home First Finance Company India | B8: NSE | C8: 4538.1 | D8: 44 | E8: 52 | F8: =SUM(D8,E8) -> 96 | H8: Home First Finance Company India | I8: NSE | J8: -1938.55 | K8: 36 | L8: 69 | M8: =SUM(K8,L8) -> 105
A9: Five-Star Business Finance | B9: NSE | C9: 621.9 | D9: 39 | E9: 56 | F9: =SUM(D9,E9) -> 95 | H9: Five-Star Business Finance | I9: NSE | J9: -2686.9 | K9: 31 | L9: 61 | M9: =SUM(K9,L9) -> 92
A10: IIFL Finance | B10: NSE | C10: 303.2 | D10: 43 | E10: 73 | F10: =SUM(D10,E10) -> 116 | H10: IIFL Finance | I10: NSE | J10: -2292 | K10: 44 | L10: 73 | M10: =SUM(K10,L10) -> 117
A11: Manappuram Finance | B11: NSE | C11: -433.85 | D11: 35 | E11: 50 | F11: =SUM(D11,E11) -> 85 | H11: Manappuram Finance | I11: NSE | J11: -689.94 | K11: 36 | L11: 48 | M11: =SUM(K11,L11) -> 84
A12: LIC Housing Finance | B12: NSE | C12: 1107.9 | D12: 36 | E12: 54 | F12: =SUM(D12,E12) -> 90 | H12: LIC Housing Finance | I12: NSE | J12: 421.55 | K12: 36 | L12: 48 | M12: =SUM(K12,L12) -> 84
A13: Poonawalla Fincorp | B13: NSE | C13: 1735.5 | D13: 45 | E13: 56 | F13: =SUM(D13,E13) -> 101 | H13: Poonawalla Fincorp | I13: NSE | J13: -6259.9 | K13: 30 | L13: 78 | M13: =SUM(K13,L13) -> 108
A14: Mahindra & Mahindra Financial Services | B14: NSE | C14: -2159.8 | D14: 34 | E14: 55 | F14: =SUM(D14,E14) -> 89 | H14: Mahindra & Mahindra Financial Services | I14: NSE | J14: -774.4 | K14: 33 | L14: 48 | M14: =SUM(K14,L14) -> 81
A15: Sundaram Finance | B15: NSE | C15: 1625.6 | D15: 39 | E15: 56 | F15: =SUM(D15,E15) -> 95 | H15: Sundaram Finance | I15: NSE | J15: -2078.2 | K15: 27 | L15: 61 | M15: =SUM(K15,L15) -> 88
A16: L&T Finance | B16: NSE | C16: 1905.93 | D16: 39 | E16: 51 | F16: =SUM(D16,E16) -> 90 | H16: L&T Finance | I16: NSE | J16: -2328.34 | K16: 29 | L16: 61 | M16: =SUM(K16,L16) -> 90
A17: Aditya Birla Capital | B17: NSE | C17: 2749.69 | D17: 45 | E17: 53 | F17: =SUM(D17,E17) -> 98 | H17: Aditya Birla Capital | I17: NSE | J17: -3002.83 | K17: 34 | L17: 67 | M17: =SUM(K17,L17) -> 101
A18: Muthoot Finance | B18: NSE | C18: 2557.65 | D18: 42 | E18: 46 | F18: =SUM(D18,E18) -> 88 | H18: Muthoot Finance | I18: NSE | J18: -4103.6 | K18: 26 | L18: 61 | M18: =SUM(K18,L18) -> 87
... A21: Bajaj Finance | B21: NSE | C21: 398.95 | D21: 35 | E21: 44 | F21: =SUM(D21,E21) -> 79 | H21: Bajaj Finance | I21: NSE | J21: -1344.8 | K21: 31 | L21: 47 | M21: =SUM(K21,L21) -> 78
A22: TOTAL | C22: =SUM(C7:C21) -> 15615.72 | D22: =SUM(D7:D21) -> 582 | E22: =SUM(E7:E21) -> 817 | F22: =SUM(F7:F21) -> 1399 | H22: TOTAL | J22: =SUM(J7:J21) -> -25519.86 | K22: =SUM(K7:K21) -> 507 | L22: =SUM(L7:L21) -> 871 | M22: =SUM(M7:M21) -> 1378
A24: Q2 (Quarter 2): July 2, 2025 – September 30, 2025
A25: BUY / LONG CALL SIDE | H25: SELL / SHORT CALL SIDE
A26: Company Name | B26: Segment | C26: P&L (₹) | D26: Wins | E26: Losses | F26: Total Trades | H26: Company Name | I26: Segment | J26: P&L (₹) | K26: Wins | L26: Losses | M26: Total Trades
A27: Aavas Financiers | B27: NSE | C27: -1746.2 | D27: 29 | E27: 55 | F27: =SUM(D27,E27) -> 84 | H27: Aavas Financiers | I27: NSE | J27: 4687.35 | K27: 43 | L27: 37 | M27: =SUM(K27,L27) -> 80
A28: Home First Finance Company India | B28: NSE | C28: 218.35 | D28: 37 | E28: 55 | F28: =SUM(D28,E28) -> 92 | H28: Home First Finance Company India | I28: NSE | J28: -1364.45 | K28: 37 | L28: 68 | M28: =SUM(K28,L28) -> 105
A29: Five-Star Business Finance | B29: NSE | C29: -1278.25 | D29: 35 | E29: 55 | F29: =SUM(D29,E29) -> 90 | H29: Five-Star Business Finance | I29: NSE | J29: 708.4 | K29: 38 | L29: 51 | M29: =SUM(K29,L29) -> 89
A30: IIFL Finance | B30: NSE | C30: 589 | D30: 40 | E30: 56 | F30: =SUM(D30,E30) -> 96 | H30: IIFL Finance | I30: NSE | J30: 1937.05 | K30: 44 | L30: 52 | M30: =SUM(K30,L30) -> 96
A31: Manappuram Finance | B31: NSE | C31: 495.85 | D31: 37 | E31: 48 | F31: =SUM(D31,E31) -> 85 | H31: Manappuram Finance | I31: NSE | J31: 3307.75 | K31: 44 | L31: 53 | M31: =SUM(K31,L31) -> 97
A32: LIC Housing Finance | B32: NSE | C32: -1021.5 | D32: 28 | E32: 41 | F32: =SUM(D32,E32) -> 69 | H32: LIC Housing Finance | I32: NSE | J32: 3516.65 | K32: 43 | L32: 27 | M32: =SUM(K32,L32) -> 70
A33: Poonawalla Fincorp | B33: NSE | C33: -123.9 | D33: 37 | E33: 59 | F33: =SUM(D33,E33) -> 96 | H33: Poonawalla Fincorp | I33: NSE | J33: -70.25 | K33: 39 | L33: 49 | M33: =SUM(K33,L33) -> 88
A34: Mahindra & Mahindra Financial Services | B34: NSE | C34: 1101.05 | D34: 38 | E34: 51 | F34: =SUM(D34,E34) -> 89 | H34: Mahindra & Mahindra Financial Services | I34: NSE | J34: -440.3 | K34: 36 | L34: 46 | M34: =SUM(K34,L34) -> 82
A35: Sundaram Finance | B35: NSE | C35: 0.9 | D35: 37 | E35: 47 | F35: =SUM(D35,E35) -> 84 | H35: Sundaram Finance | I35: NSE | J35: 421.15 | K35: 32 | L35: 47 | M35: =SUM(K35,L35) -> 79
A36: L&T Finance | B36: NSE | C36: 1870.58 | D36: 41 | E36: 48 | F36: =SUM(D36,E36) -> 89 | H36: L&T Finance | I36: NSE | J36: -140.63 | K36: 41 | L36: 51 | M36: =SUM(K36,L36) -> 92
A37: Aditya Birla Capital | B37: NSE | C37: -343.6 | D37: 33 | E37: 53 | F37: =SUM(D37,E37) -> 86 | H37: Aditya Birla Capital | I37: NSE | J37: 5241.8 | K37: 44 | L37: 37 | M37: =SUM(K37,L37) -> 81
A38: Muthoot Finance | B38: NSE | C38: 1021.65 | D38: 38 | E38: 46 | F38: =SUM(D38,E38) -> 84 | H38: Muthoot Finance | I38: NSE | J38: -1070.3 | K38: 35 | L38: 52 | M38: =SUM(K38,L38) -> 87
... A41: Bajaj Finance | B41: NSE | C41: 1098.95 | D41: 39 | E41: 36 | F41: =SUM(D41,E41) -> 75 | H41: Bajaj Finance | I41: NSE | J41: 246.3 | K41: 32 | L41: 40 | M41: =SUM(K41,L41) -> 72
A42: TOTAL | C42: =SUM(C27:C41) -> 692.33 | D42: =SUM(D27:D41) -> 536 | E42: =SUM(E27:E41) -> 747 | F42: =SUM(F27:F41) -> 1283 | H42: TOTAL | J42: =SUM(J27:J41) -> 18475.32 | K42: =SUM(K27:K41) -> 583 | L42: =SUM(L27:L41) -> 692 | M42: =SUM(M27:M41) -> 1275
A44: Q3 (Quarter 3): October 2, 2025 – December 31, 2025
A45: BUY / LONG CALL SIDE | H45: SELL / SHORT CALL SIDE
A46: Company Name | B46: Segment | C46: P&L (₹) | D46: Wins | E46: Losses | F46: Total Trades | H46: Company Name | I46: Segment | J46: P&L (₹) | K46: Wins | L46: Losses | M46: Total Trades
A47: Aavas Financiers | B47: NSE | C47: 185.5 | D47: 33 | E47: 45 | F47: =SUM(D47,E47) -> 78 | H47: Aavas Financiers | I47: NSE | J47: 48.8 | K47: 36 | L47: 42 | M47: =SUM(K47,L47) -> 78
A48: Home First Finance Company India | B48: NSE | C48: -3308.2 | D48: 26 | E48: 59 | F48: =SUM(D48,E48) -> 85 | H48: Home First Finance Company India | I48: NSE | J48: 3390.45 | K48: 40 | L48: 40 | M48: =SUM(K48,L48) -> 80
A49: Five-Star Business Finance | B49: NSE | C49: 788.9 | D49: 37 | E49: 50 | F49: =SUM(D49,E49) -> 87 | H49: Five-Star Business Finance | I49: NSE | J49: -2739.95 | K49: 31 | L49: 62 | M49: =SUM(K49,L49) -> 93
A50: IIFL Finance | B50: NSE | C50: 1180.7 | D50: 34 | E50: 52 | F50: =SUM(D50,E50) -> 86 | H50: IIFL Finance | I50: NSE | J50: -1270.55 | K50: 35 | L50: 59 | M50: =SUM(K50,L50) -> 94
A51: Manappuram Finance | B51: NSE | C51: 695.3 | D51: 32 | E51: 43 | F51: =SUM(D51,E51) -> 75 | H51: Manappuram Finance | I51: NSE | J51: 2333.1 | K51: 38 | L51: 46 | M51: =SUM(K51,L51) -> 84
A52: LIC Housing Finance | B52: NSE | C52: -1202.05 | D52: 24 | E52: 42 | F52: =SUM(D52,E52) -> 66 | H52: LIC Housing Finance | I52: NSE | J52: 2392.7 | K52: 37 | L52: 27 | M52: =SUM(K52,L52) -> 64
A53: Poonawalla Fincorp | B53: NSE | C53: 821.8 | D53: 34 | E53: 45 | F53: =SUM(D53,E53) -> 79 | H53: Poonawalla Fincorp | I53: NSE | J53: 2725.75 | K53: 40 | L53: 46 | M53: =SUM(K53,L53) -> 86
A54: Mahindra & Mahindra Financial Services | B54: NSE | C54: 3604.35 | D54: 41 | E54: 52 | F54: =SUM(D54,E54) -> 93 | H54: Mahindra & Mahindra Financial Services | I54: NSE | J54: -1305 | K54: 31 | L54: 54 | M54: =SUM(K54,L54) -> 85
A55: Sundaram Finance | B55: NSE | C55: 2255.15 | D55: 38 | E55: 45 | F55: =SUM(D55,E55) -> 83 | H55: Sundaram Finance | I55: NSE | J55: -2433.95 | K55: 28 | L55: 53 | M55: =SUM(K55,L55) -> 81
A56: L&T Finance | B56: NSE | C56: -1576.58 | D56: 26 | E56: 54 | F56: =SUM(D56,E56) -> 80 | H56: L&T Finance | I56: NSE | J56: 1264.9 | K56: 38 | L56: 41 | M56: =SUM(K56,L56) -> 79
A57: Aditya Birla Capital | B57: NSE | C57: -938.6 | D57: 36 | E57: 53 | F57: =SUM(D57,E57) -> 89 | H57: Aditya Birla Capital | I57: NSE | J57: 1295.85 | K57: 38 | L57: 41 | M57: =SUM(K57,L57) -> 79
A58: Muthoot Finance | B58: NSE | C58: 2845.85 | D58: 38 | E58: 29 | F58: =SUM(D58,E58) -> 67 | H58: Muthoot Finance | I58: NSE | J58: -499.45 | K58: 27 | L58: 45 | M58: =SUM(K58,L58) -> 72
... A61: Bajaj Finance | B61: NSE | C61: -427.35 | D61: 28 | E61: 37 | F61: =SUM(D61,E61) -> 65 | H61: Bajaj Finance | I61: NSE | J61: 1885.65 | K61: 37 | L61: 29 | M61: =SUM(K61,L61) -> 66
A62: TOTAL | C62: =SUM(C47:C61) -> 10325.97 | D62: =SUM(D47:D61) -> 502 | E62: =SUM(E47:E61) -> 691 | F62: =SUM(F47:F61) -> 1193 | H62: TOTAL | J62: =SUM(J47:J61) -> -224.55 | K62: =SUM(K47:K61) -> 514 | L62: =SUM(L47:L61) -> 689 | M62: =SUM(M47:M61) -> 1203
A64: Q4 (Quarter 4): January 1, 2026 – March 31, 2026
A65: BUY / LONG CALL SIDE | H65: SELL / SHORT CALL SIDE
A66: Company Name | B66: Segment | C66: P&L (₹) | D66: Wins | E66: Losses | F66: Total Trades | H66: Company Name | I66: Segment | J66: P&L (₹) | K66: Wins | L66: Losses | M66: Total Trades
A67: Aavas Financiers | B67: NSE | C67: 1657.8 | D67: 38 | E67: 47 | F67: =SUM(D67,E67) -> 85 | H67: Aavas Financiers | I67: NSE | J67: 1268.2 | K67: 34 | L67: 39 | M67: =SUM(K67,L67) -> 73
A68: Home First Finance Company India | B68: NSE | C68: -4010.8 | D68: 30 | E68: 63 | F68: =SUM(D68,E68) -> 93 | H68: Home First Finance Company India | I68: NSE | J68: 3056.15 | K68: 44 | L68: 51 | M68: =SUM(K68,L68) -> 95
A69: Five-Star Business Finance | B69: NSE | C69: -739.95 | D69: 34 | E69: 63 | F69: =SUM(D69,E69) -> 97 | H69: Five-Star Business Finance | I69: NSE | J69: 4223.2 | K69: 44 | L69: 42 | M69: =SUM(K69,L69) -> 86
A70: IIFL Finance | B70: NSE | C70: -1986.25 | D70: 43 | E70: 80 | F70: =SUM(D70,E70) -> 123 | H70: IIFL Finance | I70: NSE | J70: 106.25 | K70: 44 | L70: 72 | M70: =SUM(K70,L70) -> 116
A71: Manappuram Finance | B71: NSE | C71: 1441.05 | D71: 42 | E71: 57 | F71: =SUM(D71,E71) -> 99 | H71: Manappuram Finance | I71: NSE | J71: 3936.8 | K71: 48 | L71: 59 | M71: =SUM(K71,L71) -> 107
A72: LIC Housing Finance | B72: NSE | C72: -1419.1 | D72: 33 | E72: 52 | F72: =SUM(D72,E72) -> 85 | H72: LIC Housing Finance | I72: NSE | J72: 1584.05 | K72: 35 | L72: 48 | M72: =SUM(K72,L72) -> 83
A73: Poonawalla Fincorp | B73: NSE | C73: -1646.55 | D73: 35 | E73: 70 | F73: =SUM(D73,E73) -> 105 | H73: Poonawalla Fincorp | I73: NSE | J73: 6171.45 | K73: 50 | L73: 51 | M73: =SUM(K73,L73) -> 101
A74: Mahindra & Mahindra Financial Services | B74: NSE | C74: -928.8 | D74: 31 | E74: 58 | F74: =SUM(D74,E74) -> 89 | H74: Mahindra & Mahindra Financial Services | I74: NSE | J74: 3373.6 | K74: 42 | L74: 51 | M74: =SUM(K74,L74) -> 93
A75: Sundaram Finance | B75: NSE | C75: 3785.3 | D75: 45 | E75: 51 | F75: =SUM(D75,E75) -> 96 | H75: Sundaram Finance | I75: NSE | J75: -3088.15 | K75: 30 | L75: 64 | M75: =SUM(K75,L75) -> 94
A76: L&T Finance | B76: NSE | C76: -4358.2 | D76: 28 | E76: 69 | F76: =SUM(D76,E76) -> 97 | H76: L&T Finance | I76: NSE | J76: 3330.85 | K76: 44 | L76: 51 | M76: =SUM(K76,L76) -> 95
A77: Aditya Birla Capital | B77: NSE | C77: -540.05 | D77: 41 | E77: 63 | F77: =SUM(D77,E77) -> 104 | H77: Aditya Birla Capital | I77: NSE | J77: 4041.75 | K77: 45 | L77: 56 | M77: =SUM(K77,L77) -> 101
A78: Muthoot Finance | B78: NSE | C78: 583.4 | D78: 37 | E78: 46 | F78: =SUM(D78,E78) -> 83 | H78: Muthoot Finance | I78: NSE | J78: 1314.05 | K78: 36 | L78: 51 | M78: =SUM(K78,L78) -> 87
... A81: Bajaj Finance | B81: NSE | C81: -1102.3 | D81: 32 | E81: 45 | F81: =SUM(D81,E81) -> 77 | H81: Bajaj Finance | I81: NSE | J81: 326.35 | K81: 35 | L81: 49 | M81: =SUM(K81,L81) -> 84
A82: TOTAL | C82: =SUM(C67:C81) -> -13261.6 | D82: =SUM(D67:D81) -> 536 | E82: =SUM(E67:E81) -> 877 | F82: =SUM(F67:F81) -> 1413 | H82: TOTAL | J82: =SUM(J67:J81) -> 36321.6 | K82: =SUM(K67:K81) -> 611 | L82: =SUM(L67:L81) -> 771 | M82: =SUM(M67:M81) -> 1382
A84: FINANCIAL YEAR SUMMARY — FY 2025–26
C85: Metric | D85: P&L (₹) | E85: Wins | F85: Losses | G85: Total Trades | H85: Win Rate %
C86: Buy Side – Full Year | D86: =SUM(C22,C42,C62,C82) -> 13372.42 | E86: =SUM(D82,D62,D42,D22) -> 2156 | F86: =SUM(E82,E62,E42,E22) -> 3132 | G86: =SUM(E86:F86) -> 5288 | H86: =E86/G86 -> 0.40771558
C87: Sell Side – Full Year | D87: =SUM(J22,J42,J62,J82) -> 29052.51 | E87: =SUM(K82,K62,K42,K22) -> 2215 | F87: =SUM(L82,L62,L42,L22) -> 3023 | G87: =SUM(E87:F87) -> 5238 | H87: =E87/G87 -> 0.42287132
C88: Combined Net P&L – FY 2025–26 | D88: =SUM(D86:D87) -> 42424.93 | E88: =SUM(E86:E87) -> 4371 | F88: =SUM(F86:F87) -> 6155 | G88: =SUM(G86:G87) -> 10526 | H88: =AVERAGE(H86,H87) -> 0.41529345
A90: 📌 Note: Green = Profit | Red = Loss | All P&L figures in Indian Rupees (₹) | Win Rate = Wins ÷ Total Trades

Sheet SuperTrend
A1: NBFC – General Sector | Backtesting Report
A2: Student: Vishv Jeet Singh Thakur | Institution: UPES | Strategy: SuperTrend Intraday (5-Minute) | Time: 9:15 AM – 3:00 PM | FY 2025–26
A4: Q1 (Quarter 1): April 1, 2025 – June 30, 2025
A5: BUY / LONG CALL SIDE | H5: SELL / SHORT CALL SIDE
A6: Company Name | B6: Segment | C6: P&L (₹) | D6: Wins | E6: Losses | F6: Total Trades | H6: Company Name | I6: Segment | J6: P&L (₹) | K6: Wins | L6: Losses | M6: Total Trades
A7: Aavas Financiers | B7: NSE | C7: -280.4 | D7: 18 | E7: 30 | F7: =SUM(D7,E7) -> 48 | H7: Aavas Financiers | I7: NSE | J7: -1082.5 | K7: 18 | L7: 30 | M7: =SUM(K7,L7) -> 48
A8: Home First Finance Company India | B8: NSE | C8: 620.75 | D8: 21 | E8: 32 | F8: =SUM(D8,E8) -> 53 | H8: Home First Finance Company India | I8: NSE | J8: -2712.6 | K8: 13 | L8: 35 | M8: =SUM(K8,L8) -> 48
A9: Five-Star Business Finance | B9: NSE | C9: 389.55 | D9: 16 | E9: 25 | F9: =SUM(D9,E9) -> 41 | H9: Five-Star Business Finance | I9: NSE | J9: -1140.85 | K9: 15 | L9: 29 | M9: =SUM(K9,L9) -> 44
A10: IIFL Finance | B10: NSE | C10: 837.4 | D10: 23 | E10: 31 | F10: =SUM(D10,E10) -> 54 | H10: IIFL Finance | I10: NSE | J10: 688.3 | K10: 22 | L10: 31 | M10: =SUM(K10,L10) -> 53
A11: Manappuram Finance | B11: NSE | C11: 39.53 | D11: 24 | E11: 27 | F11: =SUM(D11,E11) -> 51 | H11: Manappuram Finance | I11: NSE | J11: -2462.54 | K11: 13 | L11: 33 | M11: =SUM(K11,L11) -> 46
A12: LIC Housing Finance | B12: NSE | C12: -957.5 | D12: 18 | E12: 29 | F12: =SUM(D12,E12) -> 47 | H12: LIC Housing Finance | I12: NSE | J12: 1427 | K12: 27 | L12: 21 | M12: =SUM(K12,L12) -> 48
A13: Poonawalla Fincorp | B13: NSE | C13: -1501.35 | D13: 25 | E13: 33 | F13: =SUM(D13,E13) -> 58 | H13: Poonawalla Fincorp | I13: NSE | J13: -2030.5 | K13: 16 | L13: 39 | M13: =SUM(K13,L13) -> 55
A14: Mahindra & Mahindra Financial Services | B14: NSE | C14: -1753.05 | D14: 18 | E14: 35 | F14: =SUM(D14,E14) -> 53 | H14: Mahindra & Mahindra Financial Services | I14: NSE | J14: -813.9 | K14: 20 | L14: 32 | M14: =SUM(K14,L14) -> 52
A15: Sundaram Finance | B15: NSE | C15: 2491.55 | D15: 26 | E15: 27 | F15: =SUM(D15,E15) -> 53 | H15: Sundaram Finance | I15: NSE | J15: -1571.1 | K15: 15 | L15: 33 | M15: =SUM(K15,L15) -> 48
A16: L&T Finance | B16: NSE | C16: 2787.74 | D16: 23 | E16: 25 | F16: =SUM(D16,E16) -> 48 | H16: L&T Finance | I16: NSE | J16: 41.61 | K16: 24 | L16: 32 | M16: =SUM(K16,L16) -> 56
A17: Aditya Birla Capital | B17: NSE | C17: 522.15 | D17: 22 | E17: 32 | F17: =SUM(D17,E17) -> 54 | H17: Aditya Birla Capital | I17: NSE | J17: -1671.84 | K17: 20 | L17: 34 | M17: =SUM(K17,L17) -> 54
A18: Muthoot Finance | B18: NSE | C18: 1544.2 | D18: 26 | E18: 21 | F18: =SUM(D18,E18) -> 47 | H18: Muthoot Finance | I18: NSE | J18: -1775.65 | K18: 18 | L18: 33 | M18: =SUM(K18,L18) -> 51
... A21: Bajaj Finance | B21: NSE | C21: 1560.4 | D21: 27 | E21: 18 | F21: =SUM(D21,E21) -> 45 | H21: Bajaj Finance | I21: NSE | J21: -787.8 | K21: 20 | L21: 25 | M21: =SUM(K21,L21) -> 45
A22: TOTAL | C22: =SUM(C7:C21) -> 5779.27 | D22: =SUM(D7:D21) -> 327 | E22: =SUM(E7:E21) -> 424 | F22: =SUM(F7:F21) -> 751 | H22: TOTAL | J22: =SUM(J7:J21) -> -12505.27 | K22: =SUM(K7:K21) -> 284 | L22: =SUM(L7:L21) -> 459 | M22: =SUM(M7:M21) -> 743
A24: Q2 (Quarter 2): July 2, 2025 – September 30, 2025
A25: BUY / LONG CALL SIDE | H25: SELL / SHORT CALL SIDE
A26: Company Name | B26: Segment | C26: P&L (₹) | D26: Wins | E26: Losses | F26: Total Trades | H26: Company Name | I26: Segment | J26: P&L (₹) | K26: Wins | L26: Losses | M26: Total Trades
A27: Aavas Financiers | B27: NSE | C27: -549.1 | D27: 18 | E27: 30 | F27: =SUM(D27,E27) -> 48 | H27: Aavas Financiers | I27: NSE | J27: 27.9 | K27: 17 | L27: 29 | M27: =SUM(K27,L27) -> 46
A28: Home First Finance Company India | B28: NSE | C28: 1015.55 | D28: 19 | E28: 19 | F28: =SUM(D28,E28) -> 38 | H28: Home First Finance Company India | I28: NSE | J28: 463 | K28: 16 | L28: 18 | M28: =SUM(K28,L28) -> 34
A29: Five-Star Business Finance | B29: NSE | C29: -633.65 | D29: 21 | E29: 32 | F29: =SUM(D29,E29) -> 53 | H29: Five-Star Business Finance | I29: NSE | J29: -427.35 | K29: 21 | L29: 33 | M29: =SUM(K29,L29) -> 54
A30: IIFL Finance | B30: NSE | C30: 683.25 | D30: 21 | E30: 30 | F30: =SUM(D30,E30) -> 51 | H30: IIFL Finance | I30: NSE | J30: 728.2 | K30: 27 | L30: 27 | M30: =SUM(K30,L30) -> 54
A31: Manappuram Finance | B31: NSE | C31: -1799.35 | D31: 22 | E31: 36 | F31: =SUM(D31,E31) -> 58 | H31: Manappuram Finance | I31: NSE | J31: 1731.25 | K31: 30 | L31: 30 | M31: =SUM(K31,L31) -> 60
A32: LIC Housing Finance | B32: NSE | C32: -1412.35 | D32: 18 | E32: 30 | F32: =SUM(D32,E32) -> 48 | H32: LIC Housing Finance | I32: NSE | J32: 686.85 | K32: 30 | L32: 25 | M32: =SUM(K32,L32) -> 55
A33: Poonawalla Fincorp | B33: NSE | C33: 2170.7 | D33: 30 | E33: 23 | F33: =SUM(D33,E33) -> 53 | H33: Poonawalla Fincorp | I33: NSE | J33: 1324.15 | K33: 22 | L33: 27 | M33: =SUM(K33,L33) -> 49
A34: Mahindra & Mahindra Financial Services | B34: NSE | C34: 2365.3 | D34: 31 | E34: 26 | F34: =SUM(D34,E34) -> 57 | H34: Mahindra & Mahindra Financial Services | I34: NSE | J34: -147.55 | K34: 21 | L34: 26 | M34: =SUM(K34,L34) -> 47
A35: Sundaram Finance | B35: NSE | C35: 731.25 | D35: 24 | E35: 21 | F35: =SUM(D35,E35) -> 45 | H35: Sundaram Finance | I35: NSE | J35: 1049.55 | K35: 19 | L35: 28 | M35: =SUM(K35,L35) -> 47
A36: L&T Finance | B36: NSE | C36: 650.19 | D36: 26 | E36: 38 | F36: =SUM(D36,E36) -> 64 | H36: L&T Finance | I36: NSE | J36: 283.66 | K36: 28 | L36: 31 | M36: =SUM(K36,L36) -> 59
A37: Aditya Birla Capital | B37: NSE | C37: 471.55 | D37: 27 | E37: 34 | F37: =SUM(D37,E37) -> 61 | H37: Aditya Birla Capital | I37: NSE | J37: 383.3 | K37: 28 | L37: 31 | M37: =SUM(K37,L37) -> 59
A38: Muthoot Finance | B38: NSE | C38: 400.4 | D38: 27 | E38: 31 | F38: =SUM(D38,E38) -> 58 | H38: Muthoot Finance | I38: NSE | J38: -831.75 | K38: 24 | L38: 31 | M38: =SUM(K38,L38) -> 55
... A41: Bajaj Finance | B41: NSE | C41: -1500.65 | D41: 20 | E41: 30 | F41: =SUM(D41,E41) -> 50 | H41: Bajaj Finance | I41: NSE | J41: 824.95 | K41: 25 | L41: 20 | M41: =SUM(K41,L41) -> 45
A42: TOTAL | C42: =SUM(C27:C41) -> 2517.64 | D42: =SUM(D27:D41) -> 348 | E42: =SUM(E27:E41) -> 440 | F42: =SUM(F27:F41) -> 788 | H42: TOTAL | J42: =SUM(J27:J41) -> 6879.66 | K42: =SUM(K27:K41) -> 359 | L42: =SUM(L27:L41) -> 407 | M42: =SUM(M27:M41) -> 766
A44: Q3 (Quarter 3): October 2, 2025 – December 31, 2025
A45: BUY / LONG CALL SIDE | H45: SELL / SHORT CALL SIDE
A46: Company Name | B46: Segment | C46: P&L (₹) | D46: Wins | E46: Losses | F46: Total Trades | H46: Company Name | I46: Segment | J46: P&L (₹) | K46: Wins | L46: Losses | M46: Total Trades
A47: Aavas Financiers | B47: NSE | C47: -562.35 | D47: 20 | E47: 29 | F47: =SUM(D47,E47) -> 49 | H47: Aavas Financiers | I47: NSE | J47: -84.2 | K47: 21 | L47: 29 | M47: =SUM(K47,L47) -> 50
A48: Home First Finance Company India | B48: NSE | C48: -25.95 | D48: 16 | E48: 31 | F48: =SUM(D48,E48) -> 47 | H48: Home First Finance Company India | I48: NSE | J48: 1237.3 | K48: 18 | L48: 24 | M48: =SUM(K48,L48) -> 42
A49: Five-Star Business Finance | B49: NSE | C49: 1511.7 | D49: 26 | E49: 28 | F49: =SUM(D49,E49) -> 54 | H49: Five-Star Business Finance | I49: NSE | J49: 785.7 | K49: 21 | L49: 28 | M49: =SUM(K49,L49) -> 49
A50: IIFL Finance | B50: NSE | C50: 2523.55 | D50: 24 | E50: 28 | F50: =SUM(D50,E50) -> 52 | H50: IIFL Finance | I50: NSE | J50: -1004.8 | K50: 23 | L50: 35 | M50: =SUM(K50,L50) -> 58
A51: Manappuram Finance | B51: NSE | C51: 946.4 | D51: 23 | E51: 27 | F51: =SUM(D51,E51) -> 50 | H51: Manappuram Finance | I51: NSE | J51: 369.45 | K51: 27 | L51: 26 | M51: =SUM(K51,L51) -> 53
A52: LIC Housing Finance | B52: NSE | C52: -399.1 | D52: 18 | E52: 31 | F52: =SUM(D52,E52) -> 49 | H52: LIC Housing Finance | I52: NSE | J52: 1133.95 | K52: 23 | L52: 31 | M52: =SUM(K52,L52) -> 54
A53: Poonawalla Fincorp | B53: NSE | C53: 2023 | D53: 23 | E53: 19 | F53: =SUM(D53,E53) -> 42 | H53: Poonawalla Fincorp | I53: NSE | J53: 2067.95 | K53: 21 | L53: 24 | M53: =SUM(K53,L53) -> 45
A54: Mahindra & Mahindra Financial Services | B54: NSE | C54: 3194.35 | D54: 25 | E54: 28 | F54: =SUM(D54,E54) -> 53 | H54: Mahindra & Mahindra Financial Services | I54: NSE | J54: 490.15 | K54: 21 | L54: 29 | M54: =SUM(K54,L54) -> 50
A55: Sundaram Finance | B55: NSE | C55: 2125.4 | D55: 27 | E55: 28 | F55: =SUM(D55,E55) -> 55 | H55: Sundaram Finance | I55: NSE | J55: -1544.3 | K55: 15 | L55: 31 | M55: =SUM(K55,L55) -> 46
A56: L&T Finance | B56: NSE | C56: -209.78 | D56: 20 | E56: 34 | F56: =SUM(D56,E56) -> 54 | H56: L&T Finance | I56: NSE | J56: -266.95 | K56: 23 | L56: 30 | M56: =SUM(K56,L56) -> 53
A57: Aditya Birla Capital | B57: NSE | C57: -548.15 | D57: 19 | E57: 36 | F57: =SUM(D57,E57) -> 55 | H57: Aditya Birla Capital | I57: NSE | J57: -839.4 | K57: 25 | L57: 31 | M57: =SUM(K57,L57) -> 56
A58: Muthoot Finance | B58: NSE | C58: 1397.3 | D58: 24 | E58: 26 | F58: =SUM(D58,E58) -> 50 | H58: Muthoot Finance | I58: NSE | J58: -1458.95 | K58: 20 | L58: 28 | M58: =SUM(K58,L58) -> 48
... A61: Bajaj Finance | B61: NSE | C61: 352.5 | D61: 18 | E61: 23 | F61: =SUM(D61,E61) -> 41 | H61: Bajaj Finance | I61: NSE | J61: 2063.85 | K61: 24 | L61: 19 | M61: =SUM(K61,L61) -> 43
A62: TOTAL | C62: =SUM(C47:C61) -> 15394.97 | D62: =SUM(D47:D61) -> 327 | E62: =SUM(E47:E61) -> 413 | F62: =SUM(F47:F61) -> 740 | H62: TOTAL | J62: =SUM(J47:J61) -> 2792.85 | K62: =SUM(K47:K61) -> 323 | L62: =SUM(L47:L61) -> 414 | M62: =SUM(M47:M61) -> 737
A64: Q4 (Quarter 4): January 1, 2026 – March 31, 2026
A65: BUY / LONG CALL SIDE | H65: SELL / SHORT CALL SIDE
A66: Company Name | B66: Segment | C66: P&L (₹) | D66: Wins | E66: Losses | F66: Total Trades | H66: Company Name | I66: Segment | J66: P&L (₹) | K66: Wins | L66: Losses | M66: Total Trades
A67: Aavas Financiers | B67: NSE | C67: 1711.05 | D67: 25 | E67: 27 | F67: =SUM(D67,E67) -> 52 | H67: Aavas Financiers | I67: NSE | J67: -1503.55 | K67: 13 | L67: 29 | M67: =SUM(K67,L67) -> 42
A68: Home First Finance Company India | B68: NSE | C68: -1860.05 | D68: 14 | E68: 33 | F68: =SUM(D68,E68) -> 47 | H68: Home First Finance Company India | I68: NSE | J68: -1341.35 | K68: 17 | L68: 34 | M68: =SUM(K68,L68) -> 51
A69: Five-Star Business Finance | B69: NSE | C69: 2562.85 | D69: 24 | E69: 23 | F69: =SUM(D69,E69) -> 47 | H69: Five-Star Business Finance | I69: NSE | J69: 1131.45 | K69: 23 | L69: 22 | M69: =SUM(K69,L69) -> 45
A70: IIFL Finance | B70: NSE | C70: -658.15 | D70: 19 | E70: 33 | F70: =SUM(D70,E70) -> 52 | H70: IIFL Finance | I70: NSE | J70: 1897.5 | K70: 25 | L70: 30 | M70: =SUM(K70,L70) -> 55
A71: Manappuram Finance | B71: NSE | C71: -1590.1 | D71: 21 | E71: 38 | F71: =SUM(D71,E71) -> 59 | H71: Manappuram Finance | I71: NSE | J71: 1315.2 | K71: 23 | L71: 34 | M71: =SUM(K71,L71) -> 57
A72: LIC Housing Finance | B72: NSE | C72: 467.45 | D72: 30 | E72: 29 | F72: =SUM(D72,E72) -> 59 | H72: LIC Housing Finance | I72: NSE | J72: -353.2 | K72: 22 | L72: 35 | M72: =SUM(K72,L72) -> 57
A73: Poonawalla Fincorp | B73: NSE | C73: 84.05 | D73: 24 | E73: 40 | F73: =SUM(D73,E73) -> 64 | H73: Poonawalla Fincorp | I73: NSE | J73: 1797.45 | K73: 25 | L73: 32 | M73: =SUM(K73,L73) -> 57
A74: Mahindra & Mahindra Financial Services | B74: NSE | C74: -1557.95 | D74: 19 | E74: 34 | F74: =SUM(D74,E74) -> 53 | H74: Mahindra & Mahindra Financial Services | I74: NSE | J74: -1798 | K74: 16 | L74: 35 | M74: =SUM(K74,L74) -> 51
A75: Sundaram Finance | B75: NSE | C75: 1353.5 | D75: 22 | E75: 31 | F75: =SUM(D75,E75) -> 53 | H75: Sundaram Finance | I75: NSE | J75: -220.55 | K75: 17 | L75: 26 | M75: =SUM(K75,L75) -> 43
A76: L&T Finance | B76: NSE | C76: -2076.15 | D76: 16 | E76: 37 | F76: =SUM(D76,E76) -> 53 | H76: L&T Finance | I76: NSE | J76: -564.2 | K76: 21 | L76: 35 | M76: =SUM(K76,L76) -> 56
A77: Aditya Birla Capital | B77: NSE | C77: 767 | D77: 27 | E77: 28 | F77: =SUM(D77,E77) -> 55 | H77: Aditya Birla Capital | I77: NSE | J77: -2402.8 | K77: 18 | L77: 36 | M77: =SUM(K77,L77) -> 54
A78: Muthoot Finance | B78: NSE | C78: 2286.85 | D78: 27 | E78: 20 | F78: =SUM(D78,E78) -> 47 | H78: Muthoot Finance | I78: NSE | J78: -912.75 | K78: 17 | L78: 33 | M78: =SUM(K78,L78) -> 50
... A81: Bajaj Finance | B81: NSE | C81: -624.15 | D81: 24 | E81: 22 | F81: =SUM(D81,E81) -> 46 | H81: Bajaj Finance | I81: NSE | J81: 539.1 | K81: 25 | L81: 26 | M81: =SUM(K81,L81) -> 51
A82: TOTAL | C82: =SUM(C67:C81) -> -24.55 | D82: =SUM(D67:D81) -> 336 | E82: =SUM(E67:E81) -> 454 | F82: =SUM(F67:F81) -> 790 | H82: TOTAL | J82: =SUM(J67:J81) -> -2282.3 | K82: =SUM(K67:K81) -> 306 | L82: =SUM(L67:L81) -> 473 | M82: =SUM(M67:M81) -> 779
A84: FINANCIAL YEAR SUMMARY — FY 2025–26
C85: Metric | D85: P&L (₹) | E85: Wins | F85: Losses | G85: Total Trades | H85: Win Rate %
C86: Buy Side – Full Year | D86: =SUM(C22,C42,C62,C82) -> 23667.33 | E86: =SUM(D82,D62,D42,D22) -> 1338 | F86: =SUM(E82,E62,E42,E22) -> 1731 | G86: =SUM(E86:F86) -> 3069 | H86: =E86/G86 -> 0.43597263
C87: Sell Side – Full Year | D87: =SUM(J22,J42,J62,J82) -> -5115.06 | E87: =SUM(K82,K62,K42,K22) -> 1272 | F87: =SUM(L82,L62,L42,L22) -> 1753 | G87: =SUM(E87:F87) -> 3025 | H87: =E87/G87 -> 0.42049587
C88: Combined Net P&L – FY 2025–26 | D88: =SUM(D86:D87) -> 18552.27 | E88: =SUM(E86:E87) -> 2610 | F88: =SUM(F86:F87) -> 3484 | G88: =SUM(G86:G87) -> 6094 | H88: =AVERAGE(H86,H87) -> 0.42823425
A90: 📌 Note: Green = Profit | Red = Loss | All P&L figures in Indian Rupees (₹) | Win Rate = Wins ÷ Total Trades

Sheet MA
A1: NBFC – General Sector | Backtesting Report
A2: Student: Vishv Jeet Singh Thakur | Institution: UPES | Strategy: Moving Average (MA) Intraday (5-Minute) | Time: 9:15 AM – 3:00 PM | FY 2025–26
A4: Q1 (Quarter 1): April 1, 2025 – June 30, 2025
A5: BUY / LONG CALL SIDE | H5: SELL / SHORT CALL SIDE
A6: Company Name | B6: Segment | C6: P&L (₹) | D6: Wins | E6: Losses | F6: Total Trades | H6: Company Name | I6: Segment | J6: P&L (₹) | K6: Wins | L6: Losses | M6: Total Trades
A7: Aavas Financiers | B7: NSE | C7: 668.65 | D7: 14 | E7: 17 | F7: =SUM(D7,E7) -> 31 | H7: Aavas Financiers | I7: NSE | J7: 134.6 | K7: 15 | L7: 16 | M7: =SUM(K7,L7) -> 31
A8: Home First Finance Company India | B8: NSE | C8: 1217.55 | D8: 16 | E8: 19 | F8: =SUM(D8,E8) -> 35 | H8: Home First Finance Company India | I8: NSE | J8: -1811.3 | K8: 10 | L8: 23 | M8: =SUM(K8,L8) -> 33
A9: Five-Star Business Finance | B9: NSE | C9: -201.55 | D9: 6 | E9: 10 | F9: =SUM(D9,E9) -> 16 | H9: Five-Star Business Finance | I9: NSE | J9: 458.9 | K9: 8 | L9: 13 | M9: =SUM(K9,L9) -> 21
A10: IIFL Finance | B10: NSE | C10: 5.55 | D10: 18 | E10: 26 | F10: =SUM(D10,E10) -> 44 | H10: IIFL Finance | I10: NSE | J10: 398.9 | K10: 19 | L10: 24 | M10: =SUM(K10,L10) -> 43
A11: Manappuram Finance | B11: NSE | C11: 165.21 | D11: 12 | E11: 20 | F11: =SUM(D11,E11) -> 32 | H11: Manappuram Finance | I11: NSE | J11: -904.93 | K11: 14 | L11: 22 | M11: =SUM(K11,L11) -> 36
A12: LIC Housing Finance | B12: NSE | C12: 1377 | D12: 20 | E12: 16 | F12: =SUM(D12,E12) -> 36 | H12: LIC Housing Finance | I12: NSE | J12: -419.1 | K12: 13 | L12: 19 | M12: =SUM(K12,L12) -> 32
A13: Poonawalla Fincorp | B13: NSE | C13: 64.25 | D13: 17 | E13: 21 | F13: =SUM(D13,E13) -> 38 | H13: Poonawalla Fincorp | I13: NSE | J13: -1056 | K13: 15 | L13: 21 | M13: =SUM(K13,L13) -> 36
A14: Mahindra & Mahindra Financial Services | B14: NSE | C14: -510.3 | D14: 14 | E14: 20 | F14: =SUM(D14,E14) -> 34 | H14: Mahindra & Mahindra Financial Services | I14: NSE | J14: 843.05 | K14: 16 | L14: 19 | M14: =SUM(K14,L14) -> 35
A15: Sundaram Finance | B15: NSE | C15: 1177.45 | D15: 16 | E15: 13 | F15: =SUM(D15,E15) -> 29 | H15: Sundaram Finance | I15: NSE | J15: 110.85 | K15: 13 | L15: 20 | M15: =SUM(K15,L15) -> 33
A16: L&T Finance | B16: NSE | C16: 814.41 | D16: 13 | E16: 19 | F16: =SUM(D16,E16) -> 32 | H16: L&T Finance | I16: NSE | J16: 892.8 | K16: 13 | L16: 16 | M16: =SUM(K16,L16) -> 29
A17: Aditya Birla Capital | B17: NSE | C17: 2354.17 | D17: 18 | E17: 16 | F17: =SUM(D17,E17) -> 34 | H17: Aditya Birla Capital | I17: NSE | J17: -156.31 | K17: 13 | L17: 18 | M17: =SUM(K17,L17) -> 31
A18: Muthoot Finance | B18: NSE | C18: 1034.85 | D18: 17 | E18: 10 | F18: =SUM(D18,E18) -> 27 | H18: Muthoot Finance | I18: NSE | J18: -1457.25 | K18: 9 | L18: 22 | M18: =SUM(K18,L18) -> 31
... A21: Bajaj Finance | B21: NSE | C21: 850.65 | D21: 17 | E21: 13 | F21: =SUM(D21,E21) -> 30 | H21: Bajaj Finance | I21: NSE | J21: -637.65 | K21: 15 | L21: 18 | M21: =SUM(K21,L21) -> 33
A22: TOTAL | C22: =SUM(C7:C21) -> 9635.24 | D22: =SUM(D7:D21) -> 228 | E22: =SUM(E7:E21) -> 250 | F22: =SUM(F7:F21) -> 478 | H22: TOTAL | J22: =SUM(J7:J21) -> -3935.09 | K22: =SUM(K7:K21) -> 198 | L22: =SUM(L7:L21) -> 286 | M22: =SUM(M7:M21) -> 484
A24: Q2 (Quarter 2): July 2, 2025 – September 30, 2025
A25: BUY / LONG CALL SIDE | H25: SELL / SHORT CALL SIDE
A26: Company Name | B26: Segment | C26: P&L (₹) | D26: Wins | E26: Losses | F26: Total Trades | H26: Company Name | I26: Segment | J26: P&L (₹) | K26: Wins | L26: Losses | M26: Total Trades
A27: Aavas Financiers | B27: NSE | C27: -685 | D27: 9 | E27: 21 | F27: =SUM(D27,E27) -> 30 | H27: Aavas Financiers | I27: NSE | J27: 1796.7 | K27: 18 | L27: 12 | M27: =SUM(K27,L27) -> 30
A28: Home First Finance Company India | B28: NSE | C28: 98.9 | D28: 11 | E28: 18 | F28: =SUM(D28,E28) -> 29 | H28: Home First Finance Company India | I28: NSE | J28: -1210.85 | K28: 11 | L28: 17 | M28: =SUM(K28,L28) -> 28
A29: Five-Star Business Finance | B29: NSE | C29: -2373.8 | D29: 7 | E29: 27 | F29: =SUM(D29,E29) -> 34 | H29: Five-Star Business Finance | I29: NSE | J29: 1547.2 | K29: 18 | L29: 13 | M29: =SUM(K29,L29) -> 31
A30: IIFL Finance | B30: NSE | C30: 39.35 | D30: 16 | E30: 17 | F30: =SUM(D30,E30) -> 33 | H30: IIFL Finance | I30: NSE | J30: 1719.65 | K30: 20 | L30: 14 | M30: =SUM(K30,L30) -> 34
A31: Manappuram Finance | B31: NSE | C31: -706.8 | D31: 12 | E31: 17 | F31: =SUM(D31,E31) -> 29 | H31: Manappuram Finance | I31: NSE | J31: 359.2 | K31: 15 | L31: 17 | M31: =SUM(K31,L31) -> 32
A32: LIC Housing Finance | B32: NSE | C32: -3075.2 | D32: 8 | E32: 30 | F32: =SUM(D32,E32) -> 38 | H32: LIC Housing Finance | I32: NSE | J32: 1084.3 | K32: 21 | L32: 17 | M32: =SUM(K32,L32) -> 38
A33: Poonawalla Fincorp | B33: NSE | C33: 469.9 | D33: 15 | E33: 20 | F33: =SUM(D33,E33) -> 35 | H33: Poonawalla Fincorp | I33: NSE | J33: 1250.45 | K33: 16 | L33: 17 | M33: =SUM(K33,L33) -> 33
A34: Mahindra & Mahindra Financial Services | B34: NSE | C34: 1784.4 | D34: 22 | E34: 13 | F34: =SUM(D34,E34) -> 35 | H34: Mahindra & Mahindra Financial Services | I34: NSE | J34: -440.2 | K34: 15 | L34: 20 | M34: =SUM(K34,L34) -> 35
A35: Sundaram Finance | B35: NSE | C35: 235 | D35: 13 | E35: 15 | F35: =SUM(D35,E35) -> 28 | H35: Sundaram Finance | I35: NSE | J35: 1981.9 | K35: 16 | L35: 10 | M35: =SUM(K35,L35) -> 26
A36: L&T Finance | B36: NSE | C36: 198.42 | D36: 14 | E36: 24 | F36: =SUM(D36,E36) -> 38 | H36: L&T Finance | I36: NSE | J36: -462.47 | K36: 17 | L36: 19 | M36: =SUM(K36,L36) -> 36
A37: Aditya Birla Capital | B37: NSE | C37: -536.45 | D37: 17 | E37: 26 | F37: =SUM(D37,E37) -> 43 | H37: Aditya Birla Capital | I37: NSE | J37: -275.05 | K37: 21 | L37: 22 | M37: =SUM(K37,L37) -> 43
A38: Muthoot Finance | B38: NSE | C38: 60 | D38: 18 | E38: 22 | F38: =SUM(D38,E38) -> 40 | H38: Muthoot Finance | I38: NSE | J38: -999.8 | K38: 16 | L38: 24 | M38: =SUM(K38,L38) -> 40
... A41: Bajaj Finance | B41: NSE | C41: -177.85 | D41: 16 | E41: 14 | F41: =SUM(D41,E41) -> 30 | H41: Bajaj Finance | I41: NSE | J41: 1464.15 | K41: 19 | L41: 10 | M41: =SUM(K41,L41) -> 29
A42: TOTAL | C42: =SUM(C27:C41) -> -4798.08 | D42: =SUM(D27:D41) -> 210 | E42: =SUM(E27:E41) -> 300 | F42: =SUM(F27:F41) -> 510 | H42: TOTAL | J42: =SUM(J27:J41) -> 9800.33 | K42: =SUM(K27:K41) -> 260 | L42: =SUM(L27:L41) -> 247 | M42: =SUM(M27:M41) -> 507
A44: Q3 (Quarter 3): October 2, 2025 – December 31, 2025
A45: BUY / LONG CALL SIDE | H45: SELL / SHORT CALL SIDE
A46: Company Name | B46: Segment | C46: P&L (₹) | D46: Wins | E46: Losses | F46: Total Trades | H46: Company Name | I46: Segment | J46: P&L (₹) | K46: Wins | L46: Losses | M46: Total Trades
A47: Aavas Financiers | B47: NSE | C47: -24.5 | D47: 13 | E47: 18 | F47: =SUM(D47,E47) -> 31 | H47: Aavas Financiers | I47: NSE | J47: -723.5 | K47: 10 | L47: 18 | M47: =SUM(K47,L47) -> 28
A48: Home First Finance Company India | B48: NSE | C48: -280.15 | D48: 11 | E48: 18 | F48: =SUM(D48,E48) -> 29 | H48: Home First Finance Company India | I48: NSE | J48: 215.35 | K48: 16 | L48: 19 | M48: =SUM(K48,L48) -> 35
A49: Five-Star Business Finance | B49: NSE | C49: 783.3 | D49: 13 | E49: 16 | F49: =SUM(D49,E49) -> 29 | H49: Five-Star Business Finance | I49: NSE | J49: -1387.1 | K49: 9 | L49: 17 | M49: =SUM(K49,L49) -> 26
A50: IIFL Finance | B50: NSE | C50: -157.7 | D50: 13 | E50: 22 | F50: =SUM(D50,E50) -> 35 | H50: IIFL Finance | I50: NSE | J50: 94.15 | K50: 19 | L50: 16 | M50: =SUM(K50,L50) -> 35
A51: Manappuram Finance | B51: NSE | C51: -208.85 | D51: 13 | E51: 20 | F51: =SUM(D51,E51) -> 33 | H51: Manappuram Finance | I51: NSE | J51: 1154.6 | K51: 21 | L51: 17 | M51: =SUM(K51,L51) -> 38
A52: LIC Housing Finance | B52: NSE | C52: -888.8 | D52: 12 | E52: 25 | F52: =SUM(D52,E52) -> 37 | H52: LIC Housing Finance | I52: NSE | J52: 307.15 | K52: 16 | L52: 20 | M52: =SUM(K52,L52) -> 36
A53: Poonawalla Fincorp | B53: NSE | C53: -998.2 | D53: 14 | E53: 22 | F53: =SUM(D53,E53) -> 36 | H53: Poonawalla Fincorp | I53: NSE | J53: 2767.6 | K53: 24 | L53: 10 | M53: =SUM(K53,L53) -> 34
A54: Mahindra & Mahindra Financial Services | B54: NSE | C54: 909.55 | D54: 13 | E54: 19 | F54: =SUM(D54,E54) -> 32 | H54: Mahindra & Mahindra Financial Services | I54: NSE | J54: -362.9 | K54: 12 | L54: 19 | M54: =SUM(K54,L54) -> 31
A55: Sundaram Finance | B55: NSE | C55: 1911.55 | D55: 15 | E55: 16 | F55: =SUM(D55,E55) -> 31 | H55: Sundaram Finance | I55: NSE | J55: -2680.6 | K55: 11 | L55: 23 | M55: =SUM(K55,L55) -> 34
A56: L&T Finance | B56: NSE | C56: 793.92 | D56: 13 | E56: 17 | F56: =SUM(D56,E56) -> 30 | H56: L&T Finance | I56: NSE | J56: -1126.58 | K56: 16 | L56: 19 | M56: =SUM(K56,L56) -> 35
A57: Aditya Birla Capital | B57: NSE | C57: -35.3 | D57: 15 | E57: 21 | F57: =SUM(D57,E57) -> 36 | H57: Aditya Birla Capital | I57: NSE | J57: 148.1 | K57: 15 | L57: 17 | M57: =SUM(K57,L57) -> 32
A58: Muthoot Finance | B58: NSE | C58: 940.65 | D58: 14 | E58: 18 | F58: =SUM(D58,E58) -> 32 | H58: Muthoot Finance | I58: NSE | J58: -183.85 | K58: 15 | L58: 19 | M58: =SUM(K58,L58) -> 34
... A61: Bajaj Finance | B61: NSE | C61: 114.15 | D61: 11 | E61: 17 | F61: =SUM(D61,E61) -> 28 | H61: Bajaj Finance | I61: NSE | J61: 1339.65 | K61: 16 | L61: 12 | M61: =SUM(K61,L61) -> 28
A62: TOTAL | C62: =SUM(C47:C61) -> 4169.12 | D62: =SUM(D47:D61) -> 200 | E62: =SUM(E47:E61) -> 282 | F62: =SUM(F47:F61) -> 482 | H62: TOTAL | J62: =SUM(J47:J61) -> -1236.33 | K62: =SUM(K47:K61) -> 228 | L62: =SUM(L47:L61) -> 261 | M62: =SUM(M47:M61) -> 489
A64: Q4 (Quarter 4): January 1, 2026 – March 31, 2026
A65: BUY / LONG CALL SIDE | H65: SELL / SHORT CALL SIDE
A66: Company Name | B66: Segment | C66: P&L (₹) | D66: Wins | E66: Losses | F66: Total Trades | H66: Company Name | I66: Segment | J66: P&L (₹) | K66: Wins | L66: Losses | M66: Total Trades
A67: Aavas Financiers | B67: NSE | C67: 1167.1 | D67: 16 | E67: 12 | F67: =SUM(D67,E67) -> 28 | H67: Aavas Financiers | I67: NSE | J67: -1486.7 | K67: 8 | L67: 21 | M67: =SUM(K67,L67) -> 29
A68: Home First Finance Company India | B68: NSE | C68: -1814.4 | D68: 11 | E68: 24 | F68: =SUM(D68,E68) -> 35 | H68: Home First Finance Company India | I68: NSE | J68: 38.75 | K68: 15 | L68: 19 | M68: =SUM(K68,L68) -> 34
A69: Five-Star Business Finance | B69: NSE | C69: 118.35 | D69: 13 | E69: 18 | F69: =SUM(D69,E69) -> 31 | H69: Five-Star Business Finance | I69: NSE | J69: 636.8 | K69: 16 | L69: 16 | M69: =SUM(K69,L69) -> 32
A70: IIFL Finance | B70: NSE | C70: -1449.25 | D70: 9 | E70: 20 | F70: =SUM(D70,E70) -> 29 | H70: IIFL Finance | I70: NSE | J70: 972.55 | K70: 16 | L70: 16 | M70: =SUM(K70,L70) -> 32
A71: Manappuram Finance | B71: NSE | C71: -507.95 | D71: 13 | E71: 22 | F71: =SUM(D71,E71) -> 35 | H71: Manappuram Finance | I71: NSE | J71: 133 | K71: 16 | L71: 23 | M71: =SUM(K71,L71) -> 39
A72: LIC Housing Finance | B72: NSE | C72: -487.75 | D72: 10 | E72: 16 | F72: =SUM(D72,E72) -> 26 | H72: LIC Housing Finance | I72: NSE | J72: 2125.65 | K72: 18 | L72: 11 | M72: =SUM(K72,L72) -> 29
A73: Poonawalla Fincorp | B73: NSE | C73: -1525.7 | D73: 10 | E73: 22 | F73: =SUM(D73,E73) -> 32 | H73: Poonawalla Fincorp | I73: NSE | J73: 2209.5 | K73: 18 | L73: 15 | M73: =SUM(K73,L73) -> 33
A74: Mahindra & Mahindra Financial Services | B74: NSE | C74: -528.35 | D74: 8 | E74: 16 | F74: =SUM(D74,E74) -> 24 | H74: Mahindra & Mahindra Financial Services | I74: NSE | J74: 8.9 | K74: 10 | L74: 17 | M74: =SUM(K74,L74) -> 27
A75: Sundaram Finance | B75: NSE | C75: 1587.25 | D75: 18 | E75: 18 | F75: =SUM(D75,E75) -> 36 | H75: Sundaram Finance | I75: NSE | J75: 1636 | K75: 15 | L75: 15 | M75: =SUM(K75,L75) -> 30
A76: L&T Finance | B76: NSE | C76: -829.3 | D76: 8 | E76: 18 | F76: =SUM(D76,E76) -> 26 | H76: L&T Finance | I76: NSE | J76: 357.95 | K76: 14 | L76: 16 | M76: =SUM(K76,L76) -> 30
A77: Aditya Birla Capital | B77: NSE | C77: -883.65 | D77: 15 | E77: 23 | F77: =SUM(D77,E77) -> 38 | H77: Aditya Birla Capital | I77: NSE | J77: 1307.1 | K77: 14 | L77: 23 | M77: =SUM(K77,L77) -> 37
A78: Muthoot Finance | B78: NSE | C78: 1407.05 | D78: 15 | E78: 10 | F78: =SUM(D78,E78) -> 25 | H78: Muthoot Finance | I78: NSE | J78: 720.8 | K78: 14 | L78: 19 | M78: =SUM(K78,L78) -> 33
... A81: Bajaj Finance | B81: NSE | C81: -810.2 | D81: 13 | E81: 19 | F81: =SUM(D81,E81) -> 32 | H81: Bajaj Finance | I81: NSE | J81: 1651.55 | K81: 19 | L81: 13 | M81: =SUM(K81,L81) -> 32
A82: TOTAL | C82: =SUM(C67:C81) -> -6092.55 | D82: =SUM(D67:D81) -> 179 | E82: =SUM(E67:E81) -> 272 | F82: =SUM(F67:F81) -> 451 | H82: TOTAL | J82: =SUM(J67:J81) -> 12219.45 | K82: =SUM(K67:K81) -> 222 | L82: =SUM(L67:L81) -> 257 | M82: =SUM(M67:M81) -> 479
A84: FINANCIAL YEAR SUMMARY — FY 2025–26
C85: Metric | D85: P&L (₹) | E85: Wins | F85: Losses | G85: Total Trades | H85: Win Rate %
C86: Buy Side – Full Year | D86: =SUM(C22,C42,C62,C82) -> 2913.73 | E86: =SUM(D82,D62,D42,D22) -> 817 | F86: =SUM(E82,E62,E42,E22) -> 1104 | G86: =SUM(E86:F86) -> 1921 | H86: =E86/G86 -> 0.42529932
C87: Sell Side – Full Year | D87: =SUM(J22,J42,J62,J82) -> 16848.36 | E87: =SUM(K82,K62,K42,K22) -> 908 | F87: =SUM(L82,L62,L42,L22) -> 1051 | G87: =SUM(E87:F87) -> 1959 | H87: =E87/G87 -> 0.46350179
C88: Combined Net P&L – FY 2025–26 | D88: =SUM(D86:D87) -> 19762.09 | E88: =SUM(E86:E87) -> 1725 | F88: =SUM(F86:F87) -> 2155 | G88: =SUM(G86:G87) -> 3880 | H88: =AVERAGE(H86,H87) -> 0.44440055
A90: 📌 Note: Green = Profit | Red = Loss | All P&L figures in Indian Rupees (₹) | Win Rate = Wins ÷ Total Trades

Sheet MACD
A1: NBFC – General Sector | Backtesting Report
A2: Student: Vishv Jeet Singh Thakur | Institution: UPES | Strategy: MACD Intraday (5-Minute) | Time: 9:15 AM – 3:00 PM | FY 2025–26
A4: Q1 (Quarter 1): April 1, 2025 – June 30, 2025
A5: BUY / LONG CALL SIDE | H5: SELL / SHORT CALL SIDE
A6: Company Name | B6: Segment | C6: P&L (₹) | D6: Wins | E6: Losses | F6: Total Trades | H6: Company Name | I6: Segment | J6: P&L (₹) | K6: Wins | L6: Losses | M6: Total Trades
A7: Aavas Financiers | B7: NSE | C7: 809.6 | D7: 50 | E7: 76 | F7: =SUM(D7,E7) -> 126 | H7: Aavas Financiers | I7: NSE | J7: 1804.65 | K7: 54 | L7: 60 | M7: =SUM(K7,L7) -> 114
A8: Home First Finance Company India | B8: NSE | C8: 3345.5 | D8: 62 | E8: 74 | F8: =SUM(D8,E8) -> 136 | H8: Home First Finance Company India | I8: NSE | J8: -6938.1 | K8: 39 | L8: 94 | M8: =SUM(K8,L8) -> 133
A9: Five-Star Business Finance | B9: NSE | C9: 2020.2 | D9: 56 | E9: 67 | F9: =SUM(D9,E9) -> 123 | H9: Five-Star Business Finance | I9: NSE | J9: -1395.35 | K9: 46 | L9: 80 | M9: =SUM(K9,L9) -> 126
A10: IIFL Finance | B10: NSE | C10: -192.6 | D10: 51 | E10: 95 | F10: =SUM(D10,E10) -> 146 | H10: IIFL Finance | I10: NSE | J10: -473.1 | K10: 60 | L10: 82 | M10: =SUM(K10,L10) -> 142
A11: Manappuram Finance | B11: NSE | C11: 376.81 | D11: 45 | E11: 61 | F11: =SUM(D11,E11) -> 106 | H11: Manappuram Finance | I11: NSE | J11: -2851.93 | K11: 43 | L11: 60 | M11: =SUM(K11,L11) -> 103
A12: LIC Housing Finance | B12: NSE | C12: -602.25 | D12: 50 | E12: 68 | F12: =SUM(D12,E12) -> 118 | H12: LIC Housing Finance | I12: NSE | J12: -37.3 | K12: 42 | L12: 69 | M12: =SUM(K12,L12) -> 111
A13: Poonawalla Fincorp | B13: NSE | C13: 3334.5 | D13: 62 | E13: 65 | F13: =SUM(D13,E13) -> 127 | H13: Poonawalla Fincorp | I13: NSE | J13: -5659.85 | K13: 47 | L13: 95 | M13: =SUM(K13,L13) -> 142
A14: Mahindra & Mahindra Financial Services | B14: NSE | C14: -1160.05 | D14: 49 | E14: 66 | F14: =SUM(D14,E14) -> 115 | H14: Mahindra & Mahindra Financial Services | I14: NSE | J14: -3052.05 | K14: 42 | L14: 77 | M14: =SUM(K14,L14) -> 119
A15: Sundaram Finance | B15: NSE | C15: 1850.9 | D15: 55 | E15: 72 | F15: =SUM(D15,E15) -> 127 | H15: Sundaram Finance | I15: NSE | J15: -2818.15 | K15: 38 | L15: 68 | M15: =SUM(K15,L15) -> 106
A16: L&T Finance | B16: NSE | C16: 3578.7 | D16: 59 | E16: 64 | F16: =SUM(D16,E16) -> 123 | H16: L&T Finance | I16: NSE | J16: -5212.53 | K16: 47 | L16: 92 | M16: =SUM(K16,L16) -> 139
A17: Aditya Birla Capital | B17: NSE | C17: 2489.91 | D17: 57 | E17: 71 | F17: =SUM(D17,E17) -> 128 | H17: Aditya Birla Capital | I17: NSE | J17: -4872.53 | K17: 48 | L17: 94 | M17: =SUM(K17,L17) -> 142
A18: Muthoot Finance | B18: NSE | C18: 3058.5 | D18: 52 | E18: 58 | F18: =SUM(D18,E18) -> 110 | H18: Muthoot Finance | I18: NSE | J18: -3210.15 | K18: 43 | L18: 69 | M18: =SUM(K18,L18) -> 112
... A21: Bajaj Finance | B21: NSE | C21: 726.55 | D21: 46 | E21: 51 | F21: =SUM(D21,E21) -> 97 | H21: Bajaj Finance | I21: NSE | J21: -430.3 | K21: 45 | L21: 52 | M21: =SUM(K21,L21) -> 97
A22: TOTAL | C22: =SUM(C7:C21) -> 22095.27 | D22: =SUM(D7:D21) -> 810 | E22: =SUM(E7:E21) -> 1023 | F22: =SUM(F7:F21) -> 1833 | H22: TOTAL | J22: =SUM(J7:J21) -> -35779.89 | K22: =SUM(K7:K21) -> 693 | L22: =SUM(L7:L21) -> 1124 | M22: =SUM(M7:M21) -> 1817
A24: Q2 (Quarter 2): July 2, 2025 – September 30, 2025
A25: BUY / LONG CALL SIDE | H25: SELL / SHORT CALL SIDE
A26: Company Name | B26: Segment | C26: P&L (₹) | D26: Wins | E26: Losses | F26: Total Trades | H26: Company Name | I26: Segment | J26: P&L (₹) | K26: Wins | L26: Losses | M26: Total Trades
A27: Aavas Financiers | B27: NSE | C27: -3774.4 | D27: 44 | E27: 79 | F27: =SUM(D27,E27) -> 123 | H27: Aavas Financiers | I27: NSE | J27: 2869.15 | K27: 50 | L27: 50 | M27: =SUM(K27,L27) -> 100
A28: Home First Finance Company India | B28: NSE | C28: -3274.35 | D28: 47 | E28: 81 | F28: =SUM(D28,E28) -> 128 | H28: Home First Finance Company India | I28: NSE | J28: 1197.45 | K28: 50 | L28: 59 | M28: =SUM(K28,L28) -> 109
A29: Five-Star Business Finance | B29: NSE | C29: -2944.7 | D29: 52 | E29: 80 | F29: =SUM(D29,E29) -> 132 | H29: Five-Star Business Finance | I29: NSE | J29: 4325.75 | K29: 60 | L29: 50 | M29: =SUM(K29,L29) -> 110
A30: IIFL Finance | B30: NSE | C30: -1942.8 | D30: 49 | E30: 83 | F30: =SUM(D30,E30) -> 132 | H30: IIFL Finance | I30: NSE | J30: 1590.85 | K30: 51 | L30: 66 | M30: =SUM(K30,L30) -> 117
A31: Manappuram Finance | B31: NSE | C31: 236.1 | D31: 54 | E31: 67 | F31: =SUM(D31,E31) -> 121 | H31: Manappuram Finance | I31: NSE | J31: 2294.3 | K31: 54 | L31: 57 | M31: =SUM(K31,L31) -> 111
A32: LIC Housing Finance | B32: NSE | C32: -1725.45 | D32: 40 | E32: 52 | F32: =SUM(D32,E32) -> 92 | H32: LIC Housing Finance | I32: NSE | J32: 2287.7 | K32: 47 | L32: 40 | M32: =SUM(K32,L32) -> 87
A33: Poonawalla Fincorp | B33: NSE | C33: -965.1 | D33: 47 | E33: 85 | F33: =SUM(D33,E33) -> 132 | H33: Poonawalla Fincorp | I33: NSE | J33: 506.85 | K33: 54 | L33: 68 | M33: =SUM(K33,L33) -> 122
A34: Mahindra & Mahindra Financial Services | B34: NSE | C34: 2268.05 | D34: 50 | E34: 57 | F34: =SUM(D34,E34) -> 107 | H34: Mahindra & Mahindra Financial Services | I34: NSE | J34: -2230.8 | K34: 37 | L34: 69 | M34: =SUM(K34,L34) -> 106
A35: Sundaram Finance | B35: NSE | C35: -2673.2 | D35: 39 | E35: 73 | F35: =SUM(D35,E35) -> 112 | H35: Sundaram Finance | I35: NSE | J35: -614.85 | K35: 46 | L35: 63 | M35: =SUM(K35,L35) -> 109
A36: L&T Finance | B36: NSE | C36: 1065.92 | D36: 46 | E36: 65 | F36: =SUM(D36,E36) -> 111 | H36: L&T Finance | I36: NSE | J36: 1016.83 | K36: 54 | L36: 60 | M36: =SUM(K36,L36) -> 114
A37: Aditya Birla Capital | B37: NSE | C37: -2007.45 | D37: 40 | E37: 77 | F37: =SUM(D37,E37) -> 117 | H37: Aditya Birla Capital | I37: NSE | J37: 3396.35 | K37: 52 | L37: 55 | M37: =SUM(K37,L37) -> 107
A38: Muthoot Finance | B38: NSE | C38: 994.95 | D38: 53 | E38: 52 | F38: =SUM(D38,E38) -> 105 | H38: Muthoot Finance | I38: NSE | J38: -1717.7 | K38: 39 | L38: 56 | M38: =SUM(K38,L38) -> 95
... A41: Bajaj Finance | B41: NSE | C41: -1141.3 | D41: 40 | E41: 47 | F41: =SUM(D41,E41) -> 87 | H41: Bajaj Finance | I41: NSE | J41: -1018.45 | K41: 42 | L41: 55 | M41: =SUM(K41,L41) -> 97
A42: TOTAL | C42: =SUM(C27:C41) -> -16711.28 | D42: =SUM(D27:D41) -> 688 | E42: =SUM(E27:E41) -> 1021 | F42: =SUM(F27:F41) -> 1709 | H42: TOTAL | J42: =SUM(J27:J41) -> 15932.78 | K42: =SUM(K27:K41) -> 726 | L42: =SUM(L27:L41) -> 856 | M42: =SUM(M27:M41) -> 1582
A44: Q3 (Quarter 3): October 2, 2025 – December 31, 2025
A45: BUY / LONG CALL SIDE | H45: SELL / SHORT CALL SIDE
A46: Company Name | B46: Segment | C46: P&L (₹) | D46: Wins | E46: Losses | F46: Total Trades | H46: Company Name | I46: Segment | J46: P&L (₹) | K46: Wins | L46: Losses | M46: Total Trades
A47: Aavas Financiers | B47: NSE | C47: -587.85 | D47: 47 | E47: 62 | F47: =SUM(D47,E47) -> 109 | H47: Aavas Financiers | I47: NSE | J47: 828.05 | K47: 49 | L47: 61 | M47: =SUM(K47,L47) -> 110
A48: Home First Finance Company India | B48: NSE | C48: -3889.8 | D48: 38 | E48: 84 | F48: =SUM(D48,E48) -> 122 | H48: Home First Finance Company India | I48: NSE | J48: 1905.1 | K48: 48 | L48: 56 | M48: =SUM(K48,L48) -> 104
A49: Five-Star Business Finance | B49: NSE | C49: 2243.1 | D49: 53 | E49: 60 | F49: =SUM(D49,E49) -> 113 | H49: Five-Star Business Finance | I49: NSE | J49: 249.8 | K49: 45 | L49: 64 | M49: =SUM(K49,L49) -> 109
A50: IIFL Finance | B50: NSE | C50: 1632.75 | D50: 48 | E50: 59 | F50: =SUM(D50,E50) -> 107 | H50: IIFL Finance | I50: NSE | J50: -1233.05 | K50: 54 | L50: 77 | M50: =SUM(K50,L50) -> 131
A51: Manappuram Finance | B51: NSE | C51: -612.2 | D51: 50 | E51: 56 | F51: =SUM(D51,E51) -> 106 | H51: Manappuram Finance | I51: NSE | J51: -2009.4 | K51: 44 | L51: 71 | M51: =SUM(K51,L51) -> 115
A52: LIC Housing Finance | B52: NSE | C52: -1294.9 | D52: 35 | E52: 48 | F52: =SUM(D52,E52) -> 83 | H52: LIC Housing Finance | I52: NSE | J52: 1795.35 | K52: 42 | L52: 36 | M52: =SUM(K52,L52) -> 78
A53: Poonawalla Fincorp | B53: NSE | C53: -1793.7 | D53: 49 | E53: 74 | F53: =SUM(D53,E53) -> 123 | H53: Poonawalla Fincorp | I53: NSE | J53: -698.4 | K53: 48 | L53: 71 | M53: =SUM(K53,L53) -> 119
A54: Mahindra & Mahindra Financial Services | B54: NSE | C54: 7135.8 | D54: 64 | E54: 58 | F54: =SUM(D54,E54) -> 122 | H54: Mahindra & Mahindra Financial Services | I54: NSE | J54: -4314.35 | K54: 41 | L54: 77 | M54: =SUM(K54,L54) -> 118
A55: Sundaram Finance | B55: NSE | C55: 2797.35 | D55: 47 | E55: 54 | F55: =SUM(D55,E55) -> 101 | H55: Sundaram Finance | I55: NSE | J55: -3836.7 | K55: 37 | L55: 68 | M55: =SUM(K55,L55) -> 105
A56: L&T Finance | B56: NSE | C56: -1444.39 | D56: 48 | E56: 65 | F56: =SUM(D56,E56) -> 113 | H56: L&T Finance | I56: NSE | J56: -37.05 | K56: 48 | L56: 54 | M56: =SUM(K56,L56) -> 102
A57: Aditya Birla Capital | B57: NSE | C57: 996 | D57: 48 | E57: 53 | F57: =SUM(D57,E57) -> 101 | H57: Aditya Birla Capital | I57: NSE | J57: -2743.45 | K57: 47 | L57: 64 | M57: =SUM(K57,L57) -> 111
A58: Muthoot Finance | B58: NSE | C58: 794.75 | D58: 39 | E58: 50 | F58: =SUM(D58,E58) -> 89 | H58: Muthoot Finance | I58: NSE | J58: -2848 | K58: 35 | L58: 62 | M58: =SUM(K58,L58) -> 97
... A61: Bajaj Finance | B61: NSE | C61: 742.75 | D61: 40 | E61: 44 | F61: =SUM(D61,E61) -> 84 | H61: Bajaj Finance | I61: NSE | J61: 1283.4 | K61: 44 | L61: 37 | M61: =SUM(K61,L61) -> 81
A62: TOTAL | C62: =SUM(C47:C61) -> 12663.21 | D62: =SUM(D47:D61) -> 702 | E62: =SUM(E47:E61) -> 860 | F62: =SUM(F47:F61) -> 1562 | H62: TOTAL | J62: =SUM(J47:J61) -> -18853.7 | K62: =SUM(K47:K61) -> 662 | L62: =SUM(L47:L61) -> 939 | M62: =SUM(M47:M61) -> 1601
A64: Q4 (Quarter 4): January 1, 2026 – March 31, 2026
A65: BUY / LONG CALL SIDE | H65: SELL / SHORT CALL SIDE
A66: Company Name | B66: Segment | C66: P&L (₹) | D66: Wins | E66: Losses | F66: Total Trades | H66: Company Name | I66: Segment | J66: P&L (₹) | K66: Wins | L66: Losses | M66: Total Trades
A67: Aavas Financiers | B67: NSE | C67: 5046.25 | D67: 57 | E67: 57 | F67: =SUM(D67,E67) -> 114 | H67: Aavas Financiers | I67: NSE | J67: -4907.75 | K67: 34 | L67: 75 | M67: =SUM(K67,L67) -> 109
A68: Home First Finance Company India | B68: NSE | C68: -991.25 | D68: 46 | E68: 81 | F68: =SUM(D68,E68) -> 127 | H68: Home First Finance Company India | I68: NSE | J68: 1916.05 | K68: 54 | L68: 67 | M68: =SUM(K68,L68) -> 121
A69: Five-Star Business Finance | B69: NSE | C69: -4070.8 | D69: 37 | E69: 101 | F69: =SUM(D69,E69) -> 138 | H69: Five-Star Business Finance | I69: NSE | J69: 106.3 | K69: 53 | L69: 75 | M69: =SUM(K69,L69) -> 128
A70: IIFL Finance | B70: NSE | C70: 1763.65 | D70: 63 | E70: 84 | F70: =SUM(D70,E70) -> 147 | H70: IIFL Finance | I70: NSE | J70: 967.75 | K70: 64 | L70: 85 | M70: =SUM(K70,L70) -> 149
A71: Manappuram Finance | B71: NSE | C71: 2488.75 | D71: 59 | E71: 71 | F71: =SUM(D71,E71) -> 130 | H71: Manappuram Finance | I71: NSE | J71: 2740.15 | K71: 57 | L71: 71 | M71: =SUM(K71,L71) -> 128
A72: LIC Housing Finance | B72: NSE | C72: -885.25 | D72: 46 | E72: 69 | F72: =SUM(D72,E72) -> 115 | H72: LIC Housing Finance | I72: NSE | J72: 3564.95 | K72: 49 | L72: 44 | M72: =SUM(K72,L72) -> 93
A73: Poonawalla Fincorp | B73: NSE | C73: 425.15 | D73: 55 | E73: 86 | F73: =SUM(D73,E73) -> 141 | H73: Poonawalla Fincorp | I73: NSE | J73: 2383.2 | K73: 56 | L73: 75 | M73: =SUM(K73,L73) -> 131
A74: Mahindra & Mahindra Financial Services | B74: NSE | C74: -1203.45 | D74: 45 | E74: 77 | F74: =SUM(D74,E74) -> 122 | H74: Mahindra & Mahindra Financial Services | I74: NSE | J74: 3083.4 | K74: 50 | L74: 66 | M74: =SUM(K74,L74) -> 116
A75: Sundaram Finance | B75: NSE | C75: 605.5 | D75: 47 | E75: 75 | F75: =SUM(D75,E75) -> 122 | H75: Sundaram Finance | I75: NSE | J75: -210 | K75: 44 | L75: 69 | M75: =SUM(K75,L75) -> 113
A76: L&T Finance | B76: NSE | C76: -1187.6 | D76: 55 | E76: 73 | F76: =SUM(D76,E76) -> 128 | H76: L&T Finance | I76: NSE | J76: 2005.25 | K76: 49 | L76: 71 | M76: =SUM(K76,L76) -> 120
A77: Aditya Birla Capital | B77: NSE | C77: 769.9 | D77: 59 | E77: 75 | F77: =SUM(D77,E77) -> 134 | H77: Aditya Birla Capital | I77: NSE | J77: -60.35 | K77: 51 | L77: 81 | M77: =SUM(K77,L77) -> 132
A78: Muthoot Finance | B78: NSE | C78: 3855.1 | D78: 57 | E78: 59 | F78: =SUM(D78,E78) -> 116 | H78: Muthoot Finance | I78: NSE | J78: -228 | K78: 44 | L78: 70 | M78: =SUM(K78,L78) -> 114
... A81: Bajaj Finance | B81: NSE | C81: -1198.05 | D81: 46 | E81: 53 | F81: =SUM(D81,E81) -> 99 | H81: Bajaj Finance | I81: NSE | J81: 1537.75 | K81: 46 | L81: 58 | M81: =SUM(K81,L81) -> 104
A82: TOTAL | C82: =SUM(C67:C81) -> 3124.5 | D82: =SUM(D67:D81) -> 759 | E82: =SUM(E67:E81) -> 1098 | F82: =SUM(F67:F81) -> 1857 | H82: TOTAL | J82: =SUM(J67:J81) -> 16594.3 | K82: =SUM(K67:K81) -> 749 | L82: =SUM(L67:L81) -> 1019 | M82: =SUM(M67:M81) -> 1768
A84: FINANCIAL YEAR SUMMARY — FY 2025–26
C85: Metric | D85: P&L (₹) | E85: Wins | F85: Losses | G85: Total Trades | H85: Win Rate %
C86: Buy Side – Full Year | D86: =SUM(C22,C42,C62,C82) -> 21171.7 | E86: =SUM(D82,D62,D42,D22) -> 2959 | F86: =SUM(E82,E62,E42,E22) -> 4002 | G86: =SUM(E86:F86) -> 6961 | H86: =E86/G86 -> 0.4250826
C87: Sell Side – Full Year | D87: =SUM(J22,J42,J62,J82) -> -22106.51 | E87: =SUM(K82,K62,K42,K22) -> 2830 | F87: =SUM(L82,L62,L42,L22) -> 3938 | G87: =SUM(E87:F87) -> 6768 | H87: =E87/G87 -> 0.41814421
C88: Combined Net P&L – FY 2025–26 | D88: =SUM(D86:D87) -> -934.81 | E88: =SUM(E86:E87) -> 5789 | F88: =SUM(F86:F87) -> 7940 | G88: =SUM(G86:G87) -> 13729 | H88: =AVERAGE(H86,H87) -> 0.42161341
A90: 📌 Note: Green = Profit | Red = Loss | All P&L figures in Indian Rupees (₹) | Win Rate = Wins ÷ Total Trades

Sheet RSI
A1: NBFC – General Sector | Backtesting Report
A2: Student: Vishv Jeet Singh Thakur | Institution: UPES | Strategy: RSI Intraday (5-Minute) | Time: 9:15 AM – 3:00 PM | FY 2025–26
A4: Q1 (Quarter 1): April 1, 2025 – June 30, 2025
A5: BUY / LONG CALL SIDE | H5: SELL / SHORT CALL SIDE
A6: Company Name | B6: Segment | C6: P&L (₹) | D6: Wins | E6: Losses | F6: Total Trades | H6: Company Name | I6: Segment | J6: P&L (₹) | K6: Wins | L6: Losses | M6: Total Trades
A7: Aavas Financiers | B7: NSE | C7: 1889.85 | D7: 34 | E7: 46 | F7: =SUM(D7,E7) -> 80 | H7: Aavas Financiers | I7: NSE | J7: -1504 | K7: 34 | L7: 51 | M7: =SUM(K7,L7) -> 85
A8: Home First Finance Company India | B8: NSE | C8: -119.2 | D8: 37 | E8: 60 | F8: =SUM(D8,E8) -> 97 | H8: Home First Finance Company India | I8: NSE | J8: -4611.35 | K8: 27 | L8: 66 | M8: =SUM(K8,L8) -> 93
A9: Five-Star Business Finance | B9: NSE | C9: -2.8 | D9: 35 | E9: 54 | F9: =SUM(D9,E9) -> 89 | H9: Five-Star Business Finance | I9: NSE | J9: -2228.05 | K9: 32 | L9: 62 | M9: =SUM(K9,L9) -> 94
A10: IIFL Finance | B10: NSE | C10: -645.1 | D10: 43 | E10: 65 | F10: =SUM(D10,E10) -> 108 | H10: IIFL Finance | I10: NSE | J10: -421.95 | K10: 42 | L10: 56 | M10: =SUM(K10,L10) -> 98
A11: Manappuram Finance | B11: NSE | C11: 1127.94 | D11: 37 | E11: 50 | F11: =SUM(D11,E11) -> 87 | H11: Manappuram Finance | I11: NSE | J11: -2324.82 | K11: 35 | L11: 46 | M11: =SUM(K11,L11) -> 81
A12: LIC Housing Finance | B12: NSE | C12: 1984.65 | D12: 37 | E12: 43 | F12: =SUM(D12,E12) -> 80 | H12: LIC Housing Finance | I12: NSE | J12: 1773.55 | K12: 37 | L12: 36 | M12: =SUM(K12,L12) -> 73
A13: Poonawalla Fincorp | B13: NSE | C13: -90.15 | D13: 41 | E13: 54 | F13: =SUM(D13,E13) -> 95 | H13: Poonawalla Fincorp | I13: NSE | J13: -1230.85 | K13: 30 | L13: 56 | M13: =SUM(K13,L13) -> 86
A14: Mahindra & Mahindra Financial Services | B14: NSE | C14: -618 | D14: 38 | E14: 46 | F14: =SUM(D14,E14) -> 84 | H14: Mahindra & Mahindra Financial Services | I14: NSE | J14: -1371.45 | K14: 37 | L14: 49 | M14: =SUM(K14,L14) -> 86
A15: Sundaram Finance | B15: NSE | C15: 2124.05 | D15: 40 | E15: 52 | F15: =SUM(D15,E15) -> 92 | H15: Sundaram Finance | I15: NSE | J15: -1464.7 | K15: 29 | L15: 53 | M15: =SUM(K15,L15) -> 82
A16: L&T Finance | B16: NSE | C16: 3538.72 | D16: 45 | E16: 48 | F16: =SUM(D16,E16) -> 93 | H16: L&T Finance | I16: NSE | J16: -921.96 | K16: 28 | L16: 52 | M16: =SUM(K16,L16) -> 80
A17: Aditya Birla Capital | B17: NSE | C17: 3090.38 | D17: 45 | E17: 50 | F17: =SUM(D17,E17) -> 95 | H17: Aditya Birla Capital | I17: NSE | J17: -631.31 | K17: 34 | L17: 53 | M17: =SUM(K17,L17) -> 87
A18: Muthoot Finance | B18: NSE | C18: 1923.15 | D18: 39 | E18: 40 | F18: =SUM(D18,E18) -> 79 | H18: Muthoot Finance | I18: NSE | J18: -2474.85 | K18: 27 | L18: 50 | M18: =SUM(K18,L18) -> 77
... A21: Bajaj Finance | B21: NSE | C21: 1311.9 | D21: 38 | E21: 36 | F21: =SUM(D21,E21) -> 74 | H21: Bajaj Finance | I21: NSE | J21: -375.05 | K21: 36 | L21: 42 | M21: =SUM(K21,L21) -> 78
A22: TOTAL | C22: =SUM(C7:C21) -> 17070.79 | D22: =SUM(D7:D21) -> 589 | E22: =SUM(E7:E21) -> 747 | F22: =SUM(F7:F21) -> 1336 | H22: TOTAL | J22: =SUM(J7:J21) -> -15632.39 | K22: =SUM(K7:K21) -> 500 | L22: =SUM(L7:L21) -> 753 | M22: =SUM(M7:M21) -> 1253
A24: Q2 (Quarter 2): July 2, 2025 – September 30, 2025
A25: BUY / LONG CALL SIDE | H25: SELL / SHORT CALL SIDE
A26: Company Name | B26: Segment | C26: P&L (₹) | D26: Wins | E26: Losses | F26: Total Trades | H26: Company Name | I26: Segment | J26: P&L (₹) | K26: Wins | L26: Losses | M26: Total Trades
A27: Aavas Financiers | B27: NSE | C27: -1583.9 | D27: 32 | E27: 53 | F27: =SUM(D27,E27) -> 85 | H27: Aavas Financiers | I27: NSE | J27: 3081.95 | K27: 40 | L27: 38 | M27: =SUM(K27,L27) -> 78
A28: Home First Finance Company India | B28: NSE | C28: 769.35 | D28: 41 | E28: 45 | F28: =SUM(D28,E28) -> 86 | H28: Home First Finance Company India | I28: NSE | J28: 1613.65 | K28: 39 | L28: 49 | M28: =SUM(K28,L28) -> 88
A29: Five-Star Business Finance | B29: NSE | C29: -2192.2 | D29: 31 | E29: 60 | F29: =SUM(D29,E29) -> 91 | H29: Five-Star Business Finance | I29: NSE | J29: 13.3 | K29: 40 | L29: 52 | M29: =SUM(K29,L29) -> 92
A30: IIFL Finance | B30: NSE | C30: 1627.55 | D30: 34 | E30: 43 | F30: =SUM(D30,E30) -> 77 | H30: IIFL Finance | I30: NSE | J30: 3230.2 | K30: 40 | L30: 43 | M30: =SUM(K30,L30) -> 83
A31: Manappuram Finance | B31: NSE | C31: -1565.35 | D31: 33 | E31: 56 | F31: =SUM(D31,E31) -> 89 | H31: Manappuram Finance | I31: NSE | J31: 3471.8 | K31: 39 | L31: 37 | M31: =SUM(K31,L31) -> 76
A32: LIC Housing Finance | B32: NSE | C32: -1193.85 | D32: 35 | E32: 40 | F32: =SUM(D32,E32) -> 75 | H32: LIC Housing Finance | I32: NSE | J32: 2000.55 | K32: 48 | L32: 30 | M32: =SUM(K32,L32) -> 78
A33: Poonawalla Fincorp | B33: NSE | C33: 1236.95 | D33: 42 | E33: 49 | F33: =SUM(D33,E33) -> 91 | H33: Poonawalla Fincorp | I33: NSE | J33: 184.9 | K33: 39 | L33: 48 | M33: =SUM(K33,L33) -> 87
A34: Mahindra & Mahindra Financial Services | B34: NSE | C34: 2716.6 | D34: 41 | E34: 35 | F34: =SUM(D34,E34) -> 76 | H34: Mahindra & Mahindra Financial Services | I34: NSE | J34: 15.35 | K34: 35 | L34: 41 | M34: =SUM(K34,L34) -> 76
A35: Sundaram Finance | B35: NSE | C35: 2141.2 | D35: 35 | E35: 34 | F35: =SUM(D35,E35) -> 69 | H35: Sundaram Finance | I35: NSE | J35: 3626.85 | K35: 42 | L35: 38 | M35: =SUM(K35,L35) -> 80
A36: L&T Finance | B36: NSE | C36: 1292.68 | D36: 39 | E36: 54 | F36: =SUM(D36,E36) -> 93 | H36: L&T Finance | I36: NSE | J36: -95.73 | K36: 38 | L36: 41 | M36: =SUM(K36,L36) -> 79
A37: Aditya Birla Capital | B37: NSE | C37: -1508.6 | D37: 37 | E37: 50 | F37: =SUM(D37,E37) -> 87 | H37: Aditya Birla Capital | I37: NSE | J37: 2539.95 | K37: 44 | L37: 37 | M37: =SUM(K37,L37) -> 81
A38: Muthoot Finance | B38: NSE | C38: 634.35 | D38: 38 | E38: 41 | F38: =SUM(D38,E38) -> 79 | H38: Muthoot Finance | I38: NSE | J38: 552.5 | K38: 35 | L38: 37 | M38: =SUM(K38,L38) -> 72
... A41: Bajaj Finance | B41: NSE | C41: -1082.3 | D41: 36 | E41: 36 | F41: =SUM(D41,E41) -> 72 | H41: Bajaj Finance | I41: NSE | J41: -523.8 | K41: 34 | L41: 39 | M41: =SUM(K41,L41) -> 73
A42: TOTAL | C42: =SUM(C27:C41) -> -261.87 | D42: =SUM(D27:D41) -> 544 | E42: =SUM(E27:E41) -> 691 | F42: =SUM(F27:F41) -> 1235 | H42: TOTAL | J42: =SUM(J27:J41) -> 22303.82 | K42: =SUM(K27:K41) -> 588 | L42: =SUM(L27:L41) -> 609 | M42: =SUM(M27:M41) -> 1197
A44: Q3 (Quarter 3): October 2, 2025 – December 31, 2025
A45: BUY / LONG CALL SIDE | H45: SELL / SHORT CALL SIDE
A46: Company Name | B46: Segment | C46: P&L (₹) | D46: Wins | E46: Losses | F46: Total Trades | H46: Company Name | I46: Segment | J46: P&L (₹) | K46: Wins | L46: Losses | M46: Total Trades
A47: Aavas Financiers | B47: NSE | C47: 1249.6 | D47: 32 | E47: 46 | F47: =SUM(D47,E47) -> 78 | H47: Aavas Financiers | I47: NSE | J47: -575.75 | K47: 32 | L47: 49 | M47: =SUM(K47,L47) -> 81
A48: Home First Finance Company India | B48: NSE | C48: -1832 | D48: 27 | E48: 55 | F48: =SUM(D48,E48) -> 82 | H48: Home First Finance Company India | I48: NSE | J48: 2371.55 | K48: 36 | L48: 40 | M48: =SUM(K48,L48) -> 76
A49: Five-Star Business Finance | B49: NSE | C49: 1062.8 | D49: 37 | E49: 50 | F49: =SUM(D49,E49) -> 87 | H49: Five-Star Business Finance | I49: NSE | J49: 1008.7 | K49: 38 | L49: 42 | M49: =SUM(K49,L49) -> 80
A50: IIFL Finance | B50: NSE | C50: 389.05 | D50: 36 | E50: 53 | F50: =SUM(D50,E50) -> 89 | H50: IIFL Finance | I50: NSE | J50: 949.05 | K50: 36 | L50: 42 | M50: =SUM(K50,L50) -> 78
A51: Manappuram Finance | B51: NSE | C51: -1490.85 | D51: 34 | E51: 53 | F51: =SUM(D51,E51) -> 87 | H51: Manappuram Finance | I51: NSE | J51: -828.55 | K51: 34 | L51: 44 | M51: =SUM(K51,L51) -> 78
A52: LIC Housing Finance | B52: NSE | C52: -1477.85 | D52: 28 | E52: 41 | F52: =SUM(D52,E52) -> 69 | H52: LIC Housing Finance | I52: NSE | J52: 233.1 | K52: 30 | L52: 38 | M52: =SUM(K52,L52) -> 68
A53: Poonawalla Fincorp | B53: NSE | C53: 1101.8 | D53: 34 | E53: 41 | F53: =SUM(D53,E53) -> 75 | H53: Poonawalla Fincorp | I53: NSE | J53: 906.45 | K53: 36 | L53: 47 | M53: =SUM(K53,L53) -> 83
A54: Mahindra & Mahindra Financial Services | B54: NSE | C54: 6781.25 | D54: 46 | E54: 40 | F54: =SUM(D54,E54) -> 86 | H54: Mahindra & Mahindra Financial Services | I54: NSE | J54: 64.1 | K54: 28 | L54: 44 | M54: =SUM(K54,L54) -> 72
A55: Sundaram Finance | B55: NSE | C55: 4194.65 | D55: 40 | E55: 38 | F55: =SUM(D55,E55) -> 78 | H55: Sundaram Finance | I55: NSE | J55: -1972.4 | K55: 21 | L55: 44 | M55: =SUM(K55,L55) -> 65
A56: L&T Finance | B56: NSE | C56: -1564.83 | D56: 33 | E56: 59 | F56: =SUM(D56,E56) -> 92 | H56: L&T Finance | I56: NSE | J56: 1112.53 | K56: 35 | L56: 35 | M56: =SUM(K56,L56) -> 70
A57: Aditya Birla Capital | B57: NSE | C57: 282.7 | D57: 37 | E57: 57 | F57: =SUM(D57,E57) -> 94 | H57: Aditya Birla Capital | I57: NSE | J57: -1862.7 | K57: 33 | L57: 48 | M57: =SUM(K57,L57) -> 81
A58: Muthoot Finance | B58: NSE | C58: 1282.6 | D58: 35 | E58: 41 | F58: =SUM(D58,E58) -> 76 | H58: Muthoot Finance | I58: NSE | J58: -195.15 | K58: 29 | L58: 37 | M58: =SUM(K58,L58) -> 66
... A61: Bajaj Finance | B61: NSE | C61: 996.45 | D61: 28 | E61: 37 | F61: =SUM(D61,E61) -> 65 | H61: Bajaj Finance | I61: NSE | J61: 1807.85 | K61: 36 | L61: 31 | M61: =SUM(K61,L61) -> 67
A62: TOTAL | C62: =SUM(C47:C61) -> 14216.97 | D62: =SUM(D47:D61) -> 523 | E62: =SUM(E47:E61) -> 693 | F62: =SUM(F47:F61) -> 1216 | H62: TOTAL | J62: =SUM(J47:J61) -> 1139.43 | K62: =SUM(K47:K61) -> 490 | L62: =SUM(L47:L61) -> 619 | M62: =SUM(M47:M61) -> 1109
A64: Q4 (Quarter 4): January 1, 2026 – March 31, 2026
A65: BUY / LONG CALL SIDE | H65: SELL / SHORT CALL SIDE
A66: Company Name | B66: Segment | C66: P&L (₹) | D66: Wins | E66: Losses | F66: Total Trades | H66: Company Name | I66: Segment | J66: P&L (₹) | K66: Wins | L66: Losses | M66: Total Trades
A67: Aavas Financiers | B67: NSE | C67: 1716.75 | D67: 33 | E67: 42 | F67: =SUM(D67,E67) -> 75 | H67: Aavas Financiers | I67: NSE | J67: -3220.85 | K67: 30 | L67: 54 | M67: =SUM(K67,L67) -> 84
A68: Home First Finance Company India | B68: NSE | C68: -603.1 | D68: 32 | E68: 52 | F68: =SUM(D68,E68) -> 84 | H68: Home First Finance Company India | I68: NSE | J68: 743.65 | K68: 44 | L68: 55 | M68: =SUM(K68,L68) -> 99
A69: Five-Star Business Finance | B69: NSE | C69: -1057.65 | D69: 29 | E69: 50 | F69: =SUM(D69,E69) -> 79 | H69: Five-Star Business Finance | I69: NSE | J69: 2463.75 | K69: 46 | L69: 43 | M69: =SUM(K69,L69) -> 89
A70: IIFL Finance | B70: NSE | C70: -443.9 | D70: 38 | E70: 60 | F70: =SUM(D70,E70) -> 98 | H70: IIFL Finance | I70: NSE | J70: 1033 | K70: 41 | L70: 62 | M70: =SUM(K70,L70) -> 103
A71: Manappuram Finance | B71: NSE | C71: -1309 | D71: 39 | E71: 62 | F71: =SUM(D71,E71) -> 101 | H71: Manappuram Finance | I71: NSE | J71: 1870.85 | K71: 40 | L71: 62 | M71: =SUM(K71,L71) -> 102
A72: LIC Housing Finance | B72: NSE | C72: -466.9 | D72: 35 | E72: 43 | F72: =SUM(D72,E72) -> 78 | H72: LIC Housing Finance | I72: NSE | J72: 2539.25 | K72: 37 | L72: 39 | M72: =SUM(K72,L72) -> 76
A73: Poonawalla Fincorp | B73: NSE | C73: 838.15 | D73: 36 | E73: 56 | F73: =SUM(D73,E73) -> 92 | H73: Poonawalla Fincorp | I73: NSE | J73: 4155.85 | K73: 46 | L73: 48 | M73: =SUM(K73,L73) -> 94
A74: Mahindra & Mahindra Financial Services | B74: NSE | C74: -1856.3 | D74: 32 | E74: 60 | F74: =SUM(D74,E74) -> 92 | H74: Mahindra & Mahindra Financial Services | I74: NSE | J74: 549.05 | K74: 38 | L74: 59 | M74: =SUM(K74,L74) -> 97
A75: Sundaram Finance | B75: NSE | C75: 3187.3 | D75: 34 | E75: 41 | F75: =SUM(D75,E75) -> 75 | H75: Sundaram Finance | I75: NSE | J75: -86.35 | K75: 37 | L75: 56 | M75: =SUM(K75,L75) -> 93
A76: L&T Finance | B76: NSE | C76: -1846.4 | D76: 32 | E76: 55 | F76: =SUM(D76,E76) -> 87 | H76: L&T Finance | I76: NSE | J76: 3470.95 | K76: 41 | L76: 51 | M76: =SUM(K76,L76) -> 92
A77: Aditya Birla Capital | B77: NSE | C77: -1499.3 | D77: 41 | E77: 52 | F77: =SUM(D77,E77) -> 93 | H77: Aditya Birla Capital | I77: NSE | J77: -1077.3 | K77: 36 | L77: 65 | M77: =SUM(K77,L77) -> 101
A78: Muthoot Finance | B78: NSE | C78: 2762.55 | D78: 41 | E78: 37 | F78: =SUM(D78,E78) -> 78 | H78: Muthoot Finance | I78: NSE | J78: 767.05 | K78: 30 | L78: 53 | M78: =SUM(K78,L78) -> 83
... A81: Bajaj Finance | B81: NSE | C81: -534.75 | D81: 32 | E81: 39 | F81: =SUM(D81,E81) -> 71 | H81: Bajaj Finance | I81: NSE | J81: 2334.7 | K81: 38 | L81: 39 | M81: =SUM(K81,L81) -> 77
A82: TOTAL | C82: =SUM(C67:C81) -> -4682.35 | D82: =SUM(D67:D81) -> 519 | E82: =SUM(E67:E81) -> 748 | F82: =SUM(F67:F81) -> 1267 | H82: TOTAL | J82: =SUM(J67:J81) -> 17566.2 | K82: =SUM(K67:K81) -> 577 | L82: =SUM(L67:L81) -> 770 | M82: =SUM(M67:M81) -> 1347
A84: FINANCIAL YEAR SUMMARY — FY 2025–26
C85: Metric | D85: P&L (₹) | E85: Wins | F85: Losses | G85: Total Trades | H85: Win Rate %
C86: Buy Side – Full Year | D86: =SUM(C22,C42,C62,C82) -> 26343.54 | E86: =SUM(D82,D62,D42,D22) -> 2175 | F86: =SUM(E82,E62,E42,E22) -> 2879 | G86: =SUM(E86:F86) -> 5054 | H86: =E86/G86 -> 0.4303522
C87: Sell Side – Full Year | D87: =SUM(J22,J42,J62,J82) -> 25377.06 | E87: =SUM(K82,K62,K42,K22) -> 2155 | F87: =SUM(L82,L62,L42,L22) -> 2751 | G87: =SUM(E87:F87) -> 4906 | H87: =E87/G87 -> 0.43925805
C88: Combined Net P&L – FY 2025–26 | D88: =SUM(D86:D87) -> 51720.6 | E88: =SUM(E86:E87) -> 4330 | F88: =SUM(F86:F87) -> 5630 | G88: =SUM(G86:G87) -> 9960 | H88: =AVERAGE(H86,H87) -> 0.43480512
A90: 📌 Note: Green = Profit | Red = Loss | All P&L figures in Indian Rupees (₹) | Win Rate = Wins ÷ Total Trades

Sheet Stochastic RSI
A1: NBFC – General Sector | Backtesting Report
A2: Student: Vishv Jeet Singh Thakur | Institution: UPES | Strategy: Stochastic RSI Intraday (5-Minute) | Time: 9:15 AM – 3:00 PM | FY 2025–26
A4: Q1 (Quarter 1): April 1, 2025 – June 30, 2025
A5: BUY / LONG CALL SIDE | H5: SELL / SHORT CALL SIDE
A6: Company Name | B6: Segment | C6: P&L (₹) | D6: Wins | E6: Losses | F6: Total Trades | H6: Company Name | I6: Segment | J6: P&L (₹) | K6: Wins | L6: Losses | M6: Total Trades
A7: Aavas Financiers | B7: NSE | C7: -2833.8 | D7: 41 | E7: 81 | F7: =SUM(D7,E7) -> 122 | H7: Aavas Financiers | I7: NSE | J7: -3033 | K7: 62 | L7: 112 | M7: =SUM(K7,L7) -> 174
A8: Home First Finance Company India | B8: NSE | C8: 5512.55 | D8: 62 | E8: 64 | F8: =SUM(D8,E8) -> 126 | H8: Home First Finance Company India | I8: NSE | J8: -10245.95 | K8: 52 | L8: 133 | M8: =SUM(K8,L8) -> 185
A9: Five-Star Business Finance | B9: NSE | C9: 2362.45 | D9: 55 | E9: 68 | F9: =SUM(D9,E9) -> 123 | H9: Five-Star Business Finance | I9: NSE | J9: 676.8 | K9: 59 | L9: 99 | M9: =SUM(K9,L9) -> 158
A10: IIFL Finance | B10: NSE | C10: -537.9 | D10: 54 | E10: 91 | F10: =SUM(D10,E10) -> 145 | H10: IIFL Finance | I10: NSE | J10: -2312.45 | K10: 73 | L10: 115 | M10: =SUM(K10,L10) -> 188
A11: Manappuram Finance | B11: NSE | C11: 3757.27 | D11: 51 | E11: 45 | F11: =SUM(D11,E11) -> 96 | H11: Manappuram Finance | I11: NSE | J11: -2570.57 | K11: 59 | L11: 70 | M11: =SUM(K11,L11) -> 129
A12: LIC Housing Finance | B12: NSE | C12: -1385.65 | D12: 44 | E12: 68 | F12: =SUM(D12,E12) -> 112 | H12: LIC Housing Finance | I12: NSE | J12: 1108.15 | K12: 53 | L12: 77 | M12: =SUM(K12,L12) -> 130
A13: Poonawalla Fincorp | B13: NSE | C13: 1763.65 | D13: 54 | E13: 68 | F13: =SUM(D13,E13) -> 122 | H13: Poonawalla Fincorp | I13: NSE | J13: -7776.15 | K13: 51 | L13: 119 | M13: =SUM(K13,L13) -> 170
A14: Mahindra & Mahindra Financial Services | B14: NSE | C14: -427.6 | D14: 53 | E14: 57 | F14: =SUM(D14,E14) -> 110 | H14: Mahindra & Mahindra Financial Services | I14: NSE | J14: -1705 | K14: 55 | L14: 82 | M14: =SUM(K14,L14) -> 137
A15: Sundaram Finance | B15: NSE | C15: 3557.8 | D15: 52 | E15: 62 | F15: =SUM(D15,E15) -> 114 | H15: Sundaram Finance | I15: NSE | J15: -3025.95 | K15: 47 | L15: 87 | M15: =SUM(K15,L15) -> 134
A16: L&T Finance | B16: NSE | C16: 3967.62 | D16: 59 | E16: 62 | F16: =SUM(D16,E16) -> 121 | H16: L&T Finance | I16: NSE | J16: -5926.86 | K16: 58 | L16: 111 | M16: =SUM(K16,L16) -> 169
A17: Aditya Birla Capital | B17: NSE | C17: 1707.33 | D17: 53 | E17: 72 | F17: =SUM(D17,E17) -> 125 | H17: Aditya Birla Capital | I17: NSE | J17: -5569.87 | K17: 49 | L17: 108 | M17: =SUM(K17,L17) -> 157
A18: Muthoot Finance | B18: NSE | C18: 1411.05 | D18: 48 | E18: 60 | F18: =SUM(D18,E18) -> 108 | H18: Muthoot Finance | I18: NSE | J18: -3860.7 | K18: 51 | L18: 90 | M18: =SUM(K18,L18) -> 141
... A21: Bajaj Finance | B21: NSE | C21: 224.35 | D21: 51 | E21: 53 | F21: =SUM(D21,E21) -> 104 | H21: Bajaj Finance | I21: NSE | J21: -2597.9 | K21: 53 | L21: 70 | M21: =SUM(K21,L21) -> 123
A22: TOTAL | C22: =SUM(C7:C21) -> 21505.02 | D22: =SUM(D7:D21) -> 780 | E22: =SUM(E7:E21) -> 982 | F22: =SUM(F7:F21) -> 1762 | H22: TOTAL | J22: =SUM(J7:J21) -> -48716.45 | K22: =SUM(K7:K21) -> 838 | L22: =SUM(L7:L21) -> 1453 | M22: =SUM(M7:M21) -> 2291
A24: Q2 (Quarter 2): July 2, 2025 – September 30, 2025
A25: BUY / LONG CALL SIDE | H25: SELL / SHORT CALL SIDE
A26: Company Name | B26: Segment | C26: P&L (₹) | D26: Wins | E26: Losses | F26: Total Trades | H26: Company Name | I26: Segment | J26: P&L (₹) | K26: Wins | L26: Losses | M26: Total Trades
A27: Aavas Financiers | B27: NSE | C27: -913.9 | D27: 49 | E27: 71 | F27: =SUM(D27,E27) -> 120 | H27: Aavas Financiers | I27: NSE | J27: 4247.05 | K27: 64 | L27: 67 | M27: =SUM(K27,L27) -> 131
A28: Home First Finance Company India | B28: NSE | C28: -541.3 | D28: 44 | E28: 65 | F28: =SUM(D28,E28) -> 109 | H28: Home First Finance Company India | I28: NSE | J28: 1652.95 | K28: 62 | L28: 83 | M28: =SUM(K28,L28) -> 145
A29: Five-Star Business Finance | B29: NSE | C29: -2954.9 | D29: 43 | E29: 72 | F29: =SUM(D29,E29) -> 115 | H29: Five-Star Business Finance | I29: NSE | J29: 6157.5 | K29: 74 | L29: 59 | M29: =SUM(K29,L29) -> 133
A30: IIFL Finance | B30: NSE | C30: -1262.3 | D30: 46 | E30: 72 | F30: =SUM(D30,E30) -> 118 | H30: IIFL Finance | I30: NSE | J30: 77.6 | K30: 68 | L30: 96 | M30: =SUM(K30,L30) -> 164
A31: Manappuram Finance | B31: NSE | C31: -1160.05 | D31: 55 | E31: 68 | F31: =SUM(D31,E31) -> 123 | H31: Manappuram Finance | I31: NSE | J31: 4230.95 | K31: 65 | L31: 73 | M31: =SUM(K31,L31) -> 138
A32: LIC Housing Finance | B32: NSE | C32: -2773 | D32: 39 | E32: 56 | F32: =SUM(D32,E32) -> 95 | H32: LIC Housing Finance | I32: NSE | J32: 2285.55 | K32: 53 | L32: 50 | M32: =SUM(K32,L32) -> 103
A33: Poonawalla Fincorp | B33: NSE | C33: -88.1 | D33: 46 | E33: 71 | F33: =SUM(D33,E33) -> 117 | H33: Poonawalla Fincorp | I33: NSE | J33: -468.55 | K33: 69 | L33: 92 | M33: =SUM(K33,L33) -> 161
A34: Mahindra & Mahindra Financial Services | B34: NSE | C34: 1406.5 | D34: 44 | E34: 53 | F34: =SUM(D34,E34) -> 97 | H34: Mahindra & Mahindra Financial Services | I34: NSE | J34: -2578.25 | K34: 48 | L34: 72 | M34: =SUM(K34,L34) -> 120
A35: Sundaram Finance | B35: NSE | C35: -1121.9 | D35: 41 | E35: 63 | F35: =SUM(D35,E35) -> 104 | H35: Sundaram Finance | I35: NSE | J35: 1432.6 | K35: 54 | L35: 72 | M35: =SUM(K35,L35) -> 126
A36: L&T Finance | B36: NSE | C36: 420.35 | D36: 43 | E36: 68 | F36: =SUM(D36,E36) -> 111 | H36: L&T Finance | I36: NSE | J36: -195.65 | K36: 66 | L36: 74 | M36: =SUM(K36,L36) -> 140
A37: Aditya Birla Capital | B37: NSE | C37: -3264 | D37: 41 | E37: 73 | F37: =SUM(D37,E37) -> 114 | H37: Aditya Birla Capital | I37: NSE | J37: 3581.2 | K37: 64 | L37: 70 | M37: =SUM(K37,L37) -> 134
A38: Muthoot Finance | B38: NSE | C38: 581.95 | D38: 43 | E38: 46 | F38: =SUM(D38,E38) -> 89 | H38: Muthoot Finance | I38: NSE | J38: -874.9 | K38: 45 | L38: 55 | M38: =SUM(K38,L38) -> 100
... A41: Bajaj Finance | B41: NSE | C41: 1307.8 | D41: 45 | E41: 45 | F41: =SUM(D41,E41) -> 90 | H41: Bajaj Finance | I41: NSE | J41: 76.95 | K41: 44 | L41: 57 | M41: =SUM(K41,L41) -> 101
A42: TOTAL | C42: =SUM(C27:C41) -> -9907.2 | D42: =SUM(D27:D41) -> 663 | E42: =SUM(E27:E41) -> 942 | F42: =SUM(F27:F41) -> 1605 | H42: TOTAL | J42: =SUM(J27:J41) -> 23159.55 | K42: =SUM(K27:K41) -> 883 | L42: =SUM(L27:L41) -> 1043 | M42: =SUM(M27:M41) -> 1926
A44: Q3 (Quarter 3): October 2, 2025 – December 31, 2025
A45: BUY / LONG CALL SIDE | H45: SELL / SHORT CALL SIDE
A46: Company Name | B46: Segment | C46: P&L (₹) | D46: Wins | E46: Losses | F46: Total Trades | H46: Company Name | I46: Segment | J46: P&L (₹) | K46: Wins | L46: Losses | M46: Total Trades
A47: Aavas Financiers | B47: NSE | C47: -530 | D47: 42 | E47: 66 | F47: =SUM(D47,E47) -> 108 | H47: Aavas Financiers | I47: NSE | J47: 2023.55 | K47: 59 | L47: 67 | M47: =SUM(K47,L47) -> 126
A48: Home First Finance Company India | B48: NSE | C48: -2501.1 | D48: 38 | E48: 75 | F48: =SUM(D48,E48) -> 113 | H48: Home First Finance Company India | I48: NSE | J48: 3060.45 | K48: 59 | L48: 67 | M48: =SUM(K48,L48) -> 126
A49: Five-Star Business Finance | B49: NSE | C49: 437.95 | D49: 50 | E49: 65 | F49: =SUM(D49,E49) -> 115 | H49: Five-Star Business Finance | I49: NSE | J49: -2658.3 | K49: 54 | L49: 96 | M49: =SUM(K49,L49) -> 150
A50: IIFL Finance | B50: NSE | C50: 481 | D50: 49 | E50: 67 | F50: =SUM(D50,E50) -> 116 | H50: IIFL Finance | I50: NSE | J50: -1784.1 | K50: 61 | L50: 93 | M50: =SUM(K50,L50) -> 154
A51: Manappuram Finance | B51: NSE | C51: 1293.55 | D51: 53 | E51: 61 | F51: =SUM(D51,E51) -> 114 | H51: Manappuram Finance | I51: NSE | J51: 2700.35 | K51: 61 | L51: 64 | M51: =SUM(K51,L51) -> 125
A52: LIC Housing Finance | B52: NSE | C52: -588.45 | D52: 35 | E52: 42 | F52: =SUM(D52,E52) -> 77 | H52: LIC Housing Finance | I52: NSE | J52: 2076.2 | K52: 46 | L52: 38 | M52: =SUM(K52,L52) -> 84
A53: Poonawalla Fincorp | B53: NSE | C53: 1515.95 | D53: 53 | E53: 72 | F53: =SUM(D53,E53) -> 125 | H53: Poonawalla Fincorp | I53: NSE | J53: -2280.9 | K53: 56 | L53: 95 | M53: =SUM(K53,L53) -> 151
A54: Mahindra & Mahindra Financial Services | B54: NSE | C54: 6559.65 | D54: 62 | E54: 59 | F54: =SUM(D54,E54) -> 121 | H54: Mahindra & Mahindra Financial Services | I54: NSE | J54: -5847.75 | K54: 50 | L54: 108 | M54: =SUM(K54,L54) -> 158
A55: Sundaram Finance | B55: NSE | C55: 4333.15 | D55: 45 | E55: 49 | F55: =SUM(D55,E55) -> 94 | H55: Sundaram Finance | I55: NSE | J55: -5150.3 | K55: 40 | L55: 80 | M55: =SUM(K55,L55) -> 120
A56: L&T Finance | B56: NSE | C56: 391.79 | D56: 45 | E56: 62 | F56: =SUM(D56,E56) -> 107 | H56: L&T Finance | I56: NSE | J56: -528.11 | K56: 50 | L56: 71 | M56: =SUM(K56,L56) -> 121
A57: Aditya Birla Capital | B57: NSE | C57: 618.4 | D57: 50 | E57: 58 | F57: =SUM(D57,E57) -> 108 | H57: Aditya Birla Capital | I57: NSE | J57: -20.3 | K57: 52 | L57: 73 | M57: =SUM(K57,L57) -> 125
A58: Muthoot Finance | B58: NSE | C58: 934.5 | D58: 43 | E58: 48 | F58: =SUM(D58,E58) -> 91 | H58: Muthoot Finance | I58: NSE | J58: -1610.55 | K58: 47 | L58: 64 | M58: =SUM(K58,L58) -> 111
... A61: Bajaj Finance | B61: NSE | C61: -281.85 | D61: 39 | E61: 50 | F61: =SUM(D61,E61) -> 89 | H61: Bajaj Finance | I61: NSE | J61: -521.95 | K61: 46 | L61: 53 | M61: =SUM(K61,L61) -> 99
A62: TOTAL | C62: =SUM(C47:C61) -> 17499.39 | D62: =SUM(D47:D61) -> 703 | E62: =SUM(E47:E61) -> 873 | F62: =SUM(F47:F61) -> 1576 | H62: TOTAL | J62: =SUM(J47:J61) -> -17995.96 | K62: =SUM(K47:K61) -> 780 | L62: =SUM(L47:L61) -> 1128 | M62: =SUM(M47:M61) -> 1908
A64: Q4 (Quarter 4): January 1, 2026 – March 31, 2026
A65: BUY / LONG CALL SIDE | H65: SELL / SHORT CALL SIDE
A66: Company Name | B66: Segment | C66: P&L (₹) | D66: Wins | E66: Losses | F66: Total Trades | H66: Company Name | I66: Segment | J66: P&L (₹) | K66: Wins | L66: Losses | M66: Total Trades
A67: Aavas Financiers | B67: NSE | C67: 3633.85 | D67: 52 | E67: 61 | F67: =SUM(D67,E67) -> 113 | H67: Aavas Financiers | I67: NSE | J67: -1997.45 | K67: 49 | L67: 82 | M67: =SUM(K67,L67) -> 131
A68: Home First Finance Company India | B68: NSE | C68: -1085.65 | D68: 45 | E68: 77 | F68: =SUM(D68,E68) -> 122 | H68: Home First Finance Company India | I68: NSE | J68: 4796.8 | K68: 74 | L68: 80 | M68: =SUM(K68,L68) -> 154
A69: Five-Star Business Finance | B69: NSE | C69: -630.7 | D69: 43 | E69: 74 | F69: =SUM(D69,E69) -> 117 | H69: Five-Star Business Finance | I69: NSE | J69: 3753.35 | K69: 71 | L69: 92 | M69: =SUM(K69,L69) -> 163
A70: IIFL Finance | B70: NSE | C70: 206.9 | D70: 59 | E70: 87 | F70: =SUM(D70,E70) -> 146 | H70: IIFL Finance | I70: NSE | J70: 2315.05 | K70: 75 | L70: 112 | M70: =SUM(K70,L70) -> 187
A71: Manappuram Finance | B71: NSE | C71: 856.8 | D71: 58 | E71: 81 | F71: =SUM(D71,E71) -> 139 | H71: Manappuram Finance | I71: NSE | J71: -1735.55 | K71: 69 | L71: 121 | M71: =SUM(K71,L71) -> 190
A72: LIC Housing Finance | B72: NSE | C72: -1931.4 | D72: 42 | E72: 66 | F72: =SUM(D72,E72) -> 108 | H72: LIC Housing Finance | I72: NSE | J72: 3230.8 | K72: 58 | L72: 65 | M72: =SUM(K72,L72) -> 123
A73: Poonawalla Fincorp | B73: NSE | C73: -924.05 | D73: 53 | E73: 97 | F73: =SUM(D73,E73) -> 150 | H73: Poonawalla Fincorp | I73: NSE | J73: 5131.65 | K73: 72 | L73: 90 | M73: =SUM(K73,L73) -> 162
A74: Mahindra & Mahindra Financial Services | B74: NSE | C74: -2428.95 | D74: 41 | E74: 85 | F74: =SUM(D74,E74) -> 126 | H74: Mahindra & Mahindra Financial Services | I74: NSE | J74: 7056.35 | K74: 78 | L74: 86 | M74: =SUM(K74,L74) -> 164
A75: Sundaram Finance | B75: NSE | C75: 1418.6 | D75: 48 | E75: 75 | F75: =SUM(D75,E75) -> 123 | H75: Sundaram Finance | I75: NSE | J75: -4005.05 | K75: 50 | L75: 95 | M75: =SUM(K75,L75) -> 145
A76: L&T Finance | B76: NSE | C76: -3325.1 | D76: 51 | E76: 79 | F76: =SUM(D76,E76) -> 130 | H76: L&T Finance | I76: NSE | J76: 514.05 | K76: 65 | L76: 100 | M76: =SUM(K76,L76) -> 165
A77: Aditya Birla Capital | B77: NSE | C77: -1902.3 | D77: 45 | E77: 79 | F77: =SUM(D77,E77) -> 124 | H77: Aditya Birla Capital | I77: NSE | J77: 3316.45 | K77: 73 | L77: 88 | M77: =SUM(K77,L77) -> 161
A78: Muthoot Finance | B78: NSE | C78: 3441.75 | D78: 60 | E78: 64 | F78: =SUM(D78,E78) -> 124 | H78: Muthoot Finance | I78: NSE | J78: 69.2 | K78: 60 | L78: 92 | M78: =SUM(K78,L78) -> 152
... A81: Bajaj Finance | B81: NSE | C81: -1018.75 | D81: 39 | E81: 60 | F81: =SUM(D81,E81) -> 99 | H81: Bajaj Finance | I81: NSE | J81: -560.75 | K81: 53 | L81: 83 | M81: =SUM(K81,L81) -> 136
A82: TOTAL | C82: =SUM(C67:C81) -> -4696.25 | D82: =SUM(D67:D81) -> 731 | E82: =SUM(E67:E81) -> 1122 | F82: =SUM(F67:F81) -> 1853 | H82: TOTAL | J82: =SUM(J67:J81) -> 26104 | K82: =SUM(K67:K81) -> 972 | L82: =SUM(L67:L81) -> 1348 | M82: =SUM(M67:M81) -> 2320
A84: FINANCIAL YEAR SUMMARY — FY 2025–26
C85: Metric | D85: P&L (₹) | E85: Wins | F85: Losses | G85: Total Trades | H85: Win Rate %
C86: Buy Side – Full Year | D86: =SUM(C22,C42,C62,C82) -> 24400.96 | E86: =SUM(D82,D62,D42,D22) -> 2877 | F86: =SUM(E82,E62,E42,E22) -> 3919 | G86: =SUM(E86:F86) -> 6796 | H86: =E86/G86 -> 0.42333726
C87: Sell Side – Full Year | D87: =SUM(J22,J42,J62,J82) -> -17448.86 | E87: =SUM(K82,K62,K42,K22) -> 3473 | F87: =SUM(L82,L62,L42,L22) -> 4972 | G87: =SUM(E87:F87) -> 8445 | H87: =E87/G87 -> 0.41124926
C88: Combined Net P&L – FY 2025–26 | D88: =SUM(D86:D87) -> 6952.1 | E88: =SUM(E86:E87) -> 6350 | F88: =SUM(F86:F87) -> 8891 | G88: =SUM(G86:G87) -> 15241 | H88: =AVERAGE(H86,H87) -> 0.41729326
A90: 📌 Note: Green = Profit | Red = Loss | All P&L figures in Indian Rupees (₹) | Win Rate = Wins ÷ Total Trades

Sheet BB
A1: NBFC – General Sector | Backtesting Report
A2: Student: Vishv Jeet Singh Thakur | Institution: UPES | Strategy: Bollinger Bands (BB) Intraday (5-Minute) | Time: 9:15 AM – 3:00 PM | FY 2025–26
A4: Q1 (Quarter 1): April 1, 2025 – June 30, 2025
A5: BUY / LONG CALL SIDE | H5: SELL / SHORT CALL SIDE
A6: Company Name | B6: Segment | C6: P&L (₹) | D6: Wins | E6: Losses | F6: Total Trades | H6: Company Name | I6: Segment | J6: P&L (₹) | K6: Wins | L6: Losses | M6: Total Trades
A7: Aavas Financiers | B7: NSE | C7: 1755.85 | D7: 28 | E7: 38 | F7: =SUM(D7,E7) -> 66 | H7: Aavas Financiers | I7: NSE | J7: 751.3 | K7: 32 | L7: 42 | M7: =SUM(K7,L7) -> 74
A8: Home First Finance Company India | B8: NSE | C8: 1732.7 | D8: 36 | E8: 46 | F8: =SUM(D8,E8) -> 82 | H8: Home First Finance Company India | I8: NSE | J8: -3541.55 | K8: 22 | L8: 52 | M8: =SUM(K8,L8) -> 74
A9: Five-Star Business Finance | B9: NSE | C9: 1459.55 | D9: 36 | E9: 49 | F9: =SUM(D9,E9) -> 85 | H9: Five-Star Business Finance | I9: NSE | J9: 619.3 | K9: 28 | L9: 46 | M9: =SUM(K9,L9) -> 74
A10: IIFL Finance | B10: NSE | C10: 2751.4 | D10: 40 | E10: 46 | F10: =SUM(D10,E10) -> 86 | H10: IIFL Finance | I10: NSE | J10: -203.75 | K10: 36 | L10: 44 | M10: =SUM(K10,L10) -> 80
A11: Manappuram Finance | B11: NSE | C11: -1127.41 | D11: 31 | E11: 45 | F11: =SUM(D11,E11) -> 76 | H11: Manappuram Finance | I11: NSE | J11: -1306.06 | K11: 27 | L11: 38 | M11: =SUM(K11,L11) -> 65
A12: LIC Housing Finance | B12: NSE | C12: 1621.6 | D12: 32 | E12: 36 | F12: =SUM(D12,E12) -> 68 | H12: LIC Housing Finance | I12: NSE | J12: 3024.45 | K12: 35 | L12: 34 | M12: =SUM(K12,L12) -> 69
A13: Poonawalla Fincorp | B13: NSE | C13: -668.9 | D13: 35 | E13: 48 | F13: =SUM(D13,E13) -> 83 | H13: Poonawalla Fincorp | I13: NSE | J13: -2832.1 | K13: 18 | L13: 49 | M13: =SUM(K13,L13) -> 67
A14: Mahindra & Mahindra Financial Services | B14: NSE | C14: -1200.05 | D14: 29 | E14: 37 | F14: =SUM(D14,E14) -> 66 | H14: Mahindra & Mahindra Financial Services | I14: NSE | J14: 289.5 | K14: 29 | L14: 44 | M14: =SUM(K14,L14) -> 73
A15: Sundaram Finance | B15: NSE | C15: 2167.5 | D15: 34 | E15: 41 | F15: =SUM(D15,E15) -> 75 | H15: Sundaram Finance | I15: NSE | J15: -2212.25 | K15: 21 | L15: 43 | M15: =SUM(K15,L15) -> 64
A16: L&T Finance | B16: NSE | C16: 3268.17 | D16: 41 | E16: 46 | F16: =SUM(D16,E16) -> 87 | H16: L&T Finance | I16: NSE | J16: -888.8 | K16: 24 | L16: 37 | M16: =SUM(K16,L16) -> 61
A17: Aditya Birla Capital | B17: NSE | C17: 1286.28 | D17: 33 | E17: 48 | F17: =SUM(D17,E17) -> 81 | H17: Aditya Birla Capital | I17: NSE | J17: -2066.47 | K17: 28 | L17: 46 | M17: =SUM(K17,L17) -> 74
A18: Muthoot Finance | B18: NSE | C18: 2877.35 | D18: 39 | E18: 39 | F18: =SUM(D18,E18) -> 78 | H18: Muthoot Finance | I18: NSE | J18: -103.55 | K18: 28 | L18: 39 | M18: =SUM(K18,L18) -> 67
... A21: Bajaj Finance | B21: NSE | C21: 1176.9 | D21: 38 | E21: 30 | F21: =SUM(D21,E21) -> 68 | H21: Bajaj Finance | I21: NSE | J21: -1064.7 | K21: 28 | L21: 37 | M21: =SUM(K21,L21) -> 65
A22: TOTAL | C22: =SUM(C7:C21) -> 20613.69 | D22: =SUM(D7:D21) -> 522 | E22: =SUM(E7:E21) -> 631 | F22: =SUM(F7:F21) -> 1153 | H22: TOTAL | J22: =SUM(J7:J21) -> -10593.63 | K22: =SUM(K7:K21) -> 410 | L22: =SUM(L7:L21) -> 633 | M22: =SUM(M7:M21) -> 1043
A24: Q2 (Quarter 2): July 2, 2025 – September 30, 2025
A25: BUY / LONG CALL SIDE | H25: SELL / SHORT CALL SIDE
A26: Company Name | B26: Segment | C26: P&L (₹) | D26: Wins | E26: Losses | F26: Total Trades | H26: Company Name | I26: Segment | J26: P&L (₹) | K26: Wins | L26: Losses | M26: Total Trades
A27: Aavas Financiers | B27: NSE | C27: -168.2 | D27: 30 | E27: 40 | F27: =SUM(D27,E27) -> 70 | H27: Aavas Financiers | I27: NSE | J27: -106.3 | K27: 30 | L27: 46 | M27: =SUM(K27,L27) -> 76
A28: Home First Finance Company India | B28: NSE | C28: 516.1 | D28: 35 | E28: 42 | F28: =SUM(D28,E28) -> 77 | H28: Home First Finance Company India | I28: NSE | J28: 2493.9 | K28: 30 | L28: 34 | M28: =SUM(K28,L28) -> 64
A29: Five-Star Business Finance | B29: NSE | C29: 202.75 | D29: 31 | E29: 38 | F29: =SUM(D29,E29) -> 69 | H29: Five-Star Business Finance | I29: NSE | J29: 2941.45 | K29: 36 | L29: 35 | M29: =SUM(K29,L29) -> 71
A30: IIFL Finance | B30: NSE | C30: 3013.45 | D30: 34 | E30: 34 | F30: =SUM(D30,E30) -> 68 | H30: IIFL Finance | I30: NSE | J30: 2615.25 | K30: 37 | L30: 36 | M30: =SUM(K30,L30) -> 73
A31: Manappuram Finance | B31: NSE | C31: -515.95 | D31: 29 | E31: 42 | F31: =SUM(D31,E31) -> 71 | H31: Manappuram Finance | I31: NSE | J31: 1107.7 | K31: 35 | L31: 39 | M31: =SUM(K31,L31) -> 74
A32: LIC Housing Finance | B32: NSE | C32: -2147.05 | D32: 23 | E32: 43 | F32: =SUM(D32,E32) -> 66 | H32: LIC Housing Finance | I32: NSE | J32: 773.9 | K32: 35 | L32: 29 | M32: =SUM(K32,L32) -> 64
A33: Poonawalla Fincorp | B33: NSE | C33: 1863.15 | D33: 37 | E33: 43 | F33: =SUM(D33,E33) -> 80 | H33: Poonawalla Fincorp | I33: NSE | J33: 399.15 | K33: 31 | L33: 38 | M33: =SUM(K33,L33) -> 69
A34: Mahindra & Mahindra Financial Services | B34: NSE | C34: 2147.5 | D34: 35 | E34: 37 | F34: =SUM(D34,E34) -> 72 | H34: Mahindra & Mahindra Financial Services | I34: NSE | J34: -1654.1 | K34: 27 | L34: 41 | M34: =SUM(K34,L34) -> 68
A35: Sundaram Finance | B35: NSE | C35: 1007.8 | D35: 26 | E35: 28 | F35: =SUM(D35,E35) -> 54 | H35: Sundaram Finance | I35: NSE | J35: 1642.7 | K35: 30 | L35: 37 | M35: =SUM(K35,L35) -> 67
A36: L&T Finance | B36: NSE | C36: 366.94 | D36: 32 | E36: 48 | F36: =SUM(D36,E36) -> 80 | H36: L&T Finance | I36: NSE | J36: -386.24 | K36: 34 | L36: 40 | M36: =SUM(K36,L36) -> 74
A37: Aditya Birla Capital | B37: NSE | C37: 983.35 | D37: 30 | E37: 36 | F37: =SUM(D37,E37) -> 66 | H37: Aditya Birla Capital | I37: NSE | J37: -59.35 | K37: 38 | L37: 41 | M37: =SUM(K37,L37) -> 79
A38: Muthoot Finance | B38: NSE | C38: -204.35 | D38: 33 | E38: 33 | F38: =SUM(D38,E38) -> 66 | H38: Muthoot Finance | I38: NSE | J38: -1822.1 | K38: 24 | L38: 36 | M38: =SUM(K38,L38) -> 60
... A41: Bajaj Finance | B41: NSE | C41: 1656.9 | D41: 33 | E41: 30 | F41: =SUM(D41,E41) -> 63 | H41: Bajaj Finance | I41: NSE | J41: 636.2 | K41: 28 | L41: 27 | M41: =SUM(K41,L41) -> 55
A42: TOTAL | C42: =SUM(C27:C41) -> 8725.14 | D42: =SUM(D27:D41) -> 468 | E42: =SUM(E27:E41) -> 572 | F42: =SUM(F27:F41) -> 1040 | H42: TOTAL | J42: =SUM(J27:J41) -> 10736.56 | K42: =SUM(K27:K41) -> 478 | L42: =SUM(L27:L41) -> 551 | M42: =SUM(M27:M41) -> 1029
A44: Q3 (Quarter 3): October 2, 2025 – December 31, 2025
A45: BUY / LONG CALL SIDE | H45: SELL / SHORT CALL SIDE
A46: Company Name | B46: Segment | C46: P&L (₹) | D46: Wins | E46: Losses | F46: Total Trades | H46: Company Name | I46: Segment | J46: P&L (₹) | K46: Wins | L46: Losses | M46: Total Trades
A47: Aavas Financiers | B47: NSE | C47: 321.6 | D47: 25 | E47: 41 | F47: =SUM(D47,E47) -> 66 | H47: Aavas Financiers | I47: NSE | J47: 674.3 | K47: 24 | L47: 36 | M47: =SUM(K47,L47) -> 60
A48: Home First Finance Company India | B48: NSE | C48: -630.9 | D48: 28 | E48: 44 | F48: =SUM(D48,E48) -> 72 | H48: Home First Finance Company India | I48: NSE | J48: 3678.4 | K48: 31 | L48: 31 | M48: =SUM(K48,L48) -> 62
A49: Five-Star Business Finance | B49: NSE | C49: 1665.45 | D49: 33 | E49: 42 | F49: =SUM(D49,E49) -> 75 | H49: Five-Star Business Finance | I49: NSE | J49: 2693.55 | K49: 30 | L49: 32 | M49: =SUM(K49,L49) -> 62
A50: IIFL Finance | B50: NSE | C50: -435.45 | D50: 32 | E50: 51 | F50: =SUM(D50,E50) -> 83 | H50: IIFL Finance | I50: NSE | J50: -984.8 | K50: 28 | L50: 39 | M50: =SUM(K50,L50) -> 67
A51: Manappuram Finance | B51: NSE | C51: -989.55 | D51: 30 | E51: 43 | F51: =SUM(D51,E51) -> 73 | H51: Manappuram Finance | I51: NSE | J51: -613.45 | K51: 28 | L51: 35 | M51: =SUM(K51,L51) -> 63
A52: LIC Housing Finance | B52: NSE | C52: -1671.7 | D52: 21 | E52: 38 | F52: =SUM(D52,E52) -> 59 | H52: LIC Housing Finance | I52: NSE | J52: 554.5 | K52: 27 | L52: 33 | M52: =SUM(K52,L52) -> 60
A53: Poonawalla Fincorp | B53: NSE | C53: 1738.1 | D53: 33 | E53: 39 | F53: =SUM(D53,E53) -> 72 | H53: Poonawalla Fincorp | I53: NSE | J53: 2352.9 | K53: 32 | L53: 33 | M53: =SUM(K53,L53) -> 65
A54: Mahindra & Mahindra Financial Services | B54: NSE | C54: 7818.95 | D54: 47 | E54: 32 | F54: =SUM(D54,E54) -> 79 | H54: Mahindra & Mahindra Financial Services | I54: NSE | J54: 208.2 | K54: 25 | L54: 36 | M54: =SUM(K54,L54) -> 61
A55: Sundaram Finance | B55: NSE | C55: 2335.55 | D55: 27 | E55: 28 | F55: =SUM(D55,E55) -> 55 | H55: Sundaram Finance | I55: NSE | J55: -1954.45 | K55: 20 | L55: 39 | M55: =SUM(K55,L55) -> 59
A56: L&T Finance | B56: NSE | C56: 235.77 | D56: 29 | E56: 46 | F56: =SUM(D56,E56) -> 75 | H56: L&T Finance | I56: NSE | J56: -649.97 | K56: 25 | L56: 36 | M56: =SUM(K56,L56) -> 61
A57: Aditya Birla Capital | B57: NSE | C57: 271 | D57: 31 | E57: 39 | F57: =SUM(D57,E57) -> 70 | H57: Aditya Birla Capital | I57: NSE | J57: 50.6 | K57: 28 | L57: 32 | M57: =SUM(K57,L57) -> 60
A58: Muthoot Finance | B58: NSE | C58: 1029.9 | D58: 33 | E58: 40 | F58: =SUM(D58,E58) -> 73 | H58: Muthoot Finance | I58: NSE | J58: 28.65 | K58: 24 | L58: 26 | M58: =SUM(K58,L58) -> 50
... A61: Bajaj Finance | B61: NSE | C61: 1704.15 | D61: 27 | E61: 31 | F61: =SUM(D61,E61) -> 58 | H61: Bajaj Finance | I61: NSE | J61: 939.8 | K61: 31 | L61: 26 | M61: =SUM(K61,L61) -> 57
A62: TOTAL | C62: =SUM(C47:C61) -> 14762.12 | D62: =SUM(D47:D61) -> 461 | E62: =SUM(E47:E61) -> 595 | F62: =SUM(F47:F61) -> 1056 | H62: TOTAL | J62: =SUM(J47:J61) -> 3920.08 | K62: =SUM(K47:K61) -> 401 | L62: =SUM(L47:L61) -> 506 | M62: =SUM(M47:M61) -> 907
A64: Q4 (Quarter 4): January 1, 2026 – March 31, 2026
A65: BUY / LONG CALL SIDE | H65: SELL / SHORT CALL SIDE
A66: Company Name | B66: Segment | C66: P&L (₹) | D66: Wins | E66: Losses | F66: Total Trades | H66: Company Name | I66: Segment | J66: P&L (₹) | K66: Wins | L66: Losses | M66: Total Trades
A67: Aavas Financiers | B67: NSE | C67: 3034.8 | D67: 33 | E67: 30 | F67: =SUM(D67,E67) -> 63 | H67: Aavas Financiers | I67: NSE | J67: -3391.5 | K67: 20 | L67: 51 | M67: =SUM(K67,L67) -> 71
A68: Home First Finance Company India | B68: NSE | C68: -471.75 | D68: 25 | E68: 42 | F68: =SUM(D68,E68) -> 67 | H68: Home First Finance Company India | I68: NSE | J68: 2518.65 | K68: 37 | L68: 40 | M68: =SUM(K68,L68) -> 77
A69: Five-Star Business Finance | B69: NSE | C69: 1343.8 | D69: 28 | E69: 36 | F69: =SUM(D69,E69) -> 64 | H69: Five-Star Business Finance | I69: NSE | J69: 1082.4 | K69: 37 | L69: 43 | M69: =SUM(K69,L69) -> 80
A70: IIFL Finance | B70: NSE | C70: -1370 | D70: 29 | E70: 48 | F70: =SUM(D70,E70) -> 77 | H70: IIFL Finance | I70: NSE | J70: -530.3 | K70: 32 | L70: 55 | M70: =SUM(K70,L70) -> 87
A71: Manappuram Finance | B71: NSE | C71: -484.6 | D71: 30 | E71: 44 | F71: =SUM(D71,E71) -> 74 | H71: Manappuram Finance | I71: NSE | J71: 2422.95 | K71: 31 | L71: 37 | M71: =SUM(K71,L71) -> 68
A72: LIC Housing Finance | B72: NSE | C72: -1094.6 | D72: 28 | E72: 47 | F72: =SUM(D72,E72) -> 75 | H72: LIC Housing Finance | I72: NSE | J72: 448.35 | K72: 34 | L72: 40 | M72: =SUM(K72,L72) -> 74
A73: Poonawalla Fincorp | B73: NSE | C73: 1626.85 | D73: 29 | E73: 37 | F73: =SUM(D73,E73) -> 66 | H73: Poonawalla Fincorp | I73: NSE | J73: 3949.7 | K73: 36 | L73: 36 | M73: =SUM(K73,L73) -> 72
A74: Mahindra & Mahindra Financial Services | B74: NSE | C74: -1106.75 | D74: 26 | E74: 45 | F74: =SUM(D74,E74) -> 71 | H74: Mahindra & Mahindra Financial Services | I74: NSE | J74: -1106.45 | K74: 27 | L74: 52 | M74: =SUM(K74,L74) -> 79
A75: Sundaram Finance | B75: NSE | C75: 888.1 | D75: 23 | E75: 33 | F75: =SUM(D75,E75) -> 56 | H75: Sundaram Finance | I75: NSE | J75: -438.05 | K75: 26 | L75: 39 | M75: =SUM(K75,L75) -> 65
A76: L&T Finance | B76: NSE | C76: -1940.9 | D76: 24 | E76: 43 | F76: =SUM(D76,E76) -> 67 | H76: L&T Finance | I76: NSE | J76: 932.95 | K76: 33 | L76: 49 | M76: =SUM(K76,L76) -> 82
A77: Aditya Birla Capital | B77: NSE | C77: 148.95 | D77: 28 | E77: 39 | F77: =SUM(D77,E77) -> 67 | H77: Aditya Birla Capital | I77: NSE | J77: 393.2 | K77: 29 | L77: 50 | M77: =SUM(K77,L77) -> 79
A78: Muthoot Finance | B78: NSE | C78: 2394.95 | D78: 35 | E78: 32 | F78: =SUM(D78,E78) -> 67 | H78: Muthoot Finance | I78: NSE | J78: -1375.75 | K78: 25 | L78: 44 | M78: =SUM(K78,L78) -> 69
... A81: Bajaj Finance | B81: NSE | C81: 622.8 | D81: 30 | E81: 35 | F81: =SUM(D81,E81) -> 65 | H81: Bajaj Finance | I81: NSE | J81: 2408.15 | K81: 31 | L81: 33 | M81: =SUM(K81,L81) -> 64
A82: TOTAL | C82: =SUM(C67:C81) -> 1709.75 | D82: =SUM(D67:D81) -> 428 | E82: =SUM(E67:E81) -> 596 | F82: =SUM(F67:F81) -> 1024 | H82: TOTAL | J82: =SUM(J67:J81) -> 8890.65 | K82: =SUM(K67:K81) -> 462 | L82: =SUM(L67:L81) -> 650 | M82: =SUM(M67:M81) -> 1112
A84: FINANCIAL YEAR SUMMARY — FY 2025–26
C85: Metric | D85: P&L (₹) | E85: Wins | F85: Losses | G85: Total Trades | H85: Win Rate %
C86: Buy Side – Full Year | D86: =SUM(C22,C42,C62,C82) -> 45810.7 | E86: =SUM(D82,D62,D42,D22) -> 1879 | F86: =SUM(E82,E62,E42,E22) -> 2394 | G86: =SUM(E86:F86) -> 4273 | H86: =E86/G86 -> 0.43973789
C87: Sell Side – Full Year | D87: =SUM(J22,J42,J62,J82) -> 12953.66 | E87: =SUM(K82,K62,K42,K22) -> 1751 | F87: =SUM(L82,L62,L42,L22) -> 2340 | G87: =SUM(E87:F87) -> 4091 | H87: =E87/G87 -> 0.42801271
C88: Combined Net P&L – FY 2025–26 | D88: =SUM(D86:D87) -> 58764.36 | E88: =SUM(E86:E87) -> 3630 | F88: =SUM(F86:F87) -> 4734 | G88: =SUM(G86:G87) -> 8364 | H88: =AVERAGE(H86,H87) -> 0.4338753
A90: 📌 Note: Green = Profit | Red = Loss | All P&L figures in Indian Rupees (₹) | Win Rate = Wins ÷ Total Trades

Sheet AO
A1: NBFC – General Sector | Backtesting Report
A2: Student: Vishv Jeet Singh Thakur | Institution: UPES | Strategy: Awesome Oscillator (AO) Intraday (5-Minute) | Time: 9:15 AM – 3:00 PM | FY 2025–26
A4: Q1 (Quarter 1): April 1, 2025 – June 30, 2025
A5: BUY / LONG CALL SIDE | H5: SELL / SHORT CALL SIDE
A6: Company Name | B6: Segment | C6: P&L (₹) | D6: Wins | E6: Losses | F6: Total Trades | H6: Company Name | I6: Segment | J6: P&L (₹) | K6: Wins | L6: Losses | M6: Total Trades
A7: Aavas Financiers | B7: NSE | C7: 1677.55 | D7: 28 | E7: 33 | F7: =SUM(D7,E7) -> 61 | H7: Aavas Financiers | I7: NSE | J7: 1357.35 | K7: 30 | L7: 34 | M7: =SUM(K7,L7) -> 64
A8: Home First Finance Company India | B8: NSE | C8: 2181 | D8: 33 | E8: 36 | F8: =SUM(D8,E8) -> 69 | H8: Home First Finance Company India | I8: NSE | J8: -2502.85 | K8: 22 | L8: 43 | M8: =SUM(K8,L8) -> 65
A9: Five-Star Business Finance | B9: NSE | C9: 1613.95 | D9: 31 | E9: 34 | F9: =SUM(D9,E9) -> 65 | H9: Five-Star Business Finance | I9: NSE | J9: -2432.45 | K9: 21 | L9: 53 | M9: =SUM(K9,L9) -> 74
A10: IIFL Finance | B10: NSE | C10: -508.9 | D10: 27 | E10: 46 | F10: =SUM(D10,E10) -> 73 | H10: IIFL Finance | I10: NSE | J10: 1132.8 | K10: 37 | L10: 34 | M10: =SUM(K10,L10) -> 71
A11: Manappuram Finance | B11: NSE | C11: 1256.31 | D11: 31 | E11: 39 | F11: =SUM(D11,E11) -> 70 | H11: Manappuram Finance | I11: NSE | J11: -1329.52 | K11: 29 | L11: 39 | M11: =SUM(K11,L11) -> 68
A12: LIC Housing Finance | B12: NSE | C12: 1916.95 | D12: 32 | E12: 31 | F12: =SUM(D12,E12) -> 63 | H12: LIC Housing Finance | I12: NSE | J12: 926.5 | K12: 29 | L12: 33 | M12: =SUM(K12,L12) -> 62
A13: Poonawalla Fincorp | B13: NSE | C13: -2812.7 | D13: 23 | E13: 47 | F13: =SUM(D13,E13) -> 70 | H13: Poonawalla Fincorp | I13: NSE | J13: -1461.4 | K13: 23 | L13: 45 | M13: =SUM(K13,L13) -> 68
A14: Mahindra & Mahindra Financial Services | B14: NSE | C14: 755.25 | D14: 29 | E14: 34 | F14: =SUM(D14,E14) -> 63 | H14: Mahindra & Mahindra Financial Services | I14: NSE | J14: -454.1 | K14: 31 | L14: 38 | M14: =SUM(K14,L14) -> 69
A15: Sundaram Finance | B15: NSE | C15: 1724.6 | D15: 30 | E15: 35 | F15: =SUM(D15,E15) -> 65 | H15: Sundaram Finance | I15: NSE | J15: -1195.05 | K15: 28 | L15: 42 | M15: =SUM(K15,L15) -> 70
A16: L&T Finance | B16: NSE | C16: 2194.05 | D16: 30 | E16: 31 | F16: =SUM(D16,E16) -> 61 | H16: L&T Finance | I16: NSE | J16: 290.56 | K16: 30 | L16: 37 | M16: =SUM(K16,L16) -> 67
A17: Aditya Birla Capital | B17: NSE | C17: 1798.27 | D17: 31 | E17: 38 | F17: =SUM(D17,E17) -> 69 | H17: Aditya Birla Capital | I17: NSE | J17: -986 | K17: 28 | L17: 38 | M17: =SUM(K17,L17) -> 66
A18: Muthoot Finance | B18: NSE | C18: 3135.25 | D18: 37 | E18: 20 | F18: =SUM(D18,E18) -> 57 | H18: Muthoot Finance | I18: NSE | J18: -1272.65 | K18: 28 | L18: 37 | M18: =SUM(K18,L18) -> 65
... A21: Bajaj Finance | B21: NSE | C21: 1618.95 | D21: 33 | E21: 22 | F21: =SUM(D21,E21) -> 55 | H21: Bajaj Finance | I21: NSE | J21: -396 | K21: 27 | L21: 30 | M21: =SUM(K21,L21) -> 57
A22: TOTAL | C22: =SUM(C7:C21) -> 18142.83 | D22: =SUM(D7:D21) -> 459 | E22: =SUM(E7:E21) -> 513 | F22: =SUM(F7:F21) -> 972 | H22: TOTAL | J22: =SUM(J7:J21) -> -9698.71 | K22: =SUM(K7:K21) -> 414 | L22: =SUM(L7:L21) -> 582 | M22: =SUM(M7:M21) -> 996
A24: Q2 (Quarter 2): July 2, 2025 – September 30, 2025
A25: BUY / LONG CALL SIDE | H25: SELL / SHORT CALL SIDE
A26: Company Name | B26: Segment | C26: P&L (₹) | D26: Wins | E26: Losses | F26: Total Trades | H26: Company Name | I26: Segment | J26: P&L (₹) | K26: Wins | L26: Losses | M26: Total Trades
A27: Aavas Financiers | B27: NSE | C27: 1005.85 | D27: 32 | E27: 36 | F27: =SUM(D27,E27) -> 68 | H27: Aavas Financiers | I27: NSE | J27: 2684.65 | K27: 32 | L27: 28 | M27: =SUM(K27,L27) -> 60
A28: Home First Finance Company India | B28: NSE | C28: -777.2 | D28: 30 | E28: 38 | F28: =SUM(D28,E28) -> 68 | H28: Home First Finance Company India | I28: NSE | J28: 109.4 | K28: 25 | L28: 36 | M28: =SUM(K28,L28) -> 61
A29: Five-Star Business Finance | B29: NSE | C29: -1684.95 | D29: 29 | E29: 48 | F29: =SUM(D29,E29) -> 77 | H29: Five-Star Business Finance | I29: NSE | J29: 1536.8 | K29: 38 | L29: 40 | M29: =SUM(K29,L29) -> 78
A30: IIFL Finance | B30: NSE | C30: -226.35 | D30: 29 | E30: 40 | F30: =SUM(D30,E30) -> 69 | H30: IIFL Finance | I30: NSE | J30: 1668.05 | K30: 33 | L30: 37 | M30: =SUM(K30,L30) -> 70
A31: Manappuram Finance | B31: NSE | C31: -3222 | D31: 27 | E31: 52 | F31: =SUM(D31,E31) -> 79 | H31: Manappuram Finance | I31: NSE | J31: 2918.35 | K31: 33 | L31: 32 | M31: =SUM(K31,L31) -> 65
A32: LIC Housing Finance | B32: NSE | C32: -3199.35 | D32: 22 | E32: 41 | F32: =SUM(D32,E32) -> 63 | H32: LIC Housing Finance | I32: NSE | J32: 2486.95 | K32: 40 | L32: 22 | M32: =SUM(K32,L32) -> 62
A33: Poonawalla Fincorp | B33: NSE | C33: 977.65 | D33: 30 | E33: 39 | F33: =SUM(D33,E33) -> 69 | H33: Poonawalla Fincorp | I33: NSE | J33: 1533.95 | K33: 33 | L33: 27 | M33: =SUM(K33,L33) -> 60
A34: Mahindra & Mahindra Financial Services | B34: NSE | C34: 2127.15 | D34: 31 | E34: 33 | F34: =SUM(D34,E34) -> 64 | H34: Mahindra & Mahindra Financial Services | I34: NSE | J34: -955.8 | K34: 27 | L34: 38 | M34: =SUM(K34,L34) -> 65
A35: Sundaram Finance | B35: NSE | C35: -1142.35 | D35: 28 | E35: 38 | F35: =SUM(D35,E35) -> 66 | H35: Sundaram Finance | I35: NSE | J35: 3041.3 | K35: 35 | L35: 28 | M35: =SUM(K35,L35) -> 63
A36: L&T Finance | B36: NSE | C36: 548.48 | D36: 30 | E36: 42 | F36: =SUM(D36,E36) -> 72 | H36: L&T Finance | I36: NSE | J36: -493.65 | K36: 33 | L36: 37 | M36: =SUM(K36,L36) -> 70
A37: Aditya Birla Capital | B37: NSE | C37: -2292.15 | D37: 27 | E37: 45 | F37: =SUM(D37,E37) -> 72 | H37: Aditya Birla Capital | I37: NSE | J37: 2280.9 | K37: 35 | L37: 32 | M37: =SUM(K37,L37) -> 67
A38: Muthoot Finance | B38: NSE | C38: 1166.85 | D38: 38 | E38: 33 | F38: =SUM(D38,E38) -> 71 | H38: Muthoot Finance | I38: NSE | J38: 882.35 | K38: 34 | L38: 32 | M38: =SUM(K38,L38) -> 66
... A41: Bajaj Finance | B41: NSE | C41: -50.5 | D41: 33 | E41: 33 | F41: =SUM(D41,E41) -> 66 | H41: Bajaj Finance | I41: NSE | J41: -1214.7 | K41: 28 | L41: 38 | M41: =SUM(K41,L41) -> 66
A42: TOTAL | C42: =SUM(C27:C41) -> -7706.82 | D42: =SUM(D27:D41) -> 445 | E42: =SUM(E27:E41) -> 593 | F42: =SUM(F27:F41) -> 1038 | H42: TOTAL | J42: =SUM(J27:J41) -> 18164.3 | K42: =SUM(K27:K41) -> 486 | L42: =SUM(L27:L41) -> 497 | M42: =SUM(M27:M41) -> 983
A44: Q3 (Quarter 3): October 2, 2025 – December 31, 2025
A45: BUY / LONG CALL SIDE | H45: SELL / SHORT CALL SIDE
A46: Company Name | B46: Segment | C46: P&L (₹) | D46: Wins | E46: Losses | F46: Total Trades | H46: Company Name | I46: Segment | J46: P&L (₹) | K46: Wins | L46: Losses | M46: Total Trades
A47: Aavas Financiers | B47: NSE | C47: -248.1 | D47: 27 | E47: 37 | F47: =SUM(D47,E47) -> 64 | H47: Aavas Financiers | I47: NSE | J47: 610.35 | K47: 28 | L47: 35 | M47: =SUM(K47,L47) -> 63
A48: Home First Finance Company India | B48: NSE | C48: -3664.75 | D48: 16 | E48: 49 | F48: =SUM(D48,E48) -> 65 | H48: Home First Finance Company India | I48: NSE | J48: 2519.9 | K48: 36 | L48: 31 | M48: =SUM(K48,L48) -> 67
A49: Five-Star Business Finance | B49: NSE | C49: 3322.9 | D49: 35 | E49: 26 | F49: =SUM(D49,E49) -> 61 | H49: Five-Star Business Finance | I49: NSE | J49: -741.95 | K49: 26 | L49: 37 | M49: =SUM(K49,L49) -> 63
A50: IIFL Finance | B50: NSE | C50: -1180.65 | D50: 24 | E50: 42 | F50: =SUM(D50,E50) -> 66 | H50: IIFL Finance | I50: NSE | J50: 721.2 | K50: 33 | L50: 37 | M50: =SUM(K50,L50) -> 70
A51: Manappuram Finance | B51: NSE | C51: 452.65 | D51: 29 | E51: 34 | F51: =SUM(D51,E51) -> 63 | H51: Manappuram Finance | I51: NSE | J51: 369.4 | K51: 31 | L51: 40 | M51: =SUM(K51,L51) -> 71
A52: LIC Housing Finance | B52: NSE | C52: 123.25 | D52: 30 | E52: 32 | F52: =SUM(D52,E52) -> 62 | H52: LIC Housing Finance | I52: NSE | J52: 752.05 | K52: 33 | L52: 31 | M52: =SUM(K52,L52) -> 64
A53: Poonawalla Fincorp | B53: NSE | C53: 566.4 | D53: 29 | E53: 35 | F53: =SUM(D53,E53) -> 64 | H53: Poonawalla Fincorp | I53: NSE | J53: 3300.45 | K53: 33 | L53: 31 | M53: =SUM(K53,L53) -> 64
A54: Mahindra & Mahindra Financial Services | B54: NSE | C54: 2300.05 | D54: 31 | E54: 36 | F54: =SUM(D54,E54) -> 67 | H54: Mahindra & Mahindra Financial Services | I54: NSE | J54: -717.75 | K54: 25 | L54: 41 | M54: =SUM(K54,L54) -> 66
A55: Sundaram Finance | B55: NSE | C55: 2969.35 | D55: 32 | E55: 36 | F55: =SUM(D55,E55) -> 68 | H55: Sundaram Finance | I55: NSE | J55: -3707.85 | K55: 23 | L55: 47 | M55: =SUM(K55,L55) -> 70
A56: L&T Finance | B56: NSE | C56: -751.83 | D56: 28 | E56: 42 | F56: =SUM(D56,E56) -> 70 | H56: L&T Finance | I56: NSE | J56: 618.11 | K56: 32 | L56: 30 | M56: =SUM(K56,L56) -> 62
A57: Aditya Birla Capital | B57: NSE | C57: -2001.35 | D57: 28 | E57: 44 | F57: =SUM(D57,E57) -> 72 | H57: Aditya Birla Capital | I57: NSE | J57: -425.35 | K57: 29 | L57: 39 | M57: =SUM(K57,L57) -> 68
A58: Muthoot Finance | B58: NSE | C58: 2646.5 | D58: 33 | E58: 28 | F58: =SUM(D58,E58) -> 61 | H58: Muthoot Finance | I58: NSE | J58: -226.85 | K58: 25 | L58: 36 | M58: =SUM(K58,L58) -> 61
... A61: Bajaj Finance | B61: NSE | C61: 30.5 | D61: 26 | E61: 30 | F61: =SUM(D61,E61) -> 56 | H61: Bajaj Finance | I61: NSE | J61: 1681.6 | K61: 31 | L61: 29 | M61: =SUM(K61,L61) -> 60
A62: TOTAL | C62: =SUM(C47:C61) -> 6196.77 | D62: =SUM(D47:D61) -> 424 | E62: =SUM(E47:E61) -> 535 | F62: =SUM(F47:F61) -> 959 | H62: TOTAL | J62: =SUM(J47:J61) -> 4080.16 | K62: =SUM(K47:K61) -> 441 | L62: =SUM(L47:L61) -> 532 | M62: =SUM(M47:M61) -> 973
A64: Q4 (Quarter 4): January 1, 2026 – March 31, 2026
A65: BUY / LONG CALL SIDE | H65: SELL / SHORT CALL SIDE
A66: Company Name | B66: Segment | C66: P&L (₹) | D66: Wins | E66: Losses | F66: Total Trades | H66: Company Name | I66: Segment | J66: P&L (₹) | K66: Wins | L66: Losses | M66: Total Trades
A67: Aavas Financiers | B67: NSE | C67: 2660.35 | D67: 31 | E67: 29 | F67: =SUM(D67,E67) -> 60 | H67: Aavas Financiers | I67: NSE | J67: -2411.35 | K67: 27 | L67: 38 | M67: =SUM(K67,L67) -> 65
A68: Home First Finance Company India | B68: NSE | C68: -224.05 | D68: 21 | E68: 40 | F68: =SUM(D68,E68) -> 61 | H68: Home First Finance Company India | I68: NSE | J68: -2937.4 | K68: 25 | L68: 44 | M68: =SUM(K68,L68) -> 69
A69: Five-Star Business Finance | B69: NSE | C69: -74.65 | D69: 23 | E69: 36 | F69: =SUM(D69,E69) -> 59 | H69: Five-Star Business Finance | I69: NSE | J69: 3714.3 | K69: 34 | L69: 25 | M69: =SUM(K69,L69) -> 59
A70: IIFL Finance | B70: NSE | C70: -344.35 | D70: 29 | E70: 39 | F70: =SUM(D70,E70) -> 68 | H70: IIFL Finance | I70: NSE | J70: 1394 | K70: 31 | L70: 34 | M70: =SUM(K70,L70) -> 65
A71: Manappuram Finance | B71: NSE | C71: 301.75 | D71: 33 | E71: 45 | F71: =SUM(D71,E71) -> 78 | H71: Manappuram Finance | I71: NSE | J71: 1510.25 | K71: 35 | L71: 50 | M71: =SUM(K71,L71) -> 85
A72: LIC Housing Finance | B72: NSE | C72: -690.55 | D72: 31 | E72: 40 | F72: =SUM(D72,E72) -> 71 | H72: LIC Housing Finance | I72: NSE | J72: 768.25 | K72: 32 | L72: 35 | M72: =SUM(K72,L72) -> 67
A73: Poonawalla Fincorp | B73: NSE | C73: -1655.85 | D73: 26 | E73: 49 | F73: =SUM(D73,E73) -> 75 | H73: Poonawalla Fincorp | I73: NSE | J73: 2099.75 | K73: 32 | L73: 39 | M73: =SUM(K73,L73) -> 71
A74: Mahindra & Mahindra Financial Services | B74: NSE | C74: -2976.95 | D74: 23 | E74: 46 | F74: =SUM(D74,E74) -> 69 | H74: Mahindra & Mahindra Financial Services | I74: NSE | J74: -44.25 | K74: 29 | L74: 40 | M74: =SUM(K74,L74) -> 69
A75: Sundaram Finance | B75: NSE | C75: 1537.95 | D75: 26 | E75: 40 | F75: =SUM(D75,E75) -> 66 | H75: Sundaram Finance | I75: NSE | J75: -2254.25 | K75: 24 | L75: 43 | M75: =SUM(K75,L75) -> 67
A76: L&T Finance | B76: NSE | C76: 258.55 | D76: 32 | E76: 36 | F76: =SUM(D76,E76) -> 68 | H76: L&T Finance | I76: NSE | J76: -203.15 | K76: 26 | L76: 48 | M76: =SUM(K76,L76) -> 74
A77: Aditya Birla Capital | B77: NSE | C77: -946.15 | D77: 30 | E77: 43 | F77: =SUM(D77,E77) -> 73 | H77: Aditya Birla Capital | I77: NSE | J77: 423.35 | K77: 31 | L77: 46 | M77: =SUM(K77,L77) -> 77
A78: Muthoot Finance | B78: NSE | C78: 5004.2 | D78: 41 | E78: 23 | F78: =SUM(D78,E78) -> 64 | H78: Muthoot Finance | I78: NSE | J78: 180.8 | K78: 25 | L78: 39 | M78: =SUM(K78,L78) -> 64
... A81: Bajaj Finance | B81: NSE | C81: 449 | D81: 27 | E81: 32 | F81: =SUM(D81,E81) -> 59 | H81: Bajaj Finance | I81: NSE | J81: 1209.5 | K81: 31 | L81: 37 | M81: =SUM(K81,L81) -> 68
A82: TOTAL | C82: =SUM(C67:C81) -> 2799.85 | D82: =SUM(D67:D81) -> 422 | E82: =SUM(E67:E81) -> 569 | F82: =SUM(F67:F81) -> 991 | H82: TOTAL | J82: =SUM(J67:J81) -> 3695.55 | K82: =SUM(K67:K81) -> 434 | L82: =SUM(L67:L81) -> 591 | M82: =SUM(M67:M81) -> 1025
A84: FINANCIAL YEAR SUMMARY — FY 2025–26
C85: Metric | D85: P&L (₹) | E85: Wins | F85: Losses | G85: Total Trades | H85: Win Rate %
C86: Buy Side – Full Year | D86: =SUM(C22,C42,C62,C82) -> 19432.63 | E86: =SUM(D82,D62,D42,D22) -> 1750 | F86: =SUM(E82,E62,E42,E22) -> 2210 | G86: =SUM(E86:F86) -> 3960 | H86: =E86/G86 -> 0.44191919
C87: Sell Side – Full Year | D87: =SUM(J22,J42,J62,J82) -> 16241.3 | E87: =SUM(K82,K62,K42,K22) -> 1775 | F87: =SUM(L82,L62,L42,L22) -> 2202 | G87: =SUM(E87:F87) -> 3977 | H87: =E87/G87 -> 0.44631632
C88: Combined Net P&L – FY 2025–26 | D88: =SUM(D86:D87) -> 35673.93 | E88: =SUM(E86:E87) -> 3525 | F88: =SUM(F86:F87) -> 4412 | G88: =SUM(G86:G87) -> 7937 | H88: =AVERAGE(H86,H87) -> 0.44411776
A90: 📌 Note: Green = Profit | Red = Loss | All P&L figures in Indian Rupees (₹) | Win Rate = Wins ÷ Total Trades

Sheet PPS
A1: NBFC – General Sector | Backtesting Report
A2: Student: Vishv Jeet Singh Thakur | Institution: UPES | Strategy: Pivort Point Strandard (PPS) Intraday (5-Minute) | Time: 9:15 AM – 3:00 PM | FY 2025–26
A4: Q1 (Quarter 1): April 1, 2025 – June 30, 2025
A5: BUY / LONG CALL SIDE | H5: SELL / SHORT CALL SIDE
A6: Company Name | B6: Segment | C6: P&L (₹) | D6: Wins | E6: Losses | F6: Total Trades | H6: Company Name | I6: Segment | J6: P&L (₹) | K6: Wins | L6: Losses | M6: Total Trades
A7: Aavas Financiers | B7: NSE | C7: 1228.7 | D7: 9 | E7: 11 | F7: =SUM(D7,E7) -> 20 | H7: Aavas Financiers | I7: NSE | J7: -722.1 | K7: 8 | L7: 18 | M7: =SUM(K7,L7) -> 26
A8: Home First Finance Company India | B8: NSE | C8: -231.55 | D8: 11 | E8: 19 | F8: =SUM(D8,E8) -> 30 | H8: Home First Finance Company India | I8: NSE | J8: -893.5 | K8: 8 | L8: 22 | M8: =SUM(K8,L8) -> 30
A9: Five-Star Business Finance | B9: NSE | C9: 1863.7 | D9: 13 | E9: 13 | F9: =SUM(D9,E9) -> 26 | H9: Five-Star Business Finance | I9: NSE | J9: -1509.2 | K9: 8 | L9: 20 | M9: =SUM(K9,L9) -> 28
A10: IIFL Finance | B10: NSE | C10: -314 | D10: 11 | E10: 19 | F10: =SUM(D10,E10) -> 30 | H10: IIFL Finance | I10: NSE | J10: 224.65 | K10: 17 | L10: 18 | M10: =SUM(K10,L10) -> 35
A11: Manappuram Finance | B11: NSE | C11: -728.58 | D11: 12 | E11: 22 | F11: =SUM(D11,E11) -> 34 | H11: Manappuram Finance | I11: NSE | J11: -2088.66 | K11: 11 | L11: 28 | M11: =SUM(K11,L11) -> 39
A12: LIC Housing Finance | B12: NSE | C12: -697.4 | D12: 13 | E12: 22 | F12: =SUM(D12,E12) -> 35 | H12: LIC Housing Finance | I12: NSE | J12: 641.7 | K12: 16 | L12: 16 | M12: =SUM(K12,L12) -> 32
A13: Poonawalla Fincorp | B13: NSE | C13: 714.7 | D13: 12 | E13: 16 | F13: =SUM(D13,E13) -> 28 | H13: Poonawalla Fincorp | I13: NSE | J13: -1903.05 | K13: 13 | L13: 28 | M13: =SUM(K13,L13) -> 41
A14: Mahindra & Mahindra Financial Services | B14: NSE | C14: 628.15 | D14: 12 | E14: 14 | F14: =SUM(D14,E14) -> 26 | H14: Mahindra & Mahindra Financial Services | I14: NSE | J14: 683.3 | K14: 14 | L14: 14 | M14: =SUM(K14,L14) -> 28
A15: Sundaram Finance | B15: NSE | C15: 1039.05 | D15: 10 | E15: 10 | F15: =SUM(D15,E15) -> 20 | H15: Sundaram Finance | I15: NSE | J15: -1176.9 | K15: 8 | L15: 18 | M15: =SUM(K15,L15) -> 26
A16: L&T Finance | B16: NSE | C16: 1656.5 | D16: 16 | E16: 17 | F16: =SUM(D16,E16) -> 33 | H16: L&T Finance | I16: NSE | J16: -1302.19 | K16: 12 | L16: 26 | M16: =SUM(K16,L16) -> 38
A17: Aditya Birla Capital | B17: NSE | C17: -53 | D17: 16 | E17: 29 | F17: =SUM(D17,E17) -> 45 | H17: Aditya Birla Capital | I17: NSE | J17: -126.92 | K17: 17 | L17: 27 | M17: =SUM(K17,L17) -> 44
A18: Muthoot Finance | B18: NSE | C18: 983.8 | D18: 14 | E18: 14 | F18: =SUM(D18,E18) -> 28 | H18: Muthoot Finance | I18: NSE | J18: -2504.95 | K18: 8 | L18: 25 | M18: =SUM(K18,L18) -> 33
... A21: Bajaj Finance | B21: NSE | C21: -281.4 | D21: 10 | E21: 14 | F21: =SUM(D21,E21) -> 24 | H21: Bajaj Finance | I21: NSE | J21: 793.95 | K21: 15 | L21: 13 | M21: =SUM(K21,L21) -> 28
A22: TOTAL | C22: =SUM(C7:C21) -> 9168.52 | D22: =SUM(D7:D21) -> 190 | E22: =SUM(E7:E21) -> 247 | F22: =SUM(F7:F21) -> 437 | H22: TOTAL | J22: =SUM(J7:J21) -> -9753.67 | K22: =SUM(K7:K21) -> 181 | L22: =SUM(L7:L21) -> 316 | M22: =SUM(M7:M21) -> 497
A24: Q2 (Quarter 2): July 2, 2025 – September 30, 2025
A25: BUY / LONG CALL SIDE | H25: SELL / SHORT CALL SIDE
A26: Company Name | B26: Segment | C26: P&L (₹) | D26: Wins | E26: Losses | F26: Total Trades | H26: Company Name | I26: Segment | J26: P&L (₹) | K26: Wins | L26: Losses | M26: Total Trades
A27: Aavas Financiers | B27: NSE | C27: -1399.75 | D27: 7 | E27: 17 | F27: =SUM(D27,E27) -> 24 | H27: Aavas Financiers | I27: NSE | J27: -1889.15 | K27: 8 | L27: 19 | M27: =SUM(K27,L27) -> 27
A28: Home First Finance Company India | B28: NSE | C28: -1596.75 | D28: 10 | E28: 24 | F28: =SUM(D28,E28) -> 34 | H28: Home First Finance Company India | I28: NSE | J28: 289.9 | K28: 15 | L28: 22 | M28: =SUM(K28,L28) -> 37
A29: Five-Star Business Finance | B29: NSE | C29: -1981.7 | D29: 6 | E29: 20 | F29: =SUM(D29,E29) -> 26 | H29: Five-Star Business Finance | I29: NSE | J29: 1064.3 | K29: 12 | L29: 13 | M29: =SUM(K29,L29) -> 25
A30: IIFL Finance | B30: NSE | C30: 283.1 | D30: 11 | E30: 20 | F30: =SUM(D30,E30) -> 31 | H30: IIFL Finance | I30: NSE | J30: -2488.15 | K30: 12 | L30: 29 | M30: =SUM(K30,L30) -> 41
A31: Manappuram Finance | B31: NSE | C31: 1313.55 | D31: 13 | E31: 11 | F31: =SUM(D31,E31) -> 24 | H31: Manappuram Finance | I31: NSE | J31: -444.8 | K31: 11 | L31: 20 | M31: =SUM(K31,L31) -> 31
A32: LIC Housing Finance | B32: NSE | C32: -721.45 | D32: 9 | E32: 16 | F32: =SUM(D32,E32) -> 25 | H32: LIC Housing Finance | I32: NSE | J32: 1347.65 | K32: 19 | L32: 15 | M32: =SUM(K32,L32) -> 34
A33: Poonawalla Fincorp | B33: NSE | C33: 24.2 | D33: 13 | E33: 17 | F33: =SUM(D33,E33) -> 30 | H33: Poonawalla Fincorp | I33: NSE | J33: -1131.05 | K33: 12 | L33: 22 | M33: =SUM(K33,L33) -> 34
A34: Mahindra & Mahindra Financial Services | B34: NSE | C34: 829.9 | D34: 14 | E34: 12 | F34: =SUM(D34,E34) -> 26 | H34: Mahindra & Mahindra Financial Services | I34: NSE | J34: -1398.25 | K34: 11 | L34: 21 | M34: =SUM(K34,L34) -> 32
A35: Sundaram Finance | B35: NSE | C35: -101.1 | D35: 10 | E35: 14 | F35: =SUM(D35,E35) -> 24 | H35: Sundaram Finance | I35: NSE | J35: -323.65 | K35: 11 | L35: 20 | M35: =SUM(K35,L35) -> 31
A36: L&T Finance | B36: NSE | C36: 733.76 | D36: 17 | E36: 19 | F36: =SUM(D36,E36) -> 36 | H36: L&T Finance | I36: NSE | J36: -2266.12 | K36: 15 | L36: 31 | M36: =SUM(K36,L36) -> 46
A37: Aditya Birla Capital | B37: NSE | C37: 49.35 | D37: 10 | E37: 17 | F37: =SUM(D37,E37) -> 27 | H37: Aditya Birla Capital | I37: NSE | J37: 1747.35 | K37: 14 | L37: 16 | M37: =SUM(K37,L37) -> 30
A38: Muthoot Finance | B38: NSE | C38: 213.9 | D38: 11 | E38: 16 | F38: =SUM(D38,E38) -> 27 | H38: Muthoot Finance | I38: NSE | J38: -407.75 | K38: 14 | L38: 18 | M38: =SUM(K38,L38) -> 32
... A41: Bajaj Finance | B41: NSE | C41: 474.9 | D41: 12 | E41: 14 | F41: =SUM(D41,E41) -> 26 | H41: Bajaj Finance | I41: NSE | J41: -1409.6 | K41: 11 | L41: 22 | M41: =SUM(K41,L41) -> 33
A42: TOTAL | C42: =SUM(C27:C41) -> -1804.04 | D42: =SUM(D27:D41) -> 166 | E42: =SUM(E27:E41) -> 245 | F42: =SUM(F27:F41) -> 411 | H42: TOTAL | J42: =SUM(J27:J41) -> -6368.97 | K42: =SUM(K27:K41) -> 192 | L42: =SUM(L27:L41) -> 296 | M42: =SUM(M27:M41) -> 488
A44: Q3 (Quarter 3): October 2, 2025 – December 31, 2025
A45: BUY / LONG CALL SIDE | H45: SELL / SHORT CALL SIDE
A46: Company Name | B46: Segment | C46: P&L (₹) | D46: Wins | E46: Losses | F46: Total Trades | H46: Company Name | I46: Segment | J46: P&L (₹) | K46: Wins | L46: Losses | M46: Total Trades
A47: Aavas Financiers | B47: NSE | C47: 1503.65 | D47: 11 | E47: 10 | F47: =SUM(D47,E47) -> 21 | H47: Aavas Financiers | I47: NSE | J47: -1575.3 | K47: 7 | L47: 19 | M47: =SUM(K47,L47) -> 26
A48: Home First Finance Company India | B48: NSE | C48: 1038.4 | D48: 7 | E48: 9 | F48: =SUM(D48,E48) -> 16 | H48: Home First Finance Company India | I48: NSE | J48: -238.7 | K48: 7 | L48: 13 | M48: =SUM(K48,L48) -> 20
A49: Five-Star Business Finance | B49: NSE | C49: -7.85 | D49: 9 | E49: 20 | F49: =SUM(D49,E49) -> 29 | H49: Five-Star Business Finance | I49: NSE | J49: 248.65 | K49: 12 | L49: 18 | M49: =SUM(K49,L49) -> 30
A50: IIFL Finance | B50: NSE | C50: 2240.85 | D50: 19 | E50: 12 | F50: =SUM(D50,E50) -> 31 | H50: IIFL Finance | I50: NSE | J50: -2209.5 | K50: 14 | L50: 30 | M50: =SUM(K50,L50) -> 44
A51: Manappuram Finance | B51: NSE | C51: 950.05 | D51: 11 | E51: 12 | F51: =SUM(D51,E51) -> 23 | H51: Manappuram Finance | I51: NSE | J51: 2453.25 | K51: 16 | L51: 10 | M51: =SUM(K51,L51) -> 26
A52: LIC Housing Finance | B52: NSE | C52: -925.7 | D52: 9 | E52: 14 | F52: =SUM(D52,E52) -> 23 | H52: LIC Housing Finance | I52: NSE | J52: 343.9 | K52: 17 | L52: 12 | M52: =SUM(K52,L52) -> 29
A53: Poonawalla Fincorp | B53: NSE | C53: 876.85 | D53: 11 | E53: 11 | F53: =SUM(D53,E53) -> 22 | H53: Poonawalla Fincorp | I53: NSE | J53: 973.8 | K53: 14 | L53: 15 | M53: =SUM(K53,L53) -> 29
A54: Mahindra & Mahindra Financial Services | B54: NSE | C54: 2995.2 | D54: 19 | E54: 17 | F54: =SUM(D54,E54) -> 36 | H54: Mahindra & Mahindra Financial Services | I54: NSE | J54: -684.45 | K54: 16 | L54: 23 | M54: =SUM(K54,L54) -> 39
A55: Sundaram Finance | B55: NSE | C55: 97.6 | D55: 12 | E55: 16 | F55: =SUM(D55,E55) -> 28 | H55: Sundaram Finance | I55: NSE | J55: -605.8 | K55: 12 | L55: 23 | M55: =SUM(K55,L55) -> 35
A56: L&T Finance | B56: NSE | C56: 705.46 | D56: 14 | E56: 16 | F56: =SUM(D56,E56) -> 30 | H56: L&T Finance | I56: NSE | J56: 1234.55 | K56: 17 | L56: 15 | M56: =SUM(K56,L56) -> 32
A57: Aditya Birla Capital | B57: NSE | C57: 3213.95 | D57: 19 | E57: 10 | F57: =SUM(D57,E57) -> 29 | H57: Aditya Birla Capital | I57: NSE | J57: -1018.7 | K57: 13 | L57: 27 | M57: =SUM(K57,L57) -> 40
A58: Muthoot Finance | B58: NSE | C58: 243.05 | D58: 15 | E58: 15 | F58: =SUM(D58,E58) -> 30 | H58: Muthoot Finance | I58: NSE | J58: -891.45 | K58: 13 | L58: 21 | M58: =SUM(K58,L58) -> 34
... A61: Bajaj Finance | B61: NSE | C61: 1399.25 | D61: 13 | E61: 14 | F61: =SUM(D61,E61) -> 27 | H61: Bajaj Finance | I61: NSE | J61: 511.65 | K61: 15 | L61: 16 | M61: =SUM(K61,L61) -> 31
A62: TOTAL | C62: =SUM(C47:C61) -> 16372.96 | D62: =SUM(D47:D61) -> 196 | E62: =SUM(E47:E61) -> 206 | F62: =SUM(F47:F61) -> 402 | H62: TOTAL | J62: =SUM(J47:J61) -> -3129.9 | K62: =SUM(K47:K61) -> 196 | L62: =SUM(L47:L61) -> 285 | M62: =SUM(M47:M61) -> 481
A64: Q4 (Quarter 4): January 1, 2026 – March 31, 2026
A65: BUY / LONG CALL SIDE | H65: SELL / SHORT CALL SIDE
A66: Company Name | B66: Segment | C66: P&L (₹) | D66: Wins | E66: Losses | F66: Total Trades | H66: Company Name | I66: Segment | J66: P&L (₹) | K66: Wins | L66: Losses | M66: Total Trades
A67: Aavas Financiers | B67: NSE | C67: -140.3 | D67: 4 | E67: 10 | F67: =SUM(D67,E67) -> 14 | H67: Aavas Financiers | I67: NSE | J67: -364.35 | K67: 9 | L67: 7 | M67: =SUM(K67,L67) -> 16
A68: Home First Finance Company India | B68: NSE | C68: 1023.65 | D68: 9 | E68: 11 | F68: =SUM(D68,E68) -> 20 | H68: Home First Finance Company India | I68: NSE | J68: 1151.5 | K68: 10 | L68: 9 | M68: =SUM(K68,L68) -> 19
A69: Five-Star Business Finance | B69: NSE | C69: -1101.85 | D69: 6 | E69: 20 | F69: =SUM(D69,E69) -> 26 | H69: Five-Star Business Finance | I69: NSE | J69: 349.4 | K69: 13 | L69: 17 | M69: =SUM(K69,L69) -> 30
A70: IIFL Finance | B70: NSE | C70: 796.75 | D70: 11 | E70: 14 | F70: =SUM(D70,E70) -> 25 | H70: IIFL Finance | I70: NSE | J70: 386.4 | K70: 13 | L70: 16 | M70: =SUM(K70,L70) -> 29
A71: Manappuram Finance | B71: NSE | C71: 340.1 | D71: 8 | E71: 14 | F71: =SUM(D71,E71) -> 22 | H71: Manappuram Finance | I71: NSE | J71: 303.8 | K71: 7 | L71: 15 | M71: =SUM(K71,L71) -> 22
A72: LIC Housing Finance | B72: NSE | C72: -1983.75 | D72: 9 | E72: 23 | F72: =SUM(D72,E72) -> 32 | H72: LIC Housing Finance | I72: NSE | J72: 491.6 | K72: 13 | L72: 18 | M72: =SUM(K72,L72) -> 31
A73: Poonawalla Fincorp | B73: NSE | C73: 2357.2 | D73: 14 | E73: 12 | F73: =SUM(D73,E73) -> 26 | H73: Poonawalla Fincorp | I73: NSE | J73: 1429.65 | K73: 13 | L73: 17 | M73: =SUM(K73,L73) -> 30
A74: Mahindra & Mahindra Financial Services | B74: NSE | C74: -486.15 | D74: 8 | E74: 16 | F74: =SUM(D74,E74) -> 24 | H74: Mahindra & Mahindra Financial Services | I74: NSE | J74: 174.3 | K74: 11 | L74: 16 | M74: =SUM(K74,L74) -> 27
A75: Sundaram Finance | B75: NSE | C75: -12.6 | D75: 6 | E75: 8 | F75: =SUM(D75,E75) -> 14 | H75: Sundaram Finance | I75: NSE | J75: -823.05 | K75: 5 | L75: 12 | M75: =SUM(K75,L75) -> 17
A76: L&T Finance | B76: NSE | C76: -320.3 | D76: 8 | E76: 14 | F76: =SUM(D76,E76) -> 22 | H76: L&T Finance | I76: NSE | J76: 134.15 | K76: 7 | L76: 11 | M76: =SUM(K76,L76) -> 18
A77: Aditya Birla Capital | B77: NSE | C77: -1679.55 | D77: 9 | E77: 18 | F77: =SUM(D77,E77) -> 27 | H77: Aditya Birla Capital | I77: NSE | J77: 1490.3 | K77: 13 | L77: 15 | M77: =SUM(K77,L77) -> 28
A78: Muthoot Finance | B78: NSE | C78: 49.55 | D78: 11 | E78: 20 | F78: =SUM(D78,E78) -> 31 | H78: Muthoot Finance | I78: NSE | J78: -1446.4 | K78: 15 | L78: 22 | M78: =SUM(K78,L78) -> 37
... A81: Bajaj Finance | B81: NSE | C81: -684.4 | D81: 10 | E81: 16 | F81: =SUM(D81,E81) -> 26 | H81: Bajaj Finance | I81: NSE | J81: 236.65 | K81: 12 | L81: 18 | M81: =SUM(K81,L81) -> 30
A82: TOTAL | C82: =SUM(C67:C81) -> -3133.45 | D82: =SUM(D67:D81) -> 130 | E82: =SUM(E67:E81) -> 226 | F82: =SUM(F67:F81) -> 356 | H82: TOTAL | J82: =SUM(J67:J81) -> 4678.9 | K82: =SUM(K67:K81) -> 167 | L82: =SUM(L67:L81) -> 223 | M82: =SUM(M67:M81) -> 390
A84: FINANCIAL YEAR SUMMARY — FY 2025–26
C85: Metric | D85: P&L (₹) | E85: Wins | F85: Losses | G85: Total Trades | H85: Win Rate %
C86: Buy Side – Full Year | D86: =SUM(C22,C42,C62,C82) -> 20603.99 | E86: =SUM(D82,D62,D42,D22) -> 682 | F86: =SUM(E82,E62,E42,E22) -> 924 | G86: =SUM(E86:F86) -> 1606 | H86: =E86/G86 -> 0.42465753
C87: Sell Side – Full Year | D87: =SUM(J22,J42,J62,J82) -> -14573.64 | E87: =SUM(K82,K62,K42,K22) -> 736 | F87: =SUM(L82,L62,L42,L22) -> 1120 | G87: =SUM(E87:F87) -> 1856 | H87: =E87/G87 -> 0.39655172
C88: Combined Net P&L – FY 2025–26 | D88: =SUM(D86:D87) -> 6030.35 | E88: =SUM(E86:E87) -> 1418 | F88: =SUM(F86:F87) -> 2044 | G88: =SUM(G86:G87) -> 3462 | H88: =AVERAGE(H86,H87) -> 0.41060463
A90: 📌 Note: Green = Profit | Red = Loss | All P&L figures in Indian Rupees (₹) | Win Rate = Wins ÷ Total Trades

Sheet WA
A1: NBFC – General Sector | Backtesting Report
A2: Student: Vishv Jeet Singh Thakur | Institution: UPES | Strategy: Williams Alligator (WA) Intraday (5-Minute) | Time: 9:15 AM – 3:00 PM | FY 2025–26
A4: Q1 (Quarter 1): April 1, 2025 – June 30, 2025
A5: BUY / LONG CALL SIDE | H5: SELL / SHORT CALL SIDE
A6: Company Name | B6: Segment | C6: P&L (₹) | D6: Wins | E6: Losses | F6: Total Trades | H6: Company Name | I6: Segment | J6: P&L (₹) | K6: Wins | L6: Losses | M6: Total Trades
A7: Aavas Financiers | B7: NSE | C7: 1276.8 | D7: 55 | E7: 88 | F7: =SUM(D7,E7) -> 143 | H7: Aavas Financiers | I7: NSE | J7: 808.85 | K7: 58 | L7: 83 | M7: =SUM(K7,L7) -> 141
A8: Home First Finance Company India | B8: NSE | C8: 5476.25 | D8: 79 | E8: 92 | F8: =SUM(D8,E8) -> 171 | H8: Home First Finance Company India | I8: NSE | J8: -3288.85 | K8: 49 | L8: 100 | M8: =SUM(K8,L8) -> 149
A9: Five-Star Business Finance | B9: NSE | C9: 1862.1 | D9: 65 | E9: 91 | F9: =SUM(D9,E9) -> 156 | H9: Five-Star Business Finance | I9: NSE | J9: -1914.4 | K9: 50 | L9: 96 | M9: =SUM(K9,L9) -> 146
A10: IIFL Finance | B10: NSE | C10: 2241.25 | D10: 69 | E10: 102 | F10: =SUM(D10,E10) -> 171 | H10: IIFL Finance | I10: NSE | J10: -637.85 | K10: 62 | L10: 88 | M10: =SUM(K10,L10) -> 150
A11: Manappuram Finance | B11: NSE | C11: 1950 | D11: 51 | E11: 72 | F11: =SUM(D11,E11) -> 123 | H11: Manappuram Finance | I11: NSE | J11: -2037.2 | K11: 47 | L11: 67 | M11: =SUM(K11,L11) -> 114
A12: LIC Housing Finance | B12: NSE | C12: 1965.45 | D12: 49 | E12: 65 | F12: =SUM(D12,E12) -> 114 | H12: LIC Housing Finance | I12: NSE | J12: 219.65 | K12: 50 | L12: 75 | M12: =SUM(K12,L12) -> 125
A13: Poonawalla Fincorp | B13: NSE | C13: 6553.75 | D13: 71 | E13: 73 | F13: =SUM(D13,E13) -> 144 | H13: Poonawalla Fincorp | I13: NSE | J13: -3792.8 | K13: 48 | L13: 92 | M13: =SUM(K13,L13) -> 140
A14: Mahindra & Mahindra Financial Services | B14: NSE | C14: -182.05 | D14: 50 | E14: 68 | F14: =SUM(D14,E14) -> 118 | H14: Mahindra & Mahindra Financial Services | I14: NSE | J14: 2104.4 | K14: 56 | L14: 61 | M14: =SUM(K14,L14) -> 117
A15: Sundaram Finance | B15: NSE | C15: 3512.35 | D15: 63 | E15: 82 | F15: =SUM(D15,E15) -> 145 | H15: Sundaram Finance | I15: NSE | J15: -3966.85 | K15: 40 | L15: 81 | M15: =SUM(K15,L15) -> 121
A16: L&T Finance | B16: NSE | C16: 5981.25 | D16: 70 | E16: 69 | F16: =SUM(D16,E16) -> 139 | H16: L&T Finance | I16: NSE | J16: -4166.12 | K16: 46 | L16: 90 | M16: =SUM(K16,L16) -> 136
A17: Aditya Birla Capital | B17: NSE | C17: 4565.52 | D17: 67 | E17: 76 | F17: =SUM(D17,E17) -> 143 | H17: Aditya Birla Capital | I17: NSE | J17: -3119.88 | K17: 53 | L17: 89 | M17: =SUM(K17,L17) -> 142
A18: Muthoot Finance | B18: NSE | C18: 3868.2 | D18: 63 | E18: 73 | F18: =SUM(D18,E18) -> 136 | H18: Muthoot Finance | I18: NSE | J18: 970.8 | K18: 52 | L18: 68 | M18: =SUM(K18,L18) -> 120
... A21: Bajaj Finance | B21: NSE | C21: 1030.95 | D21: 50 | E21: 53 | F21: =SUM(D21,E21) -> 103 | H21: Bajaj Finance | I21: NSE | J21: 452.1 | K21: 49 | L21: 51 | M21: =SUM(K21,L21) -> 100
A22: TOTAL | C22: =SUM(C7:C21) -> 43194.97 | D22: =SUM(D7:D21) -> 922 | E22: =SUM(E7:E21) -> 1167 | F22: =SUM(F7:F21) -> 2089 | H22: TOTAL | J22: =SUM(J7:J21) -> -19336.35 | K22: =SUM(K7:K21) -> 762 | L22: =SUM(L7:L21) -> 1199 | M22: =SUM(M7:M21) -> 1961
A24: Q2 (Quarter 2): July 2, 2025 – September 30, 2025
A25: BUY / LONG CALL SIDE | H25: SELL / SHORT CALL SIDE
A26: Company Name | B26: Segment | C26: P&L (₹) | D26: Wins | E26: Losses | F26: Total Trades | H26: Company Name | I26: Segment | J26: P&L (₹) | K26: Wins | L26: Losses | M26: Total Trades
A27: Aavas Financiers | B27: NSE | C27: -227.05 | D27: 51 | E27: 77 | F27: =SUM(D27,E27) -> 128 | H27: Aavas Financiers | I27: NSE | J27: 2904.95 | K27: 62 | L27: 63 | M27: =SUM(K27,L27) -> 125
A28: Home First Finance Company India | B28: NSE | C28: -449.4 | D28: 53 | E28: 77 | F28: =SUM(D28,E28) -> 130 | H28: Home First Finance Company India | I28: NSE | J28: 1522.9 | K28: 60 | L28: 73 | M28: =SUM(K28,L28) -> 133
A29: Five-Star Business Finance | B29: NSE | C29: -3251.25 | D29: 46 | E29: 90 | F29: =SUM(D29,E29) -> 136 | H29: Five-Star Business Finance | I29: NSE | J29: 3522.1 | K29: 64 | L29: 67 | M29: =SUM(K29,L29) -> 131
A30: IIFL Finance | B30: NSE | C30: 1608.85 | D30: 58 | E30: 86 | F30: =SUM(D30,E30) -> 144 | H30: IIFL Finance | I30: NSE | J30: 3308.45 | K30: 58 | L30: 66 | M30: =SUM(K30,L30) -> 124
A31: Manappuram Finance | B31: NSE | C31: -2577.2 | D31: 55 | E31: 79 | F31: =SUM(D31,E31) -> 134 | H31: Manappuram Finance | I31: NSE | J31: 2441 | K31: 55 | L31: 66 | M31: =SUM(K31,L31) -> 121
A32: LIC Housing Finance | B32: NSE | C32: -3103.3 | D32: 37 | E32: 63 | F32: =SUM(D32,E32) -> 100 | H32: LIC Housing Finance | I32: NSE | J32: 3126.65 | K32: 47 | L32: 35 | M32: =SUM(K32,L32) -> 82
A33: Poonawalla Fincorp | B33: NSE | C33: -682.25 | D33: 61 | E33: 95 | F33: =SUM(D33,E33) -> 156 | H33: Poonawalla Fincorp | I33: NSE | J33: 3194.75 | K33: 63 | L33: 69 | M33: =SUM(K33,L33) -> 132
A34: Mahindra & Mahindra Financial Services | B34: NSE | C34: 2502.65 | D34: 50 | E34: 56 | F34: =SUM(D34,E34) -> 106 | H34: Mahindra & Mahindra Financial Services | I34: NSE | J34: -188.55 | K34: 44 | L34: 55 | M34: =SUM(K34,L34) -> 99
A35: Sundaram Finance | B35: NSE | C35: -761.55 | D35: 46 | E35: 71 | F35: =SUM(D35,E35) -> 117 | H35: Sundaram Finance | I35: NSE | J35: 2476 | K35: 56 | L35: 63 | M35: =SUM(K35,L35) -> 119
A36: L&T Finance | B36: NSE | C36: -17.73 | D36: 57 | E36: 78 | F36: =SUM(D36,E36) -> 135 | H36: L&T Finance | I36: NSE | J36: 1739.47 | K36: 52 | L36: 53 | M36: =SUM(K36,L36) -> 105
A37: Aditya Birla Capital | B37: NSE | C37: -1026.85 | D37: 52 | E37: 89 | F37: =SUM(D37,E37) -> 141 | H37: Aditya Birla Capital | I37: NSE | J37: 1990.35 | K37: 56 | L37: 61 | M37: =SUM(K37,L37) -> 117
A38: Muthoot Finance | B38: NSE | C38: -234.55 | D38: 51 | E38: 59 | F38: =SUM(D38,E38) -> 110 | H38: Muthoot Finance | I38: NSE | J38: -633.3 | K38: 41 | L38: 55 | M38: =SUM(K38,L38) -> 96
... A41: Bajaj Finance | B41: NSE | C41: 707.05 | D41: 45 | E41: 50 | F41: =SUM(D41,E41) -> 95 | H41: Bajaj Finance | I41: NSE | J41: -705.05 | K41: 39 | L41: 53 | M41: =SUM(K41,L41) -> 92
A42: TOTAL | C42: =SUM(C27:C41) -> -6614.98 | D42: =SUM(D27:D41) -> 760 | E42: =SUM(E27:E41) -> 1090 | F42: =SUM(F27:F41) -> 1850 | H42: TOTAL | J42: =SUM(J27:J41) -> 26046.62 | K42: =SUM(K27:K41) -> 799 | L42: =SUM(L27:L41) -> 893 | M42: =SUM(M27:M41) -> 1692
A44: Q3 (Quarter 3): October 2, 2025 – December 31, 2025
A45: BUY / LONG CALL SIDE | H45: SELL / SHORT CALL SIDE
A46: Company Name | B46: Segment | C46: P&L (₹) | D46: Wins | E46: Losses | F46: Total Trades | H46: Company Name | I46: Segment | J46: P&L (₹) | K46: Wins | L46: Losses | M46: Total Trades
A47: Aavas Financiers | B47: NSE | C47: 758.2 | D47: 44 | E47: 72 | F47: =SUM(D47,E47) -> 116 | H47: Aavas Financiers | I47: NSE | J47: -386.4 | K47: 51 | L47: 68 | M47: =SUM(K47,L47) -> 119
A48: Home First Finance Company India | B48: NSE | C48: -1619.3 | D48: 48 | E48: 79 | F48: =SUM(D48,E48) -> 127 | H48: Home First Finance Company India | I48: NSE | J48: 4286.9 | K48: 54 | L48: 55 | M48: =SUM(K48,L48) -> 109
A49: Five-Star Business Finance | B49: NSE | C49: 3685.45 | D49: 58 | E49: 71 | F49: =SUM(D49,E49) -> 129 | H49: Five-Star Business Finance | I49: NSE | J49: 114.15 | K49: 55 | L49: 77 | M49: =SUM(K49,L49) -> 132
A50: IIFL Finance | B50: NSE | C50: 2891.25 | D50: 58 | E50: 75 | F50: =SUM(D50,E50) -> 133 | H50: IIFL Finance | I50: NSE | J50: 220.05 | K50: 53 | L50: 64 | M50: =SUM(K50,L50) -> 117
A51: Manappuram Finance | B51: NSE | C51: -1900.15 | D51: 47 | E51: 77 | F51: =SUM(D51,E51) -> 124 | H51: Manappuram Finance | I51: NSE | J51: -1897.95 | K51: 51 | L51: 70 | M51: =SUM(K51,L51) -> 121
A52: LIC Housing Finance | B52: NSE | C52: -1279.1 | D52: 34 | E52: 46 | F52: =SUM(D52,E52) -> 80 | H52: LIC Housing Finance | I52: NSE | J52: 1952.5 | K52: 41 | L52: 37 | M52: =SUM(K52,L52) -> 78
A53: Poonawalla Fincorp | B53: NSE | C53: 1899.55 | D53: 59 | E53: 76 | F53: =SUM(D53,E53) -> 135 | H53: Poonawalla Fincorp | I53: NSE | J53: 2255.8 | K53: 60 | L53: 76 | M53: =SUM(K53,L53) -> 136
A54: Mahindra & Mahindra Financial Services | B54: NSE | C54: 6298.1 | D54: 69 | E54: 83 | F54: =SUM(D54,E54) -> 152 | H54: Mahindra & Mahindra Financial Services | I54: NSE | J54: -680.15 | K54: 46 | L54: 74 | M54: =SUM(K54,L54) -> 120
A55: Sundaram Finance | B55: NSE | C55: 3448.6 | D55: 52 | E55: 56 | F55: =SUM(D55,E55) -> 108 | H55: Sundaram Finance | I55: NSE | J55: -5246.95 | K55: 34 | L55: 79 | M55: =SUM(K55,L55) -> 113
A56: L&T Finance | B56: NSE | C56: 840.73 | D56: 50 | E56: 71 | F56: =SUM(D56,E56) -> 121 | H56: L&T Finance | I56: NSE | J56: -1656.53 | K56: 44 | L56: 60 | M56: =SUM(K56,L56) -> 104
A57: Aditya Birla Capital | B57: NSE | C57: -1284.75 | D57: 48 | E57: 80 | F57: =SUM(D57,E57) -> 128 | H57: Aditya Birla Capital | I57: NSE | J57: -2292.5 | K57: 43 | L57: 69 | M57: =SUM(K57,L57) -> 112
A58: Muthoot Finance | B58: NSE | C58: 1514.05 | D58: 48 | E58: 53 | F58: =SUM(D58,E58) -> 101 | H58: Muthoot Finance | I58: NSE | J58: -1469.6 | K58: 34 | L58: 56 | M58: =SUM(K58,L58) -> 90
... A61: Bajaj Finance | B61: NSE | C61: 1516.6 | D61: 46 | E61: 49 | F61: =SUM(D61,E61) -> 95 | H61: Bajaj Finance | I61: NSE | J61: 1164.7 | K61: 42 | L61: 44 | M61: =SUM(K61,L61) -> 86
A62: TOTAL | C62: =SUM(C47:C61) -> 25173.88 | D62: =SUM(D47:D61) -> 773 | E62: =SUM(E47:E61) -> 992 | F62: =SUM(F47:F61) -> 1765 | H62: TOTAL | J62: =SUM(J47:J61) -> -7897.83 | K62: =SUM(K47:K61) -> 690 | L62: =SUM(L47:L61) -> 952 | M62: =SUM(M47:M61) -> 1642
A64: Q4 (Quarter 4): January 1, 2026 – March 31, 2026
A65: BUY / LONG CALL SIDE | H65: SELL / SHORT CALL SIDE
A66: Company Name | B66: Segment | C66: P&L (₹) | D66: Wins | E66: Losses | F66: Total Trades | H66: Company Name | I66: Segment | J66: P&L (₹) | K66: Wins | L66: Losses | M66: Total Trades
A67: Aavas Financiers | B67: NSE | C67: 985.15 | D67: 52 | E67: 73 | F67: =SUM(D67,E67) -> 125 | H67: Aavas Financiers | I67: NSE | J67: -2672.8 | K67: 49 | L67: 79 | M67: =SUM(K67,L67) -> 128
A68: Home First Finance Company India | B68: NSE | C68: -1719.5 | D68: 51 | E68: 91 | F68: =SUM(D68,E68) -> 142 | H68: Home First Finance Company India | I68: NSE | J68: 3161.8 | K68: 67 | L68: 82 | M68: =SUM(K68,L68) -> 149
A69: Five-Star Business Finance | B69: NSE | C69: -1448.65 | D69: 51 | E69: 96 | F69: =SUM(D69,E69) -> 147 | H69: Five-Star Business Finance | I69: NSE | J69: 4357.7 | K69: 68 | L69: 82 | M69: =SUM(K69,L69) -> 150
A70: IIFL Finance | B70: NSE | C70: -607.95 | D70: 69 | E70: 109 | F70: =SUM(D70,E70) -> 178 | H70: IIFL Finance | I70: NSE | J70: -1689.45 | K70: 70 | L70: 116 | M70: =SUM(K70,L70) -> 186
A71: Manappuram Finance | B71: NSE | C71: -1888.2 | D71: 64 | E71: 97 | F71: =SUM(D71,E71) -> 161 | H71: Manappuram Finance | I71: NSE | J71: -2292.85 | K71: 57 | L71: 115 | M71: =SUM(K71,L71) -> 172
A72: LIC Housing Finance | B72: NSE | C72: -1866.75 | D72: 40 | E72: 70 | F72: =SUM(D72,E72) -> 110 | H72: LIC Housing Finance | I72: NSE | J72: 2909.45 | K72: 56 | L72: 55 | M72: =SUM(K72,L72) -> 111
A73: Poonawalla Fincorp | B73: NSE | C73: -78.9 | D73: 59 | E73: 104 | F73: =SUM(D73,E73) -> 163 | H73: Poonawalla Fincorp | I73: NSE | J73: 1816.25 | K73: 69 | L73: 95 | M73: =SUM(K73,L73) -> 164
A74: Mahindra & Mahindra Financial Services | B74: NSE | C74: -1354.85 | D74: 54 | E74: 92 | F74: =SUM(D74,E74) -> 146 | H74: Mahindra & Mahindra Financial Services | I74: NSE | J74: 5496.35 | K74: 68 | L74: 76 | M74: =SUM(K74,L74) -> 144
A75: Sundaram Finance | B75: NSE | C75: 4689.05 | D75: 53 | E75: 75 | F75: =SUM(D75,E75) -> 128 | H75: Sundaram Finance | I75: NSE | J75: -915.6 | K75: 55 | L75: 87 | M75: =SUM(K75,L75) -> 142
A76: L&T Finance | B76: NSE | C76: -2028.2 | D76: 51 | E76: 87 | F76: =SUM(D76,E76) -> 138 | H76: L&T Finance | I76: NSE | J76: 1031.85 | K76: 64 | L76: 94 | M76: =SUM(K76,L76) -> 158
A77: Aditya Birla Capital | B77: NSE | C77: -1963.7 | D77: 56 | E77: 91 | F77: =SUM(D77,E77) -> 147 | H77: Aditya Birla Capital | I77: NSE | J77: -1150.35 | K77: 57 | L77: 104 | M77: =SUM(K77,L77) -> 161
A78: Muthoot Finance | B78: NSE | C78: 3208 | D78: 63 | E78: 66 | F78: =SUM(D78,E78) -> 129 | H78: Muthoot Finance | I78: NSE | J78: 328.65 | K78: 54 | L78: 84 | M78: =SUM(K78,L78) -> 138
... A81: Bajaj Finance | B81: NSE | C81: 1695.6 | D81: 50 | E81: 50 | F81: =SUM(D81,E81) -> 100 | H81: Bajaj Finance | I81: NSE | J81: 2759.4 | K81: 50 | L81: 63 | M81: =SUM(K81,L81) -> 113
A82: TOTAL | C82: =SUM(C67:C81) -> -4433.55 | D82: =SUM(D67:D81) -> 813 | E82: =SUM(E67:E81) -> 1261 | F82: =SUM(F67:F81) -> 2074 | H82: TOTAL | J82: =SUM(J67:J81) -> 16686.65 | K82: =SUM(K67:K81) -> 895 | L82: =SUM(L67:L81) -> 1267 | M82: =SUM(M67:M81) -> 2162
A84: FINANCIAL YEAR SUMMARY — FY 2025–26
C85: Metric | D85: P&L (₹) | E85: Wins | F85: Losses | G85: Total Trades | H85: Win Rate %
C86: Buy Side – Full Year | D86: =SUM(C22,C42,C62,C82) -> 57320.32 | E86: =SUM(D82,D62,D42,D22) -> 3268 | F86: =SUM(E82,E62,E42,E22) -> 4510 | G86: =SUM(E86:F86) -> 7778 | H86: =E86/G86 -> 0.42015942
C87: Sell Side – Full Year | D87: =SUM(J22,J42,J62,J82) -> 15499.09 | E87: =SUM(K82,K62,K42,K22) -> 3146 | F87: =SUM(L82,L62,L42,L22) -> 4311 | G87: =SUM(E87:F87) -> 7457 | H87: =E87/G87 -> 0.42188548
C88: Combined Net P&L – FY 2025–26 | D88: =SUM(D86:D87) -> 72819.41 | E88: =SUM(E86:E87) -> 6414 | F88: =SUM(F86:F87) -> 8821 | G88: =SUM(G86:G87) -> 15235 | H88: =AVERAGE(H86,H87) -> 0.42102245
A90: 📌 Note: Green = Profit | Red = Loss | All P&L figures in Indian Rupees (₹) | Win Rate = Wins ÷ Total Trades

Sheet Results
A1: NBFC SECTOR — STRATEGY PERFORMANCE LEADERBOARD
A2: FY 2025–26 | All 10 Strategies Ranked by Net P&L | 15 NBFC Stocks, 5-Minute Intraday
A4: Strategy | B4: P&L (₹) | C4: Wins | D4: Losses | E4: Total Trades | F4: Win Rate % | G4: Rank
A5: Alligator | B5: =WA!D88 -> 72819.41 | C5: =WA!E88 -> 6414 | D5: =WA!F88 -> 8821 | E5: =WA!G88 -> 15235 | F5: =WA!H88 -> 0.42102245 | G5: 1
A6: BB | B6: =BB!D88 -> 58764.36 | C6: =BB!E88 -> 3630 | D6: =BB!F88 -> 4734 | E6: =BB!G88 -> 8364 | F6: =BB!H88 -> 0.4338753 | G6: 2
A7: RSI | B7: =RSI!D88 -> 51720.6 | C7: =RSI!E88 -> 4330 | D7: =RSI!F88 -> 5630 | E7: =RSI!G88 -> 9960 | F7: =RSI!H88 -> 0.43480512 | G7: 3
A8: Vwap | B8: =Vwap!D88 -> 42424.93 | C8: =Vwap!E88 -> 4371 | D8: =Vwap!F88 -> 6155 | E8: =Vwap!G88 -> 10526 | F8: =Vwap!H88 -> 0.41529345 | G8: 4
A9: AO | B9: =AO!D88 -> 35673.93 | C9: =AO!E88 -> 3525 | D9: =AO!F88 -> 4412 | E9: =AO!G88 -> 7937 | F9: =AO!H88 -> 0.44411776 | G9: 5
A10: MA | B10: =MA!D88 -> 19762.09 | C10: =MA!E88 -> 1725 | D10: =MA!F88 -> 2155 | E10: =MA!G88 -> 3880 | F10: =MA!H88 -> 0.44440055 | G10: 6
A11: SuperTrend | B11: =SuperTrend!D88 -> 18552.27 | C11: =SuperTrend!E88 -> 2610 | D11: =SuperTrend!F88 -> 3484 | E11: =SuperTrend!G88 -> 6094 | F11: =SuperTrend!H88 -> 0.42823425 | G11: 7
A12: Stochastic RSI | B12: ='Stochastic RSI'!D88 -> 6952.1 | C12: ='Stochastic RSI'!E88 -> 6350 | D12: ='Stochastic RSI'!F88 -> 8891 | E12: ='Stochastic RSI'!G88 -> 15241 | F12: ='Stochastic RSI'!H88 -> 0.41729326 | G12: 8
A13: Pivot PS | B13: =PPS!D88 -> 6030.35 | C13: =PPS!E88 -> 1418 | D13: =PPS!F88 -> 2044 | E13: =PPS!G88 -> 3462 | F13: =PPS!H88 -> 0.41060463 | G13: 9
A14: MACD | B14: =MACD!D88 -> -934.81 | C14: =MACD!E88 -> 5789 | D14: =MACD!F88 -> 7940 | E14: =MACD!G88 -> 13729 | F14: =MACD!H88 -> 0.42161341 | G14: 10
A16: KEY TAKEAWAYS FROM THE MATRIX
A18: 💡 The Illusion of Win Rate: MA had the highest win rate (44.44%), but it ranks well below the top despite trading less frequently and likely securing smaller average wins.
A19: 💡 The Big Winner: Alligator takes the crown for total profit by a wide margin, proving its winning trades heavily outpaced its losses despite a modest 42.10% win rate over a massive sample size (15,235 trades).
A20: 💡 The Underperformer: MACD is the only strategy in this dataset that net lost money, ending in the negative despite having a higher win rate than Alligator, Vwap, Stochastic RSI and Pivot PS.
A22: 📌 Leaderboard ranked by Combined Net P&L (Buy + Sell, full FY) — figures pull live from each strategy sheet
