Workbook

Sheet Cover
B2: NBFC–General Sector — PMS Structuring: Equity Research & Portfolio Construction
B3: Relative Valuation (PE/PEG) · Fundamental Ranking · Weighted Normalize Model · Rank-Weighted Portfolio Allocation
B5: Prepared for: | C5: Vishv Jeet Singh Thakur — MBA Finance, UPES Dehradun
B6: Coverage universe: | C6: 15 listed NBFCs / HFCs (India)
B7: Period: | C7: FY25 actual, FY26E estimates
B9: Contents
B10: 1. Valuation Screen | C10: Relative PE valuation and PEG screen across all 15 names.
B11: 2. Fundamental Ranking | C11: Metric-by-metric rank (GNPA, NIM, ROA, CAR, ROE) for the 10 names with full disclosure.
B12: 3. Weighted Normalize Model | C12: Min-max normalized weights blend the five metrics into one composite score and overall rank (higher score = better).
B13: 4. Portfolio Allocation | C13: Links the model's overall rank to share holdings for the model PMS portfolio.
B15: How this workbook is colour-coded
B16: Blue text | C16: Hardcoded input (price, share count, weight assumption) — safe to edit
B17: Black text | C17: Formula calculated within the same sheet
B18: Green text | C18: Formula linked from another sheet (single source of truth — edit at the source)
B20: Key assumptions & sources
B21: • Market cap, CMP, revenue, profit, EPS and PE figures: company investor presentations / NSE & BSE filings / FY25 annual reports and FY26E consensus estimates, as compiled by the user.
B22: • GNPA, NIM, ROA, CAR/CRAR and ROE for the 10 fully-disclosed names: company FY26 investor presentations and regulatory filings, as compiled by the user.
B23: • Composite weighting (GNPA 30% / NIM 25% / ROA 20% / CAR 15% / ROE 10%) is an editable analyst assumption — change the yellow cells on '3. Weighted Normalize Model'.
B24: • Each metric is min-max normalized across the 10 disclosed names (0 = worst, 1 = best) before weighting; GNPA is inverted since lower is better.
B25: • Share holdings on '4. Portfolio Allocation' are user-specified inputs (blue); Overall Rank is linked live from '3. Weighted Normalize Model'.

Sheet 1. Valuation Screen
A1: NBFC Sector — Equity Research: Relative Valuation & PEG Screen (FY25–FY26E)
A2: Valuation Call = PE Ratio vs. peer-set average PE | PEG Ratio = PE Ratio ÷ EPS Growth (%) | PEG Assessment applies only to "Over Value" names
A3: Company Name | B3: Ticker | C3: Market Cap (₹ Cr) | D3: CMP (₹) | E3: PE Ratio (x) | F3: Valuation Call | G3: Revenue FY25 (₹ Cr) | H3: Revenue FY26E (₹ Cr) | I3: Profit FY25 (₹ Cr) | J3: Profit FY26E (₹ Cr) | K3: Revenue Growth? | L3: Profit Growth? | M3: Growth Screen | N3: EPS FY25 (₹) | O3: EPS FY26E (₹) | P3: EPS Growth (%) | Q3: PEG Ratio (x) | R3: PEG Assessment | S3: GNPA | T3: NIM | U3: ROA | V3: CAR/CRAR | W3: ROE
A4: Aavas Financiers | B4: AAVAS | C4: 11813 | D4: 1507 | E4: 18.2 | F4: =IF(E4<$E$19,"Under Value","Over Value") -> Under Value | G4: 2354.51 | H4: 2683.46 | I4: 574.11 | J4: 654.88 | K4: =IF(H4>G4,"Yes","No") -> Yes | L4: =IF(J4>I4,"Yes","No") -> Yes | M4: =IF(AND(K4="No",L4="No"),"Ignore","Consider") -> Consider | N4: 72.53 | O4: 82.6 | P4: =(O4-N4)/N4 -> 0.1388391 | Q4: =IF(OR(N4<=0,P4<=0),"N/A",E4/(P4*100)) -> 1.3108699 | R4: =IF(F4="Over Value",IF(ISNUMBER(Q4),IF(AND(Q4>0,Q4<1.5),"Consider","Reject"),"Reject"),"") | S4: 0.0105 | T4: 0.0793 | U4: 0.0329 | V4: 0.446 | W4: 0.1393
A5: Home First Finance Company India | B5: HOMEFIRST | C5: 12456 | D5: 1187 | E5: 23 | F5: =IF(E5<$E$19,"Under Value","Over Value") -> Under Value | G5: 1539.08 | H5: 1921.01 | I5: 382.07 | J5: 540.38 | K5: =IF(H5>G5,"Yes","No") -> Yes | L5: =IF(J5>I5,"Yes","No") -> Yes | M5: =IF(AND(K5="No",L5="No"),"Ignore","Consider") -> Consider | N5: 42.43 | O5: 51.8 | P5: =(O5-N5)/N5 -> 0.22083432 | Q5: =IF(OR(N5<=0,P5<=0),"N/A",E5/(P5*100)) -> 1.0415048 | R5: =IF(F5="Over Value",IF(ISNUMBER(Q5),IF(AND(Q5>0,Q5<1.5),"Consider","Reject"),"Reject"),"") | S5: 0.018 | T5: 0.057 | U5: 0.039 | V5: 0.441 | W5: 0.12403852
A6: Five-Star Business Finance | B6: FIVESTAR | C6: 14670 | D6: 558 | E6: 15 | F6: =IF(E6<$E$19,"Under Value","Over Value") -> Under Value | G6: 2847.84 | H6: 3218.12 | I6: 1072.49 | J6: 1098.75 | K6: =IF(H6>G6,"Yes","No") -> Yes | L6: =IF(J6>I6,"Yes","No") -> Yes | M6: =IF(AND(K6="No",L6="No"),"Ignore","Consider") -> Consider | N6: 36.43 | O6: 37.22 | P6: =(O6-N6)/N6 -> 0.021685424 | Q6: =IF(OR(N6<=0,P6<=0),"N/A",E6/(P6*100)) -> 6.9170886 | R6: =IF(F6="Over Value",IF(ISNUMBER(Q6),IF(AND(Q6>0,Q6<1.5),"Consider","Reject"),"Reject"),"") | S6: 0.0337 | T6: 0.1986 | U6: 0.0868 | V6: 0.5189 | W6: 0.1606
A7: IIFL Finance | B7: IIFL | C7: 21679 | D7: 525 | E7: 13.4 | F7: =IF(E7<$E$19,"Under Value","Over Value") -> Under Value | G7: 10233.35 | H7: 13366.4 | I7: 378.77 | J7: 1660.8 | K7: =IF(H7>G7,"Yes","No") -> Yes | L7: =IF(J7>I7,"Yes","No") -> Yes | M7: =IF(AND(K7="No",L7="No"),"Ignore","Consider") -> Consider | N7: 8.92 | O7: 39.05 | P7: =(O7-N7)/N7 -> 3.3778027 | Q7: =IF(OR(N7<=0,P7<=0),"N/A",E7/(P7*100)) -> 0.03967076 | R7: =IF(F7="Over Value",IF(ISNUMBER(Q7),IF(AND(Q7>0,Q7<1.5),"Consider","Reject"),"Reject"),"") | S7: 0.015 | T7: 0.061 | U7: 0.024 | V7: 0.253 | W7: 0.131
A8: LIC Housing Finance | B8: LICHSGFIN | C8: 30245 | D8: 538 | E8: 5.37 | F8: =IF(E8<$E$19,"Under Value","Over Value") -> Under Value | G8: 28110.6 | H8: 28837.11 | I8: 5442.23 | J8: 5603.67 | K8: =IF(H8>G8,"Yes","No") -> Yes | L8: =IF(J8>I8,"Yes","No") -> Yes | M8: =IF(AND(K8="No",L8="No"),"Ignore","Consider") -> Consider | N8: 98.94 | O8: 101.87 | P8: =(O8-N8)/N8 -> 0.029613907 | Q8: =IF(OR(N8<=0,P8<=0),"N/A",E8/(P8*100)) -> 1.8133372 | R8: =IF(F8="Over Value",IF(ISNUMBER(Q8),IF(AND(Q8>0,Q8<1.5),"Consider","Reject"),"Reject"),"") | S8: 0.0121 | T8: 0.0268 | U8: 0.0178 | V8: 0.2422 | W8: 0.14
A9: Mahindra & Mahindra Financial Services | B9: M&MFIN | C9: 45668 | D9: 332 | E9: 15.6 | F9: =IF(E9<$E$19,"Under Value","Over Value") -> Under Value | G9: 18518.85 | H9: 21040.54 | I9: 2261.87 | J9: 2854.53 | K9: =IF(H9>G9,"Yes","No") -> Yes | L9: =IF(J9>I9,"Yes","No") -> Yes | M9: =IF(AND(K9="No",L9="No"),"Ignore","Consider") -> Consider | N9: 16.272446 | O9: 20.536187 | P9: =(O9-N9)/N9 -> 0.26202213 | Q9: =IF(OR(N9<=0,P9<=0),"N/A",E9/(P9*100)) -> 0.59536955 | R9: =IF(F9="Over Value",IF(ISNUMBER(Q9),IF(AND(Q9>0,Q9<1.5),"Consider","Reject"),"Reject"),"") | S9: 0.034 | T9: 0.071 | U9: 0.02 | V9: 0.188 | W9: 0.125
A10: Sundaram Finance | B10: SUNDARMFIN | C10: 51409 | D10: 4554 | E10: 24 | F10: =IF(E10<$E$19,"Under Value","Over Value") -> Under Value | G10: 8512.82 | H10: 9851.53 | I10: 1879.44 | J10: 2058.86 | K10: =IF(H10>G10,"Yes","No") -> Yes | L10: =IF(J10>I10,"Yes","No") -> Yes | M10: =IF(AND(K10="No",L10="No"),"Ignore","Consider") -> Consider | N10: 169.17 | O10: 185.32 | P10: =(O10-N10)/N10 -> 0.095466099 | Q10: =IF(OR(N10<=0,P10<=0),"N/A",E10/(P10*100)) -> 2.5139814 | R10: =IF(F10="Over Value",IF(ISNUMBER(Q10),IF(AND(Q10>0,Q10<1.5),"Consider","Reject"),"Reject"),"") | S10: 0.0214 | T10: 0.0537 | U10: 0.0303 | V10: 0.1895 | W10: 0.175
A11: Muthoot Finance | B11: MUTHOOTFIN | C11: 121468 | D11: 3123 | E11: 11.9 | F11: =IF(E11<$E$19,"Under Value","Over Value") -> Under Value | G11: 20214.17 | H11: 31209.23 | I11: 5332.9 | J11: 10590.34 | K11: =IF(H11>G11,"Yes","No") -> Yes | L11: =IF(J11>I11,"Yes","No") -> Yes | M11: =IF(AND(K11="No",L11="No"),"Ignore","Consider") -> Consider | N11: 132.84 | O11: 263.79 | P11: =(O11-N11)/N11 -> 0.98577236 | Q11: =IF(OR(N11<=0,P11<=0),"N/A",E11/(P11*100)) -> 0.12071753 | R11: =IF(F11="Over Value",IF(ISNUMBER(Q11),IF(AND(Q11>0,Q11<1.5),"Consider","Reject"),"Reject"),"") | S11: 0.0235 | T11: 0.0622 | U11: 0.0164 | V11: 0.31 | W11: 0.0726
A12: Shriram Finance | B12: SHRIRAMFIN | C12: 242774 | D12: 1069 | E12: 25.1 | F12: =IF(E12<$E$19,"Under Value","Over Value") -> Under Value | G12: 43940.61 | H12: 48134.57 | I12: 9553.82 | J12: 10024.16 | K12: =IF(H12>G12,"Yes","No") -> Yes | L12: =IF(J12>I12,"Yes","No") -> Yes | M12: =IF(AND(K12="No",L12="No"),"Ignore","Consider") -> Consider | N12: 50.81 | O12: 53.28 | P12: =(O12-N12)/N12 -> 0.048612478 | Q12: =IF(OR(N12<=0,P12<=0),"N/A",E12/(P12*100)) -> 5.1632834 | R12: =IF(F12="Over Value",IF(ISNUMBER(Q12),IF(AND(Q12>0,Q12<1.5),"Consider","Reject"),"Reject"),"") | S12: 0.0458 | T12: 0.0838 | U12: 0.031 | V12: 0.204 | W12: 0.1653
A13: Manappuram Finance | B13: MANAPPURAM | C13: 29918 | D13: 342 | E13: 32 | F13: =IF(E13<$E$19,"Under Value","Over Value") -> Over Value | G13: 10007 | H13: 9509.39 | I13: 1216.15 | J13: 1003.3 | K13: =IF(H13>G13,"Yes","No") -> No | L13: =IF(J13>I13,"Yes","No") -> No | M13: =IF(AND(K13="No",L13="No"),"Ignore","Consider") -> Ignore | N13: 14.37 | O13: 10.68 | P13: =(O13-N13)/N13 -> -0.25678497 | Q13: =IF(OR(N13<=0,P13<=0),"N/A",E13/(P13*100)) -> N/A | R13: =IF(F13="Over Value",IF(ISNUMBER(Q13),IF(AND(Q13>0,Q13<1.5),"Consider","Reject"),"Reject"),"") -> Reject
A14: Poonawalla Fincorp | B14: POONAWALLA | C14: 38768 | D14: 464 | E14: 75.3 | F14: =IF(E14<$E$19,"Under Value","Over Value") -> Over Value | G14: 4189.76 | H14: 6790.18 | I14: -98.34 | J14: 541.81 | K14: =IF(H14>G14,"Yes","No") -> Yes | L14: =IF(J14>I14,"Yes","No") -> Yes | M14: =IF(AND(K14="No",L14="No"),"Ignore","Consider") -> Consider | N14: -1.26 | O14: 6.67 | P14: =(O14-N14)/N14 -> -6.2936508 | Q14: =IF(OR(N14<=0,P14<=0),"N/A",E14/(P14*100)) -> N/A | R14: =IF(F14="Over Value",IF(ISNUMBER(Q14),IF(AND(Q14>0,Q14<1.5),"Consider","Reject"),"Reject"),"") -> Reject
A15: L&T Finance | B15: LTF | C15: 74915 | D15: 328 | E15: 27.4 | F15: =IF(E15<$E$19,"Under Value","Over Value") -> Over Value | G15: 15924.24 | H15: 17913.67 | I15: 2643.66 | J15: 2981.18 | K15: =IF(H15>G15,"Yes","No") -> Yes | L15: =IF(J15>I15,"Yes","No") -> Yes | M15: =IF(AND(K15="No",L15="No"),"Ignore","Consider") -> Consider | N15: 10.6 | O15: 11.9 | P15: =(O15-N15)/N15 -> 0.12264151 | Q15: =IF(OR(N15<=0,P15<=0),"N/A",E15/(P15*100)) -> 2.2341538 | R15: =IF(F15="Over Value",IF(ISNUMBER(Q15),IF(AND(Q15>0,Q15<1.5),"Consider","Reject"),"Reject"),"") -> Reject
A16: Aditya Birla Capital | B16: ABCAPITAL | C16: 106853 | D16: 406 | E16: 29.2 | F16: =IF(E16<$E$19,"Under Value","Over Value") -> Over Value | G16: 40632.23 | H16: 45508.98 | I16: 3332.32 | J16: 3764.49 | K16: =IF(H16>G16,"Yes","No") -> Yes | L16: =IF(J16>I16,"Yes","No") -> Yes | M16: =IF(AND(K16="No",L16="No"),"Ignore","Consider") -> Consider | N16: 12.78 | O16: 14.37 | P16: =(O16-N16)/N16 -> 0.12441315 | Q16: =IF(OR(N16<=0,P16<=0),"N/A",E16/(P16*100)) -> 2.3470189 | R16: =IF(F16="Over Value",IF(ISNUMBER(Q16),IF(AND(Q16>0,Q16<1.5),"Consider","Reject"),"Reject"),"") -> Reject
A17: Cholamandalam Investment and Finance Company | B17: CHOLAFIN | C17: 153397 | D17: 1852 | E17: 30.1 | F17: =IF(E17<$E$19,"Under Value","Over Value") -> Over Value | G17: 25889.77 | H17: 31073.1 | I17: 4262.7 | J17: 5232.61 | K17: =IF(H17>G17,"Yes","No") -> Yes | L17: =IF(J17>I17,"Yes","No") -> Yes | M17: =IF(AND(K17="No",L17="No"),"Ignore","Consider") -> Consider | N17: 50.69 | O17: 61.41 | P17: =(O17-N17)/N17 -> 0.21148155 | Q17: =IF(OR(N17<=0,P17<=0),"N/A",E17/(P17*100)) -> 1.423292 | R17: =IF(F17="Over Value",IF(ISNUMBER(Q17),IF(AND(Q17>0,Q17<1.5),"Consider","Reject"),"Reject"),"") -> Consider | S17: 0.044 | T17: 0.08 | U17: 0.033 | V17: 0.1921 | W17: 0.197
A18: Bajaj Finance | B18: BAJFINANCE | C18: 610393 | D18: 1037 | E18: 33.6 | F18: =IF(E18<$E$19,"Under Value","Over Value") -> Over Value | G18: 69709.44 | H18: 81982.38 | I18: 16637.82 | J18: 19017.39 | K18: =IF(H18>G18,"Yes","No") -> Yes | L18: =IF(J18>I18,"Yes","No") -> Yes | M18: =IF(AND(K18="No",L18="No"),"Ignore","Consider") -> Consider | N18: 26.77 | O18: 30.56 | P18: =(O18-N18)/N18 -> 0.14157639 | Q18: =IF(OR(N18<=0,P18<=0),"N/A",E18/(P18*100)) -> 2.373277 | R18: =IF(F18="Over Value",IF(ISNUMBER(Q18),IF(AND(Q18>0,Q18<1.5),"Consider","Reject"),"Reject"),"") -> Reject
D19: Sector Avg PE → | E19: =AVERAGE(E4:E18) -> 25.278
A21: Note: GNPA / NIM / ROA / CAR / ROE are disclosed for the 10 names carried forward into the ranking and weighted-score sheets; the remaining 5 names lack comparable disclosure and are excluded from that analysis.

Sheet 2. Fundamental Ranking
A1: NBFC Fundamental Ranking — Normal Method (1 = best on that metric)
A2: Each metric is ranked independently across the 10 companies with full disclosure. GNPA is ranked ascending (lower is better); all other metrics are ranked descending (higher is better).
A3: Company Name | B3: Ticker | C3: Gross NPA (GNPA) | D3: Rank (1 = lowest) | E3: Net Interest Margin (NIM) | F3: Rank (1 = highest) | G3: Return on Assets (ROA) | H3: Rank (1 = highest) | I3: Capital Adequacy Ratio (CAR/CRAR) | J3: Rank (1 = highest) | K3: Return on Equity (ROE) | L3: Rank (1 = highest)
A4: Aavas Financiers | B4: AAVAS | C4: 0.0105 | D4: =RANK(C4,$C$4:$C$13,1) -> 1 | E4: 0.0793 | F4: =RANK(E4,$E$4:$E$13,0) -> 4 | G4: 0.0329 | H4: =RANK(G4,$G$4:$G$13,0) -> 4 | I4: 0.446 | J4: =RANK(I4,$I$4:$I$13,0) -> 2 | K4: 0.1393 | L4: =RANK(K4,$K$4:$K$13,0) -> 6
A5: Home First Finance Company India | B5: HOMEFIRST | C5: 0.018 | D5: =RANK(C5,$C$4:$C$13,1) -> 4 | E5: 0.057 | F5: =RANK(E5,$E$4:$E$13,0) -> 8 | G5: 0.039 | H5: =RANK(G5,$G$4:$G$13,0) -> 2 | I5: 0.441 | J5: =RANK(I5,$I$4:$I$13,0) -> 3 | K5: 0.12403852 | L5: =RANK(K5,$K$4:$K$13,0) -> 9
A6: Five-Star Business Finance | B6: FIVESTAR | C6: 0.0337 | D6: =RANK(C6,$C$4:$C$13,1) -> 7 | E6: 0.1986 | F6: =RANK(E6,$E$4:$E$13,0) -> 1 | G6: 0.0868 | H6: =RANK(G6,$G$4:$G$13,0) -> 1 | I6: 0.5189 | J6: =RANK(I6,$I$4:$I$13,0) -> 1 | K6: 0.1606 | L6: =RANK(K6,$K$4:$K$13,0) -> 4
A7: IIFL Finance | B7: IIFL | C7: 0.015 | D7: =RANK(C7,$C$4:$C$13,1) -> 3 | E7: 0.061 | F7: =RANK(E7,$E$4:$E$13,0) -> 7 | G7: 0.024 | H7: =RANK(G7,$G$4:$G$13,0) -> 7 | I7: 0.253 | J7: =RANK(I7,$I$4:$I$13,0) -> 5 | K7: 0.131 | L7: =RANK(K7,$K$4:$K$13,0) -> 7
A8: LIC Housing Finance | B8: LICHSGFIN | C8: 0.0121 | D8: =RANK(C8,$C$4:$C$13,1) -> 2 | E8: 0.0268 | F8: =RANK(E8,$E$4:$E$13,0) -> 10 | G8: 0.0178 | H8: =RANK(G8,$G$4:$G$13,0) -> 9 | I8: 0.2422 | J8: =RANK(I8,$I$4:$I$13,0) -> 6 | K8: 0.14 | L8: =RANK(K8,$K$4:$K$13,0) -> 5
A9: Mahindra & Mahindra Financial Services | B9: M&MFIN | C9: 0.034 | D9: =RANK(C9,$C$4:$C$13,1) -> 8 | E9: 0.071 | F9: =RANK(E9,$E$4:$E$13,0) -> 5 | G9: 0.02 | H9: =RANK(G9,$G$4:$G$13,0) -> 8 | I9: 0.188 | J9: =RANK(I9,$I$4:$I$13,0) -> 10 | K9: 0.125 | L9: =RANK(K9,$K$4:$K$13,0) -> 8
A10: Sundaram Finance | B10: SUNDARMFIN | C10: 0.0214 | D10: =RANK(C10,$C$4:$C$13,1) -> 5 | E10: 0.0537 | F10: =RANK(E10,$E$4:$E$13,0) -> 9 | G10: 0.0303 | H10: =RANK(G10,$G$4:$G$13,0) -> 6 | I10: 0.1895 | J10: =RANK(I10,$I$4:$I$13,0) -> 9 | K10: 0.175 | L10: =RANK(K10,$K$4:$K$13,0) -> 2
A11: Muthoot Finance | B11: MUTHOOTFIN | C11: 0.0235 | D11: =RANK(C11,$C$4:$C$13,1) -> 6 | E11: 0.0622 | F11: =RANK(E11,$E$4:$E$13,0) -> 6 | G11: 0.0164 | H11: =RANK(G11,$G$4:$G$13,0) -> 10 | I11: 0.31 | J11: =RANK(I11,$I$4:$I$13,0) -> 4 | K11: 0.0726 | L11: =RANK(K11,$K$4:$K$13,0) -> 10
A12: Shriram Finance | B12: SHRIRAMFIN | C12: 0.0458 | D12: =RANK(C12,$C$4:$C$13,1) -> 10 | E12: 0.0838 | F12: =RANK(E12,$E$4:$E$13,0) -> 2 | G12: 0.031 | H12: =RANK(G12,$G$4:$G$13,0) -> 5 | I12: 0.204 | J12: =RANK(I12,$I$4:$I$13,0) -> 7 | K12: 0.1653 | L12: =RANK(K12,$K$4:$K$13,0) -> 3
A13: Cholamandalam Finance | B13: CHOLAFIN | C13: 0.044 | D13: =RANK(C13,$C$4:$C$13,1) -> 9 | E13: 0.08 | F13: =RANK(E13,$E$4:$E$13,0) -> 3 | G13: 0.033 | H13: =RANK(G13,$G$4:$G$13,0) -> 3 | I13: 0.1921 | J13: =RANK(I13,$I$4:$I$13,0) -> 8 | K13: 0.197 | L13: =RANK(K13,$K$4:$K$13,0) -> 1
A15: Metric values (blue) are user-compiled inputs and may differ marginally from the headline figures on '1. Valuation Screen' (restated disclosures / rounding). Rank columns are formulas.

Sheet 3. Weighted Normalize Model
A1: NBFC Weighted Normalize Model
A2: Each metric is min-max normalized across the 10 disclosed names (1 = best, 0 = worst); GNPA is inverted since lower is better. Composite = Σ (normalized value × weight). Higher composite = better overall rank. Edit the yellow weight cells to re-run the model.
J4: Weight assumptions
J5: GNPA | K5: 0.3
J6: NIM | K6: 0.25
J7: ROA | K7: 0.2
J8: CAR | K8: 0.15
J9: ROE | K9: 0.1
J10: Total | K10: =SUM(K5:K9) -> 1
A12: Company Name | B12: Ticker | C12: GNPA Weighted | D12: NIM Weighted | E12: ROA Weighted | F12: CAR Weighted | G12: ROE Weighted | H12: Composite Score | I12: Overall Rank
A13: Aavas Financiers | B13: AAVAS | C13: =(('2. Fundamental Ranking'!$C$12-'2. Fundamental Ranking'!C4)/('2. Fundamental Ranking'!$C$12-'2. Fundamental Ranking'!$C$4))*$K$5 -> 0.3 | D13: =(('2. Fundamental Ranking'!E4-'2. Fundamental Ranking'!$E$8)/('2. Fundamental Ranking'!$E$6-'2. Fundamental Ranking'!$E$8))*$K$6 -> 0.076396973 | E13: =(('2. Fundamental Ranking'!G4-'2. Fundamental Ranking'!$G$11)/('2. Fundamental Ranking'!$G$6-'2. Fundamental Ranking'!$G$11))*$K$7 -> 0.046875 | F13: =(('2. Fundamental Ranking'!I4-'2. Fundamental Ranking'!$I$9)/('2. Fundamental Ranking'!$I$6-'2. Fundamental Ranking'!$I$9))*$K$8 -> 0.11695376 | G13: =(('2. Fundamental Ranking'!K4-'2. Fundamental Ranking'!$K$11)/('2. Fundamental Ranking'!$K$13-'2. Fundamental Ranking'!$K$11))*$K$9 -> 0.053617363 | H13: =SUM(C13:G13) -> 0.5938431 | I13: =RANK(H13,$H$13:$H$22,0) -> 2
A14: Home First Finance Company India | B14: HOMEFIRST | C14: =(('2. Fundamental Ranking'!$C$12-'2. Fundamental Ranking'!C5)/('2. Fundamental Ranking'!$C$12-'2. Fundamental Ranking'!$C$4))*$K$5 -> 0.23626062 | D14: =(('2. Fundamental Ranking'!E5-'2. Fundamental Ranking'!$E$8)/('2. Fundamental Ranking'!$E$6-'2. Fundamental Ranking'!$E$8))*$K$6 -> 0.043946449 | E14: =(('2. Fundamental Ranking'!G5-'2. Fundamental Ranking'!$G$11)/('2. Fundamental Ranking'!$G$6-'2. Fundamental Ranking'!$G$11))*$K$7 -> 0.064204545 | F14: =(('2. Fundamental Ranking'!I5-'2. Fundamental Ranking'!$I$9)/('2. Fundamental Ranking'!$I$6-'2. Fundamental Ranking'!$I$9))*$K$8 -> 0.11468722 | G14: =(('2. Fundamental Ranking'!K5-'2. Fundamental Ranking'!$K$11)/('2. Fundamental Ranking'!$K$13-'2. Fundamental Ranking'!$K$11))*$K$9 -> 0.04134929 | H14: =SUM(C14:G14) -> 0.50044812 | I14: =RANK(H14,$H$13:$H$22,0) -> 3
A15: Five-Star Business Finance | B15: FIVESTAR | C15: =(('2. Fundamental Ranking'!$C$12-'2. Fundamental Ranking'!C6)/('2. Fundamental Ranking'!$C$12-'2. Fundamental Ranking'!$C$4))*$K$5 -> 0.10283286 | D15: =(('2. Fundamental Ranking'!E6-'2. Fundamental Ranking'!$E$8)/('2. Fundamental Ranking'!$E$6-'2. Fundamental Ranking'!$E$8))*$K$6 -> 0.25 | E15: =(('2. Fundamental Ranking'!G6-'2. Fundamental Ranking'!$G$11)/('2. Fundamental Ranking'!$G$6-'2. Fundamental Ranking'!$G$11))*$K$7 -> 0.2 | F15: =(('2. Fundamental Ranking'!I6-'2. Fundamental Ranking'!$I$9)/('2. Fundamental Ranking'!$I$6-'2. Fundamental Ranking'!$I$9))*$K$8 -> 0.15 | G15: =(('2. Fundamental Ranking'!K6-'2. Fundamental Ranking'!$K$11)/('2. Fundamental Ranking'!$K$13-'2. Fundamental Ranking'!$K$11))*$K$9 -> 0.07073955 | H15: =SUM(C15:G15) -> 0.77357241 | I15: =RANK(H15,$H$13:$H$22,0) -> 1
A16: IIFL Finance | B16: IIFL | C16: =(('2. Fundamental Ranking'!$C$12-'2. Fundamental Ranking'!C7)/('2. Fundamental Ranking'!$C$12-'2. Fundamental Ranking'!$C$4))*$K$5 -> 0.26175637 | D16: =(('2. Fundamental Ranking'!E7-'2. Fundamental Ranking'!$E$8)/('2. Fundamental Ranking'!$E$6-'2. Fundamental Ranking'!$E$8))*$K$6 -> 0.049767171 | E16: =(('2. Fundamental Ranking'!G7-'2. Fundamental Ranking'!$G$11)/('2. Fundamental Ranking'!$G$6-'2. Fundamental Ranking'!$G$11))*$K$7 -> 0.021590909 | F16: =(('2. Fundamental Ranking'!I7-'2. Fundamental Ranking'!$I$9)/('2. Fundamental Ranking'!$I$6-'2. Fundamental Ranking'!$I$9))*$K$8 -> 0.029465095 | G16: =(('2. Fundamental Ranking'!K7-'2. Fundamental Ranking'!$K$11)/('2. Fundamental Ranking'!$K$13-'2. Fundamental Ranking'!$K$11))*$K$9 -> 0.046945338 | H16: =SUM(C16:G16) -> 0.40952489 | I16: =RANK(H16,$H$13:$H$22,0) -> 4
A17: LIC Housing Finance | B17: LICHSGFIN | C17: =(('2. Fundamental Ranking'!$C$12-'2. Fundamental Ranking'!C8)/('2. Fundamental Ranking'!$C$12-'2. Fundamental Ranking'!$C$4))*$K$5 -> 0.28640227 | D17: =(('2. Fundamental Ranking'!E8-'2. Fundamental Ranking'!$E$8)/('2. Fundamental Ranking'!$E$6-'2. Fundamental Ranking'!$E$8))*$K$6 -> 0 | E17: =(('2. Fundamental Ranking'!G8-'2. Fundamental Ranking'!$G$11)/('2. Fundamental Ranking'!$G$6-'2. Fundamental Ranking'!$G$11))*$K$7 -> 0.0039772727 | F17: =(('2. Fundamental Ranking'!I8-'2. Fundamental Ranking'!$I$9)/('2. Fundamental Ranking'!$I$6-'2. Fundamental Ranking'!$I$9))*$K$8 -> 0.024569356 | G17: =(('2. Fundamental Ranking'!K8-'2. Fundamental Ranking'!$K$11)/('2. Fundamental Ranking'!$K$13-'2. Fundamental Ranking'!$K$11))*$K$9 -> 0.054180064 | H17: =SUM(C17:G17) -> 0.36912896 | I17: =RANK(H17,$H$13:$H$22,0) -> 5
A18: Mahindra & Mahindra Financial Services | B18: M&MFIN | C18: =(('2. Fundamental Ranking'!$C$12-'2. Fundamental Ranking'!C9)/('2. Fundamental Ranking'!$C$12-'2. Fundamental Ranking'!$C$4))*$K$5 -> 0.10028329 | D18: =(('2. Fundamental Ranking'!E9-'2. Fundamental Ranking'!$E$8)/('2. Fundamental Ranking'!$E$6-'2. Fundamental Ranking'!$E$8))*$K$6 -> 0.064318976 | E18: =(('2. Fundamental Ranking'!G9-'2. Fundamental Ranking'!$G$11)/('2. Fundamental Ranking'!$G$6-'2. Fundamental Ranking'!$G$11))*$K$7 -> 0.010227273 | F18: =(('2. Fundamental Ranking'!I9-'2. Fundamental Ranking'!$I$9)/('2. Fundamental Ranking'!$I$6-'2. Fundamental Ranking'!$I$9))*$K$8 -> 0 | G18: =(('2. Fundamental Ranking'!K9-'2. Fundamental Ranking'!$K$11)/('2. Fundamental Ranking'!$K$13-'2. Fundamental Ranking'!$K$11))*$K$9 -> 0.042122186 | H18: =SUM(C18:G18) -> 0.21695172 | I18: =RANK(H18,$H$13:$H$22,0) -> 9
A19: Sundaram Finance | B19: SUNDARMFIN | C19: =(('2. Fundamental Ranking'!$C$12-'2. Fundamental Ranking'!C10)/('2. Fundamental Ranking'!$C$12-'2. Fundamental Ranking'!$C$4))*$K$5 -> 0.20736544 | D19: =(('2. Fundamental Ranking'!E10-'2. Fundamental Ranking'!$E$8)/('2. Fundamental Ranking'!$E$6-'2. Fundamental Ranking'!$E$8))*$K$6 -> 0.039144354 | E19: =(('2. Fundamental Ranking'!G10-'2. Fundamental Ranking'!$G$11)/('2. Fundamental Ranking'!$G$6-'2. Fundamental Ranking'!$G$11))*$K$7 -> 0.039488636 | F19: =(('2. Fundamental Ranking'!I10-'2. Fundamental Ranking'!$I$9)/('2. Fundamental Ranking'!$I$6-'2. Fundamental Ranking'!$I$9))*$K$8 -> 0.00067996374 | G19: =(('2. Fundamental Ranking'!K10-'2. Fundamental Ranking'!$K$11)/('2. Fundamental Ranking'!$K$13-'2. Fundamental Ranking'!$K$11))*$K$9 -> 0.082315113 | H19: =SUM(C19:G19) -> 0.36899351 | I19: =RANK(H19,$H$13:$H$22,0) -> 6
A20: Muthoot Finance | B20: MUTHOOTFIN | C20: =(('2. Fundamental Ranking'!$C$12-'2. Fundamental Ranking'!C11)/('2. Fundamental Ranking'!$C$12-'2. Fundamental Ranking'!$C$4))*$K$5 -> 0.18951841 | D20: =(('2. Fundamental Ranking'!E11-'2. Fundamental Ranking'!$E$8)/('2. Fundamental Ranking'!$E$6-'2. Fundamental Ranking'!$E$8))*$K$6 -> 0.051513388 | E20: =(('2. Fundamental Ranking'!G11-'2. Fundamental Ranking'!$G$11)/('2. Fundamental Ranking'!$G$6-'2. Fundamental Ranking'!$G$11))*$K$7 -> 0 | F20: =(('2. Fundamental Ranking'!I11-'2. Fundamental Ranking'!$I$9)/('2. Fundamental Ranking'!$I$6-'2. Fundamental Ranking'!$I$9))*$K$8 -> 0.055303717 | G20: =(('2. Fundamental Ranking'!K11-'2. Fundamental Ranking'!$K$11)/('2. Fundamental Ranking'!$K$13-'2. Fundamental Ranking'!$K$11))*$K$9 -> 0 | H20: =SUM(C20:G20) -> 0.29633552 | I20: =RANK(H20,$H$13:$H$22,0) -> 7
A21: Shriram Finance | B21: SHRIRAMFIN | C21: =(('2. Fundamental Ranking'!$C$12-'2. Fundamental Ranking'!C12)/('2. Fundamental Ranking'!$C$12-'2. Fundamental Ranking'!$C$4))*$K$5 -> 0 | D21: =(('2. Fundamental Ranking'!E12-'2. Fundamental Ranking'!$E$8)/('2. Fundamental Ranking'!$E$6-'2. Fundamental Ranking'!$E$8))*$K$6 -> 0.082945285 | E21: =(('2. Fundamental Ranking'!G12-'2. Fundamental Ranking'!$G$11)/('2. Fundamental Ranking'!$G$6-'2. Fundamental Ranking'!$G$11))*$K$7 -> 0.041477273 | F21: =(('2. Fundamental Ranking'!I12-'2. Fundamental Ranking'!$I$9)/('2. Fundamental Ranking'!$I$6-'2. Fundamental Ranking'!$I$9))*$K$8 -> 0.0072529465 | G21: =(('2. Fundamental Ranking'!K12-'2. Fundamental Ranking'!$K$11)/('2. Fundamental Ranking'!$K$13-'2. Fundamental Ranking'!$K$11))*$K$9 -> 0.074517685 | H21: =SUM(C21:G21) -> 0.20619319 | I21: =RANK(H21,$H$13:$H$22,0) -> 10
A22: Cholamandalam Finance | B22: CHOLAFIN | C22: =(('2. Fundamental Ranking'!$C$12-'2. Fundamental Ranking'!C13)/('2. Fundamental Ranking'!$C$12-'2. Fundamental Ranking'!$C$4))*$K$5 -> 0.01529745 | D22: =(('2. Fundamental Ranking'!E13-'2. Fundamental Ranking'!$E$8)/('2. Fundamental Ranking'!$E$6-'2. Fundamental Ranking'!$E$8))*$K$6 -> 0.0774156 | E22: =(('2. Fundamental Ranking'!G13-'2. Fundamental Ranking'!$G$11)/('2. Fundamental Ranking'!$G$6-'2. Fundamental Ranking'!$G$11))*$K$7 -> 0.047159091 | F22: =(('2. Fundamental Ranking'!I13-'2. Fundamental Ranking'!$I$9)/('2. Fundamental Ranking'!$I$6-'2. Fundamental Ranking'!$I$9))*$K$8 -> 0.0018585675 | G22: =(('2. Fundamental Ranking'!K13-'2. Fundamental Ranking'!$K$11)/('2. Fundamental Ranking'!$K$13-'2. Fundamental Ranking'!$K$11))*$K$9 -> 0.1 | H22: =SUM(C22:G22) -> 0.24173071 | I22: =RANK(H22,$H$13:$H$22,0) -> 8
A24: Weighted columns (green) pull normalized metric values live from '2. Fundamental Ranking'. Composite (Horizontal Addition) and Overall Rank recalculate automatically when the yellow weights above are changed.

Sheet 4. Portfolio Allocation
A1: PMS Portfolio Allocation
A2: Share holdings (blue) are user-selected inputs, priced at market rates. Overall Rank (green) is linked live from '3. Weighted Normalize Model' and updates automatically if the weights or underlying data change.
A4: Total Investable Budget (₹) | B4: 100000000
A5: N (number of holdings) | B5: 10
A7: Company Name | B7: Ticker | C7: Price (₹) | D7: No. of Shares | E7: Asset Allocation (₹) | F7: Overall Rank | G7: % of Portfolio | H7: Actual Allocation (₹) | I7: % of Portfolio
A8: Aavas Financiers | B8: AAVAS | C8: 1509 | D8: 10844 | E8: =C8*D8 -> 16363596 | F8: ='3. Weighted Normalize Model'!I13 -> 2 | G8: =E8/SUM($E$8:$E$17) -> 0.16363752 | H8: =G8*C8 -> 246.92902 | I8: =H8/SUM($H$8:$H$17) -> 0.17105335
A9: Home First Finance Company India | B9: HOMEFIRST | C9: 1207 | D9: 12051 | E9: =C9*D9 -> 14545557 | F9: ='3. Weighted Normalize Model'!I14 -> 3 | G9: =E9/SUM($E$8:$E$17) -> 0.14545696 | H9: =G9*C9 -> 175.56655 | I9: =H9/SUM($H$8:$H$17) -> 0.12161894
A10: Five-Star Business Finance | B10: FIVESTAR | C10: 551 | D10: 32998 | E10: =C10*D10 -> 18181898 | F10: ='3. Weighted Normalize Model'!I15 -> 1 | G10: =E10/SUM($E$8:$E$17) -> 0.18182071 | H10: =G10*C10 -> 100.18321 | I10: =H10/SUM($H$8:$H$17) -> 0.06939919
A11: IIFL Finance | B11: IIFL | C11: 526 | D11: 24196 | E11: =C11*D11 -> 12727096 | F11: ='3. Weighted Normalize Model'!I16 -> 4 | G11: =E11/SUM($E$8:$E$17) -> 0.12727217 | H11: =G11*C11 -> 66.945163 | I11: =H11/SUM($H$8:$H$17) -> 0.046374437
A12: LIC Housing Finance | B12: LICHSGFIN | C12: 544 | D12: 20053 | E12: =C12*D12 -> 10908832 | F12: ='3. Weighted Normalize Model'!I17 -> 5 | G12: =E12/SUM($E$8:$E$17) -> 0.10908936 | H12: =G12*C12 -> 59.344612 | I12: =H12/SUM($H$8:$H$17) -> 0.041109362
A13: Mahindra & Mahindra Financial Services | B13: M&MFIN | C13: 332 | D13: 10953 | E13: =C13*D13 -> 3636396 | F13: ='3. Weighted Normalize Model'!I18 -> 9 | G13: =E13/SUM($E$8:$E$17) -> 0.036364307 | H13: =G13*C13 -> 12.07295 | I13: =H13/SUM($H$8:$H$17) -> 0.0083632069
A14: Sundaram Finance | B14: SUNDARMFIN | C14: 4784 | D14: 1900 | E14: =C14*D14 -> 9089600 | F14: ='3. Weighted Normalize Model'!I19 -> 6 | G14: =E14/SUM($E$8:$E$17) -> 0.090896866 | H14: =G14*C14 -> 434.85061 | I14: =H14/SUM($H$8:$H$17) -> 0.30123091
A15: Muthoot Finance | B15: MUTHOOTFIN | C15: 3124 | D15: 2328 | E15: =C15*D15 -> 7272672 | F15: ='3. Weighted Normalize Model'!I20 -> 7 | G15: =E15/SUM($E$8:$E$17) -> 0.072727413 | H15: =G15*C15 -> 227.20044 | I15: =H15/SUM($H$8:$H$17) -> 0.15738691
A16: Shriram Finance | B16: SHRIRAMFIN | C16: 1067 | D16: 1704 | E16: =C16*D16 -> 1818168 | F16: ='3. Weighted Normalize Model'!I21 -> 10 | G16: =E16/SUM($E$8:$E$17) -> 0.018181853 | H16: =G16*C16 -> 19.400037 | I16: =H16/SUM($H$8:$H$17) -> 0.013438847
A17: Cholamandalam Finance | B17: CHOLAFIN | C17: 1853 | D17: 2944 | E17: =C17*D17 -> 5455232 | F17: ='3. Weighted Normalize Model'!I22 -> 8 | G17: =E17/SUM($E$8:$E$17) -> 0.05455284 | H17: =G17*C17 -> 101.08641 | I17: =H17/SUM($H$8:$H$17) -> 0.070024857
A18: Total | E18: =SUM(E8:E17) -> 99999047 | G18: =SUM(G8:G17) -> 1 | H18: =SUM(H8:H17) -> 1443.579 | I18: =SUM(I8:I17) -> 1
A20: Price and No. of Shares (blue) are user-supplied inputs. Overall Rank (green) is linked live from '3. Weighted Normalize Model' — it will change automatically now that the model's rank-direction error is fixed, so you may want to revisit share allocations to match the corrected ranking.
