Workbook

Sheet Cover Page
A1: PORTFOLIO BASKET TRACKERS — WEEKLY PERFORMANCE REPORT
A2: 7-Basket Buy-and-Hold Tracking | 6/30/2026 - 7/31/2026 (5 Weekly Checkpoints)
A4: Prepared By | B4: Vishv Jeet Singh Thakur
A5: Submitted To | B5: Nikesh Ruparel
A6: Institution | B6: UPES
A7: Programme | B7: MBA in Strategic Financial Management in collaboration with EY
A8: Batch | B8: F4- Jun-2026
A9: Report Type | B9: Weekly Portfolio Basket Performance Tracker
A10: Investment Universe | B10: NSE-Listed Equities - 7 Baskets, Equal-Weighted at Inception
A12: BASKET SUMMARY - LATEST (WEEK 5) HOLDINGS & RETURN
A13: # | B13: Basket | C13: Holdings | D13: Total Investment (Rs) | E13: Return (Week 5)
A14: 1 | B14: Method 1 | C14: ='Method 1'!A87 -> 11 | D14: ='Method 1'!B87 -> 114341.55 | E14: ='Method 1'!F87 -> -0.026531038
A15: 2 | B15: Method 2 | C15: ='Method 2'!A91 -> 12 | D15: ='Method 2'!B91 -> 56331.88 | E15: ='Method 2'!F91 -> 0.075766333
A16: 3 | B16: Method 3 | C16: ='Method 3'!A87 -> 11 | D16: ='Method 3'!B87 -> 22506.79 | E16: ='Method 3'!F87 -> 0.018406445
A17: 4 | B17: Method 4 | C17: ='Method 4'!A79 -> 9 | D17: ='Method 4'!B79 -> 1153084 | E17: ='Method 4'!F79 -> 0.011477655
A18: 5 | B18: Method 5 | C18: ='Method 5'!A99 -> 14 | D18: ='Method 5'!B99 -> 134726.25 | E18: ='Method 5'!F99 -> 0.007353875
A19: 6 | B19: Method 6 | C19: ='Method 6'!A103 -> 15 | D19: ='Method 6'!B103 -> 40620.12 | E19: ='Method 6'!F103 -> 0.038195111
A20: 7 | B20: Method Self | C20: ='Method Self'!A119 -> 19 | D20: ='Method Self'!B119 -> 203585.65 | E20: ='Method Self'!F119 -> 0.04375996
A21: TOTAL / AVERAGE ACROSS ALL BASKETS | C21: =SUM(C14:C20) -> 91 | D21: =SUM(D14:D20) -> 1725196.2 | E21: =AVERAGE(E14:E20) -> 0.024061192
A23: Note: Holdings, Total Investment and Return figures pull live from the Week 5 snapshot on each basket sheet.

Sheet Content
A1: TABLE OF CONTENTS
A2: Portfolio Basket Trackers - Weekly Performance Report | 7 Baskets | 5 Weekly Checkpoints
A4: # | B4: Section | C4: What's Inside | D4: Go To
A5: 1 | B5: Cover Page | C5: Report details, submission info & basket-level Week 5 holdings / return summary | D5: Open sheet
A6: 2 | B6: Method 1 | C6: Method 1 - 5-week basket tracking: holdings, weighted allocation & weekly return snapshots | D6: Open sheet
A7: 3 | B7: Method 2 | C7: Method 2 - 5-week basket tracking: holdings, weighted allocation & weekly return snapshots | D7: Open sheet
A8: 4 | B8: Method 3 | C8: Method 3 - 5-week basket tracking: holdings, weighted allocation & weekly return snapshots | D8: Open sheet
A9: 5 | B9: Method 4 | C9: Method 4 - 5-week basket tracking: holdings, weighted allocation & weekly return snapshots | D9: Open sheet
A10: 6 | B10: Method 5 | C10: Method 5 - 5-week basket tracking: holdings, weighted allocation & weekly return snapshots | D10: Open sheet
A11: 7 | B11: Method 6 | C11: Method 6 - 5-week basket tracking: holdings, weighted allocation & weekly return snapshots | D11: Open sheet
A12: 8 | B12: Method Self | C12: Method Self - 5-week basket tracking: holdings, weighted allocation & weekly return snapshots | D12: Open sheet
A13: Note: Click "Open sheet" to jump directly to a section. Each basket sheet shows 5 weekly snapshots (holdings, capital deployed, growth, return) followed by the full stock-level holdings table for that week.

Sheet Method 1
A1: PORTFOLIO BASKET TRACKER — METHOD 1
A2: Student: Vishv Jeet Singh Thakur | Institution: UPES | Weekly Basket Performance Tracking (Basis Fixed at Inception)
A4: WEEK 1 SNAPSHOT — 6/30/2026 - 7/3/2026 | I4: QUERY / SCREENING CRITERIA
A5: Reference stock (basis fixed at inception): Polycab India Ltd (₹9961) | I5: Return on equity > 15 AND
A6: Holdings | B6: Total Investment (₹) | D6: Growth (₹) | F6: Return (6/30/2026 - 7/3/2026) | I6: Sales growth > 15 AND
A7: =COUNT(B11:B21) -> 11 | B7: =F22 -> 114341.55 | D7: =G22 -> 113377.1 | F7: =(G22-F22)/F22 -> -0.0084348166 | I7: Change in FII holding > 1
A9: HOLDINGS — WEEK 1
A10: Company Name | B10: Day 1 Closing (₹) | C10: 1 Week Closing (₹) | D10: Return (%) | E10: Basis (Shares) | F10: Investment (₹) | G10: Growth (₹)
A11: Vedanta Ltd | B11: 280.75 | C11: 280.4 | D11: =(C11-B11)/B11 -> -0.0012466607 | E11: =ROUND($B$21/B11,0) -> 35 | F11: =B11*E11 -> 9826.25 | G11: =C11*E11 -> 9814
A12: Premier Energies Ltd | B12: 1051 | C12: 1046.8 | D12: =(C12-B12)/B12 -> -0.0039961941 | E12: =ROUND($B$21/B12,0) -> 9 | F12: =B12*E12 -> 9459 | G12: =C12*E12 -> 9421.2
A13: Aegis Logistics Ltd | B13: 1173.95 | C13: 1325.4 | D13: =(C13-B13)/B13 -> 0.1290089 | E13: =ROUND($B$21/B13,0) -> 8 | F13: =B13*E13 -> 9391.6 | G13: =C13*E13 -> 10603.2
A14: Glenmark Pharmaceuticals Ltd | B14: 2204.3 | C14: 2211 | D14: =(C14-B14)/B14 -> 0.0030395137 | E14: =ROUND($B$21/B14,0) -> 5 | F14: =B14*E14 -> 11021.5 | G14: =C14*E14 -> 11055
A15: Multi Commodity Exchange of India Ltd | B15: 2837.2 | C15: 2814 | D15: =(C15-B15)/B15 -> -0.008177076 | E15: =ROUND($B$21/B15,0) -> 4 | F15: =B15*E15 -> 11348.8 | G15: =C15*E15 -> 11256
A16: Aditya Infotech Ltd | B16: 3647 | C16: 3588.4 | D16: =(C16-B16)/B16 -> -0.016068001 | E16: =ROUND($B$21/B16,0) -> 3 | F16: =B16*E16 -> 10941 | G16: =C16*E16 -> 10765.2
A17: BSE Ltd | B17: 3865.6 | C17: 3816.6 | D17: =(C17-B17)/B17 -> -0.012675911 | E17: =ROUND($B$21/B17,0) -> 3 | F17: =B17*E17 -> 11596.8 | G17: =C17*E17 -> 11449.8
A18: Hero MotoCorp Ltd | B18: 4794.3 | C18: 4852.6 | D18: =(C18-B18)/B18 -> 0.012160274 | E18: =ROUND($B$21/B18,0) -> 2 | F18: =B18*E18 -> 9588.6 | G18: =C18*E18 -> 9705.2
A19: GE Vernova T&D India Ltd | B19: 4944 | C19: 4401.5 | D19: =(C19-B19)/B19 -> -0.10972896 | E19: =ROUND($B$21/B19,0) -> 2 | F19: =B19*E19 -> 9888 | G19: =C19*E19 -> 8803
A20: Cummins India Ltd | B20: 5659.5 | C20: 5478 | D20: =(C20-B20)/B20 -> -0.032069971 | E20: =ROUND($B$21/B20,0) -> 2 | F20: =B20*E20 -> 11319 | G20: =C20*E20 -> 10956
A21: Polycab India Ltd | B21: 9961 | C21: 9548.5 | D21: =(C21-B21)/B21 -> -0.041411505 | E21: =ROUND($B$21/B21,0) -> 1 | F21: =B21*E21 -> 9961 | G21: =C21*E21 -> 9548.5
A22: Portfolio Total | F22: =SUM(F11:F21) -> 114341.55 | G22: =SUM(G11:G21) -> 113377.1
A24: WEEK 2 SNAPSHOT — 6/30/2026 - 7/10/2026
A25: Reference stock (basis fixed at inception): Hero MotoCorp Ltd (₹4794.3)
A26: Holdings | B26: Total Investment (₹) | D26: Growth (₹) | F26: Return (6/30/2026 - 7/10/2026)
A27: =COUNT(B31:B41) -> 11 | B27: =F42 -> 114341.55 | D27: =G42 -> 114188.05 | F27: =(G42-F42)/F42 -> -0.0013424691
A29: HOLDINGS — WEEK 2
A30: Company Name | B30: Day 1 Closing (₹) | C30: 2 Week Closing (₹) | D30: Return (%) | E30: Basis (Shares) | F30: Investment (₹) | G30: Growth (₹)
A31: Vedanta Ltd | B31: 280.75 | C31: 272.55 | D31: =(C31-B31)/B31 -> -0.02920748 | E31: =ROUND($B$21/B31,0) -> 35 | F31: =B31*E31 -> 9826.25 | G31: =C31*E31 -> 9539.25
A32: Premier Energies Ltd | B32: 1051 | C32: 1117.2 | D32: =(C32-B32)/B32 -> 0.062987631 | E32: =ROUND($B$21/B32,0) -> 9 | F32: =B32*E32 -> 9459 | G32: =C32*E32 -> 10054.8
A33: Aegis Logistics Ltd | B33: 1173.95 | C33: 1246.1 | D33: =(C33-B33)/B33 -> 0.061459176 | E33: =ROUND($B$21/B33,0) -> 8 | F33: =B33*E33 -> 9391.6 | G33: =C33*E33 -> 9968.8
A34: Glenmark Pharmaceuticals Ltd | B34: 2204.3 | C34: 2282.9 | D34: =(C34-B34)/B34 -> 0.035657578 | E34: =ROUND($B$21/B34,0) -> 5 | F34: =B34*E34 -> 11021.5 | G34: =C34*E34 -> 11414.5
A35: Multi Commodity Exchange of India Ltd | B35: 2837.2 | C35: 2770.7 | D35: =(C35-B35)/B35 -> -0.023438601 | E35: =ROUND($B$21/B35,0) -> 4 | F35: =B35*E35 -> 11348.8 | G35: =C35*E35 -> 11082.8
A36: Aditya Infotech Ltd | B36: 3647 | C36: 3662.4 | D36: =(C36-B36)/B36 -> 0.0042226488 | E36: =ROUND($B$21/B36,0) -> 3 | F36: =B36*E36 -> 10941 | G36: =C36*E36 -> 10987.2
A37: BSE Ltd | B37: 3865.6 | C37: 3811.6 | D37: =(C37-B37)/B37 -> -0.013969371 | E37: =ROUND($B$21/B37,0) -> 3 | F37: =B37*E37 -> 11596.8 | G37: =C37*E37 -> 11434.8
A38: Hero MotoCorp Ltd | B38: 4794.3 | C38: 4949.1 | D38: =(C38-B38)/B38 -> 0.032288342 | E38: =ROUND($B$21/B38,0) -> 2 | F38: =B38*E38 -> 9588.6 | G38: =C38*E38 -> 9898.2
A39: GE Vernova T&D India Ltd | B39: 4944 | C39: 4677.1 | D39: =(C39-B39)/B39 -> -0.053984628 | E39: =ROUND($B$21/B39,0) -> 2 | F39: =B39*E39 -> 9888 | G39: =C39*E39 -> 9354.2
A40: Cummins India Ltd | B40: 5659.5 | C40: 5621.5 | D40: =(C40-B40)/B40 -> -0.0067143741 | E40: =ROUND($B$21/B40,0) -> 2 | F40: =B40*E40 -> 11319 | G40: =C40*E40 -> 11243
A41: Polycab India Ltd | B41: 9961 | C41: 9210.5 | D41: =(C41-B41)/B41 -> -0.075343841 | E41: =ROUND($B$21/B41,0) -> 1 | F41: =B41*E41 -> 9961 | G41: =C41*E41 -> 9210.5
A42: Portfolio Total | F42: =SUM(F31:F41) -> 114341.55 | G42: =SUM(G31:G41) -> 114188.05
A44: WEEK 3 SNAPSHOT — 6/30/2026 - 7/17/2026
A45: Reference stock (basis fixed at inception): Hero MotoCorp Ltd (₹4794.3)
A46: Holdings | B46: Total Investment (₹) | D46: Growth (₹) | F46: Return (6/30/2026 - 7/17/2026)
A47: =COUNT(B51:B61) -> 11 | B47: =F62 -> 114341.55 | D47: =G62 -> 111534.05 | F47: =(G62-F62)/F62 -> -0.024553629
A49: HOLDINGS — WEEK 3
A50: Company Name | B50: Day 1 Closing (₹) | C50: 3 Week Closing (₹) | D50: Return (%) | E50: Basis (Shares) | F50: Investment (₹) | G50: Growth (₹)
A51: Vedanta Ltd | B51: 280.75 | C51: 253.05 | D51: =(C51-B51)/B51 -> -0.098664292 | E51: =ROUND($B$21/B51,0) -> 35 | F51: =B51*E51 -> 9826.25 | G51: =C51*E51 -> 8856.75
A52: Premier Energies Ltd | B52: 1051 | C52: 1086.2 | D52: =(C52-B52)/B52 -> 0.033491912 | E52: =ROUND($B$21/B52,0) -> 9 | F52: =B52*E52 -> 9459 | G52: =C52*E52 -> 9775.8
A53: Aegis Logistics Ltd | B53: 1173.95 | C53: 1349.1 | D53: =(C53-B53)/B53 -> 0.14919715 | E53: =ROUND($B$21/B53,0) -> 8 | F53: =B53*E53 -> 9391.6 | G53: =C53*E53 -> 10792.8
A54: Glenmark Pharmaceuticals Ltd | B54: 2204.3 | C54: 2235.5 | D54: =(C54-B54)/B54 -> 0.014154153 | E54: =ROUND($B$21/B54,0) -> 5 | F54: =B54*E54 -> 11021.5 | G54: =C54*E54 -> 11177.5
A55: Multi Commodity Exchange of India Ltd | B55: 2837.2 | C55: 2747.5 | D55: =(C55-B55)/B55 -> -0.031615677 | E55: =ROUND($B$21/B55,0) -> 4 | F55: =B55*E55 -> 11348.8 | G55: =C55*E55 -> 10990
A56: Aditya Infotech Ltd | B56: 3647 | C56: 3614.4 | D56: =(C56-B56)/B56 -> -0.0089388539 | E56: =ROUND($B$21/B56,0) -> 3 | F56: =B56*E56 -> 10941 | G56: =C56*E56 -> 10843.2
A57: BSE Ltd | B57: 3865.6 | C57: 3581.8 | D57: =(C57-B57)/B57 -> -0.073416805 | E57: =ROUND($B$21/B57,0) -> 3 | F57: =B57*E57 -> 11596.8 | G57: =C57*E57 -> 10745.4
A58: Hero MotoCorp Ltd | B58: 4794.3 | C58: 4909.9 | D58: =(C58-B58)/B58 -> 0.024111966 | E58: =ROUND($B$21/B58,0) -> 2 | F58: =B58*E58 -> 9588.6 | G58: =C58*E58 -> 9819.8
A59: GE Vernova T&D India Ltd | B59: 4944 | C59: 4387.4 | D59: =(C59-B59)/B59 -> -0.11258091 | E59: =ROUND($B$21/B59,0) -> 2 | F59: =B59*E59 -> 9888 | G59: =C59*E59 -> 8774.8
A60: Cummins India Ltd | B60: 5659.5 | C60: 5448 | D60: =(C60-B60)/B60 -> -0.037370792 | E60: =ROUND($B$21/B60,0) -> 2 | F60: =B60*E60 -> 11319 | G60: =C60*E60 -> 10896
A61: Polycab India Ltd | B61: 9961 | C61: 8862 | D61: =(C61-B61)/B61 -> -0.11033029 | E61: =ROUND($B$21/B61,0) -> 1 | F61: =B61*E61 -> 9961 | G61: =C61*E61 -> 8862
A62: Portfolio Total | F62: =SUM(F51:F61) -> 114341.55 | G62: =SUM(G51:G61) -> 111534.05
A64: WEEK 4 SNAPSHOT — 6/30/2026 - 7/24/2026
A65: Reference stock (basis fixed at inception): Hero MotoCorp Ltd (₹4794.3)
A66: Holdings | B66: Total Investment (₹) | D66: Growth (₹) | F66: Return (6/30/2026 - 7/24/2026)
A67: =COUNT(B71:B81) -> 11 | B67: =F82 -> 114341.55 | D67: =G82 -> 110837.85 | F67: =(G82-F82)/F82 -> -0.030642404
A69: HOLDINGS — WEEK 4
A70: Company Name | B70: Day 1 Closing (₹) | C70: 4 Week Closing (₹) | D70: Return (%) | E70: Basis (Shares) | F70: Investment (₹) | G70: Growth (₹)
A71: Vedanta Ltd | B71: 280.75 | C71: 264.65 | D71: =(C71-B71)/B71 -> -0.057346394 | E71: =ROUND($B$21/B71,0) -> 35 | F71: =B71*E71 -> 9826.25 | G71: =C71*E71 -> 9262.75
A72: Premier Energies Ltd | B72: 1051 | C72: 1019.3 | D72: =(C72-B72)/B72 -> -0.030161751 | E72: =ROUND($B$21/B72,0) -> 9 | F72: =B72*E72 -> 9459 | G72: =C72*E72 -> 9173.7
A73: Aegis Logistics Ltd | B73: 1173.95 | C73: 1349.6 | D73: =(C73-B73)/B73 -> 0.14962307 | E73: =ROUND($B$21/B73,0) -> 8 | F73: =B73*E73 -> 9391.6 | G73: =C73*E73 -> 10796.8
A74: Glenmark Pharmaceuticals Ltd | B74: 2204.3 | C74: 2192 | D74: =(C74-B74)/B74 -> -0.0055800027 | E74: =ROUND($B$21/B74,0) -> 5 | F74: =B74*E74 -> 11021.5 | G74: =C74*E74 -> 10960
A75: Multi Commodity Exchange of India Ltd | B75: 2837.2 | C75: 2730 | D75: =(C75-B75)/B75 -> -0.03778373 | E75: =ROUND($B$21/B75,0) -> 4 | F75: =B75*E75 -> 11348.8 | G75: =C75*E75 -> 10920
A76: Aditya Infotech Ltd | B76: 3647 | C76: 3543.4 | D76: =(C76-B76)/B76 -> -0.02840691 | E76: =ROUND($B$21/B76,0) -> 3 | F76: =B76*E76 -> 10941 | G76: =C76*E76 -> 10630.2
A77: BSE Ltd | B77: 3865.6 | C77: 3549.7 | D77: =(C77-B77)/B77 -> -0.08172082 | E77: =ROUND($B$21/B77,0) -> 3 | F77: =B77*E77 -> 11596.8 | G77: =C77*E77 -> 10649.1
A78: Hero MotoCorp Ltd | B78: 4794.3 | C78: 5011 | D78: =(C78-B78)/B78 -> 0.045199508 | E78: =ROUND($B$21/B78,0) -> 2 | F78: =B78*E78 -> 9588.6 | G78: =C78*E78 -> 10022
A79: GE Vernova T&D India Ltd | B79: 4944 | C79: 4157.4 | D79: =(C79-B79)/B79 -> -0.15910194 | E79: =ROUND($B$21/B79,0) -> 2 | F79: =B79*E79 -> 9888 | G79: =C79*E79 -> 8314.8
A80: Cummins India Ltd | B80: 5659.5 | C80: 5600.5 | D80: =(C80-B80)/B80 -> -0.010424949 | E80: =ROUND($B$21/B80,0) -> 2 | F80: =B80*E80 -> 11319 | G80: =C80*E80 -> 11201
A81: Polycab India Ltd | B81: 9961 | C81: 8907.5 | D81: =(C81-B81)/B81 -> -0.10576247 | E81: =ROUND($B$21/B81,0) -> 1 | F81: =B81*E81 -> 9961 | G81: =C81*E81 -> 8907.5
A82: Portfolio Total | F82: =SUM(F71:F81) -> 114341.55 | G82: =SUM(G71:G81) -> 110837.85
A84: WEEK 5 SNAPSHOT — 6/30/2026 - 7/31/2026
A85: Reference stock (basis fixed at inception): Hero MotoCorp Ltd (₹4794.3)
A86: Holdings | B86: Total Investment (₹) | D86: Growth (₹) | F86: Return (6/30/2026 - 7/31/2026)
A87: =COUNT(B91:B101) -> 11 | B87: =F102 -> 114341.55 | D87: =G102 -> 111307.95 | F87: =(G102-F102)/F102 -> -0.026531038
A89: HOLDINGS — WEEK 5
A90: Company Name | B90: Day 1 Closing (₹) | C90: 5 Week Closing (₹) | D90: Return (%) | E90: Basis (Shares) | F90: Investment (₹) | G90: Growth (₹)
A91: Vedanta Ltd | B91: 280.75 | C91: 264.25 | D91: =(C91-B91)/B91 -> -0.058771149 | E91: =ROUND($B$21/B91,0) -> 35 | F91: =B91*E91 -> 9826.25 | G91: =C91*E91 -> 9248.75
A92: Premier Energies Ltd | B92: 1051 | C92: 1022.2 | D92: =(C92-B92)/B92 -> -0.027402474 | E92: =ROUND($B$21/B92,0) -> 9 | F92: =B92*E92 -> 9459 | G92: =C92*E92 -> 9199.8
A93: Aegis Logistics Ltd | B93: 1173.95 | C93: 1280.8 | D93: =(C93-B93)/B93 -> 0.091017505 | E93: =ROUND($B$21/B93,0) -> 8 | F93: =B93*E93 -> 9391.6 | G93: =C93*E93 -> 10246.4
A94: Glenmark Pharmaceuticals Ltd | B94: 2204.3 | C94: 2233.9 | D94: =(C94-B94)/B94 -> 0.013428299 | E94: =ROUND($B$21/B94,0) -> 5 | F94: =B94*E94 -> 11021.5 | G94: =C94*E94 -> 11169.5
A95: Multi Commodity Exchange of India Ltd | B95: 2837.2 | C95: 2692.2 | D95: =(C95-B95)/B95 -> -0.051106725 | E95: =ROUND($B$21/B95,0) -> 4 | F95: =B95*E95 -> 11348.8 | G95: =C95*E95 -> 10768.8
A96: Aditya Infotech Ltd | B96: 3647 | C96: 3391 | D96: =(C96-B96)/B96 -> -0.070194681 | E96: =ROUND($B$21/B96,0) -> 3 | F96: =B96*E96 -> 10941 | G96: =C96*E96 -> 10173
A97: BSE Ltd | B97: 3865.6 | C97: 3646.2 | D97: =(C97-B97)/B97 -> -0.056757036 | E97: =ROUND($B$21/B97,0) -> 3 | F97: =B97*E97 -> 11596.8 | G97: =C97*E97 -> 10938.6
A98: Hero MotoCorp Ltd | B98: 4794.3 | C98: 5386 | D98: =(C98-B98)/B98 -> 0.12341739 | E98: =ROUND($B$21/B98,0) -> 2 | F98: =B98*E98 -> 9588.6 | G98: =C98*E98 -> 10772
A99: GE Vernova T&D India Ltd | B99: 4944 | C99: 4323.3 | D99: =(C99-B99)/B99 -> -0.12554612 | E99: =ROUND($B$21/B99,0) -> 2 | F99: =B99*E99 -> 9888 | G99: =C99*E99 -> 8646.6
A100: Cummins India Ltd | B100: 5659.5 | C100: 5519 | D100: =(C100-B100)/B100 -> -0.024825515 | E100: =ROUND($B$21/B100,0) -> 2 | F100: =B100*E100 -> 11319 | G100: =C100*E100 -> 11038
A101: Polycab India Ltd | B101: 9961 | C101: 9106.5 | D101: =(C101-B101)/B101 -> -0.08578456 | E101: =ROUND($B$21/B101,0) -> 1 | F101: =B101*E101 -> 9961 | G101: =C101*E101 -> 9106.5
A102: Portfolio Total | F102: =SUM(F91:F101) -> 114341.55 | G102: =SUM(G91:G101) -> 111307.95
A104: 📌 Note: Basis (Shares) = ROUND(Reference Price ÷ Day 1 Closing, 0), fixed at inception (Week 1) and held constant across all weeks so returns reflect price movement only. Investment (₹) = Basis × Previous Closing; Growth (₹) = Basis × Current Closing. Portfolio Return = (Total Growth − Total Investment) ÷ Total Investment.

Sheet Method 2
A1: PORTFOLIO BASKET TRACKER — METHOD 2
A2: Student: Vishv Jeet Singh Thakur | Institution: UPES | Weekly Basket Performance Tracking (Basis Fixed at Inception)
A4: WEEK 1 SNAPSHOT — 6/30/2026 - 7/3/2026 | I4: QUERY / SCREENING CRITERIA
A5: Reference stock (basis fixed at inception): Hero MotoCorp Ltd (₹4794.3) | I5: Sales > 250 AND
A6: Holdings | B6: Total Investment (₹) | D6: Growth (₹) | F6: Return (6/30/2026 - 7/3/2026) | I6: Debt to equity < 0.3 AND
A7: =COUNT(B11:B22) -> 12 | B7: =F23 -> 56331.88 | D7: =G23 -> 57544.24 | F7: =(G23-F23)/F23 -> 0.021521739 | I7: Interest Coverage Ratio > 4 AND
I8: Return on equity > 15 AND
A9: HOLDINGS — WEEK 1 | I9: Price to Earning < Industry PE AND
A10: Company Name | B10: Day 1 Closing (₹) | C10: 1 Week Closing (₹) | D10: Return (%) | E10: Basis (Shares) | F10: Investment (₹) | G10: Growth (₹) | I10: Dividend yield > 1 AND
A11: NMDC Ltd | B11: 85.16 | C11: 85.4 | D11: =(C11-B11)/B11 -> 0.0028182245 | E11: =ROUND($B$22/B11,0) -> 56 | F11: =B11*E11 -> 4768.96 | G11: =C11*E11 -> 4782.4 | I11: Price to Earning < 20
A12: Wipro Ltd | B12: 170.39 | C12: 176.08 | D12: =(C12-B12)/B12 -> 0.033393979 | E12: =ROUND($B$22/B12,0) -> 28 | F12: =B12*E12 -> 4770.92 | G12: =C12*E12 -> 4930.24
A13: Petronet LNG Ltd | B13: 280.8 | C13: 275.95 | D13: =(C13-B13)/B13 -> -0.01727208 | E13: =ROUND($B$22/B13,0) -> 17 | F13: =B13*E13 -> 4773.6 | G13: =C13*E13 -> 4691.15
A14: ITC Ltd | B14: 286.95 | C14: 289.95 | D14: =(C14-B14)/B14 -> 0.010454783 | E14: =ROUND($B$22/B14,0) -> 17 | F14: =B14*E14 -> 4878.15 | G14: =C14*E14 -> 4929.15
A15: National Aluminium Co Ltd | B15: 339.6 | C15: 347.6 | D15: =(C15-B15)/B15 -> 0.023557126 | E15: =ROUND($B$22/B15,0) -> 14 | F15: =B15*E15 -> 4754.4 | G15: =C15*E15 -> 4866.4
A16: Coal India Ltd | B16: 439.05 | C16: 438.7 | D16: =(C16-B16)/B16 -> -0.00079717572 | E16: =ROUND($B$22/B16,0) -> 11 | F16: =B16*E16 -> 4829.55 | G16: =C16*E16 -> 4825.7
A17: Infosys Ltd | B17: 1000.4 | C17: 1047.2 | D17: =(C17-B17)/B17 -> 0.046781287 | E17: =ROUND($B$22/B17,0) -> 5 | F17: =B17*E17 -> 5002 | G17: =C17*E17 -> 5236
A18: HCL Technologies Ltd | B18: 1071.8 | C18: 1139 | D18: =(C18-B18)/B18 -> 0.062698265 | E18: =ROUND($B$22/B18,0) -> 4 | F18: =B18*E18 -> 4287.2 | G18: =C18*E18 -> 4556
A19: Tata Consultancy Services Ltd | B19: 2031.5 | C19: 2093.5 | D19: =(C19-B19)/B19 -> 0.030519321 | E19: =ROUND($B$22/B19,0) -> 2 | F19: =B19*E19 -> 4063 | G19: =C19*E19 -> 4187
A20: Escorts Kubota Ltd | B20: 2935.9 | C20: 2964.9 | D20: =(C20-B20)/B20 -> 0.0098777206 | E20: =ROUND($B$22/B20,0) -> 2 | F20: =B20*E20 -> 5871.8 | G20: =C20*E20 -> 5929.8
A21: LTM Ltd | B21: 3538 | C21: 3757.8 | D21: =(C21-B21)/B21 -> 0.062125495 | E21: =ROUND($B$22/B21,0) -> 1 | F21: =B21*E21 -> 3538 | G21: =C21*E21 -> 3757.8
A22: Hero MotoCorp Ltd | B22: 4794.3 | C22: 4852.6 | D22: =(C22-B22)/B22 -> 0.012160274 | E22: =ROUND($B$22/B22,0) -> 1 | F22: =B22*E22 -> 4794.3 | G22: =C22*E22 -> 4852.6
A23: Portfolio Total | F23: =SUM(F11:F22) -> 56331.88 | G23: =SUM(G11:G22) -> 57544.24
A25: WEEK 2 SNAPSHOT — 6/30/2026 - 7/10/2026
A26: Reference stock (basis fixed at inception): Hero MotoCorp Ltd (₹4794.3)
A27: Holdings | B27: Total Investment (₹) | D27: Growth (₹) | F27: Return (6/30/2026 - 7/10/2026)
A28: =COUNT(B32:B43) -> 12 | B28: =F44 -> 56331.88 | D28: =G44 -> 58119.8 | F28: =(G44-F44)/F44 -> 0.031739044
A30: HOLDINGS — WEEK 2
A31: Company Name | B31: Day 1 Closing (₹) | C31: 2 Week Closing (₹) | D31: Return (%) | E31: Basis (Shares) | F31: Investment (₹) | G31: Growth (₹)
A32: NMDC Ltd | B32: 85.16 | C32: 84.92 | D32: =(C32-B32)/B32 -> -0.0028182245 | E32: =ROUND($B$22/B32,0) -> 56 | F32: =B32*E32 -> 4768.96 | G32: =C32*E32 -> 4755.52
A33: Wipro Ltd | B33: 170.39 | C33: 175.46 | D33: =(C33-B33)/B33 -> 0.029755267 | E33: =ROUND($B$22/B33,0) -> 28 | F33: =B33*E33 -> 4770.92 | G33: =C33*E33 -> 4912.88
A34: Petronet LNG Ltd | B34: 280.8 | C34: 278.95 | D34: =(C34-B34)/B34 -> -0.0065883191 | E34: =ROUND($B$22/B34,0) -> 17 | F34: =B34*E34 -> 4773.6 | G34: =C34*E34 -> 4742.15
A35: ITC Ltd | B35: 286.95 | C35: 281.75 | D35: =(C35-B35)/B35 -> -0.018121624 | E35: =ROUND($B$22/B35,0) -> 17 | F35: =B35*E35 -> 4878.15 | G35: =C35*E35 -> 4789.75
A36: National Aluminium Co Ltd | B36: 339.6 | C36: 354.85 | D36: =(C36-B36)/B36 -> 0.044905771 | E36: =ROUND($B$22/B36,0) -> 14 | F36: =B36*E36 -> 4754.4 | G36: =C36*E36 -> 4967.9
A37: Coal India Ltd | B37: 439.05 | C37: 429.3 | D37: =(C37-B37)/B37 -> -0.022207038 | E37: =ROUND($B$22/B37,0) -> 11 | F37: =B37*E37 -> 4829.55 | G37: =C37*E37 -> 4722.3
A38: Infosys Ltd | B38: 1000.4 | C38: 1068 | D38: =(C38-B38)/B38 -> 0.067572971 | E38: =ROUND($B$22/B38,0) -> 5 | F38: =B38*E38 -> 5002 | G38: =C38*E38 -> 5340
A39: HCL Technologies Ltd | B39: 1071.8 | C39: 1164.1 | D39: =(C39-B39)/B39 -> 0.086116813 | E39: =ROUND($B$22/B39,0) -> 4 | F39: =B39*E39 -> 4287.2 | G39: =C39*E39 -> 4656.4
A40: Tata Consultancy Services Ltd | B40: 2031.5 | C40: 2181.5 | D40: =(C40-B40)/B40 -> 0.073837066 | E40: =ROUND($B$22/B40,0) -> 2 | F40: =B40*E40 -> 4063 | G40: =C40*E40 -> 4363
A41: Escorts Kubota Ltd | B41: 2935.9 | C41: 2941.8 | D41: =(C41-B41)/B41 -> 0.0020096052 | E41: =ROUND($B$22/B41,0) -> 2 | F41: =B41*E41 -> 5871.8 | G41: =C41*E41 -> 5883.6
A42: LTM Ltd | B42: 3538 | C42: 4037.2 | D42: =(C42-B42)/B42 -> 0.14109666 | E42: =ROUND($B$22/B42,0) -> 1 | F42: =B42*E42 -> 3538 | G42: =C42*E42 -> 4037.2
A43: Hero MotoCorp Ltd | B43: 4794.3 | C43: 4949.1 | D43: =(C43-B43)/B43 -> 0.032288342 | E43: =ROUND($B$22/B43,0) -> 1 | F43: =B43*E43 -> 4794.3 | G43: =C43*E43 -> 4949.1
A44: Portfolio Total | F44: =SUM(F32:F43) -> 56331.88 | G44: =SUM(G32:G43) -> 58119.8
A46: WEEK 3 SNAPSHOT — 6/30/2026 - 7/17/2026
A47: Reference stock (basis fixed at inception): Hero MotoCorp Ltd (₹4794.3)
A48: Holdings | B48: Total Investment (₹) | D48: Growth (₹) | F48: Return (6/30/2026 - 7/17/2026)
A49: =COUNT(B53:B64) -> 12 | B49: =F65 -> 56331.88 | D49: =G65 -> 58173.17 | F49: =(G65-F65)/F65 -> 0.032686465
A51: HOLDINGS — WEEK 3
A52: Company Name | B52: Day 1 Closing (₹) | C52: 3 Week Closing (₹) | D52: Return (%) | E52: Basis (Shares) | F52: Investment (₹) | G52: Growth (₹)
A53: NMDC Ltd | B53: 85.16 | C53: 83.22 | D53: =(C53-B53)/B53 -> -0.022780648 | E53: =ROUND($B$22/B53,0) -> 56 | F53: =B53*E53 -> 4768.96 | G53: =C53*E53 -> 4660.32
A54: Wipro Ltd | B54: 170.39 | C54: 176 | D54: =(C54-B54)/B54 -> 0.032924467 | E54: =ROUND($B$22/B54,0) -> 28 | F54: =B54*E54 -> 4770.92 | G54: =C54*E54 -> 4928
A55: Petronet LNG Ltd | B55: 280.8 | C55: 273.8 | D55: =(C55-B55)/B55 -> -0.024928775 | E55: =ROUND($B$22/B55,0) -> 17 | F55: =B55*E55 -> 4773.6 | G55: =C55*E55 -> 4654.6
A56: ITC Ltd | B56: 286.95 | C56: 280.7 | D56: =(C56-B56)/B56 -> -0.021780798 | E56: =ROUND($B$22/B56,0) -> 17 | F56: =B56*E56 -> 4878.15 | G56: =C56*E56 -> 4771.9
A57: National Aluminium Co Ltd | B57: 339.6 | C57: 339.9 | D57: =(C57-B57)/B57 -> 0.00088339223 | E57: =ROUND($B$22/B57,0) -> 14 | F57: =B57*E57 -> 4754.4 | G57: =C57*E57 -> 4758.6
A58: Coal India Ltd | B58: 439.05 | C58: 427.65 | D58: =(C58-B58)/B58 -> -0.025965152 | E58: =ROUND($B$22/B58,0) -> 11 | F58: =B58*E58 -> 4829.55 | G58: =C58*E58 -> 4704.15
A59: Infosys Ltd | B59: 1000.4 | C59: 1096.5 | D59: =(C59-B59)/B59 -> 0.096061575 | E59: =ROUND($B$22/B59,0) -> 5 | F59: =B59*E59 -> 5002 | G59: =C59*E59 -> 5482.5
A60: HCL Technologies Ltd | B60: 1071.8 | C60: 1203.9 | D60: =(C60-B60)/B60 -> 0.12325061 | E60: =ROUND($B$22/B60,0) -> 4 | F60: =B60*E60 -> 4287.2 | G60: =C60*E60 -> 4815.6
A61: Tata Consultancy Services Ltd | B61: 2031.5 | C61: 2269 | D61: =(C61-B61)/B61 -> 0.11690869 | E61: =ROUND($B$22/B61,0) -> 2 | F61: =B61*E61 -> 4063 | G61: =C61*E61 -> 4538
A62: Escorts Kubota Ltd | B62: 2935.9 | C62: 2937 | D62: =(C62-B62)/B62 -> 0.00037467216 | E62: =ROUND($B$22/B62,0) -> 2 | F62: =B62*E62 -> 5871.8 | G62: =C62*E62 -> 5874
A63: LTM Ltd | B63: 3538 | C63: 4075.6 | D63: =(C63-B63)/B63 -> 0.15195025 | E63: =ROUND($B$22/B63,0) -> 1 | F63: =B63*E63 -> 3538 | G63: =C63*E63 -> 4075.6
A64: Hero MotoCorp Ltd | B64: 4794.3 | C64: 4909.9 | D64: =(C64-B64)/B64 -> 0.024111966 | E64: =ROUND($B$22/B64,0) -> 1 | F64: =B64*E64 -> 4794.3 | G64: =C64*E64 -> 4909.9
A65: Portfolio Total | F65: =SUM(F53:F64) -> 56331.88 | G65: =SUM(G53:G64) -> 58173.17
A67: WEEK 4 SNAPSHOT — 6/30/2026 - 7/24/2026
A68: Reference stock (basis fixed at inception): Hero MotoCorp Ltd (₹4794.3)
A69: Holdings | B69: Total Investment (₹) | D69: Growth (₹) | F69: Return (6/30/2026 - 7/24/2026)
A70: =COUNT(B74:B85) -> 12 | B70: =F86 -> 56331.88 | D70: =G86 -> 58353.37 | F70: =(G86-F86)/F86 -> 0.035885364
A72: HOLDINGS — WEEK 4
A73: Company Name | B73: Day 1 Closing (₹) | C73: 4 Week Closing (₹) | D73: Return (%) | E73: Basis (Shares) | F73: Investment (₹) | G73: Growth (₹)
A74: NMDC Ltd | B74: 85.16 | C74: 83.56 | D74: =(C74-B74)/B74 -> -0.018788163 | E74: =ROUND($B$22/B74,0) -> 56 | F74: =B74*E74 -> 4768.96 | G74: =C74*E74 -> 4679.36
A75: Wipro Ltd | B75: 170.39 | C75: 177.12 | D75: =(C75-B75)/B75 -> 0.039497623 | E75: =ROUND($B$22/B75,0) -> 28 | F75: =B75*E75 -> 4770.92 | G75: =C75*E75 -> 4959.36
A76: Petronet LNG Ltd | B76: 280.8 | C76: 274.7 | D76: =(C76-B76)/B76 -> -0.021723647 | E76: =ROUND($B$22/B76,0) -> 17 | F76: =B76*E76 -> 4773.6 | G76: =C76*E76 -> 4669.9
A77: ITC Ltd | B77: 286.95 | C77: 283.45 | D77: =(C77-B77)/B77 -> -0.012197247 | E77: =ROUND($B$22/B77,0) -> 17 | F77: =B77*E77 -> 4878.15 | G77: =C77*E77 -> 4818.65
A78: National Aluminium Co Ltd | B78: 339.6 | C78: 343.9 | D78: =(C78-B78)/B78 -> 0.012661955 | E78: =ROUND($B$22/B78,0) -> 14 | F78: =B78*E78 -> 4754.4 | G78: =C78*E78 -> 4814.6
A79: Coal India Ltd | B79: 439.05 | C79: 427.4 | D79: =(C79-B79)/B79 -> -0.026534563 | E79: =ROUND($B$22/B79,0) -> 11 | F79: =B79*E79 -> 4829.55 | G79: =C79*E79 -> 4701.4
A80: Infosys Ltd | B80: 1000.4 | C80: 1040.9 | D80: =(C80-B80)/B80 -> 0.040483806 | E80: =ROUND($B$22/B80,0) -> 5 | F80: =B80*E80 -> 5002 | G80: =C80*E80 -> 5204.5
A81: HCL Technologies Ltd | B81: 1071.8 | C81: 1271 | D81: =(C81-B81)/B81 -> 0.18585557 | E81: =ROUND($B$22/B81,0) -> 4 | F81: =B81*E81 -> 4287.2 | G81: =C81*E81 -> 5084
A82: Tata Consultancy Services Ltd | B82: 2031.5 | C82: 2254.3 | D82: =(C82-B82)/B82 -> 0.10967266 | E82: =ROUND($B$22/B82,0) -> 2 | F82: =B82*E82 -> 4063 | G82: =C82*E82 -> 4508.6
A83: Escorts Kubota Ltd | B83: 2935.9 | C83: 2905.1 | D83: =(C83-B83)/B83 -> -0.010490821 | E83: =ROUND($B$22/B83,0) -> 2 | F83: =B83*E83 -> 5871.8 | G83: =C83*E83 -> 5810.2
A84: LTM Ltd | B84: 3538 | C84: 4091.8 | D84: =(C84-B84)/B84 -> 0.15652911 | E84: =ROUND($B$22/B84,0) -> 1 | F84: =B84*E84 -> 3538 | G84: =C84*E84 -> 4091.8
A85: Hero MotoCorp Ltd | B85: 4794.3 | C85: 5011 | D85: =(C85-B85)/B85 -> 0.045199508 | E85: =ROUND($B$22/B85,0) -> 1 | F85: =B85*E85 -> 4794.3 | G85: =C85*E85 -> 5011
A86: Portfolio Total | F86: =SUM(F74:F85) -> 56331.88 | G86: =SUM(G74:G85) -> 58353.37
A88: WEEK 5 SNAPSHOT — 6/30/2026 - 7/31/2026
A89: Reference stock (basis fixed at inception): Hero MotoCorp Ltd (₹4794.3)
A90: Holdings | B90: Total Investment (₹) | D90: Growth (₹) | F90: Return (6/30/2026 - 7/31/2026)
A91: =COUNT(B95:B106) -> 12 | B91: =F107 -> 56331.88 | D91: =G107 -> 60599.94 | F91: =(G107-F107)/F107 -> 0.075766333
A93: HOLDINGS — WEEK 5
A94: Company Name | B94: Day 1 Closing (₹) | C94: 5 Week Closing (₹) | D94: Return (%) | E94: Basis (Shares) | F94: Investment (₹) | G94: Growth (₹)
A95: NMDC Ltd | B95: 85.16 | C95: 85.04 | D95: =(C95-B95)/B95 -> -0.0014091123 | E95: =ROUND($B$22/B95,0) -> 56 | F95: =B95*E95 -> 4768.96 | G95: =C95*E95 -> 4762.24
A96: Wipro Ltd | B96: 170.39 | C96: 183.65 | D96: =(C96-B96)/B96 -> 0.077821468 | E96: =ROUND($B$22/B96,0) -> 28 | F96: =B96*E96 -> 4770.92 | G96: =C96*E96 -> 5142.2
A97: Petronet LNG Ltd | B97: 280.8 | C97: 280.75 | D97: =(C97-B97)/B97 -> -0.00017806268 | E97: =ROUND($B$22/B97,0) -> 17 | F97: =B97*E97 -> 4773.6 | G97: =C97*E97 -> 4772.75
A98: ITC Ltd | B98: 286.95 | C98: 281 | D98: =(C98-B98)/B98 -> -0.02073532 | E98: =ROUND($B$22/B98,0) -> 17 | F98: =B98*E98 -> 4878.15 | G98: =C98*E98 -> 4777
A99: National Aluminium Co Ltd | B99: 339.6 | C99: 350.05 | D99: =(C99-B99)/B99 -> 0.030771496 | E99: =ROUND($B$22/B99,0) -> 14 | F99: =B99*E99 -> 4754.4 | G99: =C99*E99 -> 4900.7
A100: Coal India Ltd | B100: 439.05 | C100: 414.15 | D100: =(C100-B100)/B100 -> -0.056713358 | E100: =ROUND($B$22/B100,0) -> 11 | F100: =B100*E100 -> 4829.55 | G100: =C100*E100 -> 4555.65
A101: Infosys Ltd | B101: 1000.4 | C101: 1130.1 | D101: =(C101-B101)/B101 -> 0.12964814 | E101: =ROUND($B$22/B101,0) -> 5 | F101: =B101*E101 -> 5002 | G101: =C101*E101 -> 5650.5
A102: HCL Technologies Ltd | B102: 1071.8 | C102: 1346.9 | D102: =(C102-B102)/B102 -> 0.25667102 | E102: =ROUND($B$22/B102,0) -> 4 | F102: =B102*E102 -> 4287.2 | G102: =C102*E102 -> 5387.6
A103: Tata Consultancy Services Ltd | B103: 2031.5 | C103: 2365.6 | D103: =(C103-B103)/B103 -> 0.16445976 | E103: =ROUND($B$22/B103,0) -> 2 | F103: =B103*E103 -> 4063 | G103: =C103*E103 -> 4731.2
A104: Escorts Kubota Ltd | B104: 2935.9 | C104: 3086 | D104: =(C104-B104)/B104 -> 0.05112572 | E104: =ROUND($B$22/B104,0) -> 2 | F104: =B104*E104 -> 5871.8 | G104: =C104*E104 -> 6172
A105: LTM Ltd | B105: 3538 | C105: 4362.1 | D105: =(C105-B105)/B105 -> 0.23292821 | E105: =ROUND($B$22/B105,0) -> 1 | F105: =B105*E105 -> 3538 | G105: =C105*E105 -> 4362.1
A106: Hero MotoCorp Ltd | B106: 4794.3 | C106: 5386 | D106: =(C106-B106)/B106 -> 0.12341739 | E106: =ROUND($B$22/B106,0) -> 1 | F106: =B106*E106 -> 4794.3 | G106: =C106*E106 -> 5386
A107: Portfolio Total | F107: =SUM(F95:F106) -> 56331.88 | G107: =SUM(G95:G106) -> 60599.94
A109: 📌 Note: Basis (Shares) = ROUND(Reference Price ÷ Day 1 Closing, 0), fixed at inception (Week 1) and held constant across all weeks so returns reflect price movement only. Investment (₹) = Basis × Previous Closing; Growth (₹) = Basis × Current Closing. Portfolio Return = (Total Growth − Total Investment) ÷ Total Investment.

Sheet Method 3
A1: PORTFOLIO BASKET TRACKER — METHOD 3
A2: Student: Vishv Jeet Singh Thakur | Institution: UPES | Weekly Basket Performance Tracking (Basis Fixed at Inception)
A4: WEEK 1 SNAPSHOT — 6/30/2026 - 7/3/2026 | I4: QUERY / SCREENING CRITERIA
A5: Reference stock (basis fixed at inception): Tata Consultancy Services Ltd (₹2031.5) | I5: Price to Earning < 15 AND
A6: Holdings | B6: Total Investment (₹) | D6: Growth (₹) | F6: Return (6/30/2026 - 7/3/2026) | I6: Price to Earning > 0 AND
A7: =COUNT(B11:B21) -> 11 | B7: =F22 -> 22506.79 | D7: =G22 -> 22670.4 | F7: =(G22-F22)/F22 -> 0.0072693618 | I7: ROCE 3yr avg >= 15 AND
I8: Net profit >= 20 AND
A9: HOLDINGS — WEEK 1 | I9: YOY Quarterly profit growth > 0
A10: Company Name | B10: Day 1 Closing (₹) | C10: 1 Week Closing (₹) | D10: Return (%) | E10: Basis (Shares) | F10: Investment (₹) | G10: Growth (₹)
A11: NMDC Ltd | B11: 85.16 | C11: 85.4 | D11: =(C11-B11)/B11 -> 0.0028182245 | E11: =ROUND($B$21/B11,0) -> 24 | F11: =B11*E11 -> 2043.84 | G11: =C11*E11 -> 2049.6
A12: Indian Oil Corporation Ltd | B12: 139.38 | C12: 141.56 | D12: =(C12-B12)/B12 -> 0.015640695 | E12: =ROUND($B$21/B12,0) -> 15 | F12: =B12*E12 -> 2090.7 | G12: =C12*E12 -> 2123.4
A13: Vedanta Ltd | B13: 280.75 | C13: 280.4 | D13: =(C13-B13)/B13 -> -0.0012466607 | E13: =ROUND($B$21/B13,0) -> 7 | F13: =B13*E13 -> 1965.25 | G13: =C13*E13 -> 1962.8
A14: Petronet LNG Ltd | B14: 280.8 | C14: 275.95 | D14: =(C14-B14)/B14 -> -0.01727208 | E14: =ROUND($B$21/B14,0) -> 7 | F14: =B14*E14 -> 1965.6 | G14: =C14*E14 -> 1931.65
A15: Bharat Petroleum Corporation Ltd | B15: 303.55 | C15: 308.15 | D15: =(C15-B15)/B15 -> 0.015154011 | E15: =ROUND($B$21/B15,0) -> 7 | F15: =B15*E15 -> 2124.85 | G15: =C15*E15 -> 2157.05
A16: Indus Towers Ltd | B16: 391.7 | C16: 383.3 | D16: =(C16-B16)/B16 -> -0.021444983 | E16: =ROUND($B$21/B16,0) -> 5 | F16: =B16*E16 -> 1958.5 | G16: =C16*E16 -> 1916.5
A17: Hindustan Petroleum Corp Ltd | B17: 394.45 | C17: 399.25 | D17: =(C17-B17)/B17 -> 0.012168843 | E17: =ROUND($B$21/B17,0) -> 5 | F17: =B17*E17 -> 1972.25 | G17: =C17*E17 -> 1996.25
A18: Life Insurance Corporation Of India | B18: 431.65 | C18: 430.35 | D18: =(C18-B18)/B18 -> -0.0030116993 | E18: =ROUND($B$21/B18,0) -> 5 | F18: =B18*E18 -> 2158.25 | G18: =C18*E18 -> 2151.75
A19: Coal India Ltd | B19: 439.05 | C19: 438.7 | D19: =(C19-B19)/B19 -> -0.00079717572 | E19: =ROUND($B$21/B19,0) -> 5 | F19: =B19*E19 -> 2195.25 | G19: =C19*E19 -> 2193.5
A20: Infosys Ltd | B20: 1000.4 | C20: 1047.2 | D20: =(C20-B20)/B20 -> 0.046781287 | E20: =ROUND($B$21/B20,0) -> 2 | F20: =B20*E20 -> 2000.8 | G20: =C20*E20 -> 2094.4
A21: Tata Consultancy Services Ltd | B21: 2031.5 | C21: 2093.5 | D21: =(C21-B21)/B21 -> 0.030519321 | E21: =ROUND($B$21/B21,0) -> 1 | F21: =B21*E21 -> 2031.5 | G21: =C21*E21 -> 2093.5
A22: Portfolio Total | F22: =SUM(F11:F21) -> 22506.79 | G22: =SUM(G11:G21) -> 22670.4
A24: WEEK 2 SNAPSHOT — 6/30/2026 - 7/10/2026
A25: Reference stock (basis fixed at inception): Hero MotoCorp Ltd (₹4794.3)
A26: Holdings | B26: Total Investment (₹) | D26: Growth (₹) | F26: Return (6/30/2026 - 7/10/2026)
A27: =COUNT(B31:B41) -> 11 | B27: =F42 -> 22506.79 | D27: =G42 -> 22837.73 | F27: =(G42-F42)/F42 -> 0.014704007
A29: HOLDINGS — WEEK 2
A30: Company Name | B30: Day 1 Closing (₹) | C30: 2 Week Closing (₹) | D30: Return (%) | E30: Basis (Shares) | F30: Investment (₹) | G30: Growth (₹)
A31: NMDC Ltd | B31: 85.16 | C31: 84.92 | D31: =(C31-B31)/B31 -> -0.0028182245 | E31: =ROUND($B$21/B31,0) -> 24 | F31: =B31*E31 -> 2043.84 | G31: =C31*E31 -> 2038.08
A32: Indian Oil Corporation Ltd | B32: 139.38 | C32: 138.96 | D32: =(C32-B32)/B32 -> -0.0030133448 | E32: =ROUND($B$21/B32,0) -> 15 | F32: =B32*E32 -> 2090.7 | G32: =C32*E32 -> 2084.4
A33: Vedanta Ltd | B33: 280.75 | C33: 272.55 | D33: =(C33-B33)/B33 -> -0.02920748 | E33: =ROUND($B$21/B33,0) -> 7 | F33: =B33*E33 -> 1965.25 | G33: =C33*E33 -> 1907.85
A34: Petronet LNG Ltd | B34: 280.8 | C34: 278.95 | D34: =(C34-B34)/B34 -> -0.0065883191 | E34: =ROUND($B$21/B34,0) -> 7 | F34: =B34*E34 -> 1965.6 | G34: =C34*E34 -> 1952.65
A35: Bharat Petroleum Corporation Ltd | B35: 303.55 | C35: 309.75 | D35: =(C35-B35)/B35 -> 0.020424971 | E35: =ROUND($B$21/B35,0) -> 7 | F35: =B35*E35 -> 2124.85 | G35: =C35*E35 -> 2168.25
A36: Indus Towers Ltd | B36: 391.7 | C36: 406.15 | D36: =(C36-B36)/B36 -> 0.036890477 | E36: =ROUND($B$21/B36,0) -> 5 | F36: =B36*E36 -> 1958.5 | G36: =C36*E36 -> 2030.75
A37: Hindustan Petroleum Corp Ltd | B37: 394.45 | C37: 395.3 | D37: =(C37-B37)/B37 -> 0.0021548992 | E37: =ROUND($B$21/B37,0) -> 5 | F37: =B37*E37 -> 1972.25 | G37: =C37*E37 -> 1976.5
A38: Life Insurance Corporation Of India | B38: 431.65 | C38: 443.05 | D38: =(C38-B38)/B38 -> 0.026410286 | E38: =ROUND($B$21/B38,0) -> 5 | F38: =B38*E38 -> 2158.25 | G38: =C38*E38 -> 2215.25
A39: Coal India Ltd | B39: 439.05 | C39: 429.3 | D39: =(C39-B39)/B39 -> -0.022207038 | E39: =ROUND($B$21/B39,0) -> 5 | F39: =B39*E39 -> 2195.25 | G39: =C39*E39 -> 2146.5
A40: Infosys Ltd | B40: 1000.4 | C40: 1068 | D40: =(C40-B40)/B40 -> 0.067572971 | E40: =ROUND($B$21/B40,0) -> 2 | F40: =B40*E40 -> 2000.8 | G40: =C40*E40 -> 2136
A41: Tata Consultancy Services Ltd | B41: 2031.5 | C41: 2181.5 | D41: =(C41-B41)/B41 -> 0.073837066 | E41: =ROUND($B$21/B41,0) -> 1 | F41: =B41*E41 -> 2031.5 | G41: =C41*E41 -> 2181.5
A42: Portfolio Total | F42: =SUM(F31:F41) -> 22506.79 | G42: =SUM(G31:G41) -> 22837.73
A44: WEEK 3 SNAPSHOT — 6/30/2026 - 7/17/2026
A45: Reference stock (basis fixed at inception): Hero MotoCorp Ltd (₹4794.3)
A46: Holdings | B46: Total Investment (₹) | D46: Growth (₹) | F46: Return (6/30/2026 - 7/17/2026)
A47: =COUNT(B51:B61) -> 11 | B47: =F62 -> 22506.79 | D47: =G62 -> 22804.68 | F47: =(G62-F62)/F62 -> 0.013235561
A49: HOLDINGS — WEEK 3
A50: Company Name | B50: Day 1 Closing (₹) | C50: 3 Week Closing (₹) | D50: Return (%) | E50: Basis (Shares) | F50: Investment (₹) | G50: Growth (₹)
A51: NMDC Ltd | B51: 85.16 | C51: 83.22 | D51: =(C51-B51)/B51 -> -0.022780648 | E51: =ROUND($B$21/B51,0) -> 24 | F51: =B51*E51 -> 2043.84 | G51: =C51*E51 -> 1997.28
A52: Indian Oil Corporation Ltd | B52: 139.38 | C52: 141.69 | D52: =(C52-B52)/B52 -> 0.016573396 | E52: =ROUND($B$21/B52,0) -> 15 | F52: =B52*E52 -> 2090.7 | G52: =C52*E52 -> 2125.35
A53: Vedanta Ltd | B53: 280.75 | C53: 253.05 | D53: =(C53-B53)/B53 -> -0.098664292 | E53: =ROUND($B$21/B53,0) -> 7 | F53: =B53*E53 -> 1965.25 | G53: =C53*E53 -> 1771.35
A54: Petronet LNG Ltd | B54: 280.8 | C54: 273.8 | D54: =(C54-B54)/B54 -> -0.024928775 | E54: =ROUND($B$21/B54,0) -> 7 | F54: =B54*E54 -> 1965.6 | G54: =C54*E54 -> 1916.6
A55: Bharat Petroleum Corporation Ltd | B55: 303.55 | C55: 315.55 | D55: =(C55-B55)/B55 -> 0.039532202 | E55: =ROUND($B$21/B55,0) -> 7 | F55: =B55*E55 -> 2124.85 | G55: =C55*E55 -> 2208.85
A56: Indus Towers Ltd | B56: 391.7 | C56: 403.5 | D56: =(C56-B56)/B56 -> 0.030125096 | E56: =ROUND($B$21/B56,0) -> 5 | F56: =B56*E56 -> 1958.5 | G56: =C56*E56 -> 2017.5
A57: Hindustan Petroleum Corp Ltd | B57: 394.45 | C57: 400.4 | D57: =(C57-B57)/B57 -> 0.015084295 | E57: =ROUND($B$21/B57,0) -> 5 | F57: =B57*E57 -> 1972.25 | G57: =C57*E57 -> 2002
A58: Life Insurance Corporation Of India | B58: 431.65 | C58: 433.1 | D58: =(C58-B58)/B58 -> 0.0033592031 | E58: =ROUND($B$21/B58,0) -> 5 | F58: =B58*E58 -> 2158.25 | G58: =C58*E58 -> 2165.5
A59: Coal India Ltd | B59: 439.05 | C59: 427.65 | D59: =(C59-B59)/B59 -> -0.025965152 | E59: =ROUND($B$21/B59,0) -> 5 | F59: =B59*E59 -> 2195.25 | G59: =C59*E59 -> 2138.25
A60: Infosys Ltd | B60: 1000.4 | C60: 1096.5 | D60: =(C60-B60)/B60 -> 0.096061575 | E60: =ROUND($B$21/B60,0) -> 2 | F60: =B60*E60 -> 2000.8 | G60: =C60*E60 -> 2193
A61: Tata Consultancy Services Ltd | B61: 2031.5 | C61: 2269 | D61: =(C61-B61)/B61 -> 0.11690869 | E61: =ROUND($B$21/B61,0) -> 1 | F61: =B61*E61 -> 2031.5 | G61: =C61*E61 -> 2269
A62: Portfolio Total | F62: =SUM(F51:F61) -> 22506.79 | G62: =SUM(G51:G61) -> 22804.68
A64: WEEK 4 SNAPSHOT — 6/30/2026 - 7/24/2026
A65: Reference stock (basis fixed at inception): Hero MotoCorp Ltd (₹4794.3)
A66: Holdings | B66: Total Investment (₹) | D66: Growth (₹) | F66: Return (6/30/2026 - 7/24/2026)
A67: =COUNT(B71:B81) -> 11 | B67: =F82 -> 22506.79 | D67: =G82 -> 22487.09 | F67: =(G82-F82)/F82 -> -0.00087529141
A69: HOLDINGS — WEEK 4
A70: Company Name | B70: Day 1 Closing (₹) | C70: 4 Week Closing (₹) | D70: Return (%) | E70: Basis (Shares) | F70: Investment (₹) | G70: Growth (₹)
A71: NMDC Ltd | B71: 85.16 | C71: 83.56 | D71: =(C71-B71)/B71 -> -0.018788163 | E71: =ROUND($B$21/B71,0) -> 24 | F71: =B71*E71 -> 2043.84 | G71: =C71*E71 -> 2005.44
A72: Indian Oil Corporation Ltd | B72: 139.38 | C72: 138.47 | D72: =(C72-B72)/B72 -> -0.0065289138 | E72: =ROUND($B$21/B72,0) -> 15 | F72: =B72*E72 -> 2090.7 | G72: =C72*E72 -> 2077.05
A73: Vedanta Ltd | B73: 280.75 | C73: 264.65 | D73: =(C73-B73)/B73 -> -0.057346394 | E73: =ROUND($B$21/B73,0) -> 7 | F73: =B73*E73 -> 1965.25 | G73: =C73*E73 -> 1852.55
A74: Petronet LNG Ltd | B74: 280.8 | C74: 274.7 | D74: =(C74-B74)/B74 -> -0.021723647 | E74: =ROUND($B$21/B74,0) -> 7 | F74: =B74*E74 -> 1965.6 | G74: =C74*E74 -> 1922.9
A75: Bharat Petroleum Corporation Ltd | B75: 303.55 | C75: 310.15 | D75: =(C75-B75)/B75 -> 0.021742711 | E75: =ROUND($B$21/B75,0) -> 7 | F75: =B75*E75 -> 2124.85 | G75: =C75*E75 -> 2171.05
A76: Indus Towers Ltd | B76: 391.7 | C76: 394.6 | D76: =(C76-B76)/B76 -> 0.0074036252 | E76: =ROUND($B$21/B76,0) -> 5 | F76: =B76*E76 -> 1958.5 | G76: =C76*E76 -> 1973
A77: Hindustan Petroleum Corp Ltd | B77: 394.45 | C77: 381.1 | D77: =(C77-B77)/B77 -> -0.033844594 | E77: =ROUND($B$21/B77,0) -> 5 | F77: =B77*E77 -> 1972.25 | G77: =C77*E77 -> 1905.5
A78: Life Insurance Corporation Of India | B78: 431.65 | C78: 421.3 | D78: =(C78-B78)/B78 -> -0.02397776 | E78: =ROUND($B$21/B78,0) -> 5 | F78: =B78*E78 -> 2158.25 | G78: =C78*E78 -> 2106.5
A79: Coal India Ltd | B79: 439.05 | C79: 427.4 | D79: =(C79-B79)/B79 -> -0.026534563 | E79: =ROUND($B$21/B79,0) -> 5 | F79: =B79*E79 -> 2195.25 | G79: =C79*E79 -> 2137
A80: Infosys Ltd | B80: 1000.4 | C80: 1040.9 | D80: =(C80-B80)/B80 -> 0.040483806 | E80: =ROUND($B$21/B80,0) -> 2 | F80: =B80*E80 -> 2000.8 | G80: =C80*E80 -> 2081.8
A81: Tata Consultancy Services Ltd | B81: 2031.5 | C81: 2254.3 | D81: =(C81-B81)/B81 -> 0.10967266 | E81: =ROUND($B$21/B81,0) -> 1 | F81: =B81*E81 -> 2031.5 | G81: =C81*E81 -> 2254.3
A82: Portfolio Total | F82: =SUM(F71:F81) -> 22506.79 | G82: =SUM(G71:G81) -> 22487.09
A84: WEEK 5 SNAPSHOT — 6/30/2026 - 7/31/2026
A85: Reference stock (basis fixed at inception): Hero MotoCorp Ltd (₹4794.3)
A86: Holdings | B86: Total Investment (₹) | D86: Growth (₹) | F86: Return (6/30/2026 - 7/31/2026)
A87: =COUNT(B91:B101) -> 11 | B87: =F102 -> 22506.79 | D87: =G102 -> 22921.06 | F87: =(G102-F102)/F102 -> 0.018406445
A89: HOLDINGS — WEEK 5
A90: Company Name | B90: Day 1 Closing (₹) | C90: 5 Week Closing (₹) | D90: Return (%) | E90: Basis (Shares) | F90: Investment (₹) | G90: Growth (₹)
A91: NMDC Ltd | B91: 85.16 | C91: 85.04 | D91: =(C91-B91)/B91 -> -0.0014091123 | E91: =ROUND($B$21/B91,0) -> 24 | F91: =B91*E91 -> 2043.84 | G91: =C91*E91 -> 2040.96
A92: Indian Oil Corporation Ltd | B92: 139.38 | C92: 140.17 | D92: =(C92-B92)/B92 -> 0.0056679581 | E92: =ROUND($B$21/B92,0) -> 15 | F92: =B92*E92 -> 2090.7 | G92: =C92*E92 -> 2102.55
A93: Vedanta Ltd | B93: 280.75 | C93: 264.25 | D93: =(C93-B93)/B93 -> -0.058771149 | E93: =ROUND($B$21/B93,0) -> 7 | F93: =B93*E93 -> 1965.25 | G93: =C93*E93 -> 1849.75
A94: Petronet LNG Ltd | B94: 280.8 | C94: 280.75 | D94: =(C94-B94)/B94 -> -0.00017806268 | E94: =ROUND($B$21/B94,0) -> 7 | F94: =B94*E94 -> 1965.6 | G94: =C94*E94 -> 1965.25
A95: Bharat Petroleum Corporation Ltd | B95: 303.55 | C95: 319.75 | D95: =(C95-B95)/B95 -> 0.053368473 | E95: =ROUND($B$21/B95,0) -> 7 | F95: =B95*E95 -> 2124.85 | G95: =C95*E95 -> 2238.25
A96: Indus Towers Ltd | B96: 391.7 | C96: 391.1 | D96: =(C96-B96)/B96 -> -0.0015317845 | E96: =ROUND($B$21/B96,0) -> 5 | F96: =B96*E96 -> 1958.5 | G96: =C96*E96 -> 1955.5
A97: Hindustan Petroleum Corp Ltd | B97: 394.45 | C97: 389.75 | D97: =(C97-B97)/B97 -> -0.011915325 | E97: =ROUND($B$21/B97,0) -> 5 | F97: =B97*E97 -> 1972.25 | G97: =C97*E97 -> 1948.75
A98: Life Insurance Corporation Of India | B98: 431.65 | C98: 424.7 | D98: =(C98-B98)/B98 -> -0.016101008 | E98: =ROUND($B$21/B98,0) -> 5 | F98: =B98*E98 -> 2158.25 | G98: =C98*E98 -> 2123.5
A99: Coal India Ltd | B99: 439.05 | C99: 414.15 | D99: =(C99-B99)/B99 -> -0.056713358 | E99: =ROUND($B$21/B99,0) -> 5 | F99: =B99*E99 -> 2195.25 | G99: =C99*E99 -> 2070.75
A100: Infosys Ltd | B100: 1000.4 | C100: 1130.1 | D100: =(C100-B100)/B100 -> 0.12964814 | E100: =ROUND($B$21/B100,0) -> 2 | F100: =B100*E100 -> 2000.8 | G100: =C100*E100 -> 2260.2
A101: Tata Consultancy Services Ltd | B101: 2031.5 | C101: 2365.6 | D101: =(C101-B101)/B101 -> 0.16445976 | E101: =ROUND($B$21/B101,0) -> 1 | F101: =B101*E101 -> 2031.5 | G101: =C101*E101 -> 2365.6
A102: Portfolio Total | F102: =SUM(F91:F101) -> 22506.79 | G102: =SUM(G91:G101) -> 22921.06
A104: 📌 Note: Basis (Shares) = ROUND(Reference Price ÷ Day 1 Closing, 0), fixed at inception (Week 1) and held constant across all weeks so returns reflect price movement only. Investment (₹) = Basis × Previous Closing; Growth (₹) = Basis × Current Closing. Portfolio Return = (Total Growth − Total Investment) ÷ Total Investment.

Sheet Method 4
A1: PORTFOLIO BASKET TRACKER — METHOD 4
A2: Student: Vishv Jeet Singh Thakur | Institution: UPES | Weekly Basket Performance Tracking (Basis Fixed at Inception)
A4: WEEK 1 SNAPSHOT — 6/30/2026 - 7/3/2026 | I4: QUERY / SCREENING CRITERIA
A5: Reference stock (basis fixed at inception): MRF Ltd (₹127820) | I5: Method:- Peter Lynch
A6: Holdings | B6: Total Investment (₹) | D6: Growth (₹) | F6: Return (6/30/2026 - 7/3/2026) | I6: PEG Ratio < 1 AND
A7: =COUNT(B11:B19) -> 9 | B7: =F20 -> 1153084 | D7: =G20 -> 1169232.5 | F7: =(G20-F20)/F20 -> 0.014004617 | I7: Sales > 500 AND
I8: Price to Earning < 40 AND
A9: HOLDINGS — WEEK 1 | I9: Profit growth > 20 AND
A10: Company Name | B10: Day 1 Closing (₹) | C10: 1 Week Closing (₹) | D10: Return (%) | E10: Basis (Shares) | F10: Investment (₹) | G10: Growth (₹) | I10: Debt to equity < 0.2 AND
A11: Suzlon Energy Ltd | B11: 58.9 | C11: 56.87 | D11: =(C11-B11)/B11 -> -0.034465195 | E11: =ROUND($B$19/B11,0) -> 2170 | F11: =B11*E11 -> 127813 | G11: =C11*E11 -> 123407.9 | I11: Price to Cash Flow > 5
A12: General Insurance Corporation of India | B12: 363.5 | C12: 360.95 | D12: =(C12-B12)/B12 -> -0.0070151307 | E12: =ROUND($B$19/B12,0) -> 352 | F12: =B12*E12 -> 127952 | G12: =C12*E12 -> 127054.4
A13: IPCA Laboratories Ltd | B13: 1701 | C13: 1778.9 | D13: =(C13-B13)/B13 -> 0.04579659 | E13: =ROUND($B$19/B13,0) -> 75 | F13: =B13*E13 -> 127575 | G13: =C13*E13 -> 133417.5
A14: Godfrey Phillips India Ltd | B14: 2173.1 | C14: 2170.1 | D14: =(C14-B14)/B14 -> -0.0013805163 | E14: =ROUND($B$19/B14,0) -> 59 | F14: =B14*E14 -> 128212.9 | G14: =C14*E14 -> 128035.9
A15: Glenmark Pharmaceuticals Ltd | B15: 2204.3 | C15: 2211 | D15: =(C15-B15)/B15 -> 0.0030395137 | E15: =ROUND($B$19/B15,0) -> 58 | F15: =B15*E15 -> 127849.4 | G15: =C15*E15 -> 128238
A16: Escorts Kubota Ltd | B16: 2935.9 | C16: 2964.9 | D16: =(C16-B16)/B16 -> 0.0098777206 | E16: =ROUND($B$19/B16,0) -> 44 | F16: =B16*E16 -> 129179.6 | G16: =C16*E16 -> 130455.6
A17: Hero MotoCorp Ltd | B17: 4794.3 | C17: 4852.6 | D17: =(C17-B17)/B17 -> 0.012160274 | E17: =ROUND($B$19/B17,0) -> 27 | F17: =B17*E17 -> 129446.1 | G17: =C17*E17 -> 131020.2
A18: Bajaj Holdings and Investment Ltd | B18: 10603 | C18: 11079 | D18: =(C18-B18)/B18 -> 0.044892955 | E18: =ROUND($B$19/B18,0) -> 12 | F18: =B18*E18 -> 127236 | G18: =C18*E18 -> 132948
A19: MRF Ltd | B19: 127820 | C19: 134655 | D19: =(C19-B19)/B19 -> 0.053473635 | E19: =ROUND($B$19/B19,0) -> 1 | F19: =B19*E19 -> 127820 | G19: =C19*E19 -> 134655
A20: Portfolio Total | F20: =SUM(F11:F19) -> 1153084 | G20: =SUM(G11:G19) -> 1169232.5
A22: WEEK 2 SNAPSHOT — 6/30/2026 - 7/10/2026
A23: Reference stock (basis fixed at inception): Hero MotoCorp Ltd (₹4794.3)
A24: Holdings | B24: Total Investment (₹) | D24: Growth (₹) | F24: Return (6/30/2026 - 7/10/2026)
A25: =COUNT(B29:B37) -> 9 | B25: =F38 -> 1153084 | D25: =G38 -> 1162127.7 | F25: =(G38-F38)/F38 -> 0.0078430539
A27: HOLDINGS — WEEK 2
A28: Company Name | B28: Day 1 Closing (₹) | C28: 2 Week Closing (₹) | D28: Return (%) | E28: Basis (Shares) | F28: Investment (₹) | G28: Growth (₹)
A29: Suzlon Energy Ltd | B29: 58.9 | C29: 53.92 | D29: =(C29-B29)/B29 -> -0.084550085 | E29: =ROUND($B$19/B29,0) -> 2170 | F29: =B29*E29 -> 127813 | G29: =C29*E29 -> 117006.4
A30: General Insurance Corporation of India | B30: 363.5 | C30: 365 | D30: =(C30-B30)/B30 -> 0.0041265475 | E30: =ROUND($B$19/B30,0) -> 352 | F30: =B30*E30 -> 127952 | G30: =C30*E30 -> 128480
A31: IPCA Laboratories Ltd | B31: 1701 | C31: 1787.9 | D31: =(C31-B31)/B31 -> 0.051087596 | E31: =ROUND($B$19/B31,0) -> 75 | F31: =B31*E31 -> 127575 | G31: =C31*E31 -> 134092.5
A32: Godfrey Phillips India Ltd | B32: 2173.1 | C32: 2115.3 | D32: =(C32-B32)/B32 -> -0.026597948 | E32: =ROUND($B$19/B32,0) -> 59 | F32: =B32*E32 -> 128212.9 | G32: =C32*E32 -> 124802.7
A33: Glenmark Pharmaceuticals Ltd | B33: 2204.3 | C33: 2282.9 | D33: =(C33-B33)/B33 -> 0.035657578 | E33: =ROUND($B$19/B33,0) -> 58 | F33: =B33*E33 -> 127849.4 | G33: =C33*E33 -> 132408.2
A34: Escorts Kubota Ltd | B34: 2935.9 | C34: 2941.8 | D34: =(C34-B34)/B34 -> 0.0020096052 | E34: =ROUND($B$19/B34,0) -> 44 | F34: =B34*E34 -> 129179.6 | G34: =C34*E34 -> 129439.2
A35: Hero MotoCorp Ltd | B35: 4794.3 | C35: 4949.1 | D35: =(C35-B35)/B35 -> 0.032288342 | E35: =ROUND($B$19/B35,0) -> 27 | F35: =B35*E35 -> 129446.1 | G35: =C35*E35 -> 133625.7
A36: Bajaj Holdings and Investment Ltd | B36: 10603 | C36: 10654 | D36: =(C36-B36)/B36 -> 0.0048099594 | E36: =ROUND($B$19/B36,0) -> 12 | F36: =B36*E36 -> 127236 | G36: =C36*E36 -> 127848
A37: MRF Ltd | B37: 127820 | C37: 134425 | D37: =(C37-B37)/B37 -> 0.051674229 | E37: =ROUND($B$19/B37,0) -> 1 | F37: =B37*E37 -> 127820 | G37: =C37*E37 -> 134425
A38: Portfolio Total | F38: =SUM(F29:F37) -> 1153084 | G38: =SUM(G29:G37) -> 1162127.7
A40: WEEK 3 SNAPSHOT — 6/30/2026 - 7/17/2026
A41: Reference stock (basis fixed at inception): Hero MotoCorp Ltd (₹4794.3)
A42: Holdings | B42: Total Investment (₹) | D42: Growth (₹) | F42: Return (6/30/2026 - 7/17/2026)
A43: =COUNT(B47:B55) -> 9 | B43: =F56 -> 1153084 | D43: =G56 -> 1154196.7 | F43: =(G56-F56)/F56 -> 0.0009649774
A45: HOLDINGS — WEEK 3
A46: Company Name | B46: Day 1 Closing (₹) | C46: 3 Week Closing (₹) | D46: Return (%) | E46: Basis (Shares) | F46: Investment (₹) | G46: Growth (₹)
A47: Suzlon Energy Ltd | B47: 58.9 | C47: 51.99 | D47: =(C47-B47)/B47 -> -0.11731749 | E47: =ROUND($B$19/B47,0) -> 2170 | F47: =B47*E47 -> 127813 | G47: =C47*E47 -> 112818.3
A48: General Insurance Corporation of India | B48: 363.5 | C48: 362 | D48: =(C48-B48)/B48 -> -0.0041265475 | E48: =ROUND($B$19/B48,0) -> 352 | F48: =B48*E48 -> 127952 | G48: =C48*E48 -> 127424
A49: IPCA Laboratories Ltd | B49: 1701 | C49: 1900.6 | D49: =(C49-B49)/B49 -> 0.11734274 | E49: =ROUND($B$19/B49,0) -> 75 | F49: =B49*E49 -> 127575 | G49: =C49*E49 -> 142545
A50: Godfrey Phillips India Ltd | B50: 2173.1 | C50: 2109.9 | D50: =(C50-B50)/B50 -> -0.029082877 | E50: =ROUND($B$19/B50,0) -> 59 | F50: =B50*E50 -> 128212.9 | G50: =C50*E50 -> 124484.1
A51: Glenmark Pharmaceuticals Ltd | B51: 2204.3 | C51: 2235.5 | D51: =(C51-B51)/B51 -> 0.014154153 | E51: =ROUND($B$19/B51,0) -> 58 | F51: =B51*E51 -> 127849.4 | G51: =C51*E51 -> 129659
A52: Escorts Kubota Ltd | B52: 2935.9 | C52: 2937 | D52: =(C52-B52)/B52 -> 0.00037467216 | E52: =ROUND($B$19/B52,0) -> 44 | F52: =B52*E52 -> 129179.6 | G52: =C52*E52 -> 129228
A53: Hero MotoCorp Ltd | B53: 4794.3 | C53: 4909.9 | D53: =(C53-B53)/B53 -> 0.024111966 | E53: =ROUND($B$19/B53,0) -> 27 | F53: =B53*E53 -> 129446.1 | G53: =C53*E53 -> 132567.3
A54: Bajaj Holdings and Investment Ltd | B54: 10603 | C54: 10398 | D54: =(C54-B54)/B54 -> -0.019334151 | E54: =ROUND($B$19/B54,0) -> 12 | F54: =B54*E54 -> 127236 | G54: =C54*E54 -> 124776
A55: MRF Ltd | B55: 127820 | C55: 130695 | D55: =(C55-B55)/B55 -> 0.022492568 | E55: =ROUND($B$19/B55,0) -> 1 | F55: =B55*E55 -> 127820 | G55: =C55*E55 -> 130695
A56: Portfolio Total | F56: =SUM(F47:F55) -> 1153084 | G56: =SUM(G47:G55) -> 1154196.7
A58: WEEK 4 SNAPSHOT — 6/30/2026 - 7/24/2026
A59: Reference stock (basis fixed at inception): Hero MotoCorp Ltd (₹4794.3)
A60: Holdings | B60: Total Investment (₹) | D60: Growth (₹) | F60: Return (6/30/2026 - 7/24/2026)
A61: =COUNT(B65:B73) -> 9 | B61: =F74 -> 1153084 | D61: =G74 -> 1146296.9 | F61: =(G74-F74)/F74 -> -0.0058860413
A63: HOLDINGS — WEEK 4
A64: Company Name | B64: Day 1 Closing (₹) | C64: 4 Week Closing (₹) | D64: Return (%) | E64: Basis (Shares) | F64: Investment (₹) | G64: Growth (₹)
A65: Suzlon Energy Ltd | B65: 58.9 | C65: 52.28 | D65: =(C65-B65)/B65 -> -0.11239389 | E65: =ROUND($B$19/B65,0) -> 2170 | F65: =B65*E65 -> 127813 | G65: =C65*E65 -> 113447.6
A66: General Insurance Corporation of India | B66: 363.5 | C66: 357.5 | D66: =(C66-B66)/B66 -> -0.01650619 | E66: =ROUND($B$19/B66,0) -> 352 | F66: =B66*E66 -> 127952 | G66: =C66*E66 -> 125840
A67: IPCA Laboratories Ltd | B67: 1701 | C67: 1762.7 | D67: =(C67-B67)/B67 -> 0.036272781 | E67: =ROUND($B$19/B67,0) -> 75 | F67: =B67*E67 -> 127575 | G67: =C67*E67 -> 132202.5
A68: Godfrey Phillips India Ltd | B68: 2173.1 | C68: 2129.6 | D68: =(C68-B68)/B68 -> -0.020017487 | E68: =ROUND($B$19/B68,0) -> 59 | F68: =B68*E68 -> 128212.9 | G68: =C68*E68 -> 125646.4
A69: Glenmark Pharmaceuticals Ltd | B69: 2204.3 | C69: 2192 | D69: =(C69-B69)/B69 -> -0.0055800027 | E69: =ROUND($B$19/B69,0) -> 58 | F69: =B69*E69 -> 127849.4 | G69: =C69*E69 -> 127136
A70: Escorts Kubota Ltd | B70: 2935.9 | C70: 2905.1 | D70: =(C70-B70)/B70 -> -0.010490821 | E70: =ROUND($B$19/B70,0) -> 44 | F70: =B70*E70 -> 129179.6 | G70: =C70*E70 -> 127824.4
A71: Hero MotoCorp Ltd | B71: 4794.3 | C71: 5011 | D71: =(C71-B71)/B71 -> 0.045199508 | E71: =ROUND($B$19/B71,0) -> 27 | F71: =B71*E71 -> 129446.1 | G71: =C71*E71 -> 135297
A72: Bajaj Holdings and Investment Ltd | B72: 10603 | C72: 10679 | D72: =(C72-B72)/B72 -> 0.0071677827 | E72: =ROUND($B$19/B72,0) -> 12 | F72: =B72*E72 -> 127236 | G72: =C72*E72 -> 128148
A73: MRF Ltd | B73: 127820 | C73: 130755 | D73: =(C73-B73)/B73 -> 0.022961978 | E73: =ROUND($B$19/B73,0) -> 1 | F73: =B73*E73 -> 127820 | G73: =C73*E73 -> 130755
A74: Portfolio Total | F74: =SUM(F65:F73) -> 1153084 | G74: =SUM(G65:G73) -> 1146296.9
A76: WEEK 5 SNAPSHOT — 6/30/2026 - 7/31/2026
A77: Reference stock (basis fixed at inception): Hero MotoCorp Ltd (₹4794.3)
A78: Holdings | B78: Total Investment (₹) | D78: Growth (₹) | F78: Return (6/30/2026 - 7/31/2026)
A79: =COUNT(B83:B91) -> 9 | B79: =F92 -> 1153084 | D79: =G92 -> 1166318.7 | F79: =(G92-F92)/F92 -> 0.011477655
A81: HOLDINGS — WEEK 5
A82: Company Name | B82: Day 1 Closing (₹) | C82: 5 Week Closing (₹) | D82: Return (%) | E82: Basis (Shares) | F82: Investment (₹) | G82: Growth (₹)
A83: Suzlon Energy Ltd | B83: 58.9 | C83: 48.01 | D83: =(C83-B83)/B83 -> -0.18488964 | E83: =ROUND($B$19/B83,0) -> 2170 | F83: =B83*E83 -> 127813 | G83: =C83*E83 -> 104181.7
A84: General Insurance Corporation of India | B84: 363.5 | C84: 356.6 | D84: =(C84-B84)/B84 -> -0.018982118 | E84: =ROUND($B$19/B84,0) -> 352 | F84: =B84*E84 -> 127952 | G84: =C84*E84 -> 125523.2
A85: IPCA Laboratories Ltd | B85: 1701 | C85: 1747.8 | D85: =(C85-B85)/B85 -> 0.027513228 | E85: =ROUND($B$19/B85,0) -> 75 | F85: =B85*E85 -> 127575 | G85: =C85*E85 -> 131085
A86: Godfrey Phillips India Ltd | B86: 2173.1 | C86: 2133.4 | D86: =(C86-B86)/B86 -> -0.018268833 | E86: =ROUND($B$19/B86,0) -> 59 | F86: =B86*E86 -> 128212.9 | G86: =C86*E86 -> 125870.6
A87: Glenmark Pharmaceuticals Ltd | B87: 2204.3 | C87: 2233.9 | D87: =(C87-B87)/B87 -> 0.013428299 | E87: =ROUND($B$19/B87,0) -> 58 | F87: =B87*E87 -> 127849.4 | G87: =C87*E87 -> 129566.2
A88: Escorts Kubota Ltd | B88: 2935.9 | C88: 3086 | D88: =(C88-B88)/B88 -> 0.05112572 | E88: =ROUND($B$19/B88,0) -> 44 | F88: =B88*E88 -> 129179.6 | G88: =C88*E88 -> 135784
A89: Hero MotoCorp Ltd | B89: 4794.3 | C89: 5386 | D89: =(C89-B89)/B89 -> 0.12341739 | E89: =ROUND($B$19/B89,0) -> 27 | F89: =B89*E89 -> 129446.1 | G89: =C89*E89 -> 145422
A90: Bajaj Holdings and Investment Ltd | B90: 10603 | C90: 11343 | D90: =(C90-B90)/B90 -> 0.069791568 | E90: =ROUND($B$19/B90,0) -> 12 | F90: =B90*E90 -> 127236 | G90: =C90*E90 -> 136116
A91: MRF Ltd | B91: 127820 | C91: 132770 | D91: =(C91-B91)/B91 -> 0.038726334 | E91: =ROUND($B$19/B91,0) -> 1 | F91: =B91*E91 -> 127820 | G91: =C91*E91 -> 132770
A92: Portfolio Total | F92: =SUM(F83:F91) -> 1153084 | G92: =SUM(G83:G91) -> 1166318.7
A94: 📌 Note: Basis (Shares) = ROUND(Reference Price ÷ Day 1 Closing, 0), fixed at inception (Week 1) and held constant across all weeks so returns reflect price movement only. Investment (₹) = Basis × Previous Closing; Growth (₹) = Basis × Current Closing. Portfolio Return = (Total Growth − Total Investment) ÷ Total Investment.

Sheet Method 5
A1: PORTFOLIO BASKET TRACKER — METHOD 5
A2: Student: Vishv Jeet Singh Thakur | Institution: UPES | Weekly Basket Performance Tracking (Basis Fixed at Inception)
A4: WEEK 1 SNAPSHOT — 6/30/2026 - 7/3/2026 | I4: QUERY / SCREENING CRITERIA
A5: Reference stock (basis fixed at inception): Bajaj Auto Ltd (₹9716) | I5: Method:- Joel Greenblatt
A6: Holdings | B6: Total Investment (₹) | D6: Growth (₹) | F6: Return (6/30/2026 - 7/3/2026) | I6: G Factor >= 7 AND
A7: =COUNT(B11:B24) -> 14 | B7: =F25 -> 134726.25 | D7: =G25 -> 136239.98 | F7: =(G25-F25)/F25 -> 0.011235598 | I7: Market Capitalization > 25000
A9: HOLDINGS — WEEK 1
A10: Company Name | B10: Day 1 Closing (₹) | C10: 1 Week Closing (₹) | D10: Return (%) | E10: Basis (Shares) | F10: Investment (₹) | G10: Growth (₹)
A11: Central Bank of India Ltd | B11: 32.53 | C11: 32.8 | D11: =(C11-B11)/B11 -> 0.0083000307 | E11: =ROUND($B$24/B11,0) -> 299 | F11: =B11*E11 -> 9726.47 | G11: =C11*E11 -> 9807.2
A12: NMDC Ltd | B12: 85.16 | C12: 85.4 | D12: =(C12-B12)/B12 -> 0.0028182245 | E12: =ROUND($B$24/B12,0) -> 114 | F12: =B12*E12 -> 9708.24 | G12: =C12*E12 -> 9735.6
A13: Physicswallah Ltd | B13: 124.13 | C13: 130.16 | D13: =(C13-B13)/B13 -> 0.048578104 | E13: =ROUND($B$24/B13,0) -> 78 | F13: =B13*E13 -> 9682.14 | G13: =C13*E13 -> 10152.48
A14: Indian Oil Corporation Ltd | B14: 139.38 | C14: 141.56 | D14: =(C14-B14)/B14 -> 0.015640695 | E14: =ROUND($B$24/B14,0) -> 70 | F14: =B14*E14 -> 9756.6 | G14: =C14*E14 -> 9909.2
A15: Bank of India Ltd | B15: 140.4 | C15: 144.05 | D15: =(C15-B15)/B15 -> 0.025997151 | E15: =ROUND($B$24/B15,0) -> 69 | F15: =B15*E15 -> 9687.6 | G15: =C15*E15 -> 9939.45
A16: Vedanta Ltd | B16: 280.75 | C16: 280.4 | D16: =(C16-B16)/B16 -> -0.0012466607 | E16: =ROUND($B$24/B16,0) -> 35 | F16: =B16*E16 -> 9826.25 | G16: =C16*E16 -> 9814
A17: Bharat Petroleum Corporation Ltd | B17: 303.55 | C17: 308.15 | D17: =(C17-B17)/B17 -> 0.015154011 | E17: =ROUND($B$24/B17,0) -> 32 | F17: =B17*E17 -> 9713.6 | G17: =C17*E17 -> 9860.8
A18: Life Insurance Corporation Of India | B18: 431.65 | C18: 430.35 | D18: =(C18-B18)/B18 -> -0.0030116993 | E18: =ROUND($B$24/B18,0) -> 23 | F18: =B18*E18 -> 9927.95 | G18: =C18*E18 -> 9898.05
A19: Coal India Ltd | B19: 439.05 | C19: 438.7 | D19: =(C19-B19)/B19 -> -0.00079717572 | E19: =ROUND($B$24/B19,0) -> 22 | F19: =B19*E19 -> 9659.1 | G19: =C19*E19 -> 9651.4
A20: Hindustan Zinc Ltd | B20: 533.15 | C20: 536.55 | D20: =(C20-B20)/B20 -> 0.0063771922 | E20: =ROUND($B$24/B20,0) -> 18 | F20: =B20*E20 -> 9596.7 | G20: =C20*E20 -> 9657.9
A21: Nippon Life India Asset Management Ltd | B21: 1162 | C21: 1218.2 | D21: =(C21-B21)/B21 -> 0.048364888 | E21: =ROUND($B$24/B21,0) -> 8 | F21: =B21*E21 -> 9296 | G21: =C21*E21 -> 9745.6
A22: Waaree Energies Ltd | B22: 2947 | C22: 2859.2 | D22: =(C22-B22)/B22 -> -0.02979301 | E22: =ROUND($B$24/B22,0) -> 3 | F22: =B22*E22 -> 8841 | G22: =C22*E22 -> 8577.6
... A24: Bajaj Auto Ltd | B24: 9716 | C24: 9785.5 | D24: =(C24-B24)/B24 -> 0.0071531494 | E24: =ROUND($B$24/B24,0) -> 1 | F24: =B24*E24 -> 9716 | G24: =C24*E24 -> 9785.5
A25: Portfolio Total | F25: =SUM(F11:F24) -> 134726.25 | G25: =SUM(G11:G24) -> 136239.98
A27: WEEK 2 SNAPSHOT — 6/30/2026 - 7/10/2026
A28: Reference stock (basis fixed at inception): Hero MotoCorp Ltd (₹4794.3)
A29: Holdings | B29: Total Investment (₹) | D29: Growth (₹) | F29: Return (6/30/2026 - 7/10/2026)
A30: =COUNT(B34:B47) -> 14 | B30: =F48 -> 134726.25 | D30: =G48 -> 137928.72 | F30: =(G48-F48)/F48 -> 0.023770201
A32: HOLDINGS — WEEK 2
A33: Company Name | B33: Day 1 Closing (₹) | C33: 2 Week Closing (₹) | D33: Return (%) | E33: Basis (Shares) | F33: Investment (₹) | G33: Growth (₹)
A34: Central Bank of India Ltd | B34: 32.53 | C34: 32.6 | D34: =(C34-B34)/B34 -> 0.0021518598 | E34: =ROUND($B$24/B34,0) -> 299 | F34: =B34*E34 -> 9726.47 | G34: =C34*E34 -> 9747.4
A35: NMDC Ltd | B35: 85.16 | C35: 84.92 | D35: =(C35-B35)/B35 -> -0.0028182245 | E35: =ROUND($B$24/B35,0) -> 114 | F35: =B35*E35 -> 9708.24 | G35: =C35*E35 -> 9680.88
A36: Physicswallah Ltd | B36: 124.13 | C36: 147.43 | D36: =(C36-B36)/B36 -> 0.18770644 | E36: =ROUND($B$24/B36,0) -> 78 | F36: =B36*E36 -> 9682.14 | G36: =C36*E36 -> 11499.54
A37: Indian Oil Corporation Ltd | B37: 139.38 | C37: 138.96 | D37: =(C37-B37)/B37 -> -0.0030133448 | E37: =ROUND($B$24/B37,0) -> 70 | F37: =B37*E37 -> 9756.6 | G37: =C37*E37 -> 9727.2
A38: Bank of India Ltd | B38: 140.4 | C38: 144.9 | D38: =(C38-B38)/B38 -> 0.032051282 | E38: =ROUND($B$24/B38,0) -> 69 | F38: =B38*E38 -> 9687.6 | G38: =C38*E38 -> 9998.1
A39: Vedanta Ltd | B39: 280.75 | C39: 272.55 | D39: =(C39-B39)/B39 -> -0.02920748 | E39: =ROUND($B$24/B39,0) -> 35 | F39: =B39*E39 -> 9826.25 | G39: =C39*E39 -> 9539.25
A40: Bharat Petroleum Corporation Ltd | B40: 303.55 | C40: 309.75 | D40: =(C40-B40)/B40 -> 0.020424971 | E40: =ROUND($B$24/B40,0) -> 32 | F40: =B40*E40 -> 9713.6 | G40: =C40*E40 -> 9912
A41: Life Insurance Corporation Of India | B41: 431.65 | C41: 443.05 | D41: =(C41-B41)/B41 -> 0.026410286 | E41: =ROUND($B$24/B41,0) -> 23 | F41: =B41*E41 -> 9927.95 | G41: =C41*E41 -> 10190.15
A42: Coal India Ltd | B42: 439.05 | C42: 429.3 | D42: =(C42-B42)/B42 -> -0.022207038 | E42: =ROUND($B$24/B42,0) -> 22 | F42: =B42*E42 -> 9659.1 | G42: =C42*E42 -> 9444.6
A43: Hindustan Zinc Ltd | B43: 533.15 | C43: 536.95 | D43: =(C43-B43)/B43 -> 0.0071274501 | E43: =ROUND($B$24/B43,0) -> 18 | F43: =B43*E43 -> 9596.7 | G43: =C43*E43 -> 9665.1
A44: Nippon Life India Asset Management Ltd | B44: 1162 | C44: 1212.7 | D44: =(C44-B44)/B44 -> 0.04363167 | E44: =ROUND($B$24/B44,0) -> 8 | F44: =B44*E44 -> 9296 | G44: =C44*E44 -> 9701.6
A45: Waaree Energies Ltd | B45: 2947 | C45: 2922.9 | D45: =(C45-B45)/B45 -> -0.0081778079 | E45: =ROUND($B$24/B45,0) -> 3 | F45: =B45*E45 -> 8841 | G45: =C45*E45 -> 8768.7
... A47: Bajaj Auto Ltd | B47: 9716 | C47: 10156 | D47: =(C47-B47)/B47 -> 0.045286126 | E47: =ROUND($B$24/B47,0) -> 1 | F47: =B47*E47 -> 9716 | G47: =C47*E47 -> 10156
A48: Portfolio Total | F48: =SUM(F34:F47) -> 134726.25 | G48: =SUM(G34:G47) -> 137928.72
A50: WEEK 3 SNAPSHOT — 6/30/2026 - 7/17/2026
A51: Reference stock (basis fixed at inception): Hero MotoCorp Ltd (₹4794.3)
A52: Holdings | B52: Total Investment (₹) | D52: Growth (₹) | F52: Return (6/30/2026 - 7/17/2026)
A53: =COUNT(B57:B70) -> 14 | B53: =F71 -> 134726.25 | D53: =G71 -> 135293.5 | F53: =(G71-F71)/F71 -> 0.0042103896
A55: HOLDINGS — WEEK 3
A56: Company Name | B56: Day 1 Closing (₹) | C56: 3 Week Closing (₹) | D56: Return (%) | E56: Basis (Shares) | F56: Investment (₹) | G56: Growth (₹)
A57: Central Bank of India Ltd | B57: 32.53 | C57: 31.66 | D57: =(C57-B57)/B57 -> -0.026744543 | E57: =ROUND($B$24/B57,0) -> 299 | F57: =B57*E57 -> 9726.47 | G57: =C57*E57 -> 9466.34
A58: NMDC Ltd | B58: 85.16 | C58: 83.22 | D58: =(C58-B58)/B58 -> -0.022780648 | E58: =ROUND($B$24/B58,0) -> 114 | F58: =B58*E58 -> 9708.24 | G58: =C58*E58 -> 9487.08
A59: Physicswallah Ltd | B59: 124.13 | C59: 136.05 | D59: =(C59-B59)/B59 -> 0.096028357 | E59: =ROUND($B$24/B59,0) -> 78 | F59: =B59*E59 -> 9682.14 | G59: =C59*E59 -> 10611.9
A60: Indian Oil Corporation Ltd | B60: 139.38 | C60: 141.69 | D60: =(C60-B60)/B60 -> 0.016573396 | E60: =ROUND($B$24/B60,0) -> 70 | F60: =B60*E60 -> 9756.6 | G60: =C60*E60 -> 9918.3
A61: Bank of India Ltd | B61: 140.4 | C61: 143.17 | D61: =(C61-B61)/B61 -> 0.019729345 | E61: =ROUND($B$24/B61,0) -> 69 | F61: =B61*E61 -> 9687.6 | G61: =C61*E61 -> 9878.73
A62: Vedanta Ltd | B62: 280.75 | C62: 253.05 | D62: =(C62-B62)/B62 -> -0.098664292 | E62: =ROUND($B$24/B62,0) -> 35 | F62: =B62*E62 -> 9826.25 | G62: =C62*E62 -> 8856.75
A63: Bharat Petroleum Corporation Ltd | B63: 303.55 | C63: 315.55 | D63: =(C63-B63)/B63 -> 0.039532202 | E63: =ROUND($B$24/B63,0) -> 32 | F63: =B63*E63 -> 9713.6 | G63: =C63*E63 -> 10097.6
A64: Life Insurance Corporation Of India | B64: 431.65 | C64: 433.1 | D64: =(C64-B64)/B64 -> 0.0033592031 | E64: =ROUND($B$24/B64,0) -> 23 | F64: =B64*E64 -> 9927.95 | G64: =C64*E64 -> 9961.3
A65: Coal India Ltd | B65: 439.05 | C65: 427.65 | D65: =(C65-B65)/B65 -> -0.025965152 | E65: =ROUND($B$24/B65,0) -> 22 | F65: =B65*E65 -> 9659.1 | G65: =C65*E65 -> 9408.3
A66: Hindustan Zinc Ltd | B66: 533.15 | C66: 518.35 | D66: =(C66-B66)/B66 -> -0.027759542 | E66: =ROUND($B$24/B66,0) -> 18 | F66: =B66*E66 -> 9596.7 | G66: =C66*E66 -> 9330.3
A67: Nippon Life India Asset Management Ltd | B67: 1162 | C67: 1186.5 | D67: =(C67-B67)/B67 -> 0.021084337 | E67: =ROUND($B$24/B67,0) -> 8 | F67: =B67*E67 -> 9296 | G67: =C67*E67 -> 9492
A68: Waaree Energies Ltd | B68: 2947 | C68: 2840.7 | D68: =(C68-B68)/B68 -> -0.03607058 | E68: =ROUND($B$24/B68,0) -> 3 | F68: =B68*E68 -> 8841 | G68: =C68*E68 -> 8522.1
... A70: Bajaj Auto Ltd | B70: 9716 | C70: 10443 | D70: =(C70-B70)/B70 -> 0.074825031 | E70: =ROUND($B$24/B70,0) -> 1 | F70: =B70*E70 -> 9716 | G70: =C70*E70 -> 10443
A71: Portfolio Total | F71: =SUM(F57:F70) -> 134726.25 | G71: =SUM(G57:G70) -> 135293.5
A73: WEEK 4 SNAPSHOT — 6/30/2026 - 7/24/2026
A74: Reference stock (basis fixed at inception): Hero MotoCorp Ltd (₹4794.3)
A75: Holdings | B75: Total Investment (₹) | D75: Growth (₹) | F75: Return (6/30/2026 - 7/24/2026)
A76: =COUNT(B80:B93) -> 14 | B76: =F94 -> 134726.25 | D76: =G94 -> 134338.74 | F76: =(G94-F94)/F94 -> -0.0028762769
A78: HOLDINGS — WEEK 4
A79: Company Name | B79: Day 1 Closing (₹) | C79: 4 Week Closing (₹) | D79: Return (%) | E79: Basis (Shares) | F79: Investment (₹) | G79: Growth (₹)
A80: Central Bank of India Ltd | B80: 32.53 | C80: 31.03 | D80: =(C80-B80)/B80 -> -0.046111282 | E80: =ROUND($B$24/B80,0) -> 299 | F80: =B80*E80 -> 9726.47 | G80: =C80*E80 -> 9277.97
A81: NMDC Ltd | B81: 85.16 | C81: 83.56 | D81: =(C81-B81)/B81 -> -0.018788163 | E81: =ROUND($B$24/B81,0) -> 114 | F81: =B81*E81 -> 9708.24 | G81: =C81*E81 -> 9525.84
A82: Physicswallah Ltd | B82: 124.13 | C82: 128.05 | D82: =(C82-B82)/B82 -> 0.031579795 | E82: =ROUND($B$24/B82,0) -> 78 | F82: =B82*E82 -> 9682.14 | G82: =C82*E82 -> 9987.9
A83: Indian Oil Corporation Ltd | B83: 139.38 | C83: 138.47 | D83: =(C83-B83)/B83 -> -0.0065289138 | E83: =ROUND($B$24/B83,0) -> 70 | F83: =B83*E83 -> 9756.6 | G83: =C83*E83 -> 9692.9
A84: Bank of India Ltd | B84: 140.4 | C84: 142.62 | D84: =(C84-B84)/B84 -> 0.015811966 | E84: =ROUND($B$24/B84,0) -> 69 | F84: =B84*E84 -> 9687.6 | G84: =C84*E84 -> 9840.78
A85: Vedanta Ltd | B85: 280.75 | C85: 264.65 | D85: =(C85-B85)/B85 -> -0.057346394 | E85: =ROUND($B$24/B85,0) -> 35 | F85: =B85*E85 -> 9826.25 | G85: =C85*E85 -> 9262.75
A86: Bharat Petroleum Corporation Ltd | B86: 303.55 | C86: 310.15 | D86: =(C86-B86)/B86 -> 0.021742711 | E86: =ROUND($B$24/B86,0) -> 32 | F86: =B86*E86 -> 9713.6 | G86: =C86*E86 -> 9924.8
A87: Life Insurance Corporation Of India | B87: 431.65 | C87: 421.3 | D87: =(C87-B87)/B87 -> -0.02397776 | E87: =ROUND($B$24/B87,0) -> 23 | F87: =B87*E87 -> 9927.95 | G87: =C87*E87 -> 9689.9
A88: Coal India Ltd | B88: 439.05 | C88: 427.4 | D88: =(C88-B88)/B88 -> -0.026534563 | E88: =ROUND($B$24/B88,0) -> 22 | F88: =B88*E88 -> 9659.1 | G88: =C88*E88 -> 9402.8
A89: Hindustan Zinc Ltd | B89: 533.15 | C89: 531.95 | D89: =(C89-B89)/B89 -> -0.0022507737 | E89: =ROUND($B$24/B89,0) -> 18 | F89: =B89*E89 -> 9596.7 | G89: =C89*E89 -> 9575.1
A90: Nippon Life India Asset Management Ltd | B90: 1162 | C90: 1112.5 | D90: =(C90-B90)/B90 -> -0.042598967 | E90: =ROUND($B$24/B90,0) -> 8 | F90: =B90*E90 -> 9296 | G90: =C90*E90 -> 8900
A91: Waaree Energies Ltd | B91: 2947 | C91: 2702 | D91: =(C91-B91)/B91 -> -0.083135392 | E91: =ROUND($B$24/B91,0) -> 3 | F91: =B91*E91 -> 8841 | G91: =C91*E91 -> 8106
... A93: Bajaj Auto Ltd | B93: 9716 | C93: 11130 | D93: =(C93-B93)/B93 -> 0.14553314 | E93: =ROUND($B$24/B93,0) -> 1 | F93: =B93*E93 -> 9716 | G93: =C93*E93 -> 11130
A94: Portfolio Total | F94: =SUM(F80:F93) -> 134726.25 | G94: =SUM(G80:G93) -> 134338.74
A96: WEEK 5 SNAPSHOT — 6/30/2026 - 7/31/2026
A97: Reference stock (basis fixed at inception): Hero MotoCorp Ltd (₹4794.3)
A98: Holdings | B98: Total Investment (₹) | D98: Growth (₹) | F98: Return (6/30/2026 - 7/31/2026)
A99: =COUNT(B103:B116) -> 14 | B99: =F117 -> 134726.25 | D99: =G117 -> 135717.01 | F99: =(G117-F117)/F117 -> 0.007353875
A101: HOLDINGS — WEEK 5
A102: Company Name | B102: Day 1 Closing (₹) | C102: 5 Week Closing (₹) | D102: Return (%) | E102: Basis (Shares) | F102: Investment (₹) | G102: Growth (₹)
A103: Central Bank of India Ltd | B103: 32.53 | C103: 30.97 | D103: =(C103-B103)/B103 -> -0.047955733 | E103: =ROUND($B$24/B103,0) -> 299 | F103: =B103*E103 -> 9726.47 | G103: =C103*E103 -> 9260.03
A104: NMDC Ltd | B104: 85.16 | C104: 85.04 | D104: =(C104-B104)/B104 -> -0.0014091123 | E104: =ROUND($B$24/B104,0) -> 114 | F104: =B104*E104 -> 9708.24 | G104: =C104*E104 -> 9694.56
A105: Physicswallah Ltd | B105: 124.13 | C105: 124.89 | D105: =(C105-B105)/B105 -> 0.0061226134 | E105: =ROUND($B$24/B105,0) -> 78 | F105: =B105*E105 -> 9682.14 | G105: =C105*E105 -> 9741.42
A106: Indian Oil Corporation Ltd | B106: 139.38 | C106: 140.17 | D106: =(C106-B106)/B106 -> 0.0056679581 | E106: =ROUND($B$24/B106,0) -> 70 | F106: =B106*E106 -> 9756.6 | G106: =C106*E106 -> 9811.9
A107: Bank of India Ltd | B107: 140.4 | C107: 137.95 | D107: =(C107-B107)/B107 -> -0.017450142 | E107: =ROUND($B$24/B107,0) -> 69 | F107: =B107*E107 -> 9687.6 | G107: =C107*E107 -> 9518.55
A108: Vedanta Ltd | B108: 280.75 | C108: 264.25 | D108: =(C108-B108)/B108 -> -0.058771149 | E108: =ROUND($B$24/B108,0) -> 35 | F108: =B108*E108 -> 9826.25 | G108: =C108*E108 -> 9248.75
A109: Bharat Petroleum Corporation Ltd | B109: 303.55 | C109: 319.75 | D109: =(C109-B109)/B109 -> 0.053368473 | E109: =ROUND($B$24/B109,0) -> 32 | F109: =B109*E109 -> 9713.6 | G109: =C109*E109 -> 10232
A110: Life Insurance Corporation Of India | B110: 431.65 | C110: 424.7 | D110: =(C110-B110)/B110 -> -0.016101008 | E110: =ROUND($B$24/B110,0) -> 23 | F110: =B110*E110 -> 9927.95 | G110: =C110*E110 -> 9768.1
A111: Coal India Ltd | B111: 439.05 | C111: 414.15 | D111: =(C111-B111)/B111 -> -0.056713358 | E111: =ROUND($B$24/B111,0) -> 22 | F111: =B111*E111 -> 9659.1 | G111: =C111*E111 -> 9111.3
A112: Hindustan Zinc Ltd | B112: 533.15 | C112: 539.2 | D112: =(C112-B112)/B112 -> 0.011347651 | E112: =ROUND($B$24/B112,0) -> 18 | F112: =B112*E112 -> 9596.7 | G112: =C112*E112 -> 9705.6
A113: Nippon Life India Asset Management Ltd | B113: 1162 | C113: 1161.4 | D113: =(C113-B113)/B113 -> -0.00051635112 | E113: =ROUND($B$24/B113,0) -> 8 | F113: =B113*E113 -> 9296 | G113: =C113*E113 -> 9291.2
A114: Waaree Energies Ltd | B114: 2947 | C114: 2680.2 | D114: =(C114-B114)/B114 -> -0.090532745 | E114: =ROUND($B$24/B114,0) -> 3 | F114: =B114*E114 -> 8841 | G114: =C114*E114 -> 8040.6
...

Sheet Method 6
A1: PORTFOLIO BASKET TRACKER — METHOD 6
A2: Student: Vishv Jeet Singh Thakur | Institution: UPES | Weekly Basket Performance Tracking (Basis Fixed at Inception)
A4: WEEK 1 SNAPSHOT — 6/30/2026 - 7/3/2026 | I4: QUERY / SCREENING CRITERIA
A5: Reference stock (basis fixed at inception): Technocraft Industries (India) Ltd (₹2564.9) | I5: Method:- Joseph Piotroski
A6: Holdings | B6: Total Investment (₹) | D6: Growth (₹) | F6: Return (6/30/2026 - 7/3/2026) | I6: Piotroski score > 6 AND
A7: =COUNT(B11:B25) -> 15 | B7: =F26 -> 40620.12 | D7: =G26 -> 41305.65 | F7: =(G26-F26)/F26 -> 0.016876612 | I7: Return on capital employed > 15 AND
I8: Return on equity > 15 AND
A9: HOLDINGS — WEEK 1 | I9: YOY Quarterly profit growth > 7 AND
A10: Company Name | B10: Day 1 Closing (₹) | C10: 1 Week Closing (₹) | D10: Return (%) | E10: Basis (Shares) | F10: Investment (₹) | G10: Growth (₹) | I10: Current ratio > 1 AND
A11: Indiabulls Ltd | B11: 27.81 | C11: 29.3 | D11: =(C11-B11)/B11 -> 0.05357785 | E11: =ROUND($B$25/B11,0) -> 92 | F11: =B11*E11 -> 2558.52 | G11: =C11*E11 -> 2695.6 | I11: Price to book value < 3 AND
A12: Jayaswal Neco Industries Ltd | B12: 84.95 | C12: 90.99 | D12: =(C12-B12)/B12 -> 0.071100647 | E12: =ROUND($B$25/B12,0) -> 30 | F12: =B12*E12 -> 2548.5 | G12: =C12*E12 -> 2729.7 | I12: Dividend yield < 4 AND
A13: JK Tyre & Industries Ltd | B13: 394.05 | C13: 412.55 | D13: =(C13-B13)/B13 -> 0.046948357 | E13: =ROUND($B$25/B13,0) -> 7 | F13: =B13*E13 -> 2758.35 | G13: =C13*E13 -> 2887.85 | I13: Market Capitalization < 25000
A14: Deep Industries Ltd | B14: 454.55 | C14: 463.05 | D14: =(C14-B14)/B14 -> 0.018699813 | E14: =ROUND($B$25/B14,0) -> 6 | F14: =B14*E14 -> 2727.3 | G14: =C14*E14 -> 2778.3
A15: Sarda Energy & Minerals Ltd | B15: 496.3 | C15: 508 | D15: =(C15-B15)/B15 -> 0.023574451 | E15: =ROUND($B$25/B15,0) -> 5 | F15: =B15*E15 -> 2481.5 | G15: =C15*E15 -> 2540
A16: Tanla Platforms Ltd | B16: 530.1 | C16: 539.05 | D16: =(C16-B16)/B16 -> 0.016883607 | E16: =ROUND($B$25/B16,0) -> 5 | F16: =B16*E16 -> 2650.5 | G16: =C16*E16 -> 2695.25
A17: Siyaram Silk Mills Ltd | B17: 638.15 | C17: 638.9 | D17: =(C17-B17)/B17 -> 0.0011752723 | E17: =ROUND($B$25/B17,0) -> 4 | F17: =B17*E17 -> 2552.6 | G17: =C17*E17 -> 2555.6
A18: AGI Greenpac Ltd | B18: 689.3 | C18: 707.45 | D18: =(C18-B18)/B18 -> 0.02633106 | E18: =ROUND($B$25/B18,0) -> 4 | F18: =B18*E18 -> 2757.2 | G18: =C18*E18 -> 2829.8
A19: Sharda Cropchem Ltd | B19: 879.45 | C19: 910.65 | D19: =(C19-B19)/B19 -> 0.035476718 | E19: =ROUND($B$25/B19,0) -> 3 | F19: =B19*E19 -> 2638.35 | G19: =C19*E19 -> 2731.95
A20: Chennai Petroleum Corporation Ltd | B20: 1156.3 | C20: 1125.8 | D20: =(C20-B20)/B20 -> -0.026377238 | E20: =ROUND($B$25/B20,0) -> 2 | F20: =B20*E20 -> 2312.6 | G20: =C20*E20 -> 2251.6
A21: Seamec Ltd | B21: 1420.4 | C21: 1431.7 | D21: =(C21-B21)/B21 -> 0.0079555055 | E21: =ROUND($B$25/B21,0) -> 2 | F21: =B21*E21 -> 2840.8 | G21: =C21*E21 -> 2863.4
A22: Great Eastern Shipping Company Ltd | B22: 1483.1 | C22: 1440.4 | D22: =(C22-B22)/B22 -> -0.028791046 | E22: =ROUND($B$25/B22,0) -> 2 | F22: =B22*E22 -> 2966.2 | G22: =C22*E22 -> 2880.8
A23: Bombay Burmah Trading Corporation, Ltd | B23: 1535.2 | C23: 1556.7 | D23: =(C23-B23)/B23 -> 0.01400469 | E23: =ROUND($B$25/B23,0) -> 2 | F23: =B23*E23 -> 3070.4 | G23: =C23*E23 -> 3113.4
A24: Mastek Ltd | B24: 1596.2 | C24: 1621.3 | D24: =(C24-B24)/B24 -> 0.015724847 | E24: =ROUND($B$25/B24,0) -> 2 | F24: =B24*E24 -> 3192.4 | G24: =C24*E24 -> 3242.6
A25: Technocraft Industries (India) Ltd | B25: 2564.9 | C25: 2509.8 | D25: =(C25-B25)/B25 -> -0.021482319 | E25: =ROUND($B$25/B25,0) -> 1 | F25: =B25*E25 -> 2564.9 | G25: =C25*E25 -> 2509.8
A26: Portfolio Total | F26: =SUM(F11:F25) -> 40620.12 | G26: =SUM(G11:G25) -> 41305.65
A28: WEEK 2 SNAPSHOT — 6/30/2026 - 7/10/2026
A29: Reference stock (basis fixed at inception): Hero MotoCorp Ltd (₹4794.3)
A30: Holdings | B30: Total Investment (₹) | D30: Growth (₹) | F30: Return (6/30/2026 - 7/10/2026)
A31: =COUNT(B35:B49) -> 15 | B31: =F50 -> 40620.12 | D31: =G50 -> 41279.96 | F31: =(G50-F50)/F50 -> 0.016244167
A33: HOLDINGS — WEEK 2
A34: Company Name | B34: Day 1 Closing (₹) | C34: 2 Week Closing (₹) | D34: Return (%) | E34: Basis (Shares) | F34: Investment (₹) | G34: Growth (₹)
A35: Indiabulls Ltd | B35: 27.81 | C35: 29.63 | D35: =(C35-B35)/B35 -> 0.065444085 | E35: =ROUND($B$25/B35,0) -> 92 | F35: =B35*E35 -> 2558.52 | G35: =C35*E35 -> 2725.96
A36: Jayaswal Neco Industries Ltd | B36: 84.95 | C36: 84.03 | D36: =(C36-B36)/B36 -> -0.0108299 | E36: =ROUND($B$25/B36,0) -> 30 | F36: =B36*E36 -> 2548.5 | G36: =C36*E36 -> 2520.9
A37: JK Tyre & Industries Ltd | B37: 394.05 | C37: 410.3 | D37: =(C37-B37)/B37 -> 0.041238422 | E37: =ROUND($B$25/B37,0) -> 7 | F37: =B37*E37 -> 2758.35 | G37: =C37*E37 -> 2872.1
A38: Deep Industries Ltd | B38: 454.55 | C38: 465.3 | D38: =(C38-B38)/B38 -> 0.023649764 | E38: =ROUND($B$25/B38,0) -> 6 | F38: =B38*E38 -> 2727.3 | G38: =C38*E38 -> 2791.8
A39: Sarda Energy & Minerals Ltd | B39: 496.3 | C39: 500.95 | D39: =(C39-B39)/B39 -> 0.0093693331 | E39: =ROUND($B$25/B39,0) -> 5 | F39: =B39*E39 -> 2481.5 | G39: =C39*E39 -> 2504.75
A40: Tanla Platforms Ltd | B40: 530.1 | C40: 550.2 | D40: =(C40-B40)/B40 -> 0.037917374 | E40: =ROUND($B$25/B40,0) -> 5 | F40: =B40*E40 -> 2650.5 | G40: =C40*E40 -> 2751
A41: Siyaram Silk Mills Ltd | B41: 638.15 | C41: 645 | D41: =(C41-B41)/B41 -> 0.010734153 | E41: =ROUND($B$25/B41,0) -> 4 | F41: =B41*E41 -> 2552.6 | G41: =C41*E41 -> 2580
A42: AGI Greenpac Ltd | B42: 689.3 | C42: 713.55 | D42: =(C42-B42)/B42 -> 0.035180618 | E42: =ROUND($B$25/B42,0) -> 4 | F42: =B42*E42 -> 2757.2 | G42: =C42*E42 -> 2854.2
A43: Sharda Cropchem Ltd | B43: 879.45 | C43: 914.75 | D43: =(C43-B43)/B43 -> 0.040138723 | E43: =ROUND($B$25/B43,0) -> 3 | F43: =B43*E43 -> 2638.35 | G43: =C43*E43 -> 2744.25
A44: Chennai Petroleum Corporation Ltd | B44: 1156.3 | C44: 1180.7 | D44: =(C44-B44)/B44 -> 0.02110179 | E44: =ROUND($B$25/B44,0) -> 2 | F44: =B44*E44 -> 2312.6 | G44: =C44*E44 -> 2361.4
A45: Seamec Ltd | B45: 1420.4 | C45: 1424.9 | D45: =(C45-B45)/B45 -> 0.0031681217 | E45: =ROUND($B$25/B45,0) -> 2 | F45: =B45*E45 -> 2840.8 | G45: =C45*E45 -> 2849.8
A46: Great Eastern Shipping Company Ltd | B46: 1483.1 | C46: 1420.9 | D46: =(C46-B46)/B46 -> -0.041939181 | E46: =ROUND($B$25/B46,0) -> 2 | F46: =B46*E46 -> 2966.2 | G46: =C46*E46 -> 2841.8
... A49: Technocraft Industries (India) Ltd | B49: 2564.9 | C49: 2479.2 | D49: =(C49-B49)/B49 -> -0.033412609 | E49: =ROUND($B$25/B49,0) -> 1 | F49: =B49*E49 -> 2564.9 | G49: =C49*E49 -> 2479.2
A50: Portfolio Total | F50: =SUM(F35:F49) -> 40620.12 | G50: =SUM(G35:G49) -> 41279.96
A52: WEEK 3 SNAPSHOT — 6/30/2026 - 7/17/2026
A53: Reference stock (basis fixed at inception): Hero MotoCorp Ltd (₹4794.3)
A54: Holdings | B54: Total Investment (₹) | D54: Growth (₹) | F54: Return (6/30/2026 - 7/17/2026)
A55: =COUNT(B59:B73) -> 15 | B55: =F74 -> 40620.12 | D55: =G74 -> 41404.33 | F55: =(G74-F74)/F74 -> 0.01930595
A57: HOLDINGS — WEEK 3
A58: Company Name | B58: Day 1 Closing (₹) | C58: 3 Week Closing (₹) | D58: Return (%) | E58: Basis (Shares) | F58: Investment (₹) | G58: Growth (₹)
A59: Indiabulls Ltd | B59: 27.81 | C59: 28.99 | D59: =(C59-B59)/B59 -> 0.04243078 | E59: =ROUND($B$25/B59,0) -> 92 | F59: =B59*E59 -> 2558.52 | G59: =C59*E59 -> 2667.08
A60: Jayaswal Neco Industries Ltd | B60: 84.95 | C60: 90.28 | D60: =(C60-B60)/B60 -> 0.06274279 | E60: =ROUND($B$25/B60,0) -> 30 | F60: =B60*E60 -> 2548.5 | G60: =C60*E60 -> 2708.4
A61: JK Tyre & Industries Ltd | B61: 394.05 | C61: 403.2 | D61: =(C61-B61)/B61 -> 0.023220404 | E61: =ROUND($B$25/B61,0) -> 7 | F61: =B61*E61 -> 2758.35 | G61: =C61*E61 -> 2822.4
A62: Deep Industries Ltd | B62: 454.55 | C62: 476 | D62: =(C62-B62)/B62 -> 0.047189528 | E62: =ROUND($B$25/B62,0) -> 6 | F62: =B62*E62 -> 2727.3 | G62: =C62*E62 -> 2856
A63: Sarda Energy & Minerals Ltd | B63: 496.3 | C63: 499.5 | D63: =(C63-B63)/B63 -> 0.0064477131 | E63: =ROUND($B$25/B63,0) -> 5 | F63: =B63*E63 -> 2481.5 | G63: =C63*E63 -> 2497.5
A64: Tanla Platforms Ltd | B64: 530.1 | C64: 584.55 | D64: =(C64-B64)/B64 -> 0.10271647 | E64: =ROUND($B$25/B64,0) -> 5 | F64: =B64*E64 -> 2650.5 | G64: =C64*E64 -> 2922.75
A65: Siyaram Silk Mills Ltd | B65: 638.15 | C65: 631.45 | D65: =(C65-B65)/B65 -> -0.010499099 | E65: =ROUND($B$25/B65,0) -> 4 | F65: =B65*E65 -> 2552.6 | G65: =C65*E65 -> 2525.8
A66: AGI Greenpac Ltd | B66: 689.3 | C66: 696.2 | D66: =(C66-B66)/B66 -> 0.010010155 | E66: =ROUND($B$25/B66,0) -> 4 | F66: =B66*E66 -> 2757.2 | G66: =C66*E66 -> 2784.8
A67: Sharda Cropchem Ltd | B67: 879.45 | C67: 899.1 | D67: =(C67-B67)/B67 -> 0.02234351 | E67: =ROUND($B$25/B67,0) -> 3 | F67: =B67*E67 -> 2638.35 | G67: =C67*E67 -> 2697.3
A68: Chennai Petroleum Corporation Ltd | B68: 1156.3 | C68: 1200 | D68: =(C68-B68)/B68 -> 0.03779296 | E68: =ROUND($B$25/B68,0) -> 2 | F68: =B68*E68 -> 2312.6 | G68: =C68*E68 -> 2400
A69: Seamec Ltd | B69: 1420.4 | C69: 1380.4 | D69: =(C69-B69)/B69 -> -0.028161081 | E69: =ROUND($B$25/B69,0) -> 2 | F69: =B69*E69 -> 2840.8 | G69: =C69*E69 -> 2760.8
A70: Great Eastern Shipping Company Ltd | B70: 1483.1 | C70: 1345.4 | D70: =(C70-B70)/B70 -> -0.092846066 | E70: =ROUND($B$25/B70,0) -> 2 | F70: =B70*E70 -> 2966.2 | G70: =C70*E70 -> 2690.8
... A73: Technocraft Industries (India) Ltd | B73: 2564.9 | C73: 2538.3 | D73: =(C73-B73)/B73 -> -0.010370775 | E73: =ROUND($B$25/B73,0) -> 1 | F73: =B73*E73 -> 2564.9 | G73: =C73*E73 -> 2538.3
A74: Portfolio Total | F74: =SUM(F59:F73) -> 40620.12 | G74: =SUM(G59:G73) -> 41404.33
A76: WEEK 4 SNAPSHOT — 6/30/2026 - 7/24/2026
A77: Reference stock (basis fixed at inception): Hero MotoCorp Ltd (₹4794.3)
A78: Holdings | B78: Total Investment (₹) | D78: Growth (₹) | F78: Return (6/30/2026 - 7/24/2026)
A79: =COUNT(B83:B97) -> 15 | B79: =F98 -> 40620.12 | D79: =G98 -> 41146.11 | F79: =(G98-F98)/F98 -> 0.012949002
A81: HOLDINGS — WEEK 4
A82: Company Name | B82: Day 1 Closing (₹) | C82: 4 Week Closing (₹) | D82: Return (%) | E82: Basis (Shares) | F82: Investment (₹) | G82: Growth (₹)
A83: Indiabulls Ltd | B83: 27.81 | C83: 30.53 | D83: =(C83-B83)/B83 -> 0.097806544 | E83: =ROUND($B$25/B83,0) -> 92 | F83: =B83*E83 -> 2558.52 | G83: =C83*E83 -> 2808.76
A84: Jayaswal Neco Industries Ltd | B84: 84.95 | C84: 86.76 | D84: =(C84-B84)/B84 -> 0.021306651 | E84: =ROUND($B$25/B84,0) -> 30 | F84: =B84*E84 -> 2548.5 | G84: =C84*E84 -> 2602.8
A85: JK Tyre & Industries Ltd | B85: 394.05 | C85: 390.6 | D85: =(C85-B85)/B85 -> -0.0087552341 | E85: =ROUND($B$25/B85,0) -> 7 | F85: =B85*E85 -> 2758.35 | G85: =C85*E85 -> 2734.2
A86: Deep Industries Ltd | B86: 454.55 | C86: 479.6 | D86: =(C86-B86)/B86 -> 0.055109449 | E86: =ROUND($B$25/B86,0) -> 6 | F86: =B86*E86 -> 2727.3 | G86: =C86*E86 -> 2877.6
A87: Sarda Energy & Minerals Ltd | B87: 496.3 | C87: 502.25 | D87: =(C87-B87)/B87 -> 0.011988717 | E87: =ROUND($B$25/B87,0) -> 5 | F87: =B87*E87 -> 2481.5 | G87: =C87*E87 -> 2511.25
A88: Tanla Platforms Ltd | B88: 530.1 | C88: 599.75 | D88: =(C88-B88)/B88 -> 0.1313903 | E88: =ROUND($B$25/B88,0) -> 5 | F88: =B88*E88 -> 2650.5 | G88: =C88*E88 -> 2998.75
A89: Siyaram Silk Mills Ltd | B89: 638.15 | C89: 609.45 | D89: =(C89-B89)/B89 -> -0.044973752 | E89: =ROUND($B$25/B89,0) -> 4 | F89: =B89*E89 -> 2552.6 | G89: =C89*E89 -> 2437.8
A90: AGI Greenpac Ltd | B90: 689.3 | C90: 672.85 | D90: =(C90-B90)/B90 -> -0.02386479 | E90: =ROUND($B$25/B90,0) -> 4 | F90: =B90*E90 -> 2757.2 | G90: =C90*E90 -> 2691.4
A91: Sharda Cropchem Ltd | B91: 879.45 | C91: 872.95 | D91: =(C91-B91)/B91 -> -0.007390983 | E91: =ROUND($B$25/B91,0) -> 3 | F91: =B91*E91 -> 2638.35 | G91: =C91*E91 -> 2618.85
A92: Chennai Petroleum Corporation Ltd | B92: 1156.3 | C92: 1165.8 | D92: =(C92-B92)/B92 -> 0.0082158609 | E92: =ROUND($B$25/B92,0) -> 2 | F92: =B92*E92 -> 2312.6 | G92: =C92*E92 -> 2331.6
A93: Seamec Ltd | B93: 1420.4 | C93: 1396.3 | D93: =(C93-B93)/B93 -> -0.016967052 | E93: =ROUND($B$25/B93,0) -> 2 | F93: =B93*E93 -> 2840.8 | G93: =C93*E93 -> 2792.6
A94: Great Eastern Shipping Company Ltd | B94: 1483.1 | C94: 1437.9 | D94: =(C94-B94)/B94 -> -0.030476704 | E94: =ROUND($B$25/B94,0) -> 2 | F94: =B94*E94 -> 2966.2 | G94: =C94*E94 -> 2875.8
... A97: Technocraft Industries (India) Ltd | B97: 2564.9 | C97: 2566.5 | D97: =(C97-B97)/B97 -> 0.000623806 | E97: =ROUND($B$25/B97,0) -> 1 | F97: =B97*E97 -> 2564.9 | G97: =C97*E97 -> 2566.5
A98: Portfolio Total | F98: =SUM(F83:F97) -> 40620.12 | G98: =SUM(G83:G97) -> 41146.11
A100: WEEK 5 SNAPSHOT — 6/30/2026 - 7/31/2026
A101: Reference stock (basis fixed at inception): Hero MotoCorp Ltd (₹4794.3)
A102: Holdings | B102: Total Investment (₹) | D102: Growth (₹) | F102: Return (6/30/2026 - 7/31/2026)
A103: =COUNT(B107:B121) -> 15 | B103: =F122 -> 40620.12 | D103: =G122 -> 42171.61 | F103: =(G122-F122)/F122 -> 0.038195111
A105: HOLDINGS — WEEK 5
A106: Company Name | B106: Day 1 Closing (₹) | C106: 5 Week Closing (₹) | D106: Return (%) | E106: Basis (Shares) | F106: Investment (₹) | G106: Growth (₹)
A107: Indiabulls Ltd | B107: 27.81 | C107: 27.38 | D107: =(C107-B107)/B107 -> -0.015462064 | E107: =ROUND($B$25/B107,0) -> 92 | F107: =B107*E107 -> 2558.52 | G107: =C107*E107 -> 2518.96
A108: Jayaswal Neco Industries Ltd | B108: 84.95 | C108: 86.03 | D108: =(C108-B108)/B108 -> 0.012713361 | E108: =ROUND($B$25/B108,0) -> 30 | F108: =B108*E108 -> 2548.5 | G108: =C108*E108 -> 2580.9
A109: JK Tyre & Industries Ltd | B109: 394.05 | C109: 399.75 | D109: =(C109-B109)/B109 -> 0.014465169 | E109: =ROUND($B$25/B109,0) -> 7 | F109: =B109*E109 -> 2758.35 | G109: =C109*E109 -> 2798.25
A110: Deep Industries Ltd | B110: 454.55 | C110: 596.9 | D110: =(C110-B110)/B110 -> 0.31316687 | E110: =ROUND($B$25/B110,0) -> 6 | F110: =B110*E110 -> 2727.3 | G110: =C110*E110 -> 3581.4
A111: Sarda Energy & Minerals Ltd | B111: 496.3 | C111: 516.6 | D111: =(C111-B111)/B111 -> 0.04090268 | E111: =ROUND($B$25/B111,0) -> 5 | F111: =B111*E111 -> 2481.5 | G111: =C111*E111 -> 2583
A112: Tanla Platforms Ltd | B112: 530.1 | C112: 586.55 | D112: =(C112-B112)/B112 -> 0.10648934 | E112: =ROUND($B$25/B112,0) -> 5 | F112: =B112*E112 -> 2650.5 | G112: =C112*E112 -> 2932.75
A113: Siyaram Silk Mills Ltd | B113: 638.15 | C113: 602.3 | D113: =(C113-B113)/B113 -> -0.056178015 | E113: =ROUND($B$25/B113,0) -> 4 | F113: =B113*E113 -> 2552.6 | G113: =C113*E113 -> 2409.2
A114: AGI Greenpac Ltd | B114: 689.3 | C114: 709.25 | D114: =(C114-B114)/B114 -> 0.028942405 | E114: =ROUND($B$25/B114,0) -> 4 | F114: =B114*E114 -> 2757.2 | G114: =C114*E114 -> 2837
A115: Sharda Cropchem Ltd | B115: 879.45 | C115: 819.75 | D115: =(C115-B115)/B115 -> -0.067883336 | E115: =ROUND($B$25/B115,0) -> 3 | F115: =B115*E115 -> 2638.35 | G115: =C115*E115 -> 2459.25
...

Sheet Method Self
A1: PORTFOLIO BASKET TRACKER — METHOD SELF
A2: Student: Vishv Jeet Singh Thakur | Institution: UPES | Weekly Basket Performance Tracking (Basis Fixed at Inception)
A4: WEEK 1 SNAPSHOT — 6/30/2026 - 7/3/2026 | I4: QUERY / SCREENING CRITERIA
A5: Reference stock (basis fixed at inception): Oracle Financial Services Software Ltd (₹10775.5) | I5: FII holding > 1 AND
A6: Holdings | B6: Total Investment (₹) | D6: Growth (₹) | F6: Return (6/30/2026 - 7/3/2026) | I6: Return on equity > 16 AND
A7: =COUNT(B11:B29) -> 19 | B7: =F30 -> 203585.65 | D7: =G30 -> 206647.86 | F7: =(G30-F30)/F30 -> 0.015041384 | I7: Dividend yield > 2 AND
I8: Operating profit > 15 AND
A9: HOLDINGS — WEEK 1 | I9: Market Capitalization > 25000
A10: Company Name | B10: Day 1 Closing (₹) | C10: 1 Week Closing (₹) | D10: Return (%) | E10: Basis (Shares) | F10: Investment (₹) | G10: Growth (₹)
A11: NMDC Ltd | B11: 85.16 | C11: 85.4 | D11: =(C11-B11)/B11 -> 0.0028182245 | E11: =ROUND($B$29/B11,0) -> 127 | F11: =B11*E11 -> 10815.32 | G11: =C11*E11 -> 10845.8
A12: Canara Bank Ltd | B12: 125.52 | C12: 127.19 | D12: =(C12-B12)/B12 -> 0.013304653 | E12: =ROUND($B$29/B12,0) -> 86 | F12: =B12*E12 -> 10794.72 | G12: =C12*E12 -> 10938.34
A13: Indian Oil Corporation Ltd | B13: 139.38 | C13: 141.56 | D13: =(C13-B13)/B13 -> 0.015640695 | E13: =ROUND($B$29/B13,0) -> 77 | F13: =B13*E13 -> 10732.26 | G13: =C13*E13 -> 10900.12
A14: Vedanta Ltd | B14: 280.75 | C14: 280.4 | D14: =(C14-B14)/B14 -> -0.0012466607 | E14: =ROUND($B$29/B14,0) -> 38 | F14: =B14*E14 -> 10668.5 | G14: =C14*E14 -> 10655.2
A15: Petronet LNG Ltd | B15: 280.8 | C15: 275.95 | D15: =(C15-B15)/B15 -> -0.01727208 | E15: =ROUND($B$29/B15,0) -> 38 | F15: =B15*E15 -> 10670.4 | G15: =C15*E15 -> 10486.1
A16: Power Grid Corporation of India Ltd | B16: 286.3 | C16: 287.85 | D16: =(C16-B16)/B16 -> 0.0054139015 | E16: =ROUND($B$29/B16,0) -> 38 | F16: =B16*E16 -> 10879.4 | G16: =C16*E16 -> 10938.3
A17: ITC Ltd | B17: 286.95 | C17: 289.95 | D17: =(C17-B17)/B17 -> 0.010454783 | E17: =ROUND($B$29/B17,0) -> 38 | F17: =B17*E17 -> 10904.1 | G17: =C17*E17 -> 11018.1
A18: Bharat Petroleum Corporation Ltd | B18: 303.55 | C18: 308.15 | D18: =(C18-B18)/B18 -> 0.015154011 | E18: =ROUND($B$29/B18,0) -> 35 | F18: =B18*E18 -> 10624.25 | G18: =C18*E18 -> 10785.25
A19: National Aluminium Co Ltd | B19: 339.6 | C19: 347.6 | D19: =(C19-B19)/B19 -> 0.023557126 | E19: =ROUND($B$29/B19,0) -> 32 | F19: =B19*E19 -> 10867.2 | G19: =C19*E19 -> 11123.2
A20: REC Ltd | B20: 363.8 | C20: 365.15 | D20: =(C20-B20)/B20 -> 0.0037108301 | E20: =ROUND($B$29/B20,0) -> 30 | F20: =B20*E20 -> 10914 | G20: =C20*E20 -> 10954.5
A21: Hindustan Petroleum Corp Ltd | B21: 394.45 | C21: 399.25 | D21: =(C21-B21)/B21 -> 0.012168843 | E21: =ROUND($B$29/B21,0) -> 27 | F21: =B21*E21 -> 10650.15 | G21: =C21*E21 -> 10779.75
A22: Power Finance Corporation Ltd | B22: 424.3 | C22: 425.8 | D22: =(C22-B22)/B22 -> 0.0035352345 | E22: =ROUND($B$29/B22,0) -> 25 | F22: =B22*E22 -> 10607.5 | G22: =C22*E22 -> 10645
... A29: Oracle Financial Services Software Ltd | B29: 10775.5 | C29: 11248 | D29: =(C29-B29)/B29 -> 0.043849473 | E29: =ROUND($B$29/B29,0) -> 1 | F29: =B29*E29 -> 10775.5 | G29: =C29*E29 -> 11248
A30: Portfolio Total | F30: =SUM(F11:F29) -> 203585.65 | G30: =SUM(G11:G29) -> 206647.86
A32: WEEK 2 SNAPSHOT — 6/30/2026 - 7/10/2026
A33: Reference stock (basis fixed at inception): Hero MotoCorp Ltd (₹4794.3)
A34: Holdings | B34: Total Investment (₹) | D34: Growth (₹) | F34: Return (6/30/2026 - 7/10/2026)
A35: =COUNT(B39:B57) -> 19 | B35: =F58 -> 203585.65 | D35: =G58 -> 206788.29 | F35: =(G58-F58)/F58 -> 0.015731168
A37: HOLDINGS — WEEK 2
A38: Company Name | B38: Day 1 Closing (₹) | C38: 2 Week Closing (₹) | D38: Return (%) | E38: Basis (Shares) | F38: Investment (₹) | G38: Growth (₹)
A39: NMDC Ltd | B39: 85.16 | C39: 84.92 | D39: =(C39-B39)/B39 -> -0.0028182245 | E39: =ROUND($B$29/B39,0) -> 127 | F39: =B39*E39 -> 10815.32 | G39: =C39*E39 -> 10784.84
A40: Canara Bank Ltd | B40: 125.52 | C40: 128.78 | D40: =(C40-B40)/B40 -> 0.025971957 | E40: =ROUND($B$29/B40,0) -> 86 | F40: =B40*E40 -> 10794.72 | G40: =C40*E40 -> 11075.08
A41: Indian Oil Corporation Ltd | B41: 139.38 | C41: 138.96 | D41: =(C41-B41)/B41 -> -0.0030133448 | E41: =ROUND($B$29/B41,0) -> 77 | F41: =B41*E41 -> 10732.26 | G41: =C41*E41 -> 10699.92
A42: Vedanta Ltd | B42: 280.75 | C42: 272.55 | D42: =(C42-B42)/B42 -> -0.02920748 | E42: =ROUND($B$29/B42,0) -> 38 | F42: =B42*E42 -> 10668.5 | G42: =C42*E42 -> 10356.9
A43: Petronet LNG Ltd | B43: 280.8 | C43: 278.95 | D43: =(C43-B43)/B43 -> -0.0065883191 | E43: =ROUND($B$29/B43,0) -> 38 | F43: =B43*E43 -> 10670.4 | G43: =C43*E43 -> 10600.1
A44: Power Grid Corporation of India Ltd | B44: 286.3 | C44: 283.1 | D44: =(C44-B44)/B44 -> -0.011177087 | E44: =ROUND($B$29/B44,0) -> 38 | F44: =B44*E44 -> 10879.4 | G44: =C44*E44 -> 10757.8
A45: ITC Ltd | B45: 286.95 | C45: 281.75 | D45: =(C45-B45)/B45 -> -0.018121624 | E45: =ROUND($B$29/B45,0) -> 38 | F45: =B45*E45 -> 10904.1 | G45: =C45*E45 -> 10706.5
A46: Bharat Petroleum Corporation Ltd | B46: 303.55 | C46: 309.75 | D46: =(C46-B46)/B46 -> 0.020424971 | E46: =ROUND($B$29/B46,0) -> 35 | F46: =B46*E46 -> 10624.25 | G46: =C46*E46 -> 10841.25
A47: National Aluminium Co Ltd | B47: 339.6 | C47: 354.85 | D47: =(C47-B47)/B47 -> 0.044905771 | E47: =ROUND($B$29/B47,0) -> 32 | F47: =B47*E47 -> 10867.2 | G47: =C47*E47 -> 11355.2
A48: REC Ltd | B48: 363.8 | C48: 351.95 | D48: =(C48-B48)/B48 -> -0.032572842 | E48: =ROUND($B$29/B48,0) -> 30 | F48: =B48*E48 -> 10914 | G48: =C48*E48 -> 10558.5
A49: Hindustan Petroleum Corp Ltd | B49: 394.45 | C49: 395.3 | D49: =(C49-B49)/B49 -> 0.0021548992 | E49: =ROUND($B$29/B49,0) -> 27 | F49: =B49*E49 -> 10650.15 | G49: =C49*E49 -> 10673.1
A50: Power Finance Corporation Ltd | B50: 424.3 | C50: 406.5 | D50: =(C50-B50)/B50 -> -0.041951449 | E50: =ROUND($B$29/B50,0) -> 25 | F50: =B50*E50 -> 10607.5 | G50: =C50*E50 -> 10162.5
... A57: Oracle Financial Services Software Ltd | B57: 10775.5 | C57: 11651 | D57: =(C57-B57)/B57 -> 0.08124913 | E57: =ROUND($B$29/B57,0) -> 1 | F57: =B57*E57 -> 10775.5 | G57: =C57*E57 -> 11651
A58: Portfolio Total | F58: =SUM(F39:F57) -> 203585.65 | G58: =SUM(G39:G57) -> 206788.29
A60: WEEK 3 SNAPSHOT — 6/30/2026 - 7/17/2026
A61: Reference stock (basis fixed at inception): Hero MotoCorp Ltd (₹4794.3)
A62: Holdings | B62: Total Investment (₹) | D62: Growth (₹) | F62: Return (6/30/2026 - 7/17/2026)
A63: =COUNT(B67:B85) -> 19 | B63: =F86 -> 203585.65 | D63: =G86 -> 207508.58 | F63: =(G86-F86)/F86 -> 0.019269187
A65: HOLDINGS — WEEK 3
A66: Company Name | B66: Day 1 Closing (₹) | C66: 3 Week Closing (₹) | D66: Return (%) | E66: Basis (Shares) | F66: Investment (₹) | G66: Growth (₹)
A67: NMDC Ltd | B67: 85.16 | C67: 83.22 | D67: =(C67-B67)/B67 -> -0.022780648 | E67: =ROUND($B$29/B67,0) -> 127 | F67: =B67*E67 -> 10815.32 | G67: =C67*E67 -> 10568.94
A68: Canara Bank Ltd | B68: 125.52 | C68: 125.01 | D68: =(C68-B68)/B68 -> -0.0040630975 | E68: =ROUND($B$29/B68,0) -> 86 | F68: =B68*E68 -> 10794.72 | G68: =C68*E68 -> 10750.86
A69: Indian Oil Corporation Ltd | B69: 139.38 | C69: 141.69 | D69: =(C69-B69)/B69 -> 0.016573396 | E69: =ROUND($B$29/B69,0) -> 77 | F69: =B69*E69 -> 10732.26 | G69: =C69*E69 -> 10910.13
A70: Vedanta Ltd | B70: 280.75 | C70: 253.05 | D70: =(C70-B70)/B70 -> -0.098664292 | E70: =ROUND($B$29/B70,0) -> 38 | F70: =B70*E70 -> 10668.5 | G70: =C70*E70 -> 9615.9
A71: Petronet LNG Ltd | B71: 280.8 | C71: 273.8 | D71: =(C71-B71)/B71 -> -0.024928775 | E71: =ROUND($B$29/B71,0) -> 38 | F71: =B71*E71 -> 10670.4 | G71: =C71*E71 -> 10404.4
A72: Power Grid Corporation of India Ltd | B72: 286.3 | C72: 283.55 | D72: =(C72-B72)/B72 -> -0.0096053091 | E72: =ROUND($B$29/B72,0) -> 38 | F72: =B72*E72 -> 10879.4 | G72: =C72*E72 -> 10774.9
A73: ITC Ltd | B73: 286.95 | C73: 280.7 | D73: =(C73-B73)/B73 -> -0.021780798 | E73: =ROUND($B$29/B73,0) -> 38 | F73: =B73*E73 -> 10904.1 | G73: =C73*E73 -> 10666.6
A74: Bharat Petroleum Corporation Ltd | B74: 303.55 | C74: 315.55 | D74: =(C74-B74)/B74 -> 0.039532202 | E74: =ROUND($B$29/B74,0) -> 35 | F74: =B74*E74 -> 10624.25 | G74: =C74*E74 -> 11044.25
A75: National Aluminium Co Ltd | B75: 339.6 | C75: 339.9 | D75: =(C75-B75)/B75 -> 0.00088339223 | E75: =ROUND($B$29/B75,0) -> 32 | F75: =B75*E75 -> 10867.2 | G75: =C75*E75 -> 10876.8
A76: REC Ltd | B76: 363.8 | C76: 355.1 | D76: =(C76-B76)/B76 -> -0.023914239 | E76: =ROUND($B$29/B76,0) -> 30 | F76: =B76*E76 -> 10914 | G76: =C76*E76 -> 10653
A77: Hindustan Petroleum Corp Ltd | B77: 394.45 | C77: 400.4 | D77: =(C77-B77)/B77 -> 0.015084295 | E77: =ROUND($B$29/B77,0) -> 27 | F77: =B77*E77 -> 10650.15 | G77: =C77*E77 -> 10810.8
A78: Power Finance Corporation Ltd | B78: 424.3 | C78: 404.85 | D78: =(C78-B78)/B78 -> -0.045840207 | E78: =ROUND($B$29/B78,0) -> 25 | F78: =B78*E78 -> 10607.5 | G78: =C78*E78 -> 10121.25
... A85: Oracle Financial Services Software Ltd | B85: 10775.5 | C85: 11771 | D85: =(C85-B85)/B85 -> 0.092385504 | E85: =ROUND($B$29/B85,0) -> 1 | F85: =B85*E85 -> 10775.5 | G85: =C85*E85 -> 11771
A86: Portfolio Total | F86: =SUM(F67:F85) -> 203585.65 | G86: =SUM(G67:G85) -> 207508.58
A88: WEEK 4 SNAPSHOT — 6/30/2026 - 7/24/2026
A89: Reference stock (basis fixed at inception): Hero MotoCorp Ltd (₹4794.3)
A90: Holdings | B90: Total Investment (₹) | D90: Growth (₹) | F90: Return (6/30/2026 - 7/24/2026)
A91: =COUNT(B95:B113) -> 19 | B91: =F114 -> 203585.65 | D91: =G114 -> 206859.86 | F91: =(G114-F114)/F114 -> 0.016082715
A93: HOLDINGS — WEEK 4
A94: Company Name | B94: Day 1 Closing (₹) | C94: 4 Week Closing (₹) | D94: Return (%) | E94: Basis (Shares) | F94: Investment (₹) | G94: Growth (₹)
A95: NMDC Ltd | B95: 85.16 | C95: 83.56 | D95: =(C95-B95)/B95 -> -0.018788163 | E95: =ROUND($B$29/B95,0) -> 127 | F95: =B95*E95 -> 10815.32 | G95: =C95*E95 -> 10612.12
A96: Canara Bank Ltd | B96: 125.52 | C96: 125.65 | D96: =(C96-B96)/B96 -> 0.0010356915 | E96: =ROUND($B$29/B96,0) -> 86 | F96: =B96*E96 -> 10794.72 | G96: =C96*E96 -> 10805.9
A97: Indian Oil Corporation Ltd | B97: 139.38 | C97: 138.47 | D97: =(C97-B97)/B97 -> -0.0065289138 | E97: =ROUND($B$29/B97,0) -> 77 | F97: =B97*E97 -> 10732.26 | G97: =C97*E97 -> 10662.19
A98: Vedanta Ltd | B98: 280.75 | C98: 264.65 | D98: =(C98-B98)/B98 -> -0.057346394 | E98: =ROUND($B$29/B98,0) -> 38 | F98: =B98*E98 -> 10668.5 | G98: =C98*E98 -> 10056.7
A99: Petronet LNG Ltd | B99: 280.8 | C99: 274.7 | D99: =(C99-B99)/B99 -> -0.021723647 | E99: =ROUND($B$29/B99,0) -> 38 | F99: =B99*E99 -> 10670.4 | G99: =C99*E99 -> 10438.6
A100: Power Grid Corporation of India Ltd | B100: 286.3 | C100: 288.2 | D100: =(C100-B100)/B100 -> 0.0066363954 | E100: =ROUND($B$29/B100,0) -> 38 | F100: =B100*E100 -> 10879.4 | G100: =C100*E100 -> 10951.6
A101: ITC Ltd | B101: 286.95 | C101: 283.45 | D101: =(C101-B101)/B101 -> -0.012197247 | E101: =ROUND($B$29/B101,0) -> 38 | F101: =B101*E101 -> 10904.1 | G101: =C101*E101 -> 10771.1
A102: Bharat Petroleum Corporation Ltd | B102: 303.55 | C102: 310.15 | D102: =(C102-B102)/B102 -> 0.021742711 | E102: =ROUND($B$29/B102,0) -> 35 | F102: =B102*E102 -> 10624.25 | G102: =C102*E102 -> 10855.25
A103: National Aluminium Co Ltd | B103: 339.6 | C103: 343.9 | D103: =(C103-B103)/B103 -> 0.012661955 | E103: =ROUND($B$29/B103,0) -> 32 | F103: =B103*E103 -> 10867.2 | G103: =C103*E103 -> 11004.8
A104: REC Ltd | B104: 363.8 | C104: 361.6 | D104: =(C104-B104)/B104 -> -0.0060472787 | E104: =ROUND($B$29/B104,0) -> 30 | F104: =B104*E104 -> 10914 | G104: =C104*E104 -> 10848
A105: Hindustan Petroleum Corp Ltd | B105: 394.45 | C105: 381.1 | D105: =(C105-B105)/B105 -> -0.033844594 | E105: =ROUND($B$29/B105,0) -> 27 | F105: =B105*E105 -> 10650.15 | G105: =C105*E105 -> 10289.7
A106: Power Finance Corporation Ltd | B106: 424.3 | C106: 411.9 | D106: =(C106-B106)/B106 -> -0.029224605 | E106: =ROUND($B$29/B106,0) -> 25 | F106: =B106*E106 -> 10607.5 | G106: =C106*E106 -> 10297.5
... A113: Oracle Financial Services Software Ltd | B113: 10775.5 | C113: 10652 | D113: =(C113-B113)/B113 -> -0.011461185 | E113: =ROUND($B$29/B113,0) -> 1 | F113: =B113*E113 -> 10775.5 | G113: =C113*E113 -> 10652
A114: Portfolio Total | F114: =SUM(F95:F113) -> 203585.65 | G114: =SUM(G95:G113) -> 206859.86
A116: WEEK 5 SNAPSHOT — 6/30/2026 - 7/31/2026
A117: Reference stock (basis fixed at inception): Hero MotoCorp Ltd (₹4794.3)
A118: Holdings | B118: Total Investment (₹) | D118: Growth (₹) | F118: Return (6/30/2026 - 7/31/2026)
A119: =COUNT(B123:B141) -> 19 | B119: =F142 -> 203585.65 | D119: =G142 -> 212494.55 | F119: =(G142-F142)/F142 -> 0.04375996
A121: HOLDINGS — WEEK 5
A122: Company Name | B122: Day 1 Closing (₹) | C122: 5 Week Closing (₹) | D122: Return (%) | E122: Basis (Shares) | F122: Investment (₹) | G122: Growth (₹)
A123: NMDC Ltd | B123: 85.16 | C123: 85.04 | D123: =(C123-B123)/B123 -> -0.0014091123 | E123: =ROUND($B$29/B123,0) -> 127 | F123: =B123*E123 -> 10815.32 | G123: =C123*E123 -> 10800.08
A124: Canara Bank Ltd | B124: 125.52 | C124: 124.98 | D124: =(C124-B124)/B124 -> -0.0043021033 | E124: =ROUND($B$29/B124,0) -> 86 | F124: =B124*E124 -> 10794.72 | G124: =C124*E124 -> 10748.28
A125: Indian Oil Corporation Ltd | B125: 139.38 | C125: 140.17 | D125: =(C125-B125)/B125 -> 0.0056679581 | E125: =ROUND($B$29/B125,0) -> 77 | F125: =B125*E125 -> 10732.26 | G125: =C125*E125 -> 10793.09
A126: Vedanta Ltd | B126: 280.75 | C126: 264.25 | D126: =(C126-B126)/B126 -> -0.058771149 | E126: =ROUND($B$29/B126,0) -> 38 | F126: =B126*E126 -> 10668.5 | G126: =C126*E126 -> 10041.5
A127: Petronet LNG Ltd | B127: 280.8 | C127: 280.75 | D127: =(C127-B127)/B127 -> -0.00017806268 | E127: =ROUND($B$29/B127,0) -> 38 | F127: =B127*E127 -> 10670.4 | G127: =C127*E127 -> 10668.5
A128: Power Grid Corporation of India Ltd | B128: 286.3 | C128: 284.25 | D128: =(C128-B128)/B128 -> -0.0071603213 | E128: =ROUND($B$29/B128,0) -> 38 | F128: =B128*E128 -> 10879.4 | G128: =C128*E128 -> 10801.5
A129: ITC Ltd | B129: 286.95 | C129: 281 | D129: =(C129-B129)/B129 -> -0.02073532 | E129: =ROUND($B$29/B129,0) -> 38 | F129: =B129*E129 -> 10904.1 | G129: =C129*E129 -> 10678
A130: Bharat Petroleum Corporation Ltd | B130: 303.55 | C130: 319.75 | D130: =(C130-B130)/B130 -> 0.053368473 | E130: =ROUND($B$29/B130,0) -> 35 | F130: =B130*E130 -> 10624.25 | G130: =C130*E130 -> 11191.25
A131: National Aluminium Co Ltd | B131: 339.6 | C131: 350.05 | D131: =(C131-B131)/B131 -> 0.030771496 | E131: =ROUND($B$29/B131,0) -> 32 | F131: =B131*E131 -> 10867.2 | G131: =C131*E131 -> 11201.6
A132: REC Ltd | B132: 363.8 | C132: 372.95 | D132: =(C132-B132)/B132 -> 0.025151182 | E132: =ROUND($B$29/B132,0) -> 30 | F132: =B132*E132 -> 10914 | G132: =C132*E132 -> 11188.5
A133: Hindustan Petroleum Corp Ltd | B133: 394.45 | C133: 389.75 | D133: =(C133-B133)/B133 -> -0.011915325 | E133: =ROUND($B$29/B133,0) -> 27 | F133: =B133*E133 -> 10650.15 | G133: =C133*E133 -> 10523.25
...
